Workbook
Name cursos: '[1]Lista 1ºP - 6ºP'!$BG$3:$BH$20

Sheet RECIBO INGRESOS
D2: RECIBO DE CAJA | F2: No. | H2: {=MAX(('FLUJO DE CAJA'!D:D<>0)*ROW(('FLUJO DE CAJA'!D:D)))-1} -> 2
D4: INGRESOS | F4: Bs.(Efect.) | H4: 2341.56 | P4: BUSCAR CODIGO POR APELLIDO
E5: t.c. (6,97) | F5: Bs.(Tr.-QR) | P5: APELLIDO
B6: Hemos recibido de : | C6: Rafucho Rafuchin | E6: CODIGO | F6: $us. | P6: Galindo Puña Sara
E7: 2018088 | F7: PENSIONES | P7: CODIGO
B8: La suma de : | C8: {=IF(H4="", IF(H5="",IF(H6="","",[2]!cMoneda2(H6,"DOLAR AMERICANO","DOLARES AMERICANOS",0)),[2]!cMoneda2(H5,"BOLIVIANO","BOLIVIANOS",0)),[2]!cMoneda2(H4,"BOLIVIANO","BOLIVIANOS",0))} -> DOS MIL TRESCIENTOS CUARENTA Y UN BOLIVIANOS 56/100 | F8: 1a | H8: 2a | J8: 3a | P8: =VLOOKUP(P6,Códigos!C2:M858,11,FALSE) -> 2018088
F9: 4a | H9: 5a | J9: 6a
B10: Por concepto de : | C10: INGRESOS MENSUALIDAD COLEGIO DESPERTAD | F10: 7a | H10: 8a | J10: 9a
F11: 10a | H11: Unic.
B12: Observaciones :
C13: =IF(E7="","",CONCATENATE("Alumnos : ",VLOOKUP(E7,Códigos!A2:L858,3,FALSE)," - Padres : ",VLOOKUP(E7,Códigos!A2:L858,4,FALSE)," - Cursos : ",VLOOKUP(E7,Códigos!A2:L858,2,FALSE)," - Pensión : ",VLOOKUP(E7,Códigos!A2:L858,9,FALSE),," - Pensión KADI : ",VLOOKUP(E7,Códigos!A2:L858,10,FALSE))) -> Alumnos : Galindo Puña Sara - Padres : MARCELA - HENRY - Cursos : 4º Prim - Pensión : 823 - Pensión KADI : 364
C16: Cochabamba, | D16: 45308
B20: FIRMA DEL CAJERO | E20: FIRMA DEL INTERESADO
D24: RECIBO DE CAJA | F24: No. | H24: =H2 -> 2
D26: INGRESOS | F26: Bs.(Efect.) | H26: 1456.2
E27: t.c. (6,97) | F27: Bs.(Tr.-QR)
B28: Hemos recibido de : | C28: =C6 -> Rafucho Rafuchin | E28: CODIGO | F28: $us.
E29: =E7 -> 2018088 | F29: PENSIONES
B30: La suma de : | C30: =C8 -> DOS MIL TRESCIENTOS CUARENTA Y UN BOLIVIANOS 56/100 | F30: 1a | H30: 2a | J30: 3a
F31: 4a | H31: 5a | J31: 6a
B32: Por concepto de : | C32: =C10 -> INGRESOS MENSUALIDAD COLEGIO DESPERTAD | F32: 7a | H32: 8a | J32: 9a
F33: 10a | H33: Unic.
B34: Observaciones : | C34: =C12 -> 0
C35: =C13 -> Alumnos : Galindo Puña Sara - Padres : MARCELA - HENRY - Cursos : 4º Prim - Pensión : 823 - Pensión KADI : 364
C38: Cochabamba, | D38: =D16 -> 45308
B42: FIRMA DEL CAJERO | E42: FIRMA DEL INTERESADO
O1048565: FALSE
O1048566: FALSE
O1048567: FALSE
O1048568: FALSE
O1048569: FALSE
O1048570: FALSE
O1048571: FALSE
O1048572: FALSE
O1048573: FALSE
O1048574: FALSE
O1048575: FALSE

Sheet FLUJO DE CAJA
A1: FLUJO DE CAJA DE INGRESOS Y EGRESOS
A2: OP No. | B2: FECHA | C2: CODIGO | D2: DETALLE | E2: INGRESO EFECTIVO | F2: INGRESO TRANS.ó QR | G2: EGRESO | H2: OBSERVACIONES
A3: 1 | B3: 45292 | D3: REGISTRO INICIAL SIN VALORES OFICIALES | E3: 0 | F3: 0 | G3: 0
A3001: Total INGRESOS & EGRESOS | E3001: =SUBTOTAL(109,Tabla1[INGRESO EFECTIVO]) -> 0 | F3001: =SUBTOTAL(109,Tabla1[INGRESO TRANS.ó QR]) -> 0 | G3001: =SUBTOTAL(109,Tabla1[EGRESO]) -> 0
A3002: SALDO | E3002: =Tabla1[[#Totals],[INGRESO EFECTIVO]]+Tabla1[[#Totals],[INGRESO TRANS.ó QR]]-Tabla1[[#Totals],[EGRESO]] -> 0

Sheet LISTAS
A1: listas
A3: Detalle Ingresos Egresos
A4: INGRESOS CLASES IDIOMAS - ALEMAN
A5: INGRESOS CLASES IDIOMAS - IDIOMA2
A6: INGRESOS CLASES IDIOMAS - IDIOMA3
A7: INGRESOS CUOTA UNICA DE COLEGIO
A8: INGRESOS DE KIOSKO
A9: INGRESOS DEPORTES - DEPORTE4
A10: INGRESOS DEPORTES - DEPORTE5
A11: INGRESOS DEPORTES - FUTBOL
A12: INGRESOS DEPORTES - TENNIS DE MESA
A13: INGRESOS DEPORTES - VOLLEY BALL
... A42: EGRESOS SUELDOS Y SALARIOS

Sheet tarj ANVERSO
A1: CONTROL DE PENSIONES GESTION 2021
A3: Codigo del estudiante : | E3: 2018042
A4: Fecha de inscripción : | E4: =TODAY() -> 45309 | K4: Telefono - Celular | L4: =VLOOKUP(E3,Códigos!A1:L858,7,) -> 62616711m/68462255p/4795082c
A5: Nombre para la factura : | E5: =VLOOKUP(E3,Códigos!A1:L858,5,) -> SUAZNABAR | K5: NIT o CI: | L5: =VLOOKUP(E3,Códigos!A1:L858,6,) -> 4560429
A6: Nombre de Mamá o Papá : | E6: =VLOOKUP(E3,Códigos!A1:L858,4,) -> GISELLE - ESTEBAN | K6: Curso(s) : | L6: =VLOOKUP(E3,Códigos!A1:L858,2,) -> 3ºp-6ºp
A7: Pension mensual : | D7: =VLOOKUP(E3,Códigos!A1:L858,9,) | F7: No. Hermanos(as) : | I7: =VLOOKUP(E3,Códigos!A1:L858,8,) -> 3 | K7: Nivel : | L7: =VLOOKUP(E3,Códigos!A1:L858,12,) -> PRIM - SEC
A8: Nombre del estudiante : | E8: =VLOOKUP(E3,Códigos!A1:L858,3,) -> Mercado Suaznabar Cecilia - Sofia
A9: Rbo...….……Fact……….. | D9: Rbo...….……Fact……….. | G9: Rbo...….……Fact……….. | J9: Rbo...….……Fact……….. | M9: Rbo...….……Fact………..
A10: Bs. ………………….. | D10: Bs. ………………….. | G10: Bs. ………………….. | J10: Bs. ………………….. | M10: Bs. …………………..
A11: Primera Cuota - Feb | D11: Segunda Cuota - Mar | G11: Tercera Cuota - Abril | J11: Cuarta Cuota - Mayo | M11: Quinta Cuota - Junio
A12: Firma P. | D12: Firma P. | G12: Firma P. | J12: Firma P. | M12: Firma P.
A13: _______________________ | D13: _______________________ | G13: _______________________ | J13: _______________________ | M13: _______________________
A16: Rbo...….……Fact……….. | D16: Rbo...….……Fact……….. | G16: Rbo...….……Fact……….. | J16: Rbo...….……Fact……….. | M16: Rbo...….……Fact………..
A17: Bs. ………………….. | D17: Bs. ………………….. | G17: Bs. ………………….. | J17: Bs. ………………….. | M17: Bs. …………………..
A18: Sexta Cuota - Julio | D18: Septima Cuota - Agosto | G18: Octava Cuota - Sept. | J18: Novena Cuota - Octubre | M18: Decima Cuota - Noviem.
A19: Firma P. | D19: Firma P. | G19: Firma P. | J19: Firma P. | M19: Firma P.
A20: _______________________ | D20: _______________________ | G20: _______________________ | J20: _______________________ | M20: _______________________
A26: CONTROL DE PROGRAMA EXTENSIVO DE INGLES Y PROGRAMA
A27: EXTENSIVO MONTESSORI GESTION 2021
A28: Codigo del estudiante : | E28: =+E3 -> 2018042 | H28: CLASES EXTRA : | K28: CH | L28: AL | M28: FR | N28: INS
A29: Fecha de inscripción : | E29: =+E4 -> 45309 | G29: =VLOOKUP(#REF!,Códigos!#REF!,2,) -> #REF! | L29: Curso(s) : | M29: =VLOOKUP(E3,Códigos!A1:L858,2,) -> 3ºp-6ºp
A30: Monto mensual Prog Extensivo Ingles/Montessori : | G30: =VLOOKUP(E28,Códigos!A1:L837,10,) | I30: No. Hnos(as) : | K30: =VLOOKUP(E28,Códigos!A1:L837,8,) -> 3 | L30: Nivel : | M30: =VLOOKUP(E28,Códigos!A1:L837,12,) -> PRIM - SEC
A31: Nombre del estudiante : | E31: =VLOOKUP(E28,Códigos!A1:L837,3,) -> Mercado Suaznabar Cecilia - Sofia
A32: Rbo...….……Fact……….. | D32: Rbo...….……Fact……….. | G32: Rbo...….……Fact……….. | J32: Rbo...….……Fact……….. | M32: Rbo...….……Fact………..
A33: Bs. ………………….. | D33: Bs. ………………….. | G33: Bs. ………………….. | J33: Bs. ………………….. | M33: Bs. …………………..
A34: Primera Cuota - Feb | D34: Segunda Cuota - Mar | G34: Tercera Cuota - Abril | J34: Cuarta Cuota - Mayo | M34: Quinta Cuota - Junio
A35: Firma P. | D35: Firma P. | G35: Firma P. | J35: Firma P. | M35: Firma P.
A36: _______________________ | D36: _______________________ | G36: _______________________ | J36: _______________________ | M36: _______________________
A39: Rbo...….……Fact……….. | D39: Rbo...….……Fact……….. | G39: Rbo...….……Fact……….. | J39: Rbo...….……Fact……….. | M39: Rbo...….……Fact………..
A40: Bs. ………………….. | D40: Bs. ………………….. | G40: Bs. ………………….. | J40: Bs. ………………….. | M40: Bs. …………………..
A41: Sexta Cuota - Julio | D41: Septima Cuota - Agosto | G41: Octava Cuota - Sept. | J41: Novena Cuota - Octubre | M41: Decima Cuota - Noviem.
A42: Firma P. | D42: Firma P. | G42: Firma P. | J42: Firma P. | M42: Firma P.
A43: _______________________ | D43: _______________________ | G43: _______________________ | J43: _______________________ | M43: _______________________

Sheet tarj REVERSO
A4: CURSOS | B4: FECHA | C4: FEBRERO | E4: MARZO | G4: ABRIL | I4: MAYO | K4: JUNIO
A5: Varios | B5: Inicio de clases | C5: Rcbo. | D5: Bs. | E5: Rcbo. | F5: Bs. | G5: Rcbo. | H5: Bs. | I5: Rcbo. | J5: Bs. | K5: Rcbo. | L5: Bs.
A6: ALEMAN
A7: REP. MAT. MONTESSORI
A8: VARIOS 1
A9: VARIOS 2
A12: CURSOS | B12: FECHA | C12: JULIO | E12: AGOSTO | G12: SEPTIEMBRE | I12: OCTUBRE | K12: NOVIEMBRE
A13: Varios | B13: Inicio de clases | C13: Rcbo. | D13: Bs. | E13: Rcbo. | F13: Bs. | G13: Rcbo. | H13: Bs. | I13: Rcbo. | J13: Bs. | K13: Rcbo. | L13: Bs.
A14: ALEMAN
A15: REP. MAT. MONTESSORI
A16: VARIOS 1
A17: VARIOS 2

Sheet Códigos
A1: CODIGO | B1: CURSO | C1: NOMBRE DEL ESTUDIANTE | D1: NOMBRE DE MAMA O PAPA | E1: NOMBRE PARA LA FACTURA | F1: NIT | G1: TELEFONO | H1: HERMANOS | I1: PENSION | J1: PENSION KADI | K1: FECHA DE INSCRIPCION | L1: NIVEL | M1: CODIGO
A2: 2020010 | B2: 3º - 5º Prim | C2: Bayá García Alejandro - Leonardo | D2: KAREN - RAMIRO | E2: BAYA | F2: 4534980 | G2: 77960090m/78331228p | I2: 839 | J2: 371 | L2: PRIMARIA | M2: =A2 -> 2020010
A3: 2018053 | B3: I2 - 4ºp | C3: Aguila Sejas Adrian - Matias Hernan | D3: STEPHANIE - HERNAN | G3: 75497897m/77424577p/4240497c | H3: 2 | K3: 43482 | L3: INIC - PRIM | M3: =A3 -> 2018053
A4: 2018322 | B4: 6º Sec | C4: Aldunate Eterovic Cristian | D4: DRINA - OSCAR | E4: ´ | F4: 3622159 | G4: 70734118m/70757269p | I4: 807 | J4: 598 | K4: 43483 | L4: SECUNDARIA | M4: =A4 -> 2018322
A5: 2018208 | B5: 2ºB SEC | C5: Aldunate Santi Luciana Thais | D5: NORMA - JOSE MIGUEL | G5: 72207433m/70752267p/4507831c | I5: 823 | J5: 610 | L5: SECUNDARIA | M5: =A5 -> 2018208
A6: 2020020 | B6: Inicial 2 | C6: Almanza Merida Alejandra | D6: ZELMY - RODRIGO | E6: MERIDA | F6: 3615014 | G6: 79794429m/70743793p | I6: 839 | J6: 371 | L6: INICIAL | M6: =A6 -> 2020020
A7: 2018079 | B7: 4º - 6º Prim | C7: Almanza Orihuela Carlos Gabriel - Camila Gabriela | D7: GABRIELA - CARLOS | E7: ORIHUELA | F7: 4044384 | G7: 72768653m/68581473p/4247151c | I7: 823 | J7: 364 | K7: 43480 | L7: PRIMARIA | M7: =A7 -> 2018079
A8: 2018027 | B8: 2ºB Prim | C8: Altieri Laserna Florencia | D8: ALEJANDRA - JAVIER | E8: JAVIER ALTIERI | F8: 2878695 | G8: 70713114m/76401410p | I8: 807 | J8: 357 | K8: 43483 | L8: PRIMARIA | M8: =A8 -> 2018027
A9: 2018409 | B9: INICIAL 1 | C9: Alvarez Chaira Vivian Alicia | D9: FABIOLA - JULIO | E9: BEATRIZ LIA | F9: 3036522 | G9: 4351366c/76453202P/76945653M | I9: 823 | J9: 364 | L9: INICIAL | M9: =A9 -> 2018409
A10: 2018444 | B10: INICIAL I | C10: Alvarez Sejas Julio Gabriel | D10: DANIEL-MARCELA | E10: MARCELA SEJAS | F10: 6482564 | G10: 77805759p/79790719m/4236688 | I10: 807 | J10: 357 | K10: 43483 | L10: INICIAL | M10: =A10 -> 2018444
A11: 2018054 | B11: 3ºA Prim | C11: Andia Gonzales Mateo | D11: FABIOLA - ROBERTO | L11: PRIMARIA | M11: =A11 -> 2018054
A12: 2018396 | B12: 4º Prim | C12: Andia Saucedo Maria Jose | D12: MERCEDES - RODRIGO | E12: MERCEDES SAUCEDO | F12: 4185892 | G12: 77490065m/77493206p/4281981p | I12: 823 | J12: 364 | K12: 43483 | L12: PRIMARIA | M12: =A12 -> 2018396
A13: 2018080 | B13: 2ºp - 2ºs | C13: Angulo Balderrama Fabricio Fernando - Santiago Fernando | D13: KAREN - GUIDO | E13: WALDO RODRIGUEZ | F13: 823629 | G13: 70766863m/70360540p/4248931c | H13: 2 | I13: 1646 | J13: 974 | L13: PRIM - SEC | M13: =A13 -> 2018080
A14: 2018149 | B14: I2-6ºp-2ºs | C14: Angulo Cespedes Letizia - Daniel - Alejandra | D14: SILVANA - DOUGLAS | G14: 74305899m/67492168p | H14: 3 | K14: 43483 | L14: INIC-PRIM-SEC | M14: =A14 -> 2018149
A15: 2020070 | B15: 2do-3ro SEC | C15: Antezana Rojas Ariana Guadalupe-Andrea Abril | D15: JAVIER-KARINA | G15: 78333017P/78333019M/4424066C | H15: 2 | L15: SECUNDARIA | M15: =A15 -> 2020070
A16: 2018150 | B16: 6ºp - 1º Sec | C16: Antezana Rojas Santiago Israel - Angela Erika | D16: ERIKA - ISRAEL | G16: 70749010m/70750393p/4365560c | H16: 2 | K16: 43482 | L16: PRIM - SEC | M16: =A16 -> 2018150
A17: 2018350 | B17: 1ro- 4ºp | C17: Antezana Torrez Maite Valentina - Matias Andre | D17: MARIA - MIGUEL | E17: TABORGA | F17: 771441014 | G17: 70342380m/70725450p/4549901c | I17: 1646 | J17: 728 | L17: PRIMARIA | M17: =A17 -> 2018350
A18: 2018276 | B18: 4º Sec | C18: Anzoleaga Nicolas | D18: LORENA | E18: LORENA ANZOLEAGA | F18: 5153524 | G18: 78300066m/4229461c | I18: 823 | J18: 610 | K18: 43483 | L18: SECUNDARIA | M18: =A18 -> 2018276
A19: 2018244 | B19: 2º Sec B | C19: Apaza Ucharico Micaela Araceli | D19: MARINA - FREDDY | E19: UCHARICO | F19: 3361774 | G19: 79978872m/65306708p | I19: 839 | J19: 371 | K19: lunes, 20 de enero de 2020 | L19: SECUNDARIA | M19: =A19 -> 2018244
A20: 2018305 | B20: 4º - 6º Sec | C20: Arandia Cahuana Sigrid Marlene - Elias Sigfrido | D20: MARLENE - SIGFRIDO | E20: SIGFRIDO ARANDIA | F20: 3088967 | G20: 76400295m/77900040p/4458284c | H20: 2 | I20: 1646 | J20: 1220 | K20: 43483 | L20: SECUNDARIA | M20: =A20 -> 2018305
A21: 2020061 | B21: 3ro de SEC | C21: Araoz Covarrubias Mateo Alejandro | D21: HENRY-CAROLA | E21: ARAOZ | F21: 3120919 | G21: 79706668P/70795685M | H21: 0 | I21: 823 | J21: 610 | L21: SECUNDARIA | M21: =A21 -> 2020061
A22: 2018391 | B22: 3º - 6º Prim | C22: Arce Bustos Bianka Melissa - Kevin Freddy | D22: BLANCA - FREDDY | E22: FREDDY ARCE | F22: 1070861 | G22: 76404570m/61791901p/4038158c | H22: 2 | I22: 1646 | J22: 728 | K22: 43482 | L22: PRIMARIA | M22: =A22 -> 2018391
A23: 2020059 | B23: 2do PRIM | C23: Arellano Soliz Amy Fabiola | D23: AMILCAR-FAVIOLA | E23: FAVIOLA SOLIZ | F23: 3148343013 | G23: 70738020P/70799025M | H23: 0 | I23: 823 | J23: 364 | L23: PRIMARIA | M23: =A23 -> 2020059
A24: 2018055 | B24: 2º - 4º Prim | C24: Arias Mancilla Renata Sabrina - Fernanda Antonella | D24: YRENE - AMERICO | E24: YRENE MANCILLA | F24: 3817777 | G24: 71779887m/67573940p/4023654c | H24: 2 | I24: 2(823) | J24: 2(364) | K24: 43483 | L24: PRIMARIA | M24: =A24 -> 2018055
A25: 2020086 | B25: 1ro Prim | C25: Ariel Sotomayor | L25: PRIMARIA | M25: =A25 -> 2020086
A26: 2018223 | B26: 2º Sec | C26: Arispe Salaverry Andre Daniel | D26: DANIEL-SUSANA | G26: 65195354p/72264000m/4452340c | I26: 1646 | J26: 974 | L26: INI-PRIM | M26: =A26 -> 2018223
A27: 2018190 | B27: 1º Sec | C27: Arnez Vallejo Mariana | D27: M. RENEE - RONALD | E27: RONALD ARNEZ | F27: 3143281 | G27: 70384338m/75495723p/4715673c | I27: 839 | J27: 622 | K27: 43479 | L27: SECUNDARIA | M27: =A27 -> 2018190
A28: 2018245 | B28: 2º Sec | C28: Arnez Vergara Rodrigo Hernan | D28: CAROLA - ROGER | E28: ROGER ARNEZ | F28: 949885 | G28: 76470045m/76470046p/4423382c | I28: 839 | J28: 622 | K28: 43483 | L28: SECUNDARIA | M28: =A28 -> 2018245
A29: 2018306 | B29: 6º Sec | C29: Arze Isabella | D29: YIN LING - JORGE | E29: RICARDO ARZE | F29: 3614256010 | G29: 67581249p/72784849m/4487345 | I29: 823 | J29: 610 | K29: 43483 | L29: SECUNDARIA | M29: =A29 -> 2018306
A30: 2020075 | B30: 6to Primaria | C30: Arze Puri Luis Diego | D30: EDWARD-JHOVANA | E30: S/F | F30: S/F | G30: 79755556P/79737191M | H30: 0 | I30: 823 | J30: 364 | L30: PRIMARIA | M30: =A30 -> 2020075
A31: 2018209 | B31: 1º - 6º Prim | C31: Ascarrunz Pereira Isela - Rafaela - Monserrat | D31: KATIUSKA - JAIME | E31: ´ | F31: ´ | G31: 76411152m/79997207p | H31: 3 | I31: ´ | J31: ´ | K31: 43482 | L31: PRIMARIA | M31: =A31 -> 2018209
A32: 2018288 | B32: 5º Sec | C32: Aviles Coll Avril Janelle | D32: JHANNA - GABRIEL | E32: MARISCAL | F32: 3765324 | G32: 77497367m | I32: 823 | J32: 610 | K32: 43482 | L32: SECUNDARIA | M32: =A32 -> 2018288
A33: 2018002 | B33: 3º Prim | C33: Ayala Del Barco Benjamín | D33: CAROLINA - HERNAN | E33: HERNAN AYALA | F33: 3748118 | G33: 76462671m/71466531p/4582301c | I33: 823 | J33: 364 | L33: PRIMARIA | M33: =A33 -> 2018002
A34: 2018127 | B34: 5º Prim | C34: Ayala Gonzales Diana Victoria | D34: CARLA - FREDDY | E34: GONZALES | F34: 3808783013 | G34: 79730401m/70733130p/4422406c | I34: 823 | J34: 364 | K34: 43481 | L34: PRIMARIA | M34: =A34 -> 2018127
A35: 2018210 | B35: 1º Sec | C35: Ayo Fernandez Diego Gabriel | D35: MARCIA - DIEGO | E35: MUKLED | F35: 3390188016 | G35: 77290849m/70612862p/4020400c | I35: 823 | J35: 364 | K35: 43483 | L35: SECUNDARIA | M35: =A35 -> 2018210
A36: 2018028 | B36: 2ºA Prim | C36: Barco Antesana Benjamin | D36: ROBERTO-GRACE | E36: ANTEZANA | F36: 4406840 | G36: 67405642p/70760531M/4257502 | I36: 807 | J36: 357 | K36: 43483 | L36: PRIMARIA | M36: =A36 -> 2018028
A37: 2018447 | B37: 4º Sec | C37: Barrera Aguirre Estefanie | D37: MARIANELA | E37: MARIANELA AGUIRRE | F37: 3753285 | G37: 70716204 | K37: 43483 | L37: SECUNDARIA | M37: =A37 -> 2018447
A38: 2018081 | B38: 4º - 5º Prim | C38: Bautista Jaramillo Rodrigo Enrique - Camila Antonette | D38: ESTELA - ENRIQUE | E38: ENRIQUE BAUTISTA | F38: 5032188 | G38: 76401066m/76401269p/67479267o | H38: 2 | K38: 43481 | L38: PRIMARIA | M38: =A38 -> 2018081
A39: 2018029 | B39: 3º Prim | C39: Becerra Soria Addie Renata | D39: VIVIAN - LUDWING | E39: BECERRA LUDWING | F39: 3599727 | G39: 70768677m/76401141p/4443067c | I39: 823 | J39: 364 | K39: 43482 | L39: PRIMARIA | M39: =A39 -> 2018029
A40: 2020011 | B40: 1º SEC | C40: Bellido Villegas Dasha | D40: CLAUDIA - RAMIRO | G40: 69814291m | L40: SECUNDARIA | M40: =A40 -> 2020011
A41: 2018367 | B41: 2º Prim | C41: Beltran Avila Danna Sofia | D41: GABRIELA - MAURICIO | E41: ANGELA AVILA | F41: 7892594 | G41: 79783816m/70717798p | I41: 839 | J41: 371 | K41: 43480 | L41: PRIMARIA | M41: =A41 -> 2018367
A42: 2018307 | B42: 6º Sec | C42: Beltran Camacho Thais Noelia | D42: ROGER-FABIOLA | G42: 44878833p/70727105m | I42: 823 | J42: 410 | L42: SECUNDARIA | M42: =A42 -> 2018307
A43: 2020022 | B43: 4to Prim | C43: Benavidez Ruiz Helen Gabriela | D43: JUAN MIGUEL-ESTEFANIA | E43: JUAN MIGUEL BENAVIDEZ GUTIERREZ | F43: 5238051 | G43: 70303477p/60378712m | H43: 0 | I43: 839 | J43: 371 | K43: lunes, 20 de enero de 2020 | L43: PRIMARIA | M43: =A43 -> 2020022
A44: 2018056 | B44: 4º Prim | C44: Bengolea Aranibar Florencia Agustina | D44: ANTONELLA - DIEGO | E44: ARJICONS SRL | F44: 171144029 | G44: 72274742m/72200781p/4241766c | I44: 823 | J44: 364 | K44: 43480 | L44: PRIMARIA | M44: =A44 -> 2018056
A45: 2018338 | B45: Inic I - 1ºPrim | C45: Betti Goitia Genaro Emanuel - Isis | D45: ANA CECILIA - MATHIAS | G45: 72252752m/72719292p | K45: 43479 | L45: INI - PRIM | M45: =A45 -> 2018338
A46: 2018173 | B46: Inicial 1 | C46: Block Vargas Sara Catalina | D46: CARMEN - JUAN ALBERTO | E46: JUAN ALBERTO BLOCK MERRITT | F46: 3334883 | G46: 72772761m/72712073p/4434471c | H46: 2 | I46: 839 | J46: 371 | K46: 43482 | L46: INICIAL | M46: =A46 -> 2018173
A47: 2018363 | B47: 2º Prim | C47: Bonadona Sanchez José Manuel | D47: ROCIO - ADOLFO | E47: ROCIO SANCHEZ | F47: 5191508 | G47: 76403182m/72200403p/4281798c | I47: 823 | J47: 364 | K47: 43480 | L47: PRIMARIA | M47: =A47 -> 2018363
A48: 2018129 | B48: 5º Prim | C48: Bonuccelli Fernandez Nicolas Rafael | D48: CARLA - ANDRES | E48: CARLA FERNANDEZ | F48: 5152745015 | G48: 78309460m/77400202p/4249362c | K48: 43480 | L48: PRIMARIA | M48: =A48 -> 2018129
A49: 2018082 | B49: 2º - 4ºPrim | C49: Borda Rojas Victoria Micaela - Oscar Mateo | D49: M. ELENA - OSCAR | E49: BORDA | F49: 5185708 | G49: 70393643m/77483202p | H49: 2 | I49: 1646 | J49: 728 | K49: 43479 | L49: PRIMARIA | M49: =A49 -> 2018082
A50: 2018289 | B50: 5º Sec | C50: Bottega Leonardo Mateo | D50: CLAUDIA | E50: CLAUDIA BOTTEGA | F50: 3028010 | G50: 70712001m/4531322c | I50: 839 | J50: 622 | K50: 43483 | L50: SECUNDARIA | M50: =A50 -> 2018289
A51: 2018412 | B51: Inicial I-2ºA Prim | C51: Boulocq Gabela Sebastian-Nicolas | D51: DANIELA - DIEGO | G51: 72240462m/70762391p | H51: 2 | I51: 1646 | J51: 728 | L51: INI-PRIM | M51: =A51 -> 2018412
A52: 2018425 | B52: INICIAL II | C52: Bravo Gutierrez Mia Isabella | D52: PAOLO-NATALY | E52: GERMAN GUTIERREZ | F52: 959483 | G52: 70306406p/77408444m/4406049 | I52: 823 | J52: 364 | L52: INICIAL | M52: =A52 -> 2018425
A53: 2018225 | B53: 3ºp - 2ºs | C53: Bruckner Laserna Claudio - Mila | D53: MARIANA - IVAN | G53: 65362200m/77408000p | H53: 2 | I53: 2(807) | J53: 955 | L53: PRIM - SEC | M53: =A53 -> 2018225
A54: 2018030 | B54: 2ºB Prim | C54: Bucci Ojeda Jair | D54: VERTA - FRANCISCO | G54: 67528808m/76953919p | I54: 807 | J54: 357 | K54: 43483 | L54: PRIMARIA | M54: =A54 -> 2018030
A55: 2018336 | B55: 1ro Sec 5to Sec | C55: Buitrago Ortega M. Victoria-M. Emilia-Pedro | D55: KATIHUSKA - RAMON | G55: 79950455m/4553882c/4229707Trab | I55: 1646 | J55: 1936 | L55: SECUNDARIA | M55: =A55 -> 2018336
A56: 2018410 | B56: 5º Sec | C56: Burgoa Diaz Mateo | D56: ELIANA - JAIME | E56: ALEJANDRA GUMUCIO | F56: 3592051 | G56: 72224011m/71733958p | I56: 839 | J56: 610 | L56: SECUNDARIA | M56: =A56 -> 2018410
A57: 2018083 | B57: 4º Prim | C57: Bustillo Flores Sofia Victoria | D57: ADRIANA - LUIS DANIEL | E57: FLORES | F57: 4995721 | G57: 71721826m/70132204p | I57: 839 | J57: 371 | K57: 43480 | L57: PRIMARIA | M57: =A57 -> 2018083
A58: 2018389 | B58: 1º Prim | C58: Bustinza Delgado Mariana | D58: ANA - BRIAN | E58: BRIAN BUSTINZA | F58: 4325132010 | G58: 70762614m/70766526p/4365774c | I58: 823 | J58: 364 | K58: 43482 | L58: PRIMARIA | M58: =A58 -> 2018389
A59: 2018084 | B59: 3ºB Prim | C59: Caballero Carrasco Sofia Camila | L59: PRIMARIA | M59: =A59 -> 2018084
A60: 2018415 | B60: 1º Prim | C60: Caballero Cortes Julia | D60: JULIO-ALEJANDRA | G60: 76379260p/76465214m | I60: 807 | J60: 357 | K60: 43483 | L60: PRIMARIA | M60: =A60 -> 2018415
A61: 2018434 | B61: Inicial 1 | C61: Caballero Morales Sofia Rafaela | D61: ANA LIA - JOSE ANTONIO | E61: CABALLERO | F61: 3144841 | G61: 75465431P/70773664M/4240323C | K61: 43483 | L61: INICIAL | M61: =A61 -> 2018434
A62: 2020005 | B62: 2do SEC | C62: Cabezas Villagra Samuel Enrique | D62: ALVARO-INGRID | E62: INGRID VILLAGRA | F62: 3814837 | G62: 72205647m/4248478C | H62: 0 | I62: 839 | J62: 622 | K62: lunes, 20 de enero de 2020 | L62: SECUNDARIA | M62: =A62 -> 2020005
A63: 2020082 | B63: 1ro de primaria | C63: Cabezas Zambrana Sarai Micaela | D63: HOMAR-NORMA | E63: CABEZAS | F63: 5901162 | G63: 72291277P/76953620M | H63: 0 | I63: 823 | J63: 364 | L63: PRIMARIA | M63: =A63 -> 2020082
A64: 2018376 | B64: 1º Sec | C64: Caero Bermudez Nicolas | D64: ERIKA - ARIEL | E64: CAERO | F64: 4477762010 | G64: 70350264m/70350156p/4669283c | I64: 823 | J64: 610 | K64: 43481 | L64: SECUNDARIA | M64: =A64 -> 2018376
A65: 2018381 | B65: Inicial 2 | C65: Calbimonte Zurita Alejandra Belen | D65: ANDREA - DANIEL | E65: RENE ZURITA | F65: 768133010 | G65: 70760940m/75502310p/4519368c | I65: 823 | J65: 364 | K65: 43481 | L65: INICIAL | M65: =A65 -> 2018381
A66: 2018371 | B66: I2 - 5º p | C66: Calderon Callisaya Emma A. - Fabio E. | D66: HEIDY - CARLO | E66: CALDERON | F66: 4394838 | G66: 72712093m/79992460p/4121974c | H66: 2 | I66: 2(839) | J66: 2(371) | K66: 43481 | L66: INI - PRIM | M66: =A66 -> 2018371
A67: 2018413 | B67: 1ro de PRIM | C67: Calderon Sanchez Jaime Anibal | D67: MARIVEL-JAIME | G67: 79709596p/63946391m/4425396 | L67: PRIMARIA | M67: =A67 -> 2018413
A68: 2018435 | B68: 5º Sec | C68: Camacho Anaya Lucas | D68: YERKO-JEMMY | G68: 68497527p/72204977 | I68: 807 | J68: 93 | L68: SECUNDARIA | M68: =A68 -> 2018435
A69: 2018401 | B69: 6º Sec | C69: Camacho Garrón Daniel Alejandro | D69: KATTY - MARCO ANTONIO | E69: MARCO CAMACHO | F69: 3575254 | G69: 70716857m/72202872p | I69: 823 | J69: 610 | K69: 43483 | L69: SECUNDARIA | M69: =A69 -> 2018401
A70: 2018130 | B70: 5ºB Prim | C70: Camacho Pando Marcos Octavio | D70: MARITZA - MARCOS | E70: CAMACHO | F70: 4537172015 | G70: 4523880C/60721248P | I70: 823 | J70: 364 | K70: jueves, 23 de enero de 2020 | L70: PRIMARIA | M70: =A70 -> 2018130
A71: 2018085 | B71: 4º Prim | C71: Camacho Reyes Alejandra Noemi | D71: DANIELA - DANIEL | E71: REYES | F71: 4257907 | G71: 77490248m | I71: 839 | J71: 371 | K71: 43480 | L71: PRIMARIA | M71: =A71 -> 2018085
A72: 2020027 | B72: Inicial 2 | C72: Camacho Vargas Antonela Valery | D72: MELVY - ABELARDO | E72: CAMACHO | F72: 6434082 | G72: 70308893M/70736082P/4660814C | I72: 823 | J72: 364 | L72: INICIAL | M72: =A72 -> 2020027
A73: 2018423 | B73: 1ro Sec | C73: Camacho Wilstermann Santiago Nicolas | D73: DANIEL-CRISTHY | G73: 70716060p/68580090m/4019198 | I73: 807 | J73: 598 | K73: 43481 | L73: SECUNDARIA | M73: =A73 -> 2018423
A74: 2018405 | B74: 1º - 2º Prim | C74: Camargo Schnorr Luciana - Victoria | D74: VIVIAN | G74: 77999623m/4792199c | H74: 2 | I74: 2(807) | J74: 2(357) | K74: 43483 | L74: PRIMARIA | M74: =A74 -> 2018405
A75: 2018453 | B75: 1ro Primaria | C75: Campos Anaya Ignacio Santiago | D75: JOSE-MONICA | G75: 78910737m/77939023p | I75: 823 | J75: 364 | L75: PRIMARIA | M75: =A75 -> 2018453
A76: 2020008 | B76: Inicial I | C76: Campos Hermosa Ayar Ulises | D76: WARA - JORGE | E76: FERNANDEZ | F76: 986417016 | G76: 68515643m/72219643p/4248620c | I76: 839 | J76: 371 | L76: INICIAL | M76: =A76 -> 2020008
A77: 2018403 | B77: 1ro PRIM | C77: Campos Maida Amir | D77: JESICA - HERNAN | E77: JESICA MERIDA | F77: 996155 | G77: 72212230m/76408000p/4450278c | I77: 839 | J77: 371 | K77: lunes, 20 de enero de 2020 | L77: PRIMARIA | M77: =A77 -> 2018403
A78: 2018277 | B78: 2º Prim | C78: Canedo Mendoza Juan Marco | D78: LESLIE - MARCO | E78: MARCO ANTONIO CANEDO MALDONADO | F78: 4535982019 | G78: 76490242m/77423319p | K78: 43481 | L78: PRIMARIA | M78: =A78 -> 2018277
A79: 2018003 | B79: 2ºA Prim | C79: Cano Herbas Arami Leticia | D79: NAYRA-WALTER | G79: 72761555m/72782061 ABUELO | H79: 2 | I79: 750 | K79: 43480 | L79: PRIMARIA | M79: =A79 -> 2018003
A80: 2018424 | B80: Inicial 1 | C80: Cardozo Jose Manuel | D80: MANUEL(abuelo) | G80: 76466707p/4408633c | I80: 823 | J80: 364 | K80: miercoles,30 de enero de 2019 | L80: INICIAL | M80: =A80 -> 2018424
A81: 2018463 | B81: 1ro Prim | C81: Carrasco Da Rocha Aaron | D81: GLIELBER- DEIDY | G81: 73774920-4584760 ABUELA | I81: 807 | J81: 357 | K81: Martes, 7 de mayo de 2019 | L81: PRIMARIA | M81: =A81 -> 2018463
A82: 2018291 | B82: 4º Sec | C82: Carrasco Gamez Stephanie Fabiola | D82: FABIOLA - CRISTIAN | E82: CARRASCO | G82: 70775719p/4291366c | I82: 807 | J82: 598 | K82: 43483 | L82: SECUNDARIA | M82: =A82 -> 2018291
A83: 2018057 | B83: 3ºp-4ºp-4ºs | C83: Carrasco Riveiro Augusto - Valentina - Victoria | D83: REBEKA - MARCO | G83: 67452302m/60706979p | H83: 3 | K83: 43483 | L83: PRIM - SEC | M83: =A83 -> 2018057
A84: 2018258 | B84: 3º Sec | C84: Carreon Villagomez Angel Albert | D84: FRANZ-KATTY | E84: JORGE PEREDO | F84: 3029214 | G84: 70722260p/70728635m | I84: 823 | J84: 610 | L84: SECUNDARIA | M84: =A84 -> 2018258
A85: 2018468 | B85: 3ro B | C85: Carvajal Arispe Paula Isabela | D85: ALBERTO-LOYDA | G85: 75976759p/78323000m | H85: 0 | I85: 807 | J85: 357 | K85: Lunes 1 de agosto de 2019 | L85: PRIMARIA | M85: =A85 -> 2018468
A86: 2018152 | B86: 3ro B | C86: Carvajal Rodriguez Sara Gabriela - Sofia Valentina | D86: FABIOLA - ROBERTO | G86: 79367830m/70709503p | H86: 2 | K86: 43481 | L86: PRIM - SEC | M86: =A86 -> 2018152
A87: 2018211 | B87: 1ºs-2ºs-4ºs-1ºp | C87: Castellon Briana-Adrian-Maya - Campanini Samanta | D87: AMBAR - OSCAR | E87: OSCAR CAMPANINI | F87: 4450021 | G87: 79773895m/70344801p | H87: 4 | K87: 43483 | L87: PRIM - SEC | M87: =A87 -> 2018211
A88: 2018086 | B88: I1 - 3ºp | C88: Castro Calizaya Andrea Maisha - Russell Lucia | D88: DIANARDA - PEDRO | G88: 78316187m/79995674p/4310656c | H88: 2 | K88: 43483 | L88: INIC - PRIM | M88: =A88 -> 2018086
A89: 2017050 | B89: 3º - 5º Prim | C89: Castro Dorado Carlos Arturo - Nicolas Ignacio | D89: CINTHIA - JUAN CARLOS | E89: CASTRO | F89: 3970922 | G89: 79340415m | H89: 2 | I89: 1646 | J89: 728 | K89: 43480 | L89: PRIMARIA | M89: =A89 -> 2017050
A90: 2020045 | B90: Inical 1 | C90: Castro Humphries Hadasa | D90: MICHELLE - GABRIEL | E90: GABRIEL CASTRO ORTEGA | F90: 5263065 | G90: 77914690m/77900285p | I90: 823 | J90: 364 | L90: INICIAL | M90: =A90 -> 2020045
A91: 2018395 | B91: Inicial 2 | C91: Castro Machado Hugo César | D91: KARINA - CESAR | E91: CASTRO | F91: 4018039 | G91: 67497695m/77427893p/4582818c | I91: 823 | J91: 364 | K91: 43483 | L91: INICIAL | M91: =A91 -> 2018395
A92: 2017051 | B92: 2ºA Prim | C92: Castro Muriel Rafaela Belen | D92: LISE - JULIO | E92: LISE MURIEL | F92: 5269731 | G92: 70736468m/70760900p | I92: 703 | J92: 248 | K92: 43479 | L92: PRIMARIA | M92: =A92 -> 2017051
A93: 2018006 | B93: Inicial 1 | C93: Castro Oropeza Julieta Thais | D93: DAMARIS - OSVALDO | G93: 70377993m/4425055c | H93: 1 | L93: INICIAL | M93: =A93 -> 2018006
A94: 2018058 | B94: 3ºA Prim | C94: Castro Salcedo Alejandro Mateo | L94: PRIMARIA | M94: =A94 -> 2018058
A95: 2020062 | B95: 2do PRIM | C95: Cespedes Ortega Anneli Kathleen | D95: ADRIAN-JHANEL | E95: S/F | F95: S/F | G95: 74354972P/70360679M | H95: 0 | I95: 715 | J95: 0 | L95: PRIMARIA | M95: =A95 -> 2020062
A96: 2020046 | B96: 4º Prim | C96: Chacón Pérez Bruno Alejandro | D96: MAYRA - EVER | E96: PEREZ | F96: 3768771 | G96: 60366015m/79363509p | I96: 823 | J96: 364 | L96: PRIMARIA | M96: =A96 -> 2020046
A97: 2018454 | B97: Inicial 2 | C97: Chanez Montaño Stefan Gael | D97: NEYDDY - ROMER | G97: 72204969m/71441774p | I97: 823 | J97: 364 | K97: 43482 | L97: INICIAL | M97: =A97 -> 2018454
A98: 2018031 | B98: 2ºB Prim | C98: Chavez Nogales Andrés | D98: MARIA - CESAR | E98: ZUBIETA | F98: 824305 | G98: 70390357m/77442785p/4534266p | I98: 807 | J98: 357 | K98: 43483 | L98: PRIMARIA | M98: =A98 -> 2018031
A99: 2018059 | B99: 4ºp - 2ºs | C99: Choque Lopez Urias Joaquin - Jonan Nacor | D99: ANEL - WALDO | E99: WALDO CHOQUE | F99: 4474356014 | G99: 77922227m/77922422p | H99: 2 | K99: 43480 | L99: PRIM - SEC | M99: =A99 -> 2018059
A100: 2020016 | B100: 3ºp-5ºp-2ºs | C100: Choque Vega Mayte - Mario - Maria | D100: ANA - MARIO | E100: MARIO RAMIRO CHOQUE | F100: 4382504014 | G100: 70751369m/71479267p | H100: 3 | L100: PRIM - SEC | M100: =A100 -> 2020016
...

Sheet SUELDOS
B1: PLANILLA DE SUELDOS DOCENTES
B2: MES | E2: No. | F2: Bs. | G2: - Horas X | H2: Bs. DESC. | I2: Bs. DESC.
B3: 2024 | E3: Horas | F3: HABER | G3: Atra y Faltas | H3: Por F/Atrs | I3: ADELANTO | J3: LIQUIDO
A4: Nro | B4: APELLIDOS Y NOMBRE | C4: MATERIA | D4: Nro. C.I. | E4: MENSUAL | F4: MENSUAL | G4: MENSUAL | H4: MENSUAL | I4: MENSUAL | J4: PAGABLE
A5: 1 | B5: Vesna Lazaneo | C5: Directora | D5: 3603941 CB. | E5: 160 | F5: 6000 | G5: 0 | H5: =IF(B5="","",(F5/E5)*G5) -> 0 | I5: 0 | J5: =IF(B5="","",F5-H5-I5) -> 6000
A6: =A5+1 -> 2 | B6: David Antequera | C6: Director | D6: 3375300 CB. | E6: 160 | F6: 6000 | G6: 0 | H6: =IF(B6="","",(F6/E6)*G6) -> 0 | I6: 0 | J6: =IF(B6="","",F6-H6-I6) -> 6000
A7: =A6+1 -> 3 | B7: Felicidad Benito | C7: Secretaria | D7: 2797745 Or. | E7: 160 | F7: 4500 | G7: 0 | H7: =IF(B7="","",(F7/E7)*G7) -> 0 | I7: 0 | J7: =IF(B7="","",F7-H7-I7) -> 4500
A8: =A7+1 -> 4 | B8: Carmen Gomez | C8: Psicóloga | D8: 3109973 Or. | E8: 160 | F8: 4500 | G8: 0 | H8: =IF(B8="","",(F8/E8)*G8) -> 0 | I8: 0 | J8: =IF(B8="","",F8-H8-I8) -> 4500
A9: =A8+1 -> 5 | B9: Rocio Janette Cruz | C9: Maternal | D9: 7908651CB. | E9: 160 | F9: 2092 | G9: 0 | H9: =IF(B9="","",(F9/E9)*G9) -> 0 | I9: 0 | J9: =IF(B9="","",F9-H9-I9) -> 2092
A10: =A9+1 -> 6 | B10: Fabiola Herrera | C10: Aux Inicial 1 | D10: 7929725 CB. | E10: 160 | F10: 1160.5 | G10: 0 | H10: =IF(B10="","",(F10/E10)*G10) -> 0 | I10: 0 | J10: =IF(B10="","",F10-H10-I10) -> 1160.5
A11: =A10+1 -> 7 | B11: Lucy Rodriguez | C11: Maternal B | D11: 3800831 Lp. | E11: 160 | F11: 2000 | G11: 0 | H11: =IF(B11="","",(F11/E11)*G11) -> 0 | I11: 0 | J11: =IF(B11="","",F11-H11-I11) -> 2000
A12: =A11+1 -> 8 | B12: Marlene Quiñonez | C12: Prof. Mater. | D12: 5238814 CB. | E12: 160 | F12: 1350 | G12: 0 | H12: =IF(B12="","",(F12/E12)*G12) -> 0 | I12: 0 | J12: =IF(B12="","",F12-H12-I12) -> 1350
A13: =A12+1 -> 9 | B13: Lilian Herrera | C13: Prof Inicial 3 | D13: 7881370 CB. | E13: 160 | F13: 2077 | G13: 0 | H13: =IF(B13="","",(F13/E13)*G13) -> 0 | I13: 0 | J13: =IF(B13="","",F13-H13-I13) -> 2077
A14: =A13+1 -> 10 | B14: Romina Edith Mamani Cruz | C14: Aux Inicial 3 | D14: 12874630 CB. | E14: 160 | F14: 1287 | G14: 0 | H14: =IF(B14="","",(F14/E14)*G14) -> 0 | I14: 0 | J14: =IF(B14="","",F14-H14-I14) -> 1287
A15: =A14+1 -> 11 | B15: Nancy Soria | C15: Prof Inicial 2 | D15: 2337042 Lp. | E15: 160 | F15: 3571 | G15: 0 | H15: =IF(B15="","",(F15/E15)*G15) -> 0 | I15: 0 | J15: =IF(B15="","",F15-H15-I15) -> 3571
A16: =A15+1 -> 12 | B16: Thelma Cortez | C16: Aux Inicial 2 | D16: 5107060 CB. | E16: 160 | F16: 1656 | G16: 0 | H16: =IF(B16="","",(F16/E16)*G16) -> 0 | I16: 0 | J16: =IF(B16="","",F16-H16-I16) -> 1656
A17: =A16+1 -> 13 | B17: Karina Velasquez | C17: Prof. Inicial 4 | D17: 5253008 CB. | E17: 160 | F17: 3000 | G17: 0 | H17: =IF(B17="","",(F17/E17)*G17) -> 0 | I17: 0 | J17: =IF(B17="","",F17-H17-I17) -> 3000
... A28: =A27+1 -> 24 | B28: Ana Claudia Lafuente | C28: Prof. Ingles | D28: 6442423 CB. | E28: 160 | F28: 3387 | G28: 0 | H28: =IF(B28="","",(F28/E28)*G28) -> 0 | I28: 0 | J28: =IF(B28="","",F28-H28-I28) -> 3387
A29: =A28+1 -> 25 | B29: Cecilia Fernandez | C29: Prof, 4to A | D29: 0 | E29: 160 | F29: 2500 | G29: 0 | H29: =IF(B29="","",(F29/E29)*G29) -> 0 | I29: 0 | J29: =IF(B29="","",F29-H29-I29) -> 2500
A30: =A29+1 -> 26 | B30: Susana Marcus | C30: Sociales Ingles | D30: 5234822 CB. | E30: 160 | F30: 3000 | G30: 0 | H30: =IF(B30="","",(F30/E30)*G30) -> 0 | I30: 0 | J30: =IF(B30="","",F30-H30-I30) -> 3000
A31: =A30+1 -> 27 | B31: Vanessa Bustillos | C31: Ciencias | D31: 4400632 CB. | E31: 160 | F31: 4538 | G31: 0 | H31: =IF(B31="","",(F31/E31)*G31) -> 0 | I31: 0 | J31: =IF(B31="","",F31-H31-I31) -> 4538
A32: =A31+1 -> 28 | B32: Carmen Zambrana | C32: Inglés | D32: 2475663 CB. | E32: 160 | F32: 3400 | G32: 0 | H32: =IF(B32="","",(F32/E32)*G32) -> 0 | I32: 0 | J32: =IF(B32="","",F32-H32-I32) -> 3400
A33: =A32+1 -> 29 | B33: Eugenia Condori | C33: Matemáticas | D33: 5240336 CB. | E33: 160 | F33: 3100 | G33: 0 | H33: =IF(B33="","",(F33/E33)*G33) -> 0 | I33: 0 | J33: =IF(B33="","",F33-H33-I33) -> 3100
A34: =A33+1 -> 30 | B34: Ana Gabriela Villarroel | C34: Lenguaje | D34: 6551091 CB. | E34: 160 | F34: 2200 | G34: 0 | H34: =IF(B34="","",(F34/E34)*G34) -> 0 | I34: 0 | J34: =IF(B34="","",F34-H34-I34) -> 2200
A35: =A34+1 -> 31 | B35: Milena Solares | C35: Manualidades | D35: 969916 CB. | E35: 160 | F35: 1000 | G35: 0 | H35: =IF(B35="","",(F35/E35)*G35) -> 0 | I35: 0 | J35: =IF(B35="","",F35-H35-I35) -> 1000
A36: =A35+1 -> 32 | B36: Rafael Antequera | C36: Fisica | D36: 3399098 CB. | E36: 160 | F36: 3900 | G36: 0 | H36: =IF(B36="","",(F36/E36)*G36) -> 0 | I36: 0 | J36: =IF(B36="","",F36-H36-I36) -> 3900
A37: =A36+1 -> 33 | B37: Margaret Giancalone | C37: Inglés | D37: 0 | E37: 160 | F37: 3000 | G37: 0 | H37: =IF(B37="","",(F37/E37)*G37) -> 0 | I37: 0 | J37: =IF(B37="","",F37-H37-I37) -> 3000
A38: =A37+1 -> 34 | B38: Mariela Reyna | C38: Bio.Español | D38: 3117036 CB. | E38: 160 | F38: 2600 | G38: 0 | H38: =IF(B38="","",(F38/E38)*G38) -> 0 | I38: 0 | J38: =IF(B38="","",F38-H38-I38) -> 2600
A39: =A38+1 -> 35 | B39: Paola Luzio | C39: Lenguaje | D39: 3764931 CB. | E39: 160 | F39: 1944 | G39: 0 | H39: =IF(B39="","",(F39/E39)*G39) -> 0 | I39: 0 | J39: =IF(B39="","",F39-H39-I39) -> 1944
A40: =A39+1 -> 36 | B40: Marcelo Rodriguez | C40: Historia | D40: 4401361 CB. | E40: 160 | F40: 4220 | G40: 0 | H40: =IF(B40="","",(F40/E40)*G40) -> 0 | I40: 0 | J40: =IF(B40="","",F40-H40-I40) -> 4220
A41: =A40+1 -> 37 | B41: Deyna Castro | C41: Secr Secundaria | D41: 6550274CB. | E41: 160 | F41: 2637.5 | G41: 0 | H41: =IF(B41="","",(F41/E41)*G41) -> 0 | I41: 0 | J41: =IF(B41="","",F41-H41-I41) -> 2637.5
A42: =A41+1 -> 38 | B42: Victor Velarde | C42: Mantenimi. | D42: 0 | E42: 160 | F42: 3050 | G42: 0 | H42: =IF(B42="","",(F42/E42)*G42) -> 0 | I42: 0 | J42: =IF(B42="","",F42-H42-I42) -> 3050
A43: =A42+1 -> 39 | B43: Simon Martinez | C43: Regente | D43: 0 | E43: 160 | F43: 2900 | G43: 0 | H43: =IF(B43="","",(F43/E43)*G43) -> 0 | I43: 0 | J43: =IF(B43="","",F43-H43-I43) -> 2900
A44: =A43+1 -> 40 | B44: Osvaldo Terán | C44: Jardinería | D44: 0 | E44: 160 | F44: 1800 | G44: 0 | H44: =IF(B44="","",(F44/E44)*G44) -> 0 | I44: 0 | J44: =IF(B44="","",F44-H44-I44) -> 1800
A45: =A44+1 -> 41 | B45: Martha Condori | C45: Cocina | D45: 0 | E45: 160 | F45: 2215.5 | G45: 0 | H45: =IF(B45="","",(F45/E45)*G45) -> 0 | I45: 0 | J45: =IF(B45="","",F45-H45-I45) -> 2215.5
A46: =A45+1 -> 42 | B46: Rosmery Mercado | C46: Cocina | D46: 0 | E46: 160 | F46: 2005 | G46: 0 | H46: =IF(B46="","",(F46/E46)*G46) -> 0 | I46: 0 | J46: =IF(B46="","",F46-H46-I46) -> 2005
A47: =A46+1 -> 43 | B47: Ana Maria Goitia | C47: Cocina | D47: 0 | E47: 160 | F47: 1750 | G47: 0 | H47: =IF(B47="","",(F47/E47)*G47) -> 0 | I47: 0 | J47: =IF(B47="","",F47-H47-I47) -> 1750
A48: =A47+1 -> 44 | B48: Enrriqueta Pinaya | C48: Cocina | D48: 0 | E48: 160 | F48: 1900 | G48: 0 | H48: =IF(B48="","",(F48/E48)*G48) -> 0 | I48: 0 | J48: =IF(B48="","",F48-H48-I48) -> 1900
A49: =A48+1 -> 45 | B49: Betty Colquehuanca | C49: Portera | D49: 0 | E49: 160 | F49: 1741 | G49: 0 | H49: =IF(B49="","",(F49/E49)*G49) -> 0 | I49: 0 | J49: =IF(B49="","",F49-H49-I49) -> 1741
A50: =A49+1 -> 46 | B50: Carla Balderrama | C50: limpieza | D50: 4390163 CB. | E50: 160 | F50: 1800 | G50: 0 | H50: =IF(B50="","",(F50/E50)*G50) -> 0 | I50: 0 | J50: =IF(B50="","",F50-H50-I50) -> 1800
A51: =A50+1 -> 47 | B51: Casiano | C51: Jardinero | D51: 0 | E51: 160 | F51: 2500 | G51: 0 | H51: =IF(B51="","",(F51/E51)*G51) -> 0 | I51: 0 | J51: =IF(B51="","",F51-H51-I51) -> 2500
A52: =A51+1 -> 48 | B52: Nilsa Franco | C52: Auxiliar | D52: 0 | E52: 160 | F52: 1000 | G52: 0 | H52: =IF(B52="","",(F52/E52)*G52) -> 0 | I52: 0 | J52: =IF(B52="","",F52-H52-I52) -> 1000
A53: =A52+1 -> 49 | B53: Yoli Aguilar | C53: Cocina | D53: E-10131741 | E53: 160 | F53: 1000 | G53: 0 | H53: =IF(B53="","",(F53/E53)*G53) -> 0 | I53: 0 | J53: =IF(B53="","",F53-H53-I53) -> 1000
A54: =A53+1 -> 50 | B54: Rogelia Jimenez | C54: Limpieza | D54: 0 | E54: 160 | F54: 1000 | G54: 0 | H54: =IF(B54="","",(F54/E54)*G54) -> 0 | I54: 0 | J54: =IF(B54="","",F54-H54-I54) -> 1000
A55: =A54+1 -> 51 | B55: Karina | C55: limpieza | D55: 0 | E55: 160 | F55: 1000 | G55: 0 | H55: =IF(B55="","",(F55/E55)*G55) -> 0 | I55: 0 | J55: =IF(B55="","",F55-H55-I55) -> 1000
A56: =A55+1 -> 52 | B56: Maribel | C56: Cocina | D56: 0 | E56: 160 | F56: 1000 | G56: 0 | H56: =IF(B56="","",(F56/E56)*G56) -> 0 | I56: 0 | J56: =IF(B56="","",F56-H56-I56) -> 1000
A57: =A56+1 -> 53 | B57: Mishell | C57: Cocina | D57: 0 | E57: 160 | F57: 1000 | G57: 0 | H57: =IF(B57="","",(F57/E57)*G57) -> 0 | I57: 0 | J57: =IF(B57="","",F57-H57-I57) -> 1000
A58: =A57+1 -> 54 | B58: Roxana Burgoa | C58: limpieza | D58: 0 | E58: 160 | F58: 1000 | G58: 0 | H58: =IF(B58="","",(F58/E58)*G58) -> 0 | I58: 0 | J58: =IF(B58="","",F58-H58-I58) -> 1000
A59: =A58+1 -> 55 | B59: Vesna Lazaneo | C59: Directora | D59: 3603941 CB. | E59: 160 | F59: 1000 | G59: 0 | H59: =IF(B59="","",(F59/E59)*G59) -> 0 | I59: 0 | J59: =IF(B59="","",F59-H59-I59) -> 1000
A60: =A59+1 -> 56 | B60: David Antequera | C60: Director | D60: 3375300 CB. | E60: 160 | F60: 1000 | G60: 0 | H60: =IF(B60="","",(F60/E60)*G60) -> 0 | I60: 0 | J60: =IF(B60="","",F60-H60-I60) -> 1000
A61: =A60+1 -> 57 | B61: Felicidad Benito | C61: Secretaria | D61: 2797745 Or. | E61: 160 | F61: 1000 | G61: 0 | H61: =IF(B61="","",(F61/E61)*G61) -> 0 | I61: 0 | J61: =IF(B61="","",F61-H61-I61) -> 1000
A62: =A61+1 -> 58 | B62: Carmen Gomez | C62: Psicóloga | D62: 3109973 Or. | E62: 160 | F62: 1000 | G62: 0 | H62: =IF(B62="","",(F62/E62)*G62) -> 0 | I62: 0 | J62: =IF(B62="","",F62-H62-I62) -> 1000
A63: =A62+1 -> 59 | B63: Rocio Janette Cruz | C63: Maternal | D63: 7908651CB. | E63: 160 | F63: 1000 | G63: 0 | H63: =IF(B63="","",(F63/E63)*G63) -> 0 | I63: 0 | J63: =IF(B63="","",F63-H63-I63) -> 1000
A64: =A63+1 -> 60 | B64: Juana Vidal | C64: Aux Maternal A | D64: 5374807 Scz | E64: 160 | F64: 1000 | G64: 0 | H64: =IF(B64="","",(F64/E64)*G64) -> 0 | I64: 0 | J64: =IF(B64="","",F64-H64-I64) -> 1000
A65: =A64+1 -> 61 | B65: Lucy Rodriguez | C65: Maternal B | D65: 3800831 Lp. | E65: 160 | F65: 1000 | G65: 0 | H65: =IF(B65="","",(F65/E65)*G65) -> 0 | I65: 0 | J65: =IF(B65="","",F65-H65-I65) -> 1000
A66: =A65+1 -> 62 | B66: Marlene Quiñonez | C66: Prof. Mater. | D66: 5238814 CB. | E66: 160 | F66: 1000 | G66: 0 | H66: =IF(B66="","",(F66/E66)*G66) -> 0 | I66: 0 | J66: =IF(B66="","",F66-H66-I66) -> 1000
A67: =A66+1 -> 63 | B67: Blanca Condori | C67: Prof Inicial 1 | D67: 6134711LP. | E67: 160 | F67: 1000 | G67: 0 | H67: =IF(B67="","",(F67/E67)*G67) -> 0 | I67: 0 | J67: =IF(B67="","",F67-H67-I67) -> 1000
A68: =A67+1 -> 64 | B68: Fabiola Herrera | C68: Aux Inicial 1 | D68: 7929725 CB. | E68: 160 | F68: 1000 | G68: 0 | H68: =IF(B68="","",(F68/E68)*G68) -> 0 | I68: 0 | J68: =IF(B68="","",F68-H68-I68) -> 1000
A69: =A68+1 -> 65 | B69: Nancy Soria | C69: Prof Inicial 2 | D69: 2337042 Lp. | E69: 160 | F69: 1000 | G69: 0 | H69: =IF(B69="","",(F69/E69)*G69) -> 0 | I69: 0 | J69: =IF(B69="","",F69-H69-I69) -> 1000
A70: =A69+1 -> 66 | B70: Thelma Cortez | C70: Aux Inicial 2 | D70: 5107060 CB. | E70: 160 | F70: 1000 | G70: 0 | H70: =IF(B70="","",(F70/E70)*G70) -> 0 | I70: 0 | J70: =IF(B70="","",F70-H70-I70) -> 1000
... A87: =A86+1 -> 83 | B87: Ana Claudia Lafuente | C87: Prof. Ingles | D87: 6442423 CB. | E87: 160 | F87: 1000 | G87: 0 | H87: =IF(B87="","",(F87/E87)*G87) -> 0 | I87: 0 | J87: =IF(B87="","",F87-H87-I87) -> 1000
A88: =A87+1 -> 84 | B88: Cecilia Fernandez | C88: Prof, 4to A | D88: 0 | E88: 160 | F88: 1000 | G88: 0 | H88: =IF(B88="","",(F88/E88)*G88) -> 0 | I88: 0 | J88: =IF(B88="","",F88-H88-I88) -> 1000
A89: =A88+1 -> 85 | B89: Maria Geancarla Claros | C89: Prof. 4to B | D89: 4411136 CB. | E89: 160 | F89: 1000 | G89: 0 | H89: =IF(B89="","",(F89/E89)*G89) -> 0 | I89: 0 | J89: =IF(B89="","",F89-H89-I89) -> 1000
A90: =A89+1 -> 86 | B90: Susana Marcus | C90: Sociales Ingles | D90: 5234822 CB. | E90: 160 | F90: 1000 | G90: 0 | H90: =IF(B90="","",(F90/E90)*G90) -> 0 | I90: 0 | J90: =IF(B90="","",F90-H90-I90) -> 1000
A91: =A90+1 -> 87 | B91: Vanessa Bustillos | C91: Ciencias | D91: 4400632 CB. | E91: 160 | F91: 1000 | G91: 0 | H91: =IF(B91="","",(F91/E91)*G91) -> 0 | I91: 0 | J91: =IF(B91="","",F91-H91-I91) -> 1000
A92: =A91+1 -> 88 | B92: Carmen Zambrana | C92: Inglés | D92: 2475663 CB. | E92: 160 | F92: 1000 | G92: 0 | H92: =IF(B92="","",(F92/E92)*G92) -> 0 | I92: 0 | J92: =IF(B92="","",F92-H92-I92) -> 1000
A93: =A92+1 -> 89 | B93: Sandra Montero | C93: Matemática | D93: 0 | E93: 160 | F93: 1000 | G93: 0 | H93: =IF(B93="","",(F93/E93)*G93) -> 0 | I93: 0 | J93: =IF(B93="","",F93-H93-I93) -> 1000
A94: =A93+1 -> 90 | B94: Ana Gabriela Villarroel | C94: Lenguaje | D94: 6551091 CB. | E94: 160 | F94: 1000 | G94: 0 | H94: =IF(B94="","",(F94/E94)*G94) -> 0 | I94: 0 | J94: =IF(B94="","",F94-H94-I94) -> 1000
A95: =A94+1 -> 91 | B95: Adriana Castro | C95: Arte | D95: 8822542 CB. | E95: 160 | F95: 1000 | G95: 0 | H95: =IF(B95="","",(F95/E95)*G95) -> 0 | I95: 0 | J95: =IF(B95="","",F95-H95-I95) -> 1000
A96: =A95+1 -> 92 | B96: Rafael Antequera | C96: Fisica | D96: 3399098 CB. | E96: 160 | F96: 1000 | G96: 0 | H96: =IF(B96="","",(F96/E96)*G96) -> 0 | I96: 0 | J96: =IF(B96="","",F96-H96-I96) -> 1000
A97: =A96+1 -> 93 | B97: Eugenia Condori | C97: Matemáticas | D97: 5240336 CB. | E97: 160 | F97: 1000 | G97: 0 | H97: =IF(B97="","",(F97/E97)*G97) -> 0 | I97: 0 | J97: =IF(B97="","",F97-H97-I97) -> 1000
A98: =A97+1 -> 94 | B98: Paola Luzio | C98: Lenguaje | D98: 3764931 CB. | E98: 160 | F98: 1000 | G98: 0 | H98: =IF(B98="","",(F98/E98)*G98) -> 0 | I98: 0 | J98: =IF(B98="","",F98-H98-I98) -> 1000
A99: =A98+1 -> 95 | B99: Marcelo Rodriguez | C99: Historia | D99: 4401361 CB. | E99: 160 | F99: 1000 | G99: 0 | H99: =IF(B99="","",(F99/E99)*G99) -> 0 | I99: 0 | J99: =IF(B99="","",F99-H99-I99) -> 1000
A100: =A99+1 -> 96 | B100: Mariela Reyna | C100: Bio.Español | D100: 3117036 CB. | E100: 160 | F100: 1000 | G100: 0 | H100: =IF(B100="","",(F100/E100)*G100) -> 0 | I100: 0 | J100: =IF(B100="","",F100-H100-I100) -> 1000
A101: =A100+1 -> 97 | B101: Magaly Ayala | C101: Quimica | D101: 0 | E101: 160 | F101: 1000 | G101: 0 | H101: =IF(B101="","",(F101/E101)*G101) -> 0 | I101: 0 | J101: =IF(B101="","",F101-H101-I101) -> 1000
A102: =A101+1 -> 98 | B102: Salem Padilla | C102: Inglés | D102: 0 | E102: 160 | F102: 1000 | G102: 0 | H102: =IF(B102="","",(F102/E102)*G102) -> 0 | I102: 0 | J102: =IF(B102="","",F102-H102-I102) -> 1000
A103: =A102+1 -> 99 | B103: Margaret Giancalone | C103: Inglés | D103: P-522662901 | E103: 160 | F103: 1000 | G103: 0 | H103: =IF(B103="","",(F103/E103)*G103) -> 0 | I103: 0 | J103: =IF(B103="","",F103-H103-I103) -> 1000
A104: =A103+1 -> 100 | B104: Shirley Campos | C104: Matematica | D104: 0 | E104: 160 | F104: 1000 | G104: 0 | H104: =IF(B104="","",(F104/E104)*G104) -> 0 | I104: 0 | J104: =IF(B104="","",F104-H104-I104) -> 1000
A105: =A104+1 -> 101 | B105: Laura Burgoa | C105: Piscologa | D105: 0 | E105: 160 | F105: 1000 | G105: 0 | H105: =IF(B105="","",(F105/E105)*G105) -> 0 | I105: 0 | J105: =IF(B105="","",F105-H105-I105) -> 1000
A106: =A105+1 -> 102 | B106: Milena Solares | C106: Manualidades | D106: 969916 CB. | E106: 160 | F106: 1000 | G106: 0 | H106: =IF(B106="","",(F106/E106)*G106) -> 0 | I106: 0 | J106: =IF(B106="","",F106-H106-I106) -> 1000
A107: =A106+1 -> 103 | B107: Deyna Castro | C107: Secr Secundaria | D107: 6550274CB. | E107: 160 | F107: 1000 | G107: 0 | H107: =IF(B107="","",(F107/E107)*G107) -> 0 | I107: 0 | J107: =IF(B107="","",F107-H107-I107) -> 1000
A108: =A107+1 -> 104 | B108: Loyda | C108: Aux Inicial 1 | D108: 0 | E108: 160 | F108: 1000 | G108: 0 | H108: =IF(B108="","",(F108/E108)*G108) -> 0 | I108: 0 | J108: =IF(B108="","",F108-H108-I108) -> 1000
A109: =A108+1 -> 105 | B109: Ana Claudia Padilla | C109: Secretaria | D109: 0 | E109: 160 | F109: 1000 | G109: 0 | H109: =IF(B109="","",(F109/E109)*G109) -> 0 | I109: 0 | J109: =IF(B109="","",F109-H109-I109) -> 1000
A110: =A109+1 -> 106 | B110: Victor Velarde | C110: Mantenimi. | D110: 0 | E110: 160 | F110: 1000 | G110: 0 | H110: =IF(B110="","",(F110/E110)*G110) -> 0 | I110: 0 | J110: =IF(B110="","",F110-H110-I110) -> 1000
A111: =A110+1 -> 107 | B111: Simon Martinez | C111: Regente | D111: 0 | E111: 160 | F111: 1000 | G111: 0 | H111: =IF(B111="","",(F111/E111)*G111) -> 0 | I111: 0 | J111: =IF(B111="","",F111-H111-I111) -> 1000
A112: =A111+1 -> 108 | B112: Osvaldo Terán | C112: Jardinería | D112: 0 | E112: 160 | F112: 1000 | G112: 0 | H112: =IF(B112="","",(F112/E112)*G112) -> 0 | I112: 0 | J112: =IF(B112="","",F112-H112-I112) -> 1000
A113: =A112+1 -> 109 | H113: =IF(B113="","",(F113/E113)*G113) | J113: =IF(B113="","",F113-H113-I113)
A114: =A113+1 -> 110 | H114: =IF(B114="","",(F114/E114)*G114) | J114: =IF(B114="","",F114-H114-I114)
A115: =A114+1 -> 111 | H115: =IF(B115="","",(F115/E115)*G115) | J115: =IF(B115="","",F115-H115-I115)
A116: =A115+1 -> 112 | H116: =IF(B116="","",(F116/E116)*G116) | J116: =IF(B116="","",F116-H116-I116)
A117: =A116+1 -> 113 | H117: =IF(B117="","",(F117/E117)*G117) | J117: =IF(B117="","",F117-H117-I117)
A118: =A117+1 -> 114 | H118: =IF(B118="","",(F118/E118)*G118) | J118: =IF(B118="","",F118-H118-I118)
A119: =A118+1 -> 115 | H119: =IF(B119="","",(F119/E119)*G119) | J119: =IF(B119="","",F119-H119-I119)
A120: =A119+1 -> 116 | H120: =IF(B120="","",(F120/E120)*G120) | J120: =IF(B120="","",F120-H120-I120)
A121: =A120+1 -> 117 | H121: =IF(B121="","",(F121/E121)*G121) | J121: =IF(B121="","",F121-H121-I121)
A122: =A121+1 -> 118 | H122: =IF(B122="","",(F122/E122)*G122) | J122: =IF(B122="","",F122-H122-I122)
A123: =A122+1 -> 119 | H123: =IF(B123="","",(F123/E123)*G123) | J123: =IF(B123="","",F123-H123-I123)
A124: =A123+1 -> 120 | H124: =IF(B124="","",(F124/E124)*G124) | J124: =IF(B124="","",F124-H124-I124)
... A154: =A153+1 -> 150 | H154: =IF(B154="","",(F154/E154)*G154) | J154: =IF(B154="","",F154-H154-I154)
E155: =SUM(E5:E154) -> 17280 | F155: =SUM(F5:F154) -> 183280 | G155: =SUM(G5:G154) -> 0 | H155: =SUM(H5:H154) -> 0 | I155: =SUM(I5:I154) -> 0 | J155: =SUM(J5:J154) -> 183280

Sheet HOJA DE COBRO DEL SEGURO
A1: ADQUISICIÓN DE SEGURO CONTRA ACCIDENTES
A2: GESTIÓN 2020
A3: N° | B3: FAMILIA | C3: CANTIDAD | D3: MONTO | E3: OBSERVACIONES
A4: 1 | B4: Aguila Sejas Adrian - Matias Hernan
A5: 2 | B5: Aldunate Eterovic Cristian
A6: 3 | B6: Aldunate Santi Luciana Thais
A7: 4 | B7: Almanza Orihuela Carlos Gabriel - Camila Gabriela
A8: 5 | B8: Altieri Laserna Florencia
A9: 6 | B9: Alvarez Chaira Vivian Alicia
A10: 7 | B10: Alvarez Sejas Julio Gabriel
A11: 8 | B11: Andia Gonzales Mateo
A12: 9 | B12: Andia Saucedo Maria Jose
A13: 10 | B13: Angulo Balderrama Fabricio Fernando - Santiago Fernando
A14: 11 | B14: Angulo Cespedes Letizia - Daniel - Alejandra
A15: 12 | B15: Antezana Rojas Santiago Israel - Angela Erika
... A374: 371 | B374: Vidaurre Galindo Salvador
A375: 372
A376: 373
A377: 374
A378: 375
A379: 376
A380: 377
A381: 378
A382: 379
A383: 380
A384: 381
A385: 382
A386: 383
... A465: 462
