Workbook

Sheet Costo M.P.yMat.
A1: ANALISIS DE COSTOS Y DETERMINACION DE PRECIOS DE VENTA (/i1,1/,84)
A3: PRODUCTO | B3: Unidad | C3: Precio de | D3: Precio de | E3: Costo oper. | G3: Proveedor
C4: venta CF | D4: venta SF | E4: CF | F4: SF
C5: $us/unid. | D5: $us/unid. | E5: $us/unid. | F5: $us/unid.
A6: MATERIALES COMUNES PARA EL VIDRIO TEMPLADO Y LA CARPINTERIA DE ALUMINIO
A7: Silicona transparente, blanca o negra | B7: Tubo | C7: =ROUNDUP(E7*0.87*1.1/0.84,2) -> 2.76 | D7: =ROUNDUP(F7*1.1,2) -> 2.67 | E7: 2.42 | F7: 2.42 | G7: Amerix | H7: =(-D7+C7)/C7 -> 0.032608696
A8: Silicona estructural | B8: Tubo | C8: =ROUNDUP(E8*0.87*1.1/0.84,2) -> 7.98 | D8: =ROUNDUP(F8*1.1,2) -> 7.4 | E8: 7 | F8: =+E8*0.96 -> 6.72 | G8: Amerix | H8: =(-D8+C8)/C8 -> 0.072681704
A9: Cinta masking 1/2 " (rollo de 20) | B9: Rollo | C9: =ROUNDUP(E9*0.87*1.1/0.84,2) -> 0.75 | D9: =ROUNDUP(F9*1.1,2) -> 0.72 | E9: 0.65 | F9: 0.65 | G9: Ribepar | H9: =(-D9+C9)/C9 -> 0.04
A10: "U" 15 x 15 ( 16x16 ) - 0,159 Kg/Mt. | B10: Mt lineal | C10: =ROUNDUP(E10*0.87*1.1/0.84,2) -> 1.41 | D10: =ROUNDUP(F10*1.1,2) -> 1.3 | E10: =+K10/6 -> 1.2305805 | F10: =0.96*E10 -> 1.1813573 | G10: Alcoa 6,73 + 15% | H10: =(-D10+C10)/C10 -> 0.078014184 | I10: =6*0.159 -> 0.954 | J10: Kgr./barra | K10: =6.73*1.15*I10 -> 7.383483 | L10: $us./barra
A11: "U" 15 x 25 - 0,20 Kg/Mt. | B11: Mt lineal | C11: =ROUNDUP(E11*0.87*1.1/0.84,2) -> 1.77 | D11: =ROUNDUP(F11*1.1,2) -> 1.64 | E11: =+K11/6 -> 1.5479 | F11: =0.96*E11 -> 1.485984 | G11: Alcoa 6,73 + 15% | H11: =(-D11+C11)/C11 -> 0.073446328 | I11: =6*0.2 -> 1.2 | J11: Kgr./barra | K11: =6.73*1.15*I11 -> 9.2874 | L11: $us./barra
A12: Tubo 50 x 50 - 1,037 Kg/Mt. | B12: Mt lineal | C12: =ROUNDUP(E12*0.87*1.1/0.84,2) -> 9.15 | D12: =ROUNDUP(F12*1.1,2) -> 8.48 | E12: =+K12/6 -> 8.0258615 | F12: =0.96*E12 -> 7.704827 | G12: Alcoa 6,73 + 15% | H12: =(-D12+C12)/C12 -> 0.073224044 | I12: =6*1.037 -> 6.222 | J12: Kgr./barra | K12: =6.73*1.15*I12 -> 48.155169 | L12: $us./barra
A13: Tubo 40 x 40 - 0,624 Kg/Mt. | B13: Mt lineal | C13: =ROUNDUP(E13*0.87*1.1/0.84,2) -> 5.51 | D13: =ROUNDUP(F13*1.1,2) -> 5.1 | E13: =+K13/6 -> 4.829448 | F13: =0.96*E13 -> 4.6362701 | G13: Alcoa 6,73 + 15% | H13: =(-D13+C13)/C13 -> 0.074410163 | I13: =6*0.624 -> 3.744 | J13: Kgr./barra | K13: =6.73*1.15*I13 -> 28.976688 | L13: $us./barra
A14: Tubo 80 x 40 - 0,948 Kg/Mt. | B14: Mt lineal | C14: =ROUNDUP(E14*0.87*1.1/0.84,2) -> 8.36 | D14: =ROUNDUP(F14*1.1,2) -> 7.75 | E14: =+K14/6 -> 7.337046 | F14: =0.96*E14 -> 7.0435642 | G14: Alcoa 6,73 + 15% | H14: =(-D14+C14)/C14 -> 0.072966507 | I14: =6*0.948 -> 5.688 | J14: Kgr./barra | K14: =6.73*1.15*I14 -> 44.022276 | L14: $us./barra
A15: Tubo 60 x 30 - 0,705 Kg/Mt. | B15: Mt lineal | C15: =ROUNDUP(E15*0.87*1.1/0.84,2) -> 6.22 | D15: =ROUNDUP(F15*1.1,2) -> 5.77 | E15: =+K15/6 -> 5.4563475 | F15: =0.96*E15 -> 5.2380936 | G15: Alcoa 6,73 + 15% | H15: =(-D15+C15)/C15 -> 0.072347267 | I15: =6*0.705 -> 4.23 | J15: Kgr./barra | K15: =6.73*1.15*I15 -> 32.738085 | L15: $us./barra
A16: Tubo 75 x 25 - 0,786 Kg/Mt. | B16: Mt lineal | C16: =ROUNDUP(E16*0.87*1.1/0.84,2) -> 6.94 | D16: =ROUNDUP(F16*1.1,2) -> 6.43 | E16: =+K16/6 -> 6.083247 | F16: =0.96*E16 -> 5.8399171 | G16: Alcoa 6,73 + 15% | H16: =(-D16+C16)/C16 -> 0.073487032 | I16: =6*0.786 -> 4.716 | J16: Kgr./barra | K16: =6.73*1.15*I16 -> 36.499482 | L16: $us./barra
A17: Felpa | B17: Mt lineal | C17: =ROUNDUP(E17*0.87*1.1/0.84,2) -> 0.18 | D17: =ROUNDUP(F17*1.1,2) -> 0.17 | E17: 0.15 | F17: 0.15 | G17: Indalum | H17: =(-D17+C17)/C17 -> 0.055555556
A18: Remache 4 x 10 | B18: Pza. | C18: =ROUNDUP(E18*0.87*1.1/0.84,2) -> 0.04 | D18: =ROUNDUP(F18*1.1,2) -> 0.04 | E18: 0.03 | F18: 0.03 | G18: Perbol | H18: =(-D18+C18)/C18 -> 0
A19: Tarugos No. 6 | B19: Pza. | C19: =ROUNDUP(E19*0.87*1.1/0.84,2) -> 0.04 | D19: =ROUNDUP(F19*1.1,2) -> 0.04 | E19: 0.03 | F19: 0.03 | G19: Perbol | H19: =(-D19+C19)/C19 -> 0
A20: Tornillos 8 x 1 1/2 | B20: Pza. | C20: =ROUNDUP(E20*0.87*1.1/0.84,2) -> 0.04 | D20: =ROUNDUP(F20*1.1,2) -> 0.04 | E20: 0.03 | F20: 0.03 | G20: Perbol | H20: =(-D20+C20)/C20 -> 0
A21: Tornillos 8 x 1/2 | B21: Pza. | C21: =ROUNDUP(E21*0.87*1.1/0.84,2) -> 0.03 | D21: =ROUNDUP(F21*1.1,2) -> 0.03 | E21: 0.02 | F21: 0.02 | G21: Perbol | H21: =(-D21+C21)/C21 -> 0
A22: Tubo Galvanizado de 4" | B22: Mt lineal | C22: =ROUNDUP(E22*0.87*1.1/0.84,2) -> 29.91 | D22: =ROUNDUP(F22*1.1,2) -> 27.72 | E22: =150*1.05/6 -> 26.25 | F22: =+E22*0.96 -> 25.2 | G22: Las Lomas ( 150+5%uniones) | H22: =(-D22+C22)/C22 -> 0.073219659
A25: PARA EL VIDRIO TEMPLADO
A26: Vidrio Templado 10mm Incoloro | B26: Mt² | C26: =ROUNDUP(E26*0.87*1.1/0.84,2) -> 36.46 | D26: =ROUNDUP(F26*1.1,2) -> 33 | E26: 32 | F26: 30 | G26: Oriental | H26: =(-D26+C26)/C26 -> 0.094898519
A27: Vidrio Templado 8mm Incoloro | B27: Mt² | C27: =ROUNDUP(E27*0.87*1.1/0.84,2) -> 34.18 | D27: =ROUNDUP(F27*1.1,2) -> 30.8 | E27: 30 | F27: 28 | G27: Oriental | H27: =(-D27+C27)/C27 -> 0.098888239
A28: Vidrio Templado 6mm Incoloro | B28: Mt² | C28: =ROUNDUP(E28*0.87*1.1/0.84,2) -> 31.9 | D28: =ROUNDUP(F28*1.1,2) -> 30.8 | E28: 28 | F28: 28 | G28: Revibol | H28: =(-D28+C28)/C28 -> 0.034482759
A29: Vidrio Templado 5mm Incoloro | B29: Mt² | C29: =ROUNDUP(E29*0.87*1.1/0.84,2) -> 27.35 | D29: =ROUNDUP(F29*1.1,2) -> 26.4 | E29: 24 | F29: 24 | G29: Revibol | H29: =(-D29+C29)/C29 -> 0.034734918
A30: Vidrio Templado 4mm Incoloro | B30: Mt² | C30: =ROUNDUP(E30*0.87*1.1/0.84,2) -> 23.93 | D30: =ROUNDUP(F30*1.1,2) -> 23.1 | E30: 21 | F30: 21 | G30: Revibol | H30: =(-D30+C30)/C30 -> 0.034684496
A31: Vidrio Templado 10mm Color | B31: Mt² | C31: =ROUNDUP(E31*0.87*1.1/0.84,2) -> 52.41 | D31: =ROUNDUP(F31*1.1,2) -> 48.4 | E31: 46 | F31: 44 | G31: Oriental | H31: =(-D31+C31)/C31 -> 0.076512116
A32: Vidrio Templado 8mm Color | B32: Mt² | C32: =ROUNDUP(E32*0.87*1.1/0.84,2) -> 50.13 | D32: =ROUNDUP(F32*1.1,2) -> 46.2 | E32: 44 | F32: 42 | G32: Oriental | H32: =(-D32+C32)/C32 -> 0.07839617
A33: Vidrio Templado 6mm Color | B33: Mt² | C33: =ROUNDUP(E33*0.87*1.1/0.84,2) -> 33.04 | D33: =ROUNDUP(F33*1.1,2) -> 31.9 | E33: 29 | F33: 29 | G33: Revibol | H33: =(-D33+C33)/C33 -> 0.034503632
A34: Vidrio Templado 5mm Color | B34: Mt² | C34: =ROUNDUP(E34*0.87*1.1/0.84,2) -> 30.77 | D34: =ROUNDUP(F34*1.1,2) -> 29.7 | E34: 27 | F34: 27 | G34: Revibol | H34: =(-D34+C34)/C34 -> 0.034774131
A35: Vidrio Templado 4mm Color | B35: Mt² | C35: =ROUNDUP(E35*0.87*1.1/0.84,2) -> 26.21 | D35: =ROUNDUP(F35*1.1,2) -> 25.3 | E35: 23 | F35: 23 | G35: Revibol | H35: =(-D35+C35)/C35 -> 0.034719573
A36: Vidrio Templado Catedral 10mm Incoloro | B36: Mt² | C36: =ROUNDUP(E36*0.87*1.1/0.84,2) -> 50.13 | D36: =ROUNDUP(F36*1.1,2) -> 48.4 | E36: 44 | F36: 44 | G36: Revibol | H36: =(-D36+C36)/C36 -> 0.034510273
A37: Vidrio Templado Catedral 10mm Color | B37: Mt² | C37: =ROUNDUP(E37*0.87*1.1/0.84,2) -> 52.41 | D37: =ROUNDUP(F37*1.1,2) -> 50.6 | E37: 46 | F37: 46 | G37: Revibol | H37: =(-D37+C37)/C37 -> 0.034535394
A38: Cabezal Tapa Guia Tapa-guia 1.998 Kg/Mt | B38: Mt lineal | C38: =ROUNDUP(E38*0.87*1.1/0.84,2) -> 17.62 | D38: =ROUNDUP(F38*1.1,2) -> 16.33 | E38: =+K38/6 -> 15.463521 | F38: =+E38*0.96 -> 14.84498 | G38: Alcoa 6,73 + 15% | H38: =(-D38+C38)/C38 -> 0.073212259 | I38: =6*1.998 -> 11.988 | J38: Kgr./barra | K38: =6.73*1.15*I38 -> 92.781126 | L38: $us./barra
A39: Vedapres 001 - h (2,10mt/barra) Inc. | B39: Barra | C39: =ROUNDUP(E39*0.87*1.1/0.84,2) -> 5.99 | D39: =ROUNDUP(F39*1.1,2) -> 5.5 | E39: =+F39*1.05 -> 5.25 | F39: 5 | G39: Florencio Rivero | H39: =(-D39+C39)/C39 -> 0.081803005 | I39: =6*0.257 -> 1.542 | J39: Kgr./barra | K39: =6.73*1.15*I39 -> 11.934309 | L39: $us./barra | M39: =+K39*2.1/6 -> 4.1770081
A40: Vedapres 002 - Uc (2,10mt/barra) Inc. | B40: Barra | C40: =ROUNDUP(E40*0.87*1.1/0.84,2) -> 5.99 | D40: =ROUNDUP(F40*1.1,2) -> 5.5 | E40: =+F40*1.05 -> 5.25 | F40: 5 | G40: Florencio Rivero | H40: =(-D40+C40)/C40 -> 0.081803005 | I40: =6*0.151 -> 0.906 | J40: Kgr./barra | K40: =6.73*1.15*I40 -> 7.011987 | L40: $us./barra | M40: =+K40*2.1/6 -> 2.4541954
A41: Vedapres 003 - H (2,10mt/barra) Inc. | B41: Barra | C41: =ROUNDUP(E41*0.87*1.1/0.84,2) -> 5.99 | D41: =ROUNDUP(F41*1.1,2) -> 5.5 | E41: =+F41*1.05 -> 5.25 | F41: 5 | G41: Florencio Rivero | H41: =(-D41+C41)/C41 -> 0.081803005
A42: Vedapres 001 - h (2,10mt/barra) Bce. | B42: Barra | C42: =ROUNDUP(E42*0.87*1.1/0.84,2) -> 5.99 | D42: =ROUNDUP(F42*1.1,2) -> 5.5 | E42: =+F42*1.05 -> 5.25 | F42: 5 | G42: Florencio Rivero | H42: =(-D42+C42)/C42 -> 0.081803005
A43: Vedapres 002 - Uc (2,10mt/barra) Bce. | B43: Barra | C43: =ROUNDUP(E43*0.87*1.1/0.84,2) -> 5.99 | D43: =ROUNDUP(F43*1.1,2) -> 5.5 | E43: =+F43*1.05 -> 5.25 | F43: 5 | G43: Florencio Rivero | H43: =(-D43+C43)/C43 -> 0.081803005
A44: Vedapres 003 - H (2,10mt/barra) Bce. | B44: Barra | C44: =ROUNDUP(E44*0.87*1.1/0.84,2) -> 5.99 | D44: =ROUNDUP(F44*1.1,2) -> 5.5 | E44: =+F44*1.05 -> 5.25 | F44: 5 | G44: Florencio Rivero | H44: =(-D44+C44)/C44 -> 0.081803005
A45: Freno Hidráulico DORMA | B45: Pza. | C45: =ROUNDUP(E45*0.87*1.1/0.84,2) -> 101.69 | D45: =ROUNDUP(F45*1.1,2) -> 93.5 | E45: =+F45*1.05 -> 89.25 | F45: 85 | G45: Florencio Rivero | H45: =(-D45+C45)/C45 -> 0.080538893
A46: Freno Hidráulico HyH | B46: Pza. | C46: =ROUNDUP(E46*0.87*1.1/0.84,2) -> 79.75 | D46: =ROUNDUP(F46*1.1,2) -> 77 | E46: 70 | F46: 70 | G46: Cristembo La Paz | H46: =(-D46+C46)/C46 -> 0.034482759
A47: Manijones de vidrio | B47: Pza. | C47: =ROUNDUP(E47*0.87*1.1/0.84,2) -> 3.42 | D47: =ROUNDUP(F47*1.1,2) -> 3.3 | E47: 3 | F47: 3 | G47: Revibol | H47: =(-D47+C47)/C47 -> 0.035087719
A48: 1003 ( cromado ó bronce viejo ) | B48: Mt lineal | C48: =ROUNDUP(E48*0.87*1.1/0.84,2) -> 4.51 | D48: =ROUNDUP(F48*1.1,2) -> 4.11 | E48: =+F48*1.06 -> 3.9538 | F48: 3.73 | G48: Florencio Rivero | H48: =(-D48+C48)/C48 -> 0.088691796
A49: 1013 ( cromado ó bronce viejo ) | B49: Pza. | C49: =ROUNDUP(E49*0.87*1.1/0.84,2) -> 3.59 | D49: =ROUNDUP(F49*1.1,2) -> 3.27 | E49: =+F49*1.06 -> 3.1482 | F49: 2.97 | G49: Florencio Rivero | H49: =(-D49+C49)/C49 -> 0.08913649
A50: 1038 ( cromado ó bronce viejo ) | B50: Pza. | C50: =ROUNDUP(E50*0.87*1.1/0.84,2) -> 0.97 | D50: =ROUNDUP(F50*1.1,2) -> 0.88 | E50: =+F50*1.06 -> 0.848 | F50: 0.8 | G50: Florencio Rivero | H50: =(-D50+C50)/C50 -> 0.092783505
A51: 1038-C ( cromado ó bronce viejo ) | B51: Pza. | C51: =ROUNDUP(E51*0.87*1.1/0.84,2) -> 1.21 | D51: =ROUNDUP(F51*1.1,2) -> 1.1 | E51: =+F51*1.06 -> 1.06 | F51: 1 | G51: Florencio Rivero | H51: =(-D51+C51)/C51 -> 0.090909091
A52: 1101 ( cromado ó bronce viejo ) | B52: Pza. | C52: =ROUNDUP(E52*0.87*1.1/0.84,2) -> 8.89 | D52: =ROUNDUP(F52*1.1,2) -> 8.1 | E52: =+F52*1.06 -> 7.8016 | F52: 7.36 | G52: Florencio Rivero | H52: =(-D52+C52)/C52 -> 0.088863892
A53: 1103 ( cromado ó bronce viejo ) | B53: Pza. | C53: =ROUNDUP(E53*0.87*1.1/0.84,2) -> 12.08 | D53: =ROUNDUP(F53*1.1,2) -> 11 | E53: =+F53*1.06 -> 10.6 | F53: 10 | G53: Florencio Rivero | H53: =(-D53+C53)/C53 -> 0.089403974
A54: 1114 ( cromado ó bronce viejo ) | B54: Pza. | C54: =ROUNDUP(E54*0.87*1.1/0.84,2) -> 9.06 | D54: =ROUNDUP(F54*1.1,2) -> 8.25 | E54: =+F54*1.06 -> 7.95 | F54: 7.5 | G54: Florencio Rivero | H54: =(-D54+C54)/C54 -> 0.089403974
A55: 1115 ( cromado ó bronce viejo ) | B55: Pza. | C55: =ROUNDUP(E55*0.87*1.1/0.84,2) -> 9.06 | D55: =ROUNDUP(F55*1.1,2) -> 8.25 | E55: =+F55*1.06 -> 7.95 | F55: 7.5 | G55: Florencio Rivero | H55: =(-D55+C55)/C55 -> 0.089403974
A56: 1117 ( cromado ó bronce viejo ) | B56: Pza. | C56: =ROUNDUP(E56*0.87*1.1/0.84,2) -> 17.76 | D56: =ROUNDUP(F56*1.1,2) -> 16.17 | E56: =+F56*1.06 -> 15.582 | F56: 14.7 | G56: Florencio Rivero | H56: =(-D56+C56)/C56 -> 0.089527027
A57: 1123 ( cromado ó bronce viejo ) | B57: Pza. | C57: =ROUNDUP(E57*0.87*1.1/0.84,2) -> 4.86 | D57: =ROUNDUP(F57*1.1,2) -> 4.43 | E57: =+F57*1.06 -> 4.2612 | F57: 4.02 | G57: Florencio Rivero | H57: =(-D57+C57)/C57 -> 0.088477366
A58: 1125 ( cromado ó bronce viejo ) | B58: Pza. | C58: =ROUNDUP(E58*0.87*1.1/0.84,2) -> 1.57 | D58: =ROUNDUP(F58*1.1,2) -> 1.43 | E58: =+F58*1.06 -> 1.378 | F58: 1.3 | G58: Florencio Rivero | H58: =(-D58+C58)/C58 -> 0.089171975
A59: 1125-A ( cromado ó bronce viejo ) | B59: Pza. | C59: =ROUNDUP(E59*0.87*1.1/0.84,2) -> 3.87 | D59: =ROUNDUP(F59*1.1,2) -> 3.52 | E59: =+F59*1.06 -> 3.392 | F59: 3.2 | G59: Florencio Rivero | H59: =(-D59+C59)/C59 -> 0.090439276
... A84: Mano de obra instalaciòn templado | B84: Mt² | C84: =ROUNDUP(E84*0.87*1.1/0.84,2) -> 12.08 | D84: =ROUNDUP(F84*1.1,2) -> 11 | E84: =+F84*1.06 -> 10.6 | F84: 10 | G84: Hilarion 6 maestro + 4 diseno | H84: =(-D84+C84)/C84 -> 0.089403974
A85: Herraje Arana | B85: Pza. | C85: =ROUNDUP(E85*0.87*1.1/0.84,2) -> 136.72 | D85: =ROUNDUP(F85*1.1,2) -> 126.72 | E85: 120 | F85: =+E85*0.96 -> 115.2 | G85: CRISTEC | H85: =(-D85+C85)/C85 -> 0.073142188
A86: Soporte herraje - tubo | B86: Pza. | C86: =ROUNDUP(E86*0.87*1.1/0.84,2) -> 22.79 | D86: =ROUNDUP(F86*1.1,2) -> 21.12 | E86: 20 | F86: =+E86*0.96 -> 19.2 | H86: =(-D86+C86)/C86 -> 0.073277753
A88: MATERIALES Y MATERIA PRIMA PARA LA CARPINTERIA DE ALUMINIO
A89: Aluminio Anodizado Bronce o Champagne | B89: Kgr. | C89: =ROUNDUP(E89*0.87*1.1/0.84,2) -> 8.82 | D89: =ROUNDUP(F89*1.1,2) -> 8.18 | E89: =6.73*1.15 -> 7.7395 | F89: =0.96*E89 -> 7.42992 | G89: Alcoa 6,73 + 15% | H89: =(-D89+C89)/C89 -> 0.072562358
A90: Aluminio Anodizado natural | B90: Kgr. | C90: =ROUNDUP(E90*0.87*1.1/0.84,2) -> 8.82 | D90: =ROUNDUP(F90*1.1,2) -> 8.18 | E90: =6.73*1.15 -> 7.7395 | F90: =0.96*E90 -> 7.42992 | G90: Alcoa 6,73 + 15% | H90: =(-D90+C90)/C90 -> 0.072562358
A91: Vidrio Incolororo 3mm | B91: Mt² | C91: =ROUNDUP(E91*0.87*1.1/0.84,2) -> 10.07 | D91: =ROUNDUP(F91*1.1,2) -> 9.72 | E91: =7.68*1.15 -> 8.832 | F91: =7.68*1.15 -> 8.832 | G91: Oriental 7.68 + 15% | H91: =(-D91+C91)/C91 -> 0.034756703
A92: Vidrio Incolororo 4mm | B92: Mt² | C92: =ROUNDUP(E92*0.87*1.1/0.84,2) -> 12.43 | D92: =ROUNDUP(F92*1.1,2) -> 12 | E92: =9.48*1.15 -> 10.902 | F92: =9.48*1.15 -> 10.902 | G92: Oriental 9.48 + 15% | H92: =(-D92+C92)/C92 -> 0.034593725 | I92: =74/(3.66*2.134) -> 9.4744982
A93: Vidrio Incolororo 5mm | B93: Mt² | C93: =ROUNDUP(E93*0.87*1.1/0.84,2) -> 14.1 | D93: =ROUNDUP(F93*1.1,2) -> 13.62 | E93: =10.76*1.15 -> 12.374 | F93: =10.76*1.15 -> 12.374 | G93: Oriental 10.76 + 15% | H93: =(-D93+C93)/C93 -> 0.034042553 | I93: =84/(3.66*2.134) -> 10.754836
A94: Vidrio Incolororo 6mm | B94: Mt² | C94: =ROUNDUP(E94*0.87*1.1/0.84,2) -> 18.74 | D94: =ROUNDUP(F94*1.1,2) -> 18.09 | E94: =14.3*1.15 -> 16.445 | F94: =14.3*1.15 -> 16.445 | G94: Oriental 14.30 + 15% | H94: =(-D94+C94)/C94 -> 0.034685165 | I94: =110/(3.66*2.134) -> 14.083714
A95: Vidrio Color 3mm | B95: Mt² | C95: =ROUNDUP(E95*0.87*1.1/0.84,2) -> 13.22 | D95: =ROUNDUP(F95*1.1,2) -> 12.77 | E95: =10.09*1.15 -> 11.6035 | F95: =10.09*1.15 -> 11.6035 | G95: Garcia 10.09 + 15% | H95: =(-D95+C95)/C95 -> 0.034039334
A96: Vidrio Color 4mm | B96: Mt² | C96: =ROUNDUP(E96*0.87*1.1/0.84,2) -> 14.52 | D96: =ROUNDUP(F96*1.1,2) -> 14.02 | E96: =11.08*1.15 -> 12.742 | F96: =11.08*1.15 -> 12.742 | G96: Oriental 11.08 + 15% | H96: =(-D96+C96)/C96 -> 0.034435262
A97: Vidrio Color 5mm | B97: Mt² | C97: =ROUNDUP(E97*0.87*1.1/0.84,2) -> 18.78 | D97: =ROUNDUP(F97*1.1,2) -> 18.13 | E97: =14.33*1.15 -> 16.4795 | F97: =14.33*1.15 -> 16.4795 | G97: Garcia 14.33 + 15% | H97: =(-D97+C97)/C97 -> 0.034611289
A98: Vidrio Color 6mm | B98: Mt² | C98: =ROUNDUP(E98*0.87*1.1/0.84,2) -> 21.82 | D98: =ROUNDUP(F98*1.1,2) -> 21.07 | E98: =16.65*1.15 -> 19.1475 | F98: =16.65*1.15 -> 19.1475 | G98: Oriental 16.65 + 15% | H98: =(-D98+C98)/C98 -> 0.034372136
A99: Vidrio catedral claro | B99: Mt² | C99: =ROUNDUP(E99*0.87*1.1/0.84,2) -> 7.21 | D99: =ROUNDUP(F99*1.1,2) -> 6.68 | E99: =5.5*1.15 -> 6.325 | F99: =+E99*0.96 -> 6.072 | G99: Revibol - 5,55 + 15% | H99: =(-D99+C99)/C99 -> 0.073509015
A100: Vidrio catedral color | B100: Mt² | C100: =ROUNDUP(E100*0.87*1.1/0.84,2) -> 9.39 | D100: =ROUNDUP(F100*1.1,2) -> 8.7 | E100: =7.16*1.15 -> 8.234 | F100: =+E100*0.96 -> 7.90464 | G100: Revibol - 7,16 + 15% | H100: =(-D100+C100)/C100 -> 0.073482428
A101: Vidrio Reflectivo Bronce o Gris 4mm | B101: Mt² | C101: =ROUNDUP(E101*0.87*1.1/0.84,2) -> 31.45 | D101: =ROUNDUP(F101*1.1,2) -> 29.15 | E101: =24*1.15 -> 27.6 | F101: =+E101*0.96 -> 26.496 | G101: Garcia 24 + 15% | H101: =(-D101+C101)/C101 -> 0.073131955
A102: Vidrio Reflectivo Bronce o Gris 5mm | B102: Mt² | C102: =ROUNDUP(E102*0.87*1.1/0.84,2) -> 31.45 | D102: =ROUNDUP(F102*1.1,2) -> 29.15 | E102: =24*1.15 -> 27.6 | F102: =+E102*0.96 -> 26.496 | G102: Garcia 24 + 15% | H102: =(-D102+C102)/C102 -> 0.073131955
A103: Vidrio Reflectivo Bronce o Gris 6mm | B103: Mt² | C103: =ROUNDUP(E103*0.87*1.1/0.84,2) -> 0 | D103: =ROUNDUP(F103*1.1,2) -> 0
A104: Vidrio Reflectivo Azurlite 4mm | B104: Mt² | C104: =ROUNDUP(E104*0.87*1.1/0.84,2) -> 0 | D104: =ROUNDUP(F104*1.1,2) -> 0
A105: Vidrio Reflectivo Azurlite 5mm | B105: Mt² | C105: =ROUNDUP(E105*0.87*1.1/0.84,2) -> 0 | D105: =ROUNDUP(F105*1.1,2) -> 0
A106: Vidrio Reflectivo Azurlite 6mm | B106: Mt² | C106: =ROUNDUP(E106*0.87*1.1/0.84,2) -> 48.48 | D106: =ROUNDUP(F106*1.1,2) -> 44.94 | E106: =37*1.15 -> 42.55 | F106: =+E106*0.96 -> 40.848 | G106: Garcia 37 + 15% | H106: =(-D106+C106)/C106 -> 0.073019802
A107: Cinta dob.cont. 4972 - 3M 1/2"=12mm (rollo de 20) | B107: Rollo | C107: =ROUNDUP(E107*0.87*1.1/0.84,2) -> 29.85 | D107: =ROUNDUP(F107*1.1,2) -> 27.38 | E107: 26.2 | F107: =+E107*0.95 -> 24.89 | G107: America home center | H107: =(-D107+C107)/C107 -> 0.082747069
A108: Cinta dob.cont. 4972 - 3M 3/4"=19mm (rollo de 20) | B108: Rollo | C108: =ROUNDUP(E108*0.87*1.1/0.84,2) -> 47.85 | D108: =ROUNDUP(F108*1.1,2) -> 43.89 | E108: 42 | F108: =+E108*0.95 -> 39.9 | G108: America home center | H108: =(-D108+C108)/C108 -> 0.082758621
A109: Cinta dob.cont. 4972 - 3M 1"=25mm (rollo de 20) | B109: Rollo | C109: =ROUNDUP(E109*0.87*1.1/0.84,2) -> 74.06 | D109: =ROUNDUP(F109*1.1,2) -> 67.93 | E109: 65 | F109: =+E109*0.95 -> 61.75 | G109: America home center | H109: =(-D109+C109)/C109 -> 0.082770726
A110: Felpa | B110: Mt lineal | C110: =ROUNDUP(E110*0.87*1.1/0.84,2) -> 0.14 | D110: =ROUNDUP(F110*1.1,2) -> 0.14 | E110: 0.12 | F110: =+E110 -> 0.12 | G110: Indalum | H110: =(-D110+C110)/C110 -> 0
A111: Burlete | B111: Mt lineal | C111: =ROUNDUP(E111*0.87*1.1/0.84,2) -> 0.35 | D111: =ROUNDUP(F111*1.1,2) -> 0.33 | E111: 0.3 | F111: =+E111 -> 0.3 | G111: Indalum | H111: =(-D111+C111)/C111 -> 0.057142857
A112: Patin serie 25 | B112: Pza. | C112: =ROUNDUP(E112*0.87*1.1/0.84,2) -> 1.37 | D112: =ROUNDUP(F112*1.1,2) -> 1.32 | E112: 1.2 | F112: =+E112 -> 1.2 | G112: Indalum | H112: =(-D112+C112)/C112 -> 0.03649635
A113: Patin serie 20 | B113: Pza. | C113: =ROUNDUP(E113*0.87*1.1/0.84,2) -> 0.57 | D113: =ROUNDUP(F113*1.1,2) -> 0.55 | E113: 0.5 | F113: =+E113 -> 0.5 | G113: Indalum | H113: =(-D113+C113)/C113 -> 0.035087719
A114: Patin serie 50 | B114: Pza. | C114: =ROUNDUP(E114*0.87*1.1/0.84,2) -> 0.46 | D114: =ROUNDUP(F114*1.1,2) -> 0.44 | E114: 0.4 | F114: =+E114 -> 0.4 | G114: Indalum | H114: =(-D114+C114)/C114 -> 0.043478261
A115: Patin serie 4000 | B115: Pza. | C115: =ROUNDUP(E115*0.87*1.1/0.84,2) -> 0.46 | D115: =ROUNDUP(F115*1.1,2) -> 0.44 | E115: 0.4 | F115: =+E115 -> 0.4 | G115: Indalum | H115: =(-D115+C115)/C115 -> 0.043478261
A116: Patin shower door | B116: Pza. | C116: =ROUNDUP(E116*0.87*1.1/0.84,2) -> 0.57 | D116: =ROUNDUP(F116*1.1,2) -> 0.55 | E116: 0.5 | F116: =+E116 -> 0.5 | G116: Indalum | H116: =(-D116+C116)/C116 -> 0.035087719
A117: Cierre serie 20 | B117: Pza. | C117: =ROUNDUP(E117*0.87*1.1/0.84,2) -> 1.83 | D117: =ROUNDUP(F117*1.1,2) -> 1.76 | E117: 1.6 | F117: =+E117 -> 1.6 | G117: Indalum | H117: =(-D117+C117)/C117 -> 0.038251366
A118: Cierre serie 25 | B118: Pza. | C118: =ROUNDUP(E118*0.87*1.1/0.84,2) -> 3.42 | D118: =ROUNDUP(F118*1.1,2) -> 3.3 | E118: 3 | F118: =+E118 -> 3 | G118: Indalum | H118: =(-D118+C118)/C118 -> 0.035087719
A119: Guia exterior Shower door | B119: Pza. | C119: =ROUNDUP(E119*0.87*1.1/0.84,2) -> 0.12 | D119: =ROUNDUP(F119*1.1,2) -> 0.11 | E119: 0.1 | F119: =+E119 -> 0.1 | G119: Indalum | H119: =(-D119+C119)/C119 -> 0.083333333
A120: Guia serie 50 | B120: Pza. | C120: =ROUNDUP(E120*0.87*1.1/0.84,2) -> 0.12 | D120: =ROUNDUP(F120*1.1,2) -> 0.11 | E120: 0.1 | F120: =+E120 -> 0.1 | G120: Indalum | H120: =(-D120+C120)/C120 -> 0.083333333
A121: Guia serie 20 | B121: Pza. | C121: =ROUNDUP(E121*0.87*1.1/0.84,2) -> 0.12 | D121: =ROUNDUP(F121*1.1,2) -> 0.11 | E121: 0.1 | F121: =+E121 -> 0.1 | G121: Indalum | H121: =(-D121+C121)/C121 -> 0.083333333
A122: Guia serie 25 | B122: Pza. | C122: =ROUNDUP(E122*0.87*1.1/0.84,2) -> 0.12 | D122: =ROUNDUP(F122*1.1,2) -> 0.11 | E122: 0.1 | F122: =+E122 -> 0.1 | G122: Indalum | H122: =(-D122+C122)/C122 -> 0.083333333
A123: Celosias 2 aletas - 320 mm. | B123: Par | C123: =ROUNDUP(E123*0.87*1.1/0.84,2) -> 15.26 | D123: =ROUNDUP(F123*1.1,2) -> 14.3 | E123: =+F123*1.03 -> 13.39 | F123: 13 | G123: Florencio Rivero | H123: =(-D123+C123)/C123 -> 0.062909567
A124: Celosias 3 aletas - 460 mm. | B124: Par | C124: =ROUNDUP(E124*0.87*1.1/0.84,2) -> 19.95 | D124: =ROUNDUP(F124*1.1,2) -> 18.7 | E124: =+F124*1.03 -> 17.51 | F124: 17 | G124: Florencio Rivero | H124: =(-D124+C124)/C124 -> 0.062656642
A125: Celosias 4 aletas - 600 mm. | B125: Par | C125: =ROUNDUP(E125*0.87*1.1/0.84,2) -> 22.3 | D125: =ROUNDUP(F125*1.1,2) -> 20.9 | E125: =+F125*1.03 -> 19.57 | F125: 19 | G125: Florencio Rivero | H125: =(-D125+C125)/C125 -> 0.062780269
A126: Celosias 5 aletas - 740mm. | B126: Par | C126: =ROUNDUP(E126*0.87*1.1/0.84,2) -> 28.17 | D126: =ROUNDUP(F126*1.1,2) -> 26.4 | E126: =+F126*1.03 -> 24.72 | F126: 24 | G126: Florencio Rivero | H126: =(-D126+C126)/C126 -> 0.062832801
A127: Celosias 6 aletas - 880 mm. | B127: Par | C127: =ROUNDUP(E127*0.87*1.1/0.84,2) -> 30.52 | D127: =ROUNDUP(F127*1.1,2) -> 28.6 | E127: =+F127*1.03 -> 26.78 | F127: 26 | G127: Florencio Rivero | H127: =(-D127+C127)/C127 -> 0.062909567
A128: Celosias 7 aletas - 1000 mm. | B128: Par | C128: =ROUNDUP(E128*0.87*1.1/0.84,2) -> 38.73 | D128: =ROUNDUP(F128*1.1,2) -> 36.3 | E128: =+F128*1.03 -> 33.99 | F128: 33 | G128: Florencio Rivero | H128: =(-D128+C128)/C128 -> 0.06274206
...

Sheet FORMULAS
F1: B | G1: H | H1: BxH | I1: CANT. | M1: B | N1: H | O1: BxH | P1: (N-1)*H
A2: base | B2: altura | C2: cant | E2: PUERTA CORREDIZA 2 HOJAS | L2: PANO FIJO
A3: 2 | B3: 2.1 | C3: 1 | E3: Vidrio Templado 10mm Incoloro | F3: =+'P-V.Corrediza'!C128 -> 38.51 | G3: =+'P-V.Corrediza'!D128 -> 13.57476 | H3: =+'P-V.Corrediza'!E128 -> 48.54 | I3: =+'P-V.Corrediza'!G128 -> 39.11 | J3: =+F3*$A$3+G3*$B$3+H3*$A$3*$B$3+$C$3*I3 -> 348.505 | L3: Vidrio Templado 10mm Incoloro | M3: =+'Pano Fijo'!C130 -> 20.1892 | N3: =+'Pano Fijo'!D130 -> 20.1892 | O3: =+'Pano Fijo'!F130 -> 49.68 | P3: =+'Pano Fijo'!G130 -> 1.116
E4: Vidrio Templado 10mm Color | F4: =+'P-V.Corrediza'!C129 -> 38.51 | G4: =+'P-V.Corrediza'!D129 -> 13.57476 | H4: =+'P-V.Corrediza'!E129 -> 64.49 | I4: =+'P-V.Corrediza'!G129 -> 39.11 | J4: =+F4*$A$3+G4*$B$3+H4*$A$3*$B$3+$C$3*I4 -> 415.495 | L4: Vidrio Templado 10mm Color | M4: =+'Pano Fijo'!C131 -> 20.1892 | N4: =+'Pano Fijo'!D131 -> 20.1892 | O4: =+'Pano Fijo'!F131 -> 65.63 | P4: =+'Pano Fijo'!G131 -> 1.116
E5: Vidrio Templado 8mm Incoloro | F5: =+'P-V.Corrediza'!C130 -> 38.51 | G5: =+'P-V.Corrediza'!D130 -> 13.57476 | H5: =+'P-V.Corrediza'!E130 -> 46.26 | I5: =+'P-V.Corrediza'!G130 -> 39.11 | J5: =+F5*$A$3+G5*$B$3+H5*$A$3*$B$3+$C$3*I5 -> 338.929 | L5: Vidrio Templado 8mm Incoloro | M5: =+'Pano Fijo'!C132 -> 20.1892 | N5: =+'Pano Fijo'!D132 -> 20.1892 | O5: =+'Pano Fijo'!F132 -> 47.4 | P5: =+'Pano Fijo'!G132 -> 1.116
E6: Vidrio Templado 8mm Color | F6: =+'P-V.Corrediza'!C131 -> 38.51 | G6: =+'P-V.Corrediza'!D131 -> 13.57476 | H6: =+'P-V.Corrediza'!E131 -> 62.21 | I6: =+'P-V.Corrediza'!G131 -> 39.11 | J6: =+F6*$A$3+G6*$B$3+H6*$A$3*$B$3+$C$3*I6 -> 405.919 | L6: Vidrio Templado 8mm Color | M6: =+'Pano Fijo'!C133 -> 20.1892 | N6: =+'Pano Fijo'!D133 -> 20.1892 | O6: =+'Pano Fijo'!F133 -> 63.35 | P6: =+'Pano Fijo'!G133 -> 1.116
E7: PUERTA CORREDIZA 4 HOJAS
E8: Vidrio Templado 10mm Incoloro | F8: =+'P-V.Corrediza'!C162 -> 38.36 | G8: =+'P-V.Corrediza'!D162 -> 9.57036 | H8: =+'P-V.Corrediza'!E162 -> 48.54 | I8: =+'P-V.Corrediza'!G162 -> 59.81 | J8: =+F8*$A$3+G8*$B$3+H8*$A$3*$B$3+$C$3*I8 -> 360.49576 | M8: B | N8: H | O8: BxH | P8: CANT.
E9: Vidrio Templado 10mm Color | F9: =+'P-V.Corrediza'!C163 -> 38.36 | G9: =+'P-V.Corrediza'!D163 -> 9.57036 | H9: =+'P-V.Corrediza'!E163 -> 64.49 | I9: =+'P-V.Corrediza'!G163 -> 59.81 | J9: =+F9*$A$3+G9*$B$3+H9*$A$3*$B$3+$C$3*I9 -> 427.48576 | L9: PUERTA BATIENTE 1 HOJA
E10: Vidrio Templado 8mm Incoloro | F10: =+'P-V.Corrediza'!C164 -> 38.36 | G10: =+'P-V.Corrediza'!D164 -> 9.57036 | H10: =+'P-V.Corrediza'!E164 -> 46.26 | I10: =+'P-V.Corrediza'!G164 -> 59.81 | J10: =+F10*$A$3+G10*$B$3+H10*$A$3*$B$3+$C$3*I10 -> 350.91976 | L10: Vidrio Templado 10mm Incoloro | M10: =+P.Batiente!D157 -> 0 | N10: =+P.Batiente!E157 -> 0 | O10: =+P.Batiente!F157 -> 48.54 | P10: =+P.Batiente!H157 -> 146.07
E11: Vidrio Templado 8mm Color | F11: =+'P-V.Corrediza'!C165 -> 38.36 | G11: =+'P-V.Corrediza'!D165 -> 9.57036 | H11: =+'P-V.Corrediza'!E165 -> 62.21 | I11: =+'P-V.Corrediza'!G165 -> 59.81 | J11: =+F11*$A$3+G11*$B$3+H11*$A$3*$B$3+$C$3*I11 -> 417.90976 | L11: Vidrio Templado 10mm Color | M11: =+P.Batiente!D158 -> 0 | N11: =+P.Batiente!E158 -> 0 | O11: =+P.Batiente!F158 -> 64.49 | P11: =+P.Batiente!H158 -> 146.07
E12: VENTANA CORREDIZA 2 HOJAS | L12: PUERTA BATIENTE 2 HOJAS
E13: Vidrio Templado 10mm Incoloro | F13: =+'P-V.Corrediza'!C196 -> 38.36 | G13: =+'P-V.Corrediza'!D196 -> 13.27476 | H13: =+'P-V.Corrediza'!E196 -> 48.54 | I13: =+'P-V.Corrediza'!G196 -> 18.54 | J13: =+F13*$A$3+G13*$B$3+H13*$A$3*$B$3+$C$3*I13 -> 327.005 | L13: Vidrio Templado 10mm Incoloro | M13: =+P.Batiente!D139 -> 0 | N13: =+P.Batiente!E139 -> 9 | O13: =+P.Batiente!F139 -> 48.54 | P13: =+P.Batiente!H139 -> 290.43
E14: Vidrio Templado 10mm Color | F14: =+'P-V.Corrediza'!C197 -> 38.36 | G14: =+'P-V.Corrediza'!D197 -> 13.27476 | H14: =+'P-V.Corrediza'!E197 -> 64.49 | I14: =+'P-V.Corrediza'!G197 -> 18.54 | J14: =+F14*$A$3+G14*$B$3+H14*$A$3*$B$3+$C$3*I14 -> 393.995 | L14: Vidrio Templado 10mm Color | M14: =+P.Batiente!D140 -> 0 | N14: =+P.Batiente!E140 -> 9 | O14: =+P.Batiente!F140 -> 64.49 | P14: =+P.Batiente!H140 -> 290.43
E15: Vidrio Templado 8mm Incoloro | F15: =+'P-V.Corrediza'!C198 -> 38.36 | G15: =+'P-V.Corrediza'!D198 -> 13.27476 | H15: =+'P-V.Corrediza'!E198 -> 46.26 | I15: =+'P-V.Corrediza'!G198 -> 18.54 | J15: =+F15*$A$3+G15*$B$3+H15*$A$3*$B$3+$C$3*I15 -> 317.429 | L15: PUERTA BATIENTE 2 HOJAS+FIJOS
E16: Vidrio Templado 8mm Color | F16: =+'P-V.Corrediza'!C199 -> 38.36 | G16: =+'P-V.Corrediza'!D199 -> 13.27476 | H16: =+'P-V.Corrediza'!E199 -> 62.21 | I16: =+'P-V.Corrediza'!G199 -> 18.54 | J16: =+F16*$A$3+G16*$B$3+H16*$A$3*$B$3+$C$3*I16 -> 384.419 | L16: Vidrio Templado 10mm Incoloro | M16: =+P.Batiente!D117 -> 4.0239 | N16: =+P.Batiente!E117 -> 11.29195 | O16: =+P.Batiente!F117 -> 48.54 | P16: =+P.Batiente!H117 -> 290.43
E17: VENTANA CORREDIZA 4 HOJAS | L17: Vidrio Templado 10mm Color | M17: =+P.Batiente!D118 -> 4.0239 | N17: =+P.Batiente!E118 -> 11.29195 | O17: =+P.Batiente!F118 -> 64.49 | P17: =+P.Batiente!H118 -> 290.43
E18: Vidrio Templado 10mm Incoloro | F18: =+'P-V.Corrediza'!C230 -> 38.36 | G18: =+'P-V.Corrediza'!D230 -> 9.57036 | H18: =+'P-V.Corrediza'!E230 -> 48.54 | I18: =+'P-V.Corrediza'!G230 -> 37.08 | J18: =+F18*$A$3+G18*$B$3+H18*$A$3*$B$3+$C$3*I18 -> 337.76576
E19: Vidrio Templado 10mm Color | F19: =+'P-V.Corrediza'!C231 -> 38.36 | G19: =+'P-V.Corrediza'!D231 -> 9.57036 | H19: =+'P-V.Corrediza'!E231 -> 64.49 | I19: =+'P-V.Corrediza'!G231 -> 37.08 | J19: =+F19*$A$3+G19*$B$3+H19*$A$3*$B$3+$C$3*I19 -> 404.75576
E20: Vidrio Templado 8mm Incoloro | F20: =+'P-V.Corrediza'!C232 -> 38.36 | G20: =+'P-V.Corrediza'!D232 -> 9.57036 | H20: =+'P-V.Corrediza'!E232 -> 46.26 | I20: =+'P-V.Corrediza'!G232 -> 37.08 | J20: =+F20*$A$3+G20*$B$3+H20*$A$3*$B$3+$C$3*I20 -> 328.18976
E21: Vidrio Templado 8mm Color | F21: =+'P-V.Corrediza'!C233 -> 38.36 | G21: =+'P-V.Corrediza'!D233 -> 9.57036 | H21: =+'P-V.Corrediza'!E233 -> 62.21 | I21: =+'P-V.Corrediza'!G233 -> 37.08 | J21: =+F21*$A$3+G21*$B$3+H21*$A$3*$B$3+$C$3*I21 -> 395.17976
F23: B | G23: H | H23: BXH | I23: (N-1)*(M-1) | J23: (N-1) | K23: (N-1)*H | L23: (M-1)*B
E24: FACHADA CON ARANAS
E25: Vidrio Templado 10mm Incoloro | F25: =+'Fachada tub.herr.'!C107 -> 4.44316 | G25: =+'Fachada tub.herr.'!E107 -> 4.44316 | H25: =+'Fachada tub.herr.'!I107 -> 49.68 | I25: =+'Fachada tub.herr.'!J107 -> 159.51 | J25: =+'Fachada tub.herr.'!B132 -> 27.36 | K25: =+'Fachada tub.herr.'!C132 -> 30.445 | L25: =+'Fachada tub.herr.'!E132 -> 0.5442
E26: Vidrio Templado 10mm Color | F26: =+'Fachada tub.herr.'!C108 -> 4.44316 | G26: =+'Fachada tub.herr.'!E108 -> 4.44316 | H26: =+'Fachada tub.herr.'!I108 -> 65.63 | I26: =+'Fachada tub.herr.'!J108 -> 159.51 | J26: =+'Fachada tub.herr.'!B133 -> 27.36 | K26: =+'Fachada tub.herr.'!C133 -> 30.445 | L26: =+'Fachada tub.herr.'!E133 -> 0.5442
E27: Vidrio Templado 8mm Incoloro | F27: =+'Fachada tub.herr.'!C109 -> 4.44316 | G27: =+'Fachada tub.herr.'!E109 -> 4.44316 | H27: =+'Fachada tub.herr.'!I109 -> 47.4 | I27: =+'Fachada tub.herr.'!J109 -> 159.51 | J27: =+'Fachada tub.herr.'!B134 -> 27.36 | K27: =+'Fachada tub.herr.'!C134 -> 30.445 | L27: =+'Fachada tub.herr.'!E134 -> 0.5442
E28: Vidrio Templado 8mm Color | F28: =+'Fachada tub.herr.'!C110 -> 4.44316 | G28: =+'Fachada tub.herr.'!E110 -> 4.44316 | H28: =+'Fachada tub.herr.'!I110 -> 63.35 | I28: =+'Fachada tub.herr.'!J110 -> 159.51 | J28: =+'Fachada tub.herr.'!B135 -> 27.36 | K28: =+'Fachada tub.herr.'!C135 -> 30.445 | L28: =+'Fachada tub.herr.'!E135 -> 0.5442
E29: FACHADA CON HERRAJES Y VIENTOS
E30: Vidrio Templado 10mm Incoloro | F30: =+'Fachada tub.herr.'!C158 -> 4.44316 | G30: =+'Fachada tub.herr.'!E158 -> 4.44316 | H30: =+'Fachada tub.herr.'!I158 -> 49.68 | I30: =+'Fachada tub.herr.'!J158 -> 17.06 | J30: =+'Fachada tub.herr.'!B183 -> 35.54 | K30: =+'Fachada tub.herr.'!C183 -> 2.347 | L30: =+'Fachada tub.herr.'!E183 -> 0.5442
E31: Vidrio Templado 10mm Color | F31: =+'Fachada tub.herr.'!C159 -> 4.44316 | G31: =+'Fachada tub.herr.'!E159 -> 4.44316 | H31: =+'Fachada tub.herr.'!I159 -> 65.63 | I31: =+'Fachada tub.herr.'!J159 -> 17.06 | J31: =+'Fachada tub.herr.'!B184 -> 35.54 | K31: =+'Fachada tub.herr.'!C184 -> 2.347 | L31: =+'Fachada tub.herr.'!E184 -> 0.5442
E32: Vidrio Templado 8mm Incoloro | F32: =+'Fachada tub.herr.'!C160 -> 4.44316 | G32: =+'Fachada tub.herr.'!E160 -> 4.44316 | H32: =+'Fachada tub.herr.'!I160 -> 47.4 | I32: =+'Fachada tub.herr.'!J160 -> 17.06 | J32: =+'Fachada tub.herr.'!B185 -> 35.54 | K32: =+'Fachada tub.herr.'!C185 -> 2.347 | L32: =+'Fachada tub.herr.'!E185 -> 0.5442
E33: Vidrio Templado 8mm Color | F33: =+'Fachada tub.herr.'!C161 -> 4.44316 | G33: =+'Fachada tub.herr.'!E161 -> 4.44316 | H33: =+'Fachada tub.herr.'!I161 -> 63.35 | I33: =+'Fachada tub.herr.'!J161 -> 17.06 | J33: =+'Fachada tub.herr.'!B186 -> 35.54 | K33: =+'Fachada tub.herr.'!C186 -> 2.347 | L33: =+'Fachada tub.herr.'!E186 -> 0.5442

Sheet Fachada tub.herr.
A2: FACHADA EN VIDRIO TEMPLADO | D2: PF | E2: PF | F2: PF | G2: PF | I2: Total | K2: PF | L2: PF
A3: HERRAJES Y VIENTOS VIDRIO o TUBULAR 4" CON ARANA | D3: =IF(D11=8,"8 mm.","10 mm.") -> 10 mm. | E3: =IF(E11=8,"8 mm.","10 mm.") -> 10 mm. | F3: =IF(F11=8,"8 mm.","10 mm.") -> 8 mm. | G3: =IF(G11=8,"8 mm.","10 mm.") -> 8 mm. | K3: =IF(K11=8,"8 mm.","10 mm.") -> 10 mm. | L3: =IF(L11=8,"8 mm.","10 mm.") -> 10 mm.
A4: DATOS BASE PARA EL ANALISIS | D4: =IF(D10=1,"INCOLORO","COLOR") -> INCOLORO | E4: =IF(E10=1,"INCOLORO","COLOR") -> COLOR | F4: =IF(F10=1,"INCOLORO","COLOR") -> INCOLORO | G4: =IF(G10=1,"INCOLORO","COLOR") -> COLOR | K4: =IF(K10=1,"INCOLORO","COLOR") -> INCOLORO | L4: =IF(L10=1,"INCOLORO","COLOR") -> INCOLORO
A5: BASE ( Metros ) | B5: B | D5: 6 | E5: 6 | F5: 6 | G5: 6 | K5: 6 | L5: 6
A6: ALTURA ( Metros ) | B6: H | D6: 6 | E6: 6 | F6: 6 | G6: 6 | K6: 6 | L6: 6
A7: CANTIDAD DE PIEZAS | B7: N | D7: 1 | E7: 1 | F7: 1 | G7: 1 | I7: =SUM(K7:IV7) -> 32 | J7: Pzas. | K7: 16 | L7: 16
A8: n = div. Verticales | B8: NV | D8: 4 | E8: 4 | F8: 4 | G8: 4 | K8: 5 | L8: 5
A9: m = div. Horizontales | B9: NM | D9: 4 | E9: 4 | F9: 4 | G9: 4 | K9: 3 | L9: 3
A10: INCOLORO = 1 ; COLOR =2 | B10: C | D10: 1 | E10: 2 | F10: 1 | G10: 2 | K10: 1 | L10: 1
A11: ESPESOR DEL VIDRIO = 8 ó 10 mm. | B11: E | D11: 10 | E11: 10 | F11: 8 | G11: 8 | K11: 10 | L11: 10
A12: ESMERILADO = E | B12: ES
A13: VIENTOS VIDRIO ( 1 ) o TUBULAR + ARANA ( 2 ) | D13: 2 | E13: 1 | F13: 2 | G13: 2 | K13: 1 | L13: 2
A14: MODULOS
A15: ANCHO ( metros ) | D15: =+D5/D8 -> 1.5 | E15: =+E5/E8 -> 1.5 | F15: =+F5/F8 -> 1.5 | G15: =+G5/G8 -> 1.5 | K15: =+K5/K8 -> 1.2 | L15: =+L5/L8 -> 1.2
A16: ALTO ( metros ) | D16: =+D6/D9 -> 1.5 | E16: =+E6/E9 -> 1.5 | F16: =+F6/F9 -> 1.5 | G16: =+G6/G9 -> 1.5 | K16: =+K6/K9 -> 2 | L16: =+L6/L9 -> 2
A17: Total Precio c/factura | C17: pn | D17: =+D46 -> 4008.864 | E17: =+E46 -> 2944.233 | F17: =+F46 -> 3926.1 | G17: =+G46 -> 4490.046 | I17: =SUM(K17:IV17) -> 150891.84 | J17: $us. | K17: =+K46 -> 40178.336 | L17: =+L46 -> 110713.5
A18: Superficie Mt² | D18: =+D5*D6*D$7+IF(D13=1,D7*D6*(D8-1)*0.2,0) -> 36 | E18: =+E5*E6*E$7+IF(E13=1,E7*E6*(E8-1)*0.2,0) -> 39.6 | F18: =+F5*F6*F$7+IF(F13=1,F7*F6*(F8-1)*0.2,0) -> 36 | G18: =+G5*G6*G$7+IF(G13=1,G7*G6*(G8-1)*0.2,0) -> 36 | I18: =SUM(K18:IV18) -> 1228.8 | J18: Mt² | K18: =+K5*K6*K$7+IF(K13=1,K7*K6*(K8-1)*0.2,0) -> 652.8 | L18: =+L5*L6*L$7+IF(L13=1,L7*L6*(L8-1)*0.2,0) -> 576
A19: Precio con factura en $us / Mt² | D19: =+D17/D18 -> 111.35733 | E19: =+E17/E18 -> 74.349318 | F19: =+F17/F18 -> 109.05833 | G19: =+G17/G18 -> 124.7235 | I19: =+I17/I18 -> 122.79609 | J19: $us./Mt² | K19: =+K17/K18 -> 61.547696 | L19: =+L17/L18 -> 192.21094
A20: Total Precio s/factura | D20: =+D67 -> 3704.334 | E20: =+E67 -> 2722.014 | F20: =+F67 -> 3624.474 | G20: =+G67 -> 4169.634 | I20: =SUM(K20:IV20) -> 142475.01 | J20: $us. | K20: =+K67 -> 36793.344 | L20: =+L67 -> 105681.66
A21: Precio sin factura en $us / Mt² | D21: =+D20/D18 -> 102.89817 | E21: =+E20/E18 -> 68.737727 | F21: =+F20/F18 -> 100.67983 | G21: =+G20/G18 -> 115.82317 | I21: =+I20/I18 -> 115.94646 | J21: $us./Mt² | K21: =+K20/K18 -> 56.362353 | L21: =+L20/L18 -> 183.47511
A22: % descuento del con al sin | D22: =+(D17-D20)/D17 -> 0.075964163 | E22: =+(E17-E20)/E17 -> 0.075476024 | F22: =+(F17-F20)/F17 -> 0.076825858 | G22: =+(G17-G20)/G17 -> 0.071360516 | I22: =+(I17-I20)/I17 -> 0.055780564 | K22: =+(K17-K20)/K17 -> 0.084249183 | L22: =+(L17-L20)/L17 -> 0.045449198
A24: DETALLE DE MATERIALES A UTILIZAR
A25: MATERIAL | C25: Unidad | D25: =+D2 -> PF | E25: =+E2 -> PF | F25: =+F2 -> PF | G25: =+G2 -> PF | I25: Cantidad | J25: Unidad | K25: =+K2 -> PF | L25: =+L2 -> PF
A26: Vidrio Templado 10mm Incoloro | C26: Mt² | D26: =IF(D$10=1,IF(D$11=10,((D$6*0.05)+(D$5*D$6))*D$7+IF(D13=1,D$7*D6*(D8-1)*0.2,0),0),0) -> 36.3 | E26: =IF(E$10=1,IF(E$11=10,((E$6*0.05)+(E$5*E$6))*E$7+IF(E13=1,E$7*E6*(E8-1)*0.2,0),0),0) -> 0 | F26: =IF(F$10=1,IF(F$11=10,((F$6*0.05)+(F$5*F$6))*F$7+IF(F13=1,F$7*F6*(F8-1)*0.2,0),0),0) -> 0 | G26: =IF(G$10=1,IF(G$11=10,((G$6*0.05)+(G$5*G$6))*G$7+IF(G13=1,G$7*G6*(G8-1)*0.2,0),0),0) -> 0 | I26: =ROUNDUP(SUM(K26:IV26),1) -> 1238.4 | J26: Mt² | K26: =IF(K$10=1,IF(K$11=10,((K$6*0.05)+(K$5*K$6))*K$7+IF(K13=1,K$7*K6*(K8-1)*0.2,0),0),0) -> 657.6 | L26: =IF(L$10=1,IF(L$11=10,((L$6*0.05)+(L$5*L$6))*L$7+IF(L13=1,L$7*L6*(L8-1)*0.2,0),0),0) -> 580.8
A27: Vidrio Templado 10mm Color | C27: Mt² | D27: =IF(D$10=2,IF(D$11=10,((D$6*0.05)+(D$5*D$6))*D$7+IF(D13=1,D7*D6*(D8-1)*0.2,0),0),0) -> 0 | E27: =IF(E$10=2,IF(E$11=10,((E$6*0.05)+(E$5*E$6))*E$7+IF(E13=1,E7*E6*(E8-1)*0.2,0),0),0) -> 39.9 | F27: =IF(F$10=2,IF(F$11=10,((F$6*0.05)+(F$5*F$6))*F$7+IF(F13=1,F7*F6*(F8-1)*0.2,0),0),0) -> 0 | G27: =IF(G$10=2,IF(G$11=10,((G$6*0.05)+(G$5*G$6))*G$7+IF(G13=1,G7*G6*(G8-1)*0.2,0),0),0) -> 0 | I27: =ROUNDUP(SUM(K27:IV27),1) -> 0 | J27: Mt² | K27: =IF(K$10=2,IF(K$11=10,((K$6*0.05)+(K$5*K$6))*K$7+IF(K13=1,K7*K6*(K8-1)*0.2,0),0),0) -> 0 | L27: =IF(L$10=2,IF(L$11=10,((L$6*0.05)+(L$5*L$6))*L$7+IF(L13=1,L7*L6*(L8-1)*0.2,0),0),0) -> 0
A28: Vidrio Templado 8mm Incoloro | C28: Mt² | D28: =IF(D$10=1,IF(D$11=8,((D$6*0.05)+(D$5*D$6))*D$7+IF(D13=1,D7*D6*(D8-1)*0.2,0),0),0) -> 0 | E28: =IF(E$10=1,IF(E$11=8,((E$6*0.05)+(E$5*E$6))*E$7+IF(E13=1,E7*E6*(E8-1)*0.2,0),0),0) -> 0 | F28: =IF(F$10=1,IF(F$11=8,((F$6*0.05)+(F$5*F$6))*F$7+IF(F13=1,F7*F6*(F8-1)*0.2,0),0),0) -> 36.3 | G28: =IF(G$10=1,IF(G$11=8,((G$6*0.05)+(G$5*G$6))*G$7+IF(G13=1,G7*G6*(G8-1)*0.2,0),0),0) -> 0 | I28: =ROUNDUP(SUM(K28:IV28),1) -> 0 | J28: Mt² | K28: =IF(K$10=1,IF(K$11=8,((K$6*0.05)+(K$5*K$6))*K$7+IF(K13=1,K7*K6*(K8-1)*0.2,0),0),0) -> 0 | L28: =IF(L$10=1,IF(L$11=8,((L$6*0.05)+(L$5*L$6))*L$7+IF(L13=1,L7*L6*(L8-1)*0.2,0),0),0) -> 0
A29: Vidrio Templado 8mm Color | C29: Mt² | D29: =IF(D$10=2,IF(D$11=8,((D$5*D$6))*D$7+IF(D13=1,D7*D6*(D8-1)*0.2,0),0),0) -> 0 | E29: =IF(E$10=2,IF(E$11=8,((E$5*E$6))*E$7+IF(E13=1,E7*E6*(E8-1)*0.2,0),0),0) -> 0 | F29: =IF(F$10=2,IF(F$11=8,((F$5*F$6))*F$7+IF(F13=1,F7*F6*(F8-1)*0.2,0),0),0) -> 0 | G29: =IF(G$10=2,IF(G$11=8,((G$5*G$6))*G$7+IF(G13=1,G7*G6*(G8-1)*0.2,0),0),0) -> 36 | I29: =ROUNDUP(SUM(K29:IV29),1) -> 0 | J29: Mt² | K29: =IF(K$10=2,IF(K$11=8,((K$5*K$6))*K$7+IF(K13=1,K7*K6*(K8-1)*0.2,0),0),0) -> 0 | L29: =IF(L$10=2,IF(L$11=8,((L$5*L$6))*L$7+IF(L13=1,L7*L6*(L8-1)*0.2,0),0),0) -> 0
A30: Mano de obra | C30: Mt² | D30: =+D18 -> 36 | E30: =+E18 -> 39.6 | F30: =+F18 -> 36 | G30: =+G18 -> 36 | I30: =ROUNDUP(SUM(K30:IV30),1) -> 1228.8 | J30: Mt² | K30: =+K18 -> 652.8 | L30: =+L18 -> 576
A31: Silicona transp., blanca o negra | C31: Tubo | D31: =D7*(4*D5+4*D6+(D8-1)*D6+(D9-1)*D5)/6 -> 14 | E31: =E7*(4*E5+4*E6+(E8-1)*E6+(E9-1)*E5)/6 -> 14 | F31: =F7*(4*F5+4*F6+(F8-1)*F6+(F9-1)*F5)/6 -> 14 | G31: =G7*(4*G5+4*G6+(G8-1)*G6+(G9-1)*G5)/6 -> 14 | I31: =ROUNDUP(SUM(K31:IV31),1) -> 448 | J31: Tubo | K31: =K7*(4*K5+4*K6+(K8-1)*K6+(K9-1)*K5)/6 -> 224 | L31: =L7*(4*L5+4*L6+(L8-1)*L6+(L9-1)*L5)/6 -> 224
A32: Cinta masking 1/2 " (rollo de 20) | C32: Rollo | D32: =+D7*D31*12/20 -> 8.4 | E32: =+E7*E31*12/20 -> 8.4 | F32: =+F7*F31*12/20 -> 8.4 | G32: =+G7*G31*12/20 -> 8.4 | I32: =ROUNDUP(SUM(K32:IV32),1) -> 4300.8 | J32: Rollo | K32: =+K7*K31*12/20 -> 2150.4 | L32: =+L7*L31*12/20 -> 2150.4
A33: "U" 15x25 - Kg/Mt lineal. | B33: 0.2 | C33: Kgr | D33: =(2*D$6+2*D5)*$B33*D$7 -> 4.8 | E33: =(2*E$6+2*E5)*$B33*E$7 -> 4.8 | F33: =(2*F$6+2*F5)*$B33*F$7 -> 4.8 | G33: =(2*G$6+2*G5)*$B33*G$7 -> 4.8 | I33: =ROUNDUP(SUM(K33:IV33)/(6*B33),1) -> 128 | J33: BARRAS | K33: =(2*K$6+2*K5)*$B33*K$7 -> 76.8 | L33: =(2*L$6+2*L5)*$B33*L$7 -> 76.8
A34: Esmerilado | C34: Mt² | D34: =IF((D12="e"),D18*D7,IF( (D12="E"),D18*D7,0)) -> 0 | E34: =IF((E12="e"),E18*E7,IF( (E12="E"),E18*E7,0)) -> 0 | F34: =IF((F12="e"),F18*F7,IF( (F12="E"),F18*F7,0)) -> 0 | G34: =IF((G12="e"),G18*G7,IF( (G12="E"),G18*G7,0)) -> 0 | I34: =ROUNDUP(SUM(K34:IV34),1) -> 0 | J34: Mt² | K34: =IF((K12="e"),K18*K7,IF( (K12="E"),K18*K7,0)) -> 0 | L34: =IF((L12="e"),L18*L7,IF( (L12="E"),L18*L7,0)) -> 0
A35: Tarugos No. 6 | C35: Pza. | D35: =D$7*(2*D$5+2*D$6)/0.4 -> 60 | E35: =E$7*(2*E$5+2*E$6)/0.4 -> 60 | F35: =F$7*(2*F$5+2*F$6)/0.4 -> 60 | G35: =G$7*(2*G$5+2*G$6)/0.4 -> 60 | I35: =ROUNDUP(SUM(K35:IV35),1) -> 1920 | J35: Pza. | K35: =K$7*(2*K$5+2*K$6)/0.4 -> 960 | L35: =L$7*(2*L$5+2*L$6)/0.4 -> 960
A36: Tornillos 8 x 1 1/2 | C36: Pza. | D36: =D$7*(2*D$5+2*D$6)/0.4 -> 60 | E36: =E$7*(2*E$5+2*E$6)/0.4 -> 60 | F36: =F$7*(2*F$5+2*F$6)/0.4 -> 60 | G36: =G$7*(2*G$5+2*G$6)/0.4 -> 60 | I36: =ROUNDUP(SUM(K36:IV36),1) -> 1920 | J36: Pza. | K36: =K$7*(2*K$5+2*K$6)/0.4 -> 960 | L36: =L$7*(2*L$5+2*L$6)/0.4 -> 960
A37: Tubo galvanizado de 4" | C37: Mt.lin. | D37: =IF(D13=2,D7*(D8-1)*D6,0) -> 18 | E37: =IF(E13=2,E7*(E8-1)*E6,0) -> 0 | F37: =IF(F13=2,F7*(F8-1)*F6,0) -> 18 | G37: =IF(G13=2,G7*(G8-1)*G6,0) -> 18 | I37: =ROUNDUP(SUM(K37:IV37),1) -> 384 | J37: Mt.lin. | K37: =IF(K13=2,K7*(K8-1)*K6,0) -> 0 | L37: =IF(L13=2,L7*(L8-1)*L6,0) -> 384
A38: Herraje arana | C38: Pza. | D38: =IF(D13=2,D7*(D8-1)*(D9-1),0) -> 9 | E38: =IF(E13=2,E7*(E8-1)*(E9-1),0) -> 0 | F38: =IF(F13=2,F7*(F8-1)*(F9-1),0) -> 9 | G38: =IF(G13=2,G7*(G8-1)*(G9-1),0) -> 9 | I38: =ROUNDUP(SUM(K38:IV38),1) -> 128 | J38: Pza. | K38: =IF(K13=2,K7*(K8-1)*(K9-1),0) -> 0 | L38: =IF(L13=2,L7*(L8-1)*(L9-1),0) -> 128
A39: Soporte Herraje - tubo | C39: Pza. | D39: =+D38*D7 -> 9 | E39: =+E38*E7 -> 0 | F39: =+F38*F7 -> 9 | G39: =+G38*G7 -> 9 | I39: =ROUNDUP(SUM(K39:IV39),1) -> 2048 | J39: Pza. | K39: =+K38*K7 -> 0 | L39: =+L38*L7 -> 2048
A40: Anclaje tubo | C40: Pza. | D40: =+(D8-1)*2*D7 -> 6 | E40: =+(E8-1)*2*E7 -> 6 | F40: =+(F8-1)*2*F7 -> 6 | G40: =+(G8-1)*2*G7 -> 6 | I40: =ROUNDUP(SUM(K40:IV40),1) -> 256 | J40: Pza. | K40: =+(K8-1)*2*K7 -> 128 | L40: =+(L8-1)*2*L7 -> 128
A41: 1318 | C41: Pza. | D41: =IF(D13=1,D7*(D8-1)*(D9-1),0) -> 0 | E41: =IF(E13=1,E7*(E8-1)*(E9-1),0) -> 9 | F41: =IF(F13=1,F7*(F8-1)*(F9-1),0) -> 0 | G41: =IF(G13=1,G7*(G8-1)*(G9-1),0) -> 0 | I41: =ROUNDUP(SUM(K41:IV41),1) -> 128 | J41: Pza. | K41: =IF(K13=1,K7*(K8-1)*(K9-1),0) -> 128 | L41: =IF(L13=1,L7*(L8-1)*(L9-1),0) -> 0
A42: 1302 | C42: Pza. | D42: =IF(D13=1,D7*2*(D8-1),0) -> 0 | E42: =IF(E13=1,E7*2*(E8-1),0) -> 6 | F42: =IF(F13=1,F7*2*(F8-1),0) -> 0 | G42: =IF(G13=1,G7*2*(G8-1),0) -> 0 | I42: =ROUNDUP(SUM(K42:IV42),1) -> 128 | J42: Pza. | K42: =IF(K13=1,K7*2*(K8-1),0) -> 128 | L42: =IF(L13=1,L7*2*(L8-1),0) -> 0
A43: 1304 | C43: Pza. | D43: =IF(D13=1,D7*(D8-1)*(D9-1),0) -> 0 | E43: =IF(E13=1,E7*(E8-1)*(E9-1),0) -> 9 | F43: =IF(F13=1,F7*(F8-1)*(F9-1),0) -> 0 | G43: =IF(G13=1,G7*(G8-1)*(G9-1),0) -> 0 | I43: =ROUNDUP(SUM(K43:IV43),1) -> 128 | J43: Pza. | K43: =IF(K13=1,K7*(K8-1)*(K9-1),0) -> 128 | L43: =IF(L13=1,L7*(L8-1)*(L9-1),0) -> 0
A46: COSTO CON FACTURA | D46: =SUM(D47:D64) -> 4008.864 | E46: =SUM(E47:E64) -> 2944.233 | F46: =SUM(F47:F64) -> 3926.1 | G46: =SUM(G47:G64) -> 4490.046 | I46: =SUM(I47:I63) -> 150019.4 | K46: =SUM(K47:K64) -> 40178.336 | L46: =SUM(L47:L64) -> 110713.5
A47: Vidrio Templado 10mm Incoloro | C47: =+'Costo M.P.yMat.'!C26 -> 36.46 | D47: =+$C47*D26 -> 1323.498 | E47: =+$C47*E26 -> 0 | F47: =+$C47*F26 -> 0 | G47: =+$C47*G26 -> 0 | I47: =ROUNDUP(SUM(K47:IV47),1) -> 45152.1 | K47: =+$C47*K26 -> 23976.096 | L47: =+$C47*L26 -> 21175.968
A48: Vidrio Templado 10mm Color | C48: =+'Costo M.P.yMat.'!C31 -> 52.41 | D48: =+$C48*D27 -> 0 | E48: =+$C48*E27 -> 2091.159 | F48: =+$C48*F27 -> 0 | G48: =+$C48*G27 -> 0 | I48: =ROUNDUP(SUM(K48:IV48),1) -> 0 | K48: =+$C48*K27 -> 0 | L48: =+$C48*L27 -> 0
A49: Vidrio Templado 8mm Incoloro | C49: =+'Costo M.P.yMat.'!C27 -> 34.18 | D49: =+$C49*D28 -> 0 | E49: =+$C49*E28 -> 0 | F49: =+$C49*F28 -> 1240.734 | G49: =+$C49*G28 -> 0 | I49: =ROUNDUP(SUM(K49:IV49),1) -> 0 | K49: =+$C49*K28 -> 0 | L49: =+$C49*L28 -> 0
A50: Vidrio Templado 8mm Color | C50: =+'Costo M.P.yMat.'!C32 -> 50.13 | D50: =+$C50*D29 -> 0 | E50: =+$C50*E29 -> 0 | F50: =+$C50*F29 -> 0 | G50: =+$C50*G29 -> 1804.68 | I50: =ROUNDUP(SUM(K50:IV50),1) -> 0 | K50: =+$C50*K29 -> 0 | L50: =+$C50*L29 -> 0
A51: Mano de obra | C51: =+'Costo M.P.yMat.'!C84 -> 12.08 | D51: =+$C51*D30 -> 434.88 | E51: =+$C51*E30 -> 478.368 | F51: =+$C51*F30 -> 434.88 | G51: =+$C51*G30 -> 434.88 | I51: =ROUNDUP(SUM(K51:IV51),1) -> 14844 | K51: =+$C51*K30 -> 7885.824 | L51: =+$C51*L30 -> 6958.08
A52: Silicona transp., blanca o negra | C52: =+'Costo M.P.yMat.'!C7 -> 2.76 | D52: =+$C52*D31 -> 38.64 | E52: =+$C52*E31 -> 38.64 | F52: =+$C52*F31 -> 38.64 | G52: =+$C52*G31 -> 38.64 | I52: =ROUNDUP(SUM(K52:IV52),1) -> 1236.5 | K52: =+$C52*K31 -> 618.24 | L52: =+$C52*L31 -> 618.24
A53: Cinta masking 1/2 " (rollo de 20) | C53: =+'Costo M.P.yMat.'!C9 -> 0.75 | D53: =+$C53*D32 -> 6.3 | E53: =+$C53*E32 -> 6.3 | F53: =+$C53*F32 -> 6.3 | G53: =+$C53*G32 -> 6.3 | I53: =ROUNDUP(SUM(K53:IV53),1) -> 3225.6 | K53: =+$C53*K32 -> 1612.8 | L53: =+$C53*L32 -> 1612.8
A54: "U" 15x25 - Kg/Mt lineal. | B54: 0.2 | C54: =+'Costo M.P.yMat.'!$C$89 -> 8.82 | D54: =+$C54*D33 -> 42.336 | E54: =+$C54*E33 -> 42.336 | F54: =+$C54*F33 -> 42.336 | G54: =+$C54*G33 -> 42.336 | I54: =ROUNDUP(SUM(K54:IV54),1) -> 1354.8 | K54: =+$C54*K33 -> 677.376 | L54: =+$C54*L33 -> 677.376
A55: Esmerilado | C55: =+'Costo M.P.yMat.'!C160 -> 1.14 | D55: =+$C55*D34 -> 0 | E55: =+$C55*E34 -> 0 | F55: =+$C55*F34 -> 0 | G55: =+$C55*G34 -> 0 | I55: =ROUNDUP(SUM(K55:IV55),1) -> 0 | K55: =+$C55*K34 -> 0 | L55: =+$C55*L34 -> 0
A56: Tarugos No. 6 | C56: =+'Costo M.P.yMat.'!C19 -> 0.04 | D56: =+$C56*D35 -> 2.4 | E56: =+$C56*E35 -> 2.4 | F56: =+$C56*F35 -> 2.4 | G56: =+$C56*G35 -> 2.4 | I56: =ROUNDUP(SUM(K56:IV56),1) -> 76.8 | K56: =+$C56*K35 -> 38.4 | L56: =+$C56*L35 -> 38.4
A57: Tornillos 8 x 1 1/2 | C57: =+'Costo M.P.yMat.'!C20 -> 0.04 | D57: =+$C57*D36 -> 2.4 | E57: =+$C57*E36 -> 2.4 | F57: =+$C57*F36 -> 2.4 | G57: =+$C57*G36 -> 2.4 | I57: =ROUNDUP(SUM(K57:IV57),1) -> 76.8 | K57: =+$C57*K36 -> 38.4 | L57: =+$C57*L36 -> 38.4
A58: Tubo galvanizado de 4" | C58: =+'Costo M.P.yMat.'!C22 -> 29.91 | D58: =+$C58*D37 -> 538.38 | E58: =+$C58*E37 -> 0 | F58: =+$C58*F37 -> 538.38 | G58: =+$C58*G37 -> 538.38 | I58: =ROUNDUP(SUM(K58:IV58),1) -> 11485.5 | K58: =+$C58*K37 -> 0 | L58: =+$C58*L37 -> 11485.44
A59: Herraje arana | C59: =+'Costo M.P.yMat.'!C85 -> 136.72 | D59: =+$C59*D38 -> 1230.48 | E59: =+$C59*E38 -> 0 | F59: =+$C59*F38 -> 1230.48 | G59: =+$C59*G38 -> 1230.48 | I59: =ROUNDUP(SUM(K59:IV59),1) -> 17500.2 | K59: =+$C59*K38 -> 0 | L59: =+$C59*L38 -> 17500.16
A60: Soporte Herraje - tubo | C60: =+'Costo M.P.yMat.'!C86 -> 22.79 | D60: =+$C60*D39 -> 205.11 | E60: =+$C60*E39 -> 0 | F60: =+$C60*F39 -> 205.11 | G60: =+$C60*G39 -> 205.11 | I60: =ROUNDUP(SUM(K60:IV60),1) -> 46674 | K60: =+$C60*K39 -> 0 | L60: =+$C60*L39 -> 46673.92
A61: Anclaje tubo | C61: =+'Costo M.P.yMat.'!C158 -> 13.68 | D61: =+$C61*D40 -> 82.08 | E61: =+$C61*E40 -> 82.08 | F61: =+$C61*F40 -> 82.08 | G61: =+$C61*G40 -> 82.08 | I61: =ROUNDUP(SUM(K61:IV61),1) -> 3502.1 | K61: =+$C61*K40 -> 1751.04 | L61: =+$C61*L40 -> 1751.04
A62: 1318 | C62: =+'Costo M.P.yMat.'!C68 -> 17.06 | D62: =+$C62*D40 -> 102.36 | E62: =+$C62*E40 -> 102.36 | F62: =+$C62*F40 -> 102.36 | G62: =+$C62*G40 -> 102.36 | I62: =ROUNDUP(SUM(K62:IV62),1) -> 4367.4 | K62: =+$C62*K40 -> 2183.68 | L62: =+$C62*L40 -> 2183.68
A63: 1302 | C63: =+'Costo M.P.yMat.'!C64 -> 4.09 | D63: =+$C63*D41 -> 0 | E63: =+$C63*E41 -> 36.81 | F63: =+$C63*F41 -> 0 | G63: =+$C63*G41 -> 0 | I63: =ROUNDUP(SUM(K63:IV63),1) -> 523.6 | K63: =+$C63*K41 -> 523.52 | L63: =+$C63*L41 -> 0
A64: 1304 | C64: =+'Costo M.P.yMat.'!C65 -> 6.82 | D64: =+$C64*D43 -> 0 | E64: =+$C64*E43 -> 61.38 | F64: =+$C64*F43 -> 0 | G64: =+$C64*G43 -> 0 | I64: =ROUNDUP(SUM(K64:IV64),1) -> 873 | K64: =+$C64*K43 -> 872.96 | L64: =+$C64*L43 -> 0
A67: COSTO SIN FACTURA | D67: =SUM(D68:D85) -> 3704.334 | E67: =SUM(E68:E85) -> 2722.014 | F67: =SUM(F68:F85) -> 3624.474 | G67: =SUM(G68:G85) -> 4169.634 | I67: =SUM(I68:I84) -> 141680.5 | K67: =SUM(K68:K85) -> 36793.344 | L67: =SUM(L68:L85) -> 105681.66
A68: Vidrio Templado 10mm Incoloro | C68: =+'Costo M.P.yMat.'!D26 -> 33 | D68: =+$C68*D26 -> 1197.9 | E68: =+$C68*E26 -> 0 | F68: =+$C68*F26 -> 0 | G68: =+$C68*G26 -> 0 | I68: =ROUNDUP(SUM(K68:IV68),1) -> 40867.2 | K68: =+$C68*K26 -> 21700.8 | L68: =+$C68*L26 -> 19166.4
A69: Vidrio Templado 10mm Color | C69: =+'Costo M.P.yMat.'!D31 -> 48.4 | D69: =+$C69*D27 -> 0 | E69: =+$C69*E27 -> 1931.16 | F69: =+$C69*F27 -> 0 | G69: =+$C69*G27 -> 0 | I69: =ROUNDUP(SUM(K69:IV69),1) -> 0 | K69: =+$C69*K27 -> 0 | L69: =+$C69*L27 -> 0
A70: Vidrio Templado 8mm Incoloro | C70: =+'Costo M.P.yMat.'!D27 -> 30.8 | D70: =+$C70*D28 -> 0 | E70: =+$C70*E28 -> 0 | F70: =+$C70*F28 -> 1118.04 | G70: =+$C70*G28 -> 0 | I70: =ROUNDUP(SUM(K70:IV70),1) -> 0 | K70: =+$C70*K28 -> 0 | L70: =+$C70*L28 -> 0
A71: Vidrio Templado 8mm Color | C71: =+'Costo M.P.yMat.'!D32 -> 46.2 | D71: =+$C71*D29 -> 0 | E71: =+$C71*E29 -> 0 | F71: =+$C71*F29 -> 0 | G71: =+$C71*G29 -> 1663.2 | I71: =ROUNDUP(SUM(K71:IV71),1) -> 0 | K71: =+$C71*K29 -> 0 | L71: =+$C71*L29 -> 0
A72: Mano de obra | C72: =+'Costo M.P.yMat.'!D84 -> 11 | D72: =+$C72*D30 -> 396 | E72: =+$C72*E30 -> 435.6 | F72: =+$C72*F30 -> 396 | G72: =+$C72*G30 -> 396 | I72: =ROUNDUP(SUM(K72:IV72),1) -> 13516.8 | K72: =+$C72*K30 -> 7180.8 | L72: =+$C72*L30 -> 6336
A73: Silicona transp., blanca o negra | C73: =+'Costo M.P.yMat.'!D7 -> 2.67 | D73: =+$C73*D31 -> 37.38 | E73: =+$C73*E31 -> 37.38 | F73: =+$C73*F31 -> 37.38 | G73: =+$C73*G31 -> 37.38 | I73: =ROUNDUP(SUM(K73:IV73),1) -> 1196.2 | K73: =+$C73*K31 -> 598.08 | L73: =+$C73*L31 -> 598.08
A74: Cinta masking 1/2 " (rollo de 20) | C74: =+'Costo M.P.yMat.'!D9 -> 0.72 | D74: =+$C74*D32 -> 6.048 | E74: =+$C74*E32 -> 6.048 | F74: =+$C74*F32 -> 6.048 | G74: =+$C74*G32 -> 6.048 | I74: =ROUNDUP(SUM(K74:IV74),1) -> 3096.6 | K74: =+$C74*K32 -> 1548.288 | L74: =+$C74*L32 -> 1548.288
A75: "U" 15x25 - Kg/Mt lineal. | B75: 0.2 | C75: =+'Costo M.P.yMat.'!$C$89 -> 8.82 | D75: =+$C75*D33 -> 42.336 | E75: =+$C75*E33 -> 42.336 | F75: =+$C75*F33 -> 42.336 | G75: =+$C75*G33 -> 42.336 | I75: =ROUNDUP(SUM(K75:IV75),1) -> 1354.8 | K75: =+$C75*K33 -> 677.376 | L75: =+$C75*L33 -> 677.376
A76: Esmerilado | C76: =+'Costo M.P.yMat.'!D160 -> 1.1 | D76: =+$C76*D34 -> 0 | E76: =+$C76*E34 -> 0 | F76: =+$C76*F34 -> 0 | G76: =+$C76*G34 -> 0 | I76: =ROUNDUP(SUM(K76:IV76),1) -> 0 | K76: =+$C76*K34 -> 0 | L76: =+$C76*L34 -> 0
A77: Tarugos No. 6 | C77: =+'Costo M.P.yMat.'!D19 -> 0.04 | D77: =+$C77*D35 -> 2.4 | E77: =+$C77*E35 -> 2.4 | F77: =+$C77*F35 -> 2.4 | G77: =+$C77*G35 -> 2.4 | I77: =ROUNDUP(SUM(K77:IV77),1) -> 76.8 | K77: =+$C77*K35 -> 38.4 | L77: =+$C77*L35 -> 38.4
A78: Tornillos 8 x 1 1/2 | C78: =+'Costo M.P.yMat.'!D20 -> 0.04 | D78: =+$C78*D36 -> 2.4 | E78: =+$C78*E36 -> 2.4 | F78: =+$C78*F36 -> 2.4 | G78: =+$C78*G36 -> 2.4 | I78: =ROUNDUP(SUM(K78:IV78),1) -> 76.8 | K78: =+$C78*K36 -> 38.4 | L78: =+$C78*L36 -> 38.4
A79: Tubo galvanizado de 4" | C79: =+'Costo M.P.yMat.'!D22 -> 27.72 | D79: =+$C79*D37 -> 498.96 | E79: =+$C79*E37 -> 0 | F79: =+$C79*F37 -> 498.96 | G79: =+$C79*G37 -> 498.96 | I79: =ROUNDUP(SUM(K79:IV79),1) -> 10644.5 | K79: =+$C79*K37 -> 0 | L79: =+$C79*L37 -> 10644.48
A80: Herraje arana | C80: =+'Costo M.P.yMat.'!D85 -> 126.72 | D80: =+$C80*D38 -> 1140.48 | E80: =+$C80*E38 -> 0 | F80: =+$C80*F38 -> 1140.48 | G80: =+$C80*G38 -> 1140.48 | I80: =ROUNDUP(SUM(K80:IV80),1) -> 16220.2 | K80: =+$C80*K38 -> 0 | L80: =+$C80*L38 -> 16220.16
A81: Soporte Herraje - tubo | C81: =+'Costo M.P.yMat.'!C86 -> 22.79 | D81: =+$C81*D39 -> 205.11 | E81: =+$C81*E39 -> 0 | F81: =+$C81*F39 -> 205.11 | G81: =+$C81*G39 -> 205.11 | I81: =ROUNDUP(SUM(K81:IV81),1) -> 46674 | K81: =+$C81*K39 -> 0 | L81: =+$C81*L39 -> 46673.92
A82: Anclaje tubo | C82: =+'Costo M.P.yMat.'!C158 -> 13.68 | D82: =+$C82*D40 -> 82.08 | E82: =+$C82*E40 -> 82.08 | F82: =+$C82*F40 -> 82.08 | G82: =+$C82*G40 -> 82.08 | I82: =ROUNDUP(SUM(K82:IV82),1) -> 3502.1 | K82: =+$C82*K40 -> 1751.04 | L82: =+$C82*L40 -> 1751.04
A83: 1318 | C83: =+'Costo M.P.yMat.'!D68 -> 15.54 | D83: =+$C83*D40 -> 93.24 | E83: =+$C83*E40 -> 93.24 | F83: =+$C83*F40 -> 93.24 | G83: =+$C83*G40 -> 93.24 | I83: =ROUNDUP(SUM(K83:IV83),1) -> 3978.3 | K83: =+$C83*K40 -> 1989.12 | L83: =+$C83*L40 -> 1989.12
A84: 1302 | C84: =+'Costo M.P.yMat.'!D64 -> 3.72 | D84: =+$C84*D41 -> 0 | E84: =+$C84*E41 -> 33.48 | F84: =+$C84*F41 -> 0 | G84: =+$C84*G41 -> 0 | I84: =ROUNDUP(SUM(K84:IV84),1) -> 476.2 | K84: =+$C84*K41 -> 476.16 | L84: =+$C84*L41 -> 0
A85: 1304 | C85: =+'Costo M.P.yMat.'!D65 -> 6.21 | D85: =+$C85*D43 -> 0 | E85: =+$C85*E43 -> 55.89 | F85: =+$C85*F43 -> 0 | G85: =+$C85*G43 -> 0 | I85: =ROUNDUP(SUM(K85:IV85),1) -> 794.9 | K85: =+$C85*K43 -> 794.88 | L85: =+$C85*L43 -> 0
A88: FORMULA CON TUBOS Y ARANAS | C88: BASE | D88: ALTURA | E88: ALTURA | F88: ALTURA | G88: ALTURA | I88: BXH | J88: (N-1)*(M-1) | K88: ALTURA | L88: ALTURA
A89: Vidrio Templado 10mm Incoloro | B89: =+C47 -> 36.46
A90: Vidrio Templado 10mm Color | B90: =+C48 -> 52.41
A91: Vidrio Templado 8mm Incoloro | B91: =+C49 -> 34.18
A92: Vidrio Templado 8mm Color | B92: =+C50 -> 50.13
A93: Mano de obra | B93: =+C51 -> 12.08 | I93: 1
A94: Silicona transp., blanca o negra | B94: =+C52 -> 2.76 | C94: 0.34 | D94: 0.34 | E94: 0.34 | F94: 0.34 | G94: 0.34 | K94: 0.34 | L94: 0.34
A95: Cinta masking 1/2 " (rollo de 20) | B95: =+C53 -> 0.75 | C95: 0.4 | D95: 0.4 | E95: 0.4 | F95: 0.4 | G95: 0.4 | K95: 0.4 | L95: 0.4
A96: "U" 15x15 - Kg/Mt lineal. | B96: =+C54 -> 8.82 | C96: =2*0.159 -> 0.318 | D96: =2*0.159 -> 0.318 | E96: =2*0.159 -> 0.318 | F96: =2*0.159 -> 0.318 | G96: =2*0.159 -> 0.318 | K96: =2*0.159 -> 0.318 | L96: =2*0.159 -> 0.318
A97: Esmerilado | B97: =+C55 -> 1.14 | I97: 1
A98: Tarugos No. 6 | B98: =+C56 -> 0.04 | C98: 5 | D98: 5 | E98: 5 | F98: 5 | G98: 5 | K98: 5 | L98: 5
A99: Tornillos 8 x 1 1/2 | B99: =+C57 -> 0.04 | C99: 5 | D99: 5 | E99: 5 | F99: 5 | G99: 5 | K99: 5 | L99: 5
A100: Tubo galvanizado de 4" | B100: =+C58 -> 29.91
A101: Herraje arana | B101: =+C59 -> 136.72 | J101: 1
A102: Soporte Herraje - tubo | B102: =+C60 -> 22.79 | J102: 1
A103: Anclaje tubo | B103: =+C61 -> 13.68
A104: 1318 | B104: =+C62 -> 17.06
A105: 1302 | B105: =+C63 -> 4.09
A107: Vidrio Templado 10mm Incoloro | C107: =SUMPRODUCT($B$89:$B$105,C$89:C$105) -> 4.44316 | D107: =SUMPRODUCT($B$89:$B$105,D$89:D$105) -> 4.44316 | E107: =SUMPRODUCT($B$89:$B$105,E$89:E$105) -> 4.44316 | F107: =SUMPRODUCT($B$89:$B$105,F$89:F$105) -> 4.44316 | G107: =SUMPRODUCT($B$89:$B$105,G$89:G$105) -> 4.44316 | I107: =SUMPRODUCT($B$89:$B$105,I$89:I$105)+B89 -> 49.68 | J107: =SUMPRODUCT($B$89:$B$105,J$89:J$105) -> 159.51 | K107: =SUMPRODUCT($B$89:$B$105,K$89:K$105) -> 4.44316 | L107: =SUMPRODUCT($B$89:$B$105,L$89:L$105) -> 4.44316
A108: Vidrio Templado 10mm Color | C108: =SUMPRODUCT($B$89:$B$105,C$89:C$105) -> 4.44316 | D108: =SUMPRODUCT($B$89:$B$105,D$89:D$105) -> 4.44316 | E108: =SUMPRODUCT($B$89:$B$105,E$89:E$105) -> 4.44316 | F108: =SUMPRODUCT($B$89:$B$105,F$89:F$105) -> 4.44316 | G108: =SUMPRODUCT($B$89:$B$105,G$89:G$105) -> 4.44316 | I108: =SUMPRODUCT($B$89:$B$105,I$89:I$105)+B90 -> 65.63 | J108: =SUMPRODUCT($B$89:$B$105,J$89:J$105) -> 159.51 | K108: =SUMPRODUCT($B$89:$B$105,K$89:K$105) -> 4.44316 | L108: =SUMPRODUCT($B$89:$B$105,L$89:L$105) -> 4.44316
A109: Vidrio Templado 8mm Incoloro | C109: =SUMPRODUCT($B$89:$B$105,C$89:C$105) -> 4.44316 | D109: =SUMPRODUCT($B$89:$B$105,D$89:D$105) -> 4.44316 | E109: =SUMPRODUCT($B$89:$B$105,E$89:E$105) -> 4.44316 | F109: =SUMPRODUCT($B$89:$B$105,F$89:F$105) -> 4.44316 | G109: =SUMPRODUCT($B$89:$B$105,G$89:G$105) -> 4.44316 | I109: =SUMPRODUCT($B$89:$B$105,I$89:I$105)+B91 -> 47.4 | J109: =SUMPRODUCT($B$89:$B$105,J$89:J$105) -> 159.51 | K109: =SUMPRODUCT($B$89:$B$105,K$89:K$105) -> 4.44316 | L109: =SUMPRODUCT($B$89:$B$105,L$89:L$105) -> 4.44316
...

Sheet P-V.Corrediza
A2: PUERTA / VENTANA CORREDIZA | D2: =IF(D8=1,"PC2H","VC2H") -> PC2H | E2: =IF(E8=1,"PC4H","VC4H") -> PC4H | G2: Total | I2: =IF(I8=1,"PC2H","VC2H") -> VC2H | J2: =IF(J8=1,"PC2H","VC2H") -> VC2H | K2: =IF(K8=1,"PC2H","VC2H") -> VC2H | L2: =IF(L8=1,"PC2H","VC2H") -> VC2H | M2: =IF(M8=1,"PC2H","VC2H") -> VC2H | N2: =IF(N8=1,"PC2H","VC2H") -> VC2H | O2: =IF(O8=1,"PC2H","VC2H") -> VC2H | P2: =IF(P8=1,"PC2H","VC2H") -> VC2H | Q2: =IF(Q8=1,"PC2H","VC2H") -> PC2H
A3: 8 o 10 mm. c/PERFIL U 15x15 DE ALUMINIO | D3: =IF(D10=8,"8 mm.","10 mm.") -> 10 mm. | E3: =IF(E10=8,"8 mm.","10 mm.") -> 8 mm. | I3: =IF(I10=8,"8 mm.","10 mm.") -> 10 mm. | J3: =IF(J10=8,"8 mm.","10 mm.") -> 10 mm. | K3: =IF(K10=8,"8 mm.","10 mm.") -> 10 mm. | L3: =IF(L10=8,"8 mm.","10 mm.") -> 10 mm. | M3: =IF(M10=8,"8 mm.","10 mm.") -> 10 mm. | N3: =IF(N10=8,"8 mm.","10 mm.") -> 10 mm. | O3: =IF(O10=8,"8 mm.","10 mm.") -> 10 mm. | P3: =IF(P10=8,"8 mm.","10 mm.") -> 10 mm. | Q3: =IF(Q10=8,"8 mm.","10 mm.") -> 10 mm.
A4: DATOS BASE PARA EL ANALISIS | D4: =IF(D9=1,"INCOLORO","COLOR") -> INCOLORO | E4: =IF(E9=1,"INCOLORO","COLOR") -> INCOLORO | I4: =IF(I9=1,"INCOLORO","COLOR") -> INCOLORO | J4: =IF(J9=1,"INCOLORO","COLOR") -> INCOLORO | K4: =IF(K9=1,"INCOLORO","COLOR") -> INCOLORO | L4: =IF(L9=1,"INCOLORO","COLOR") -> INCOLORO | M4: =IF(M9=1,"INCOLORO","COLOR") -> INCOLORO | N4: =IF(N9=1,"INCOLORO","COLOR") -> INCOLORO | O4: =IF(O9=1,"INCOLORO","COLOR") -> INCOLORO | P4: =IF(P9=1,"INCOLORO","COLOR") -> INCOLORO | Q4: =IF(Q9=1,"INCOLORO","COLOR") -> INCOLORO
A5: BASE ( Metros ) | D5: 1 | E5: 1 | I5: 1.995 | J5: 2 | K5: 1.2 | L5: 2 | M5: 1.69 | N5: 1.51 | O5: 0.705 | P5: 1.47 | Q5: 1.72
A6: ALTURA ( Metros ) | D6: 1 | E6: 1 | I6: 0.745 | J6: 1.5 | K6: 1.025 | L6: 1.48 | M6: 1.5 | N6: 1.435 | O6: 0.505 | P6: 2 | Q6: 2.1
A7: CANTIDAD DE PIEZAS | D7: 1 | E7: 1 | G7: =SUM(I7:IV7) -> 9 | H7: Pzas. | I7: 1 | J7: 1 | K7: 1 | L7: 1 | M7: 1 | N7: 1 | O7: 1 | P7: 1 | Q7: 1
A8: PUERTA = 1; VENTANA = 2 | D8: 1 | E8: 1 | I8: 2 | J8: 2 | K8: 2 | L8: 2 | M8: 2 | N8: 2 | O8: 2 | P8: 2 | Q8: 1
A9: INCOLORO = 1 ; COLOR =2 | D9: 1 | E9: 1 | I9: 1 | J9: 1 | K9: 1 | L9: 1 | M9: 1 | N9: 1 | O9: 1 | P9: 1 | Q9: 1
A10: ESPESOR DEL VIDRIO = 8 ó 10 mm. | D10: 10 | E10: 8 | I10: 10 | J10: 10 | K10: 10 | L10: 10 | M10: 10 | N10: 10 | O10: 10 | P10: 10 | Q10: 10
A11: Total Precio c/factura | C11: pn | D11: =+D48 -> 116.9145 | E11: =+E48 -> 138.81906 | G11: =SUM(I11:IV11) -> 1573.6438 | H11: $us. | I11: =+I48 -> 138.65044 | J11: =+J48 -> 218.52259 | K11: =+K48 -> 111.90336 | L11: =+L48 -> 216.41433 | M11: =+M48 -> 189.46267 | N11: =+N48 -> 167.28333 | O11: =+O48 -> 54.786362 | P11: =+P48 -> 208.68281 | Q11: =+Q48 -> 267.93789
A12: Superficie Mt² | D12: =+D5*D6*D$7 -> 1 | E12: =+E5*E6*E$7 -> 1 | G12: =SUM(I12:IV12) -> 20.28615 | H12: Mt² | I12: =+I5*I6*I$7 -> 1.486275 | J12: =+J5*J6*J$7 -> 3 | K12: =+K5*K6*K$7 -> 1.23 | L12: =+L5*L6*L$7 -> 2.96 | M12: =+M5*M6*M$7 -> 2.535 | N12: =+N5*N6*N$7 -> 2.16685 | O12: =+O5*O6*O$7 -> 0.356025 | P12: =+P5*P6*P$7 -> 2.94 | Q12: =+Q5*Q6*Q$7 -> 3.612
A13: Precio con factura en $us / Mt² | D13: =+D11/D12 -> 116.9145 | E13: =+E11/E12 -> 138.81906 | G13: =+G11/G12 -> 77.572323 | H13: $us./Mt² | I13: =+I11/I12 -> 93.287205 | J13: =+J11/J12 -> 72.840863 | K13: =+K11/K12 -> 90.978339 | L13: =+L11/L12 -> 73.112951 | M13: =+M11/M12 -> 74.738726 | N13: =+N11/N12 -> 77.20116 | O13: =+O11/O12 -> 153.88347 | P13: =+P11/P12 -> 70.980547 | Q13: =+Q11/Q12 -> 74.179926
A14: Total Precio s/factura | D14: =+D75 -> 108.5535 | E14: =+E75 -> 128.68206 | G14: =SUM(I14:IV14) -> 1460.5356 | H14: $us. | I14: =+I75 -> 129.86611 | J14: =+J75 -> 202.70009 | K14: =+K75 -> 104.30228 | L14: =+L75 -> 200.77781 | M14: =+M75 -> 175.78289 | N14: =+N75 -> 155.30755 | O14: =+O75 -> 51.317503 | P14: =+P75 -> 193.07727 | Q14: =+Q75 -> 247.40407
A15: Precio sin factura en $us / Mt² | D15: =+D14/D12 -> 108.5535 | E15: =+E14/E12 -> 128.68206 | G15: =+G14/G12 -> 71.996686 | H15: $us./Mt² | I15: =+I14/I12 -> 87.376904 | J15: =+J14/J12 -> 67.566697 | K15: =+K14/K12 -> 84.798603 | L15: =+L14/L12 -> 67.830342 | M15: =+M14/M12 -> 69.342363 | N15: =+N14/N12 -> 71.674342 | O15: =+O14/O12 -> 144.14017 | P15: =+P14/P12 -> 65.672541 | Q15: =+Q14/Q12 -> 68.495036
A16: Total Kgr.
A17: % descuento del con al sin | D17: =+(D11-D14)/D11 -> 0.071513799 | E17: =+(E11-E14)/E11 -> 0.073023114 | G17: =ROUNDDOWN(+(G11-G14)/G11,2) -> 0.07 | I17: =+(I11-I14)/I11 -> 0.063355972 | J17: =+(J11-J14)/J11 -> 0.072406702 | K17: =+(K11-K14)/K11 -> 0.067925353 | L17: =+(L11-L14)/L11 -> 0.0722527 | M17: =+(M11-M14)/M11 -> 0.072203036 | N17: =+(N11-N14)/N11 -> 0.071589822 | O17: =+(O11-O14)/O11 -> 0.063316095 | P17: =+(P11-P14)/P11 -> 0.074781148 | Q17: =+(Q11-Q14)/Q11 -> 0.076636492
G18: =+G11+'Pano Fijo'!F12+('Costo M.P.yMat.'!I15*4) -> 1688.52
A19: DETALLE DE MATERIALES A UTILIZAR
A20: MATERIAL | C20: Unidad | D20: =+D2 -> PC2H | E20: =+E2 -> PC4H | G20: Cantidad | H20: Unidad | I20: =+I2 -> VC2H | J20: =+J2 -> VC2H | K20: =+K2 -> VC2H | L20: =+L2 -> VC2H | M20: =+M2 -> VC2H | N20: =+N2 -> VC2H | O20: =+O2 -> VC2H | P20: =+P2 -> VC2H | Q20: =+Q2 -> PC2H
A21: Vidrio Templado 10mm Incoloro | C21: Mt² | D21: =IF(D$9=1,IF(D$10=10,((D$6*0.05)+(D$5*D$6))*D$7,0),0) -> 1.05 | E21: =IF(E$9=1,IF(E$10=10,((E$6*0.05)+(E$5*E$6))*E$7,0),0) -> 0 | G21: =ROUNDUP(SUM(I21:IV21),1) -> 21 | H21: Mt² | I21: =IF(I$9=1,IF(I$10=10,((I$6*0.05)+(I$5*I$6))*I$7,0),0) -> 1.523525 | J21: =IF(J$9=1,IF(J$10=10,((J$6*0.05)+(J$5*J$6))*J$7,0),0) -> 3.075 | K21: =IF(K$9=1,IF(K$10=10,((K$6*0.05)+(K$5*K$6))*K$7,0),0) -> 1.28125 | L21: =IF(L$9=1,IF(L$10=10,((L$6*0.05)+(L$5*L$6))*L$7,0),0) -> 3.034 | M21: =IF(M$9=1,IF(M$10=10,((M$6*0.05)+(M$5*M$6))*M$7,0),0) -> 2.61 | N21: =IF(N$9=1,IF(N$10=10,((N$6*0.05)+(N$5*N$6))*N$7,0),0) -> 2.2386 | O21: =IF(O$9=1,IF(O$10=10,((O$6*0.05)+(O$5*O$6))*O$7,0),0) -> 0.381275 | P21: =IF(P$9=1,IF(P$10=10,((P$6*0.05)+(P$5*P$6))*P$7,0),0) -> 3.04 | Q21: =IF(Q$9=1,IF(Q$10=10,((Q$6*0.05)+(Q$5*Q$6))*Q$7,0),0) -> 3.717
A22: Vidrio Templado 10mm Color | C22: Mt² | D22: =IF(D$9=2,IF(D$10=10,((D$6*0.05)+(D$5*D$6))*D$7,0),0) -> 0 | E22: =IF(E$9=2,IF(E$10=10,((E$6*0.05)+(E$5*E$6))*E$7,0),0) -> 0 | G22: =ROUNDUP(SUM(I22:IV22),1) -> 0 | H22: Mt² | I22: =IF(I$9=2,IF(I$10=10,((I$6*0.05)+(I$5*I$6))*I$7,0),0) -> 0 | J22: =IF(J$9=2,IF(J$10=10,((J$6*0.05)+(J$5*J$6))*J$7,0),0) -> 0 | K22: =IF(K$9=2,IF(K$10=10,((K$6*0.05)+(K$5*K$6))*K$7,0),0) -> 0 | L22: =IF(L$9=2,IF(L$10=10,((L$6*0.05)+(L$5*L$6))*L$7,0),0) -> 0 | M22: =IF(M$9=2,IF(M$10=10,((M$6*0.05)+(M$5*M$6))*M$7,0),0) -> 0 | N22: =IF(N$9=2,IF(N$10=10,((N$6*0.05)+(N$5*N$6))*N$7,0),0) -> 0 | O22: =IF(O$9=2,IF(O$10=10,((O$6*0.05)+(O$5*O$6))*O$7,0),0) -> 0 | P22: =IF(P$9=2,IF(P$10=10,((P$6*0.05)+(P$5*P$6))*P$7,0),0) -> 0 | Q22: =IF(Q$9=2,IF(Q$10=10,((Q$6*0.05)+(Q$5*Q$6))*Q$7,0),0) -> 0
A23: Vidrio Templado 8mm Incoloro | C23: Mt² | D23: =IF(D$9=1,IF(D$10=8,((D$6*0.05)+(D$5*D$6))*D$7,0),0) -> 0 | E23: =IF(E$9=1,IF(E$10=8,((E$6*0.05)+(E$5*E$6))*E$7,0),0) -> 1.05 | G23: =ROUNDUP(SUM(I23:IV23),1) -> 0 | H23: Mt² | I23: =IF(I$9=1,IF(I$10=8,((I$6*0.05)+(I$5*I$6))*I$7,0),0) -> 0 | J23: =IF(J$9=1,IF(J$10=8,((J$6*0.05)+(J$5*J$6))*J$7,0),0) -> 0 | K23: =IF(K$9=1,IF(K$10=8,((K$6*0.05)+(K$5*K$6))*K$7,0),0) -> 0 | L23: =IF(L$9=1,IF(L$10=8,((L$6*0.05)+(L$5*L$6))*L$7,0),0) -> 0 | M23: =IF(M$9=1,IF(M$10=8,((M$6*0.05)+(M$5*M$6))*M$7,0),0) -> 0 | N23: =IF(N$9=1,IF(N$10=8,((N$6*0.05)+(N$5*N$6))*N$7,0),0) -> 0 | O23: =IF(O$9=1,IF(O$10=8,((O$6*0.05)+(O$5*O$6))*O$7,0),0) -> 0 | P23: =IF(P$9=1,IF(P$10=8,((P$6*0.05)+(P$5*P$6))*P$7,0),0) -> 0 | Q23: =IF(Q$9=1,IF(Q$10=8,((Q$6*0.05)+(Q$5*Q$6))*Q$7,0),0) -> 0
A24: Vidrio Templado 8mm Color | C24: Mt² | D24: =IF(D$9=2,IF(D$10=8,((D$6*0.05)+(D$5*D$6))*D$7,0),0) -> 0 | E24: =IF(E$9=2,IF(E$10=8,((E$6*0.05)+(E$5*E$6))*E$7,0),0) -> 0 | G24: =ROUNDUP(SUM(I24:IV24),1) -> 0 | H24: Mt² | I24: =IF(I$9=2,IF(I$10=8,((I$6*0.05)+(I$5*I$6))*I$7,0),0) -> 0 | J24: =IF(J$9=2,IF(J$10=8,((J$6*0.05)+(J$5*J$6))*J$7,0),0) -> 0 | K24: =IF(K$9=2,IF(K$10=8,((K$6*0.05)+(K$5*K$6))*K$7,0),0) -> 0 | L24: =IF(L$9=2,IF(L$10=8,((L$6*0.05)+(L$5*L$6))*L$7,0),0) -> 0 | M24: =IF(M$9=2,IF(M$10=8,((M$6*0.05)+(M$5*M$6))*M$7,0),0) -> 0 | N24: =IF(N$9=2,IF(N$10=8,((N$6*0.05)+(N$5*N$6))*N$7,0),0) -> 0 | O24: =IF(O$9=2,IF(O$10=8,((O$6*0.05)+(O$5*O$6))*O$7,0),0) -> 0 | P24: =IF(P$9=2,IF(P$10=8,((P$6*0.05)+(P$5*P$6))*P$7,0),0) -> 0 | Q24: =IF(Q$9=2,IF(Q$10=8,((Q$6*0.05)+(Q$5*Q$6))*Q$7,0),0) -> 0
A25: Mano de obra | C25: Mt² | D25: =+D12 -> 1 | E25: =+E12 -> 1 | G25: =ROUNDUP(SUM(I25:IV25),1) -> 20.3 | H25: Mt² | I25: =+I12 -> 1.486275 | J25: =+J12 -> 3 | K25: =+K12 -> 1.23 | L25: =+L12 -> 2.96 | M25: =+M12 -> 2.535 | N25: =+N12 -> 2.16685 | O25: =+O12 -> 0.356025 | P25: =+P12 -> 2.94 | Q25: =+Q12 -> 3.612
A26: Silicona transp., blanca o negra | C26: Tubo | D26: =D7*(4*D5+2*D6)/6 -> 1 | E26: =E7*(4*E5+2*E6)/6 -> 1 | G26: =ROUNDUP(SUM(I26:IV26),1) -> 13.7 | H26: Tubo | I26: =I7*(4*I5+2*I6)/6 -> 1.5783333 | J26: =J7*(4*J5+2*J6)/6 -> 1.8333333 | K26: =K7*(4*K5+2*K6)/6 -> 1.1416667 | L26: =L7*(4*L5+2*L6)/6 -> 1.8266667 | M26: =M7*(4*M5+2*M6)/6 -> 1.6266667 | N26: =N7*(4*N5+2*N6)/6 -> 1.485 | O26: =O7*(4*O5+2*O6)/6 -> 0.63833333 | P26: =P7*(4*P5+2*P6)/6 -> 1.6466667 | Q26: =Q7*(4*Q5+2*Q6)/6 -> 1.8466667
A27: Cinta masking 1/2 " (rollo de 20) | C27: Rollo | D27: =+D26*12/20 -> 0.6 | E27: =+E26*12/20 -> 0.6 | G27: =ROUNDUP(SUM(I27:IV27),1) -> 8.2 | H27: Rollo | I27: =+I26*12/20 -> 0.947 | J27: =+J26*12/20 -> 1.1 | K27: =+K26*12/20 -> 0.685 | L27: =+L26*12/20 -> 1.096 | M27: =+M26*12/20 -> 0.976 | N27: =+N26*12/20 -> 0.891 | O27: =+O26*12/20 -> 0.383 | P27: =+P26*12/20 -> 0.988 | Q27: =+Q26*12/20 -> 1.108
A28: "U" 15x25 - Kg/Mt lineal. | B28: 0.2 | C28: Kgr | D28: =2*D$6*$B28*D$7 -> 0.4 | E28: =2*E$6*$B28*E$7 -> 0.4 | G28: =ROUNDUP(SUM(I28:IV28)/(6*B28),1) -> 4.1 | H28: Barras | I28: =2*I$6*$B28*I$7 -> 0.298 | J28: =2*J$6*$B28*J$7 -> 0.6 | K28: =2*K$6*$B28*K$7 -> 0.41 | L28: =2*L$6*$B28*L$7 -> 0.592 | M28: =2*M$6*$B28*M$7 -> 0.6 | N28: =2*N$6*$B28*N$7 -> 0.574 | O28: =2*O$6*$B28*O$7 -> 0.202 | P28: =2*P$6*$B28*P$7 -> 0.8 | Q28: =2*Q$6*$B28*Q$7 -> 0.84
A29: Felpa | C29: Mt lineal | D29: =(D6+3*D5)*D7 -> 4 | E29: =(E6+3*E5)*E7 -> 4 | G29: =ROUNDUP(SUM(I29:IV29),1) -> 55.2 | H29: Mt lineal | I29: =(I6+3*I5)*I7 -> 6.73 | J29: =(J6+3*J5)*J7 -> 7.5 | K29: =(K6+3*K5)*K7 -> 4.625 | L29: =(L6+3*L5)*L7 -> 7.48 | M29: =(M6+3*M5)*M7 -> 6.57 | N29: =(N6+3*N5)*N7 -> 5.965 | O29: =(O6+3*O5)*O7 -> 2.62 | P29: =(P6+3*P5)*P7 -> 6.41 | Q29: =(Q6+3*Q5)*Q7 -> 7.26
A30: Tarugos No. 6 | C30: Pza. | D30: =D$7*(2*D$5+2*D$6)/0.4 -> 10 | E30: =E$7*(2*E$5+2*E$6)/0.4 -> 10 | G30: =ROUNDUP(SUM(I30:IV30),1) -> 132.9 | H30: Pza. | I30: =I$7*(2*I$5+2*I$6)/0.4 -> 13.7 | J30: =J$7*(2*J$5+2*J$6)/0.4 -> 17.5 | K30: =K$7*(2*K$5+2*K$6)/0.4 -> 11.125 | L30: =L$7*(2*L$5+2*L$6)/0.4 -> 17.4 | M30: =M$7*(2*M$5+2*M$6)/0.4 -> 15.95 | N30: =N$7*(2*N$5+2*N$6)/0.4 -> 14.725 | O30: =O$7*(2*O$5+2*O$6)/0.4 -> 6.05 | P30: =P$7*(2*P$5+2*P$6)/0.4 -> 17.35 | Q30: =Q$7*(2*Q$5+2*Q$6)/0.4 -> 19.1
A31: Tornillos 8 x 1 1/2 | C31: Pza. | D31: =D$7*(2*D$5+2*D$6)/0.4 -> 10 | E31: =E$7*(2*E$5+2*E$6)/0.4 -> 10 | G31: =ROUNDUP(SUM(I31:IV31),1) -> 132.9 | H31: Pza. | I31: =I$7*(2*I$5+2*I$6)/0.4 -> 13.7 | J31: =J$7*(2*J$5+2*J$6)/0.4 -> 17.5 | K31: =K$7*(2*K$5+2*K$6)/0.4 -> 11.125 | L31: =L$7*(2*L$5+2*L$6)/0.4 -> 17.4 | M31: =M$7*(2*M$5+2*M$6)/0.4 -> 15.95 | N31: =N$7*(2*N$5+2*N$6)/0.4 -> 14.725 | O31: =O$7*(2*O$5+2*O$6)/0.4 -> 6.05 | P31: =P$7*(2*P$5+2*P$6)/0.4 -> 17.35 | Q31: =Q$7*(2*Q$5+2*Q$6)/0.4 -> 19.1
A32: Vedapres 001 - u - Kg/Mt l. | B32: 0.151 | C32: Kgr | D32: =+D$6*$B32*D$7 -> 0.151 | E32: =2*E$6*$B32*E$7 -> 0.302 | G32: =ROUNDUP(SUM(I32:IV32)/(6*B32),1) -> 2.1 | H32: Barras | I32: =+I$6*$B32*I$7 -> 0.112495 | J32: =+J$6*$B32*J$7 -> 0.2265 | K32: =+K$6*$B32*K$7 -> 0.154775 | L32: =+L$6*$B32*L$7 -> 0.22348 | M32: =+M$6*$B32*M$7 -> 0.2265 | N32: =+N$6*$B32*N$7 -> 0.216685 | O32: =+O$6*$B32*O$7 -> 0.076255 | P32: =+P$6*$B32*P$7 -> 0.302 | Q32: =+Q$6*$B32*Q$7 -> 0.3171
A33: Vedapres 001 - h - Kg/Mt l. | B33: 0.257 | C33: Kgr | E33: =+E$6*$B33*E$7 -> 0.257 | G33: =ROUNDUP(SUM(I33:IV33)/(6*B33),1) -> 0 | H33: Barras
A34: Cabezal 7313 - Kg/Mt l. | B34: 1.013 | C34: Kgr | D34: =D$5*$B34*D$7 -> 1.013 | E34: =E$5*$B34*E$7 -> 1.013 | G34: =ROUNDUP(SUM(I34:IV34)/(6*B34),1) -> 2.4 | H34: Barras | I34: =I$5*$B34*I$7 -> 2.020935 | J34: =J$5*$B34*J$7 -> 2.026 | K34: =K$5*$B34*K$7 -> 1.2156 | L34: =L$5*$B34*L$7 -> 2.026 | M34: =M$5*$B34*M$7 -> 1.71197 | N34: =N$5*$B34*N$7 -> 1.52963 | O34: =O$5*$B34*O$7 -> 0.714165 | P34: =P$5*$B34*P$7 -> 1.48911 | Q34: =Q$5*$B34*Q$7 -> 1.74236
A35: Tapa 7312 - Kg/Mt l. | B35: 0.408 | C35: Kgr | D35: =D$5*$B35*D$7 -> 0.408 | E35: =E$5*$B35*E$7 -> 0.408 | G35: =ROUNDUP(SUM(I35:IV35)/(6*B35),1) -> 2.4 | H35: Barras | I35: =I$5*$B35*I$7 -> 0.81396 | J35: =J$5*$B35*J$7 -> 0.816 | K35: =K$5*$B35*K$7 -> 0.4896 | L35: =L$5*$B35*L$7 -> 0.816 | M35: =M$5*$B35*M$7 -> 0.68952 | N35: =N$5*$B35*N$7 -> 0.61608 | O35: =O$5*$B35*O$7 -> 0.28764 | P35: =P$5*$B35*P$7 -> 0.59976 | Q35: =Q$5*$B35*Q$7 -> 0.70176
A36: Trillo 7314 - Kg/Mt l. | B36: 0.478 | C36: Kgr | D36: =D$5*$B36*D$7 -> 0.478 | E36: =E$5*$B36*E$7 -> 0.478 | G36: =ROUNDUP(SUM(I36:IV36)/(6*B36),1) -> 2.4 | H36: Barras | I36: =I$5*$B36*I$7 -> 0.95361 | J36: =J$5*$B36*J$7 -> 0.956 | K36: =K$5*$B36*K$7 -> 0.5736 | L36: =L$5*$B36*L$7 -> 0.956 | M36: =M$5*$B36*M$7 -> 0.80782 | N36: =N$5*$B36*N$7 -> 0.72178 | O36: =O$5*$B36*O$7 -> 0.33699 | P36: =P$5*$B36*P$7 -> 0.70266 | Q36: =Q$5*$B36*Q$7 -> 0.82216
A37: TapaTrillo Rev. - Kg/Mt l. | B37: 0.125 | C37: Kgr | D37: =D$5*$B37*D$7 -> 0.125 | E37: =E$5*$B37*E$7 -> 0.125 | G37: =ROUNDUP(SUM(I37:IV37)/(6*B37),1) -> 2.4 | H37: Barras | I37: =I$5*$B37*I$7 -> 0.249375 | J37: =J$5*$B37*J$7 -> 0.25 | K37: =K$5*$B37*K$7 -> 0.15 | L37: =L$5*$B37*L$7 -> 0.25 | M37: =M$5*$B37*M$7 -> 0.21125 | N37: =N$5*$B37*N$7 -> 0.18875 | O37: =O$5*$B37*O$7 -> 0.088125 | P37: =P$5*$B37*P$7 -> 0.18375 | Q37: =Q$5*$B37*Q$7 -> 0.215
A38: 1510 | C38: Pza. | D38: =IF(D$8=1,+D$7,0) -> 1 | E38: =IF(E$8=1,+E$7,0) -> 1 | G38: =ROUNDUP(SUM(I38:IV38),1) -> 1 | H38: Pza. | I38: =IF(I$8=1,+I$7,0) -> 0 | J38: =IF(J$8=1,+J$7,0) -> 0 | K38: =IF(K$8=1,+K$7,0) -> 0 | L38: =IF(L$8=1,+L$7,0) -> 0 | M38: =IF(M$8=1,+M$7,0) -> 0 | N38: =IF(N$8=1,+N$7,0) -> 0 | O38: =IF(O$8=1,+O$7,0) -> 0 | P38: =IF(P$8=1,+P$7,0) -> 0 | Q38: =IF(Q$8=1,+Q$7,0) -> 1
A39: 1511 | C39: Pza. | E39: =IF(E$8=1,+E$7,0) -> 1 | G39: =ROUNDUP(SUM(I39:IV39),1) -> 0 | H39: Pza.
A40: 1511a | C40: Pza. | D40: =IF(D$8=1,+D$7,0) -> 1 | G40: =ROUNDUP(SUM(I40:IV40),1) -> 1 | H40: Pza. | I40: =IF(I$8=1,+I$7,0) -> 0 | J40: =IF(J$8=1,+J$7,0) -> 0 | K40: =IF(K$8=1,+K$7,0) -> 0 | L40: =IF(L$8=1,+L$7,0) -> 0 | M40: =IF(M$8=1,+M$7,0) -> 0 | N40: =IF(N$8=1,+N$7,0) -> 0 | O40: =IF(O$8=1,+O$7,0) -> 0 | P40: =IF(P$8=1,+P$7,0) -> 0 | Q40: =IF(Q$8=1,+Q$7,0) -> 1
A41: 1125a | C41: Pza. | D41: =2*D7 -> 2 | E41: =4*E7 -> 4 | G41: =ROUNDUP(SUM(I41:IV41),1) -> 18 | H41: Pza. | I41: =2*I7 -> 2 | J41: =2*J7 -> 2 | K41: =2*K7 -> 2 | L41: =2*L7 -> 2 | M41: =2*M7 -> 2 | N41: =2*N7 -> 2 | O41: =2*O7 -> 2 | P41: =2*P7 -> 2 | Q41: =2*Q7 -> 2
A42: 1629j | C42: Pza. | D42: =IF(D$8=2,+D$7,0) -> 0 | E42: =IF(E$8=2,2*E$7,0) -> 0 | G42: =ROUNDUP(SUM(I42:IV42),1) -> 8 | H42: Pza. | I42: =IF(I$8=2,+I$7,0) -> 1 | J42: =IF(J$8=2,+J$7,0) -> 1 | K42: =IF(K$8=2,+K$7,0) -> 1 | L42: =IF(L$8=2,+L$7,0) -> 1 | M42: =IF(M$8=2,+M$7,0) -> 1 | N42: =IF(N$8=2,+N$7,0) -> 1 | O42: =IF(O$8=2,+O$7,0) -> 1 | P42: =IF(P$8=2,+P$7,0) -> 1 | Q42: =IF(Q$8=2,+Q$7,0) -> 0
A43: 1335 | C43: Pza. | D43: =IF(D$8=2,+D$7,0) -> 0 | E43: =IF(E$8=2,2*E$7,0) -> 0 | G43: =ROUNDUP(SUM(I43:IV43),1) -> 8 | H43: Pza. | I43: =IF(I$8=2,+I$7,0) -> 1 | J43: =IF(J$8=2,+J$7,0) -> 1 | K43: =IF(K$8=2,+K$7,0) -> 1 | L43: =IF(L$8=2,+L$7,0) -> 1 | M43: =IF(M$8=2,+M$7,0) -> 1 | N43: =IF(N$8=2,+N$7,0) -> 1 | O43: =IF(O$8=2,+O$7,0) -> 1 | P43: =IF(P$8=2,+P$7,0) -> 1 | Q43: =IF(Q$8=2,+Q$7,0) -> 0
A44: 1038c | C44: Pza. | D44: =IF(D$8=2,+D$7,0) -> 0 | E44: =IF(E$8=2,2*E$7,0) -> 0 | G44: =ROUNDUP(SUM(I44:IV44),1) -> 8 | H44: Pza. | I44: =IF(I$8=2,+I$7,0) -> 1 | J44: =IF(J$8=2,+J$7,0) -> 1 | K44: =IF(K$8=2,+K$7,0) -> 1 | L44: =IF(L$8=2,+L$7,0) -> 1 | M44: =IF(M$8=2,+M$7,0) -> 1 | N44: =IF(N$8=2,+N$7,0) -> 1 | O44: =IF(O$8=2,+O$7,0) -> 1 | P44: =IF(P$8=2,+P$7,0) -> 1 | Q44: =IF(Q$8=2,+Q$7,0) -> 0
A48: COSTO CON FACTURA | D48: =SUM(D49:D72) -> 116.9145 | E48: =SUM(E49:E72) -> 138.81906 | G48: =SUM(G49:G72) -> 567.4 | I48: =SUM(I49:I72) -> 138.65044 | J48: =SUM(J49:J72) -> 218.52259 | K48: =SUM(K49:K72) -> 111.90336 | L48: =SUM(L49:L72) -> 216.41433 | M48: =SUM(M49:M72) -> 189.46267 | N48: =SUM(N49:N72) -> 167.28333 | O48: =SUM(O49:O72) -> 54.786362 | P48: =SUM(P49:P72) -> 208.68281 | Q48: =SUM(Q49:Q72) -> 267.93789
A49: Vidrio Templado 10mm Incoloro | C49: =+'Costo M.P.yMat.'!C26 -> 36.46 | D49: =+$C49*D21 -> 38.283 | E49: =+$C49*E21 -> 0 | I49: =+$C49*I21 -> 55.547722 | J49: =+$C49*J21 -> 112.1145 | K49: =+$C49*K21 -> 46.714375 | L49: =+$C49*L21 -> 110.61964 | M49: =+$C49*M21 -> 95.1606 | N49: =+$C49*N21 -> 81.619356 | O49: =+$C49*O21 -> 13.901286 | P49: =+$C49*P21 -> 110.8384 | Q49: =+$C49*Q21 -> 135.52182
A50: Vidrio Templado 10mm Color | C50: =+'Costo M.P.yMat.'!C31 -> 52.41 | D50: =+$C50*D22 -> 0 | E50: =+$C50*E22 -> 0 | G50: =ROUNDUP(SUM(I50:IV50),1) -> 0 | I50: =+$C50*I22 -> 0 | J50: =+$C50*J22 -> 0 | K50: =+$C50*K22 -> 0 | L50: =+$C50*L22 -> 0 | M50: =+$C50*M22 -> 0 | N50: =+$C50*N22 -> 0 | O50: =+$C50*O22 -> 0 | P50: =+$C50*P22 -> 0 | Q50: =+$C50*Q22 -> 0
A51: Vidrio Templado 8mm Incoloro | C51: =+'Costo M.P.yMat.'!C27 -> 34.18 | D51: =+$C51*D23 -> 0 | E51: =+$C51*E23 -> 35.889 | G51: =ROUNDUP(SUM(I51:IV51),1) -> 0 | I51: =+$C51*I23 -> 0 | J51: =+$C51*J23 -> 0 | K51: =+$C51*K23 -> 0 | L51: =+$C51*L23 -> 0 | M51: =+$C51*M23 -> 0 | N51: =+$C51*N23 -> 0 | O51: =+$C51*O23 -> 0 | P51: =+$C51*P23 -> 0 | Q51: =+$C51*Q23 -> 0
A52: Vidrio Templado 8mm Color | C52: =+'Costo M.P.yMat.'!C32 -> 50.13 | D52: =+$C52*D24 -> 0 | E52: =+$C52*E24 -> 0 | G52: =ROUNDUP(SUM(I52:IV52),1) -> 0 | I52: =+$C52*I24 -> 0 | J52: =+$C52*J24 -> 0 | K52: =+$C52*K24 -> 0 | L52: =+$C52*L24 -> 0 | M52: =+$C52*M24 -> 0 | N52: =+$C52*N24 -> 0 | O52: =+$C52*O24 -> 0 | P52: =+$C52*P24 -> 0 | Q52: =+$C52*Q24 -> 0
A53: Mano de obra | C53: =+'Costo M.P.yMat.'!C84 -> 12.08 | D53: =+$C53*D25 -> 12.08 | E53: =+$C53*E25 -> 12.08 | I53: =+$C53*I25 -> 17.954202 | J53: =+$C53*J25 -> 36.24 | K53: =+$C53*K25 -> 14.8584 | L53: =+$C53*L25 -> 35.7568 | M53: =+$C53*M25 -> 30.6228 | N53: =+$C53*N25 -> 26.175548 | O53: =+$C53*O25 -> 4.300782 | P53: =+$C53*P25 -> 35.5152 | Q53: =+$C53*Q25 -> 43.63296
A54: Silicona transp., blanca o negra | C54: =+'Costo M.P.yMat.'!C7 -> 2.76 | D54: =+$C54*D26 -> 2.76 | E54: =+$C54*E26 -> 2.76 | G54: =ROUNDUP(SUM(I54:IV54),1) -> 37.7 | I54: =+$C54*I26 -> 4.3562 | J54: =+$C54*J26 -> 5.06 | K54: =+$C54*K26 -> 3.151 | L54: =+$C54*L26 -> 5.0416 | M54: =+$C54*M26 -> 4.4896 | N54: =+$C54*N26 -> 4.0986 | O54: =+$C54*O26 -> 1.7618 | P54: =+$C54*P26 -> 4.5448 | Q54: =+$C54*Q26 -> 5.0968
A55: Cinta masking 1/2 " (rollo de 20) | C55: =+'Costo M.P.yMat.'!C9 -> 0.75 | D55: =+$C55*D27 -> 0.45 | E55: =+$C55*E27 -> 0.45 | G55: =ROUNDUP(SUM(I55:IV55),1) -> 6.2 | I55: =+$C55*I27 -> 0.71025 | J55: =+$C55*J27 -> 0.825 | K55: =+$C55*K27 -> 0.51375 | L55: =+$C55*L27 -> 0.822 | M55: =+$C55*M27 -> 0.732 | N55: =+$C55*N27 -> 0.66825 | O55: =+$C55*O27 -> 0.28725 | P55: =+$C55*P27 -> 0.741 | Q55: =+$C55*Q27 -> 0.831
A56: "U" 15x25 - Kg/Mt lineal. | B56: 0.2 | C56: =+'Costo M.P.yMat.'!$C$89 -> 8.82 | D56: =+$C56*D28 -> 3.528 | E56: =+$C56*E28 -> 3.528 | G56: =ROUNDUP(SUM(I56:IV56),1) -> 43.4 | H56: =+#REF!/6 -> #REF! | I56: =+$C56*I28 -> 2.62836 | J56: =+$C56*J28 -> 5.292 | K56: =+$C56*K28 -> 3.6162 | L56: =+$C56*L28 -> 5.22144 | M56: =+$C56*M28 -> 5.292 | N56: =+$C56*N28 -> 5.06268 | O56: =+$C56*O28 -> 1.78164 | P56: =+$C56*P28 -> 7.056 | Q56: =+$C56*Q28 -> 7.4088
A57: Felpa | C57: =+'Costo M.P.yMat.'!C17 -> 0.18 | D57: =+$C57*D29 -> 0.72 | E57: =+$C57*E29 -> 0.72 | G57: =ROUNDUP(SUM(I57:IV57),1) -> 10 | I57: =+$C57*I29 -> 1.2114 | J57: =+$C57*J29 -> 1.35 | K57: =+$C57*K29 -> 0.8325 | L57: =+$C57*L29 -> 1.3464 | M57: =+$C57*M29 -> 1.1826 | N57: =+$C57*N29 -> 1.0737 | O57: =+$C57*O29 -> 0.4716 | P57: =+$C57*P29 -> 1.1538 | Q57: =+$C57*Q29 -> 1.3068
A58: Tarugos No. 6 | C58: =+'Costo M.P.yMat.'!C19 -> 0.04 | D58: =+$C58*D30 -> 0.4 | E58: =+$C58*E30 -> 0.4 | G58: =ROUNDUP(SUM(I58:IV58),1) -> 5.4 | I58: =+$C58*I30 -> 0.548 | J58: =+$C58*J30 -> 0.7 | K58: =+$C58*K30 -> 0.445 | L58: =+$C58*L30 -> 0.696 | M58: =+$C58*M30 -> 0.638 | N58: =+$C58*N30 -> 0.589 | O58: =+$C58*O30 -> 0.242 | P58: =+$C58*P30 -> 0.694 | Q58: =+$C58*Q30 -> 0.764
A59: Tornillos 8 x 1 1/2 | C59: =+'Costo M.P.yMat.'!C20 -> 0.04 | D59: =+$C59*D31 -> 0.4 | E59: =+$C59*E31 -> 0.4 | G59: =ROUNDUP(SUM(I59:IV59),1) -> 5.4 | I59: =+$C59*I31 -> 0.548 | J59: =+$C59*J31 -> 0.7 | K59: =+$C59*K31 -> 0.445 | L59: =+$C59*L31 -> 0.696 | M59: =+$C59*M31 -> 0.638 | N59: =+$C59*N31 -> 0.589 | O59: =+$C59*O31 -> 0.242 | P59: =+$C59*P31 -> 0.694 | Q59: =+$C59*Q31 -> 0.764
A60: Vedapres 001 - u - Kg/Mt l. | B60: 0.151 | C60: =+'Costo M.P.yMat.'!$C$89 -> 8.82 | D60: =+$C60*D32 -> 1.33182 | E60: =+$C60*E32 -> 2.66364 | G60: =ROUNDUP(SUM(I60:IV60),1) -> 16.4 | I60: =+$C60*I32 -> 0.9922059 | J60: =+$C60*J32 -> 1.99773 | K60: =+$C60*K32 -> 1.3651155 | L60: =+$C60*L32 -> 1.9710936 | M60: =+$C60*M32 -> 1.99773 | N60: =+$C60*N32 -> 1.9111617 | O60: =+$C60*O32 -> 0.6725691 | P60: =+$C60*P32 -> 2.66364 | Q60: =+$C60*Q32 -> 2.796822
A61: Vedapres 001 - h - Kg/Mt l. | B61: 0.257 | C61: =+'Costo M.P.yMat.'!$C$89 -> 8.82 | D61: =+$C61*D33 -> 0 | E61: =+$C61*E33 -> 2.26674 | G61: =ROUNDUP(SUM(I61:IV61),1) -> 0 | I61: =+$C61*I33 -> 0 | J61: =+$C61*J33 -> 0 | K61: =+$C61*K33 -> 0 | L61: =+$C61*L33 -> 0 | M61: =+$C61*M33 -> 0 | N61: =+$C61*N33 -> 0 | O61: =+$C61*O33 -> 0 | P61: =+$C61*P33 -> 0 | Q61: =+$C61*Q33 -> 0
A62: Cabezal 7313 - Kg/Mt l. | B62: 1.013 | C62: =+'Costo M.P.yMat.'!$C$89 -> 8.82 | D62: =+$C62*D34 -> 8.93466 | E62: =+$C62*E34 -> 8.93466 | G62: =ROUNDUP(SUM(I62:IV62),1) -> 127.7 | I62: =+$C62*I34 -> 17.824647 | J62: =+$C62*J34 -> 17.86932 | K62: =+$C62*K34 -> 10.721592 | L62: =+$C62*L34 -> 17.86932 | M62: =+$C62*M34 -> 15.099575 | N62: =+$C62*N34 -> 13.491337 | O62: =+$C62*O34 -> 6.2989353 | P62: =+$C62*P34 -> 13.13395 | Q62: =+$C62*Q34 -> 15.367615
A63: Tapa 7312 - Kg/Mt l. | B63: 0.408 | C63: =+'Costo M.P.yMat.'!$C$89 -> 8.82 | D63: =+$C63*D35 -> 3.59856 | E63: =+$C63*E35 -> 3.59856 | G63: =ROUNDUP(SUM(I63:IV63),1) -> 51.5 | H63: =+#REF!/6 -> #REF! | I63: =+$C63*I35 -> 7.1791272 | J63: =+$C63*J35 -> 7.19712 | K63: =+$C63*K35 -> 4.318272 | L63: =+$C63*L35 -> 7.19712 | M63: =+$C63*M35 -> 6.0815664 | N63: =+$C63*N35 -> 5.4338256 | O63: =+$C63*O35 -> 2.5369848 | P63: =+$C63*P35 -> 5.2898832 | Q63: =+$C63*Q35 -> 6.1895232
A64: Trillo 7314 - Kg/Mt l. | B64: 0.478 | C64: =+'Costo M.P.yMat.'!$C$89 -> 8.82 | D64: =+$C64*D36 -> 4.21596 | E64: =+$C64*E36 -> 4.21596 | G64: =ROUNDUP(SUM(I64:IV64),1) -> 60.3 | H64: =+#REF!/6 -> #REF! | I64: =+$C64*I36 -> 8.4108402 | J64: =+$C64*J36 -> 8.43192 | K64: =+$C64*K36 -> 5.059152 | L64: =+$C64*L36 -> 8.43192 | M64: =+$C64*M36 -> 7.1249724 | N64: =+$C64*N36 -> 6.3660996 | O64: =+$C64*O36 -> 2.9722518 | P64: =+$C64*P36 -> 6.1974612 | Q64: =+$C64*Q36 -> 7.2514512
A65: TapaTrillo Rev. - Kg/Mt l. | B65: 0.125 | C65: =+'Costo M.P.yMat.'!$C$89 -> 8.82 | D65: =+$C65*D37 -> 1.1025 | E65: =+$C65*E37 -> 1.1025 | G65: =ROUNDUP(SUM(I65:IV65),1) -> 15.8 | H65: =+#REF!/6 -> #REF! | I65: =+$C65*I37 -> 2.1994875 | J65: =+$C65*J37 -> 2.205 | K65: =+$C65*K37 -> 1.323 | L65: =+$C65*L37 -> 2.205 | M65: =+$C65*M37 -> 1.863225 | N65: =+$C65*N37 -> 1.664775 | O65: =+$C65*O37 -> 0.7772625 | P65: =+$C65*P37 -> 1.620675 | Q65: =+$C65*Q37 -> 1.8963
A66: 1510 | C66: =+'Costo M.P.yMat.'!C73 -> 27.78 | D66: =+$C66*D38 -> 27.78 | E66: =+$C66*E38 -> 27.78 | G66: =ROUNDUP(SUM(I66:IV66),1) -> 27.8 | I66: =+$C66*I38 -> 0 | J66: =+$C66*J38 -> 0 | K66: =+$C66*K38 -> 0 | L66: =+$C66*L38 -> 0 | M66: =+$C66*M38 -> 0 | N66: =+$C66*N38 -> 0 | O66: =+$C66*O38 -> 0 | P66: =+$C66*P38 -> 0 | Q66: =+$C66*Q38 -> 27.78
A67: 1511 | C67: =+'Costo M.P.yMat.'!C74 -> 16.55 | D67: =+$C67*D39 -> 0 | E67: =+$C67*E39 -> 16.55 | G67: =ROUNDUP(SUM(I67:IV67),1) -> 0 | I67: =+$C67*I39 -> 0 | J67: =+$C67*J39 -> 0 | K67: =+$C67*K39 -> 0 | L67: =+$C67*L39 -> 0 | M67: =+$C67*M39 -> 0 | N67: =+$C67*N39 -> 0 | O67: =+$C67*O39 -> 0 | P67: =+$C67*P39 -> 0 | Q67: =+$C67*Q39 -> 0
A68: 1511a | C68: =+'Costo M.P.yMat.'!C75 -> 3.59 | D68: =+$C68*D40 -> 3.59 | E68: =+$C68*E40 -> 0 | G68: =ROUNDUP(SUM(I68:IV68),1) -> 3.6 | I68: =+$C68*I40 -> 0 | J68: =+$C68*J40 -> 0 | K68: =+$C68*K40 -> 0 | L68: =+$C68*L40 -> 0 | M68: =+$C68*M40 -> 0 | N68: =+$C68*N40 -> 0 | O68: =+$C68*O40 -> 0 | P68: =+$C68*P40 -> 0 | Q68: =+$C68*Q40 -> 3.59
A69: 1125a | C69: =+'Costo M.P.yMat.'!C59 -> 3.87 | D69: =+$C69*D41 -> 7.74 | E69: =+$C69*E41 -> 15.48 | G69: =ROUNDUP(SUM(I69:IV69),1) -> 69.7 | I69: =+$C69*I41 -> 7.74 | J69: =+$C69*J41 -> 7.74 | K69: =+$C69*K41 -> 7.74 | L69: =+$C69*L41 -> 7.74 | M69: =+$C69*M41 -> 7.74 | N69: =+$C69*N41 -> 7.74 | O69: =+$C69*O41 -> 7.74 | P69: =+$C69*P41 -> 7.74 | Q69: =+$C69*Q41 -> 7.74
A70: 1629j | C70: =+'Costo M.P.yMat.'!C79 -> 2.76 | D70: =+$C70*D42 -> 0 | E70: =+$C70*E42 -> 0 | G70: =ROUNDUP(SUM(I70:IV70),1) -> 22.1 | I70: =+$C70*I42 -> 2.76 | J70: =+$C70*J42 -> 2.76 | K70: =+$C70*K42 -> 2.76 | L70: =+$C70*L42 -> 2.76 | M70: =+$C70*M42 -> 2.76 | N70: =+$C70*N42 -> 2.76 | O70: =+$C70*O42 -> 2.76 | P70: =+$C70*P42 -> 2.76 | Q70: =+$C70*Q42 -> 0
A71: 1335 | C71: =+'Costo M.P.yMat.'!C70 -> 6.83 | D71: =+$C71*D43 -> 0 | E71: =+$C71*E43 -> 0 | G71: =ROUNDUP(SUM(I71:IV71),1) -> 54.7 | I71: =+$C71*I43 -> 6.83 | J71: =+$C71*J43 -> 6.83 | K71: =+$C71*K43 -> 6.83 | L71: =+$C71*L43 -> 6.83 | M71: =+$C71*M43 -> 6.83 | N71: =+$C71*N43 -> 6.83 | O71: =+$C71*O43 -> 6.83 | P71: =+$C71*P43 -> 6.83 | Q71: =+$C71*Q43 -> 0
A72: 1038c | C72: =+'Costo M.P.yMat.'!C51 -> 1.21 | D72: =+$C72*D44 -> 0 | E72: =+$C72*E44 -> 0 | G72: =ROUNDUP(SUM(I72:IV72),1) -> 9.7 | I72: =+$C72*I44 -> 1.21 | J72: =+$C72*J44 -> 1.21 | K72: =+$C72*K44 -> 1.21 | L72: =+$C72*L44 -> 1.21 | M72: =+$C72*M44 -> 1.21 | N72: =+$C72*N44 -> 1.21 | O72: =+$C72*O44 -> 1.21 | P72: =+$C72*P44 -> 1.21 | Q72: =+$C72*Q44 -> 0
A75: COSTO SIN FACTURA | D75: =SUM(D76:D99) -> 108.5535 | E75: =SUM(E76:E99) -> 128.68206 | G75: =ROUNDUP(SUM(I75:IV75),1) -> 1460.6 | I75: =SUM(I76:I99) -> 129.86611 | J75: =SUM(J76:J99) -> 202.70009 | K75: =SUM(K76:K99) -> 104.30228 | L75: =SUM(L76:L99) -> 200.77781 | M75: =SUM(M76:M99) -> 175.78289 | N75: =SUM(N76:N99) -> 155.30755 | O75: =SUM(O76:O99) -> 51.317503 | P75: =SUM(P76:P99) -> 193.07727 | Q75: =SUM(Q76:Q99) -> 247.40407
A76: Vidrio Templado 10mm Incoloro | C76: =+'Costo M.P.yMat.'!D26 -> 33 | D76: =+$C76*D21 -> 34.65 | E76: =+$C76*E21 -> 0 | G76: =ROUNDUP(SUM(I76:IV76),1) -> 689.8 | I76: =+$C76*I21 -> 50.276325 | J76: =+$C76*J21 -> 101.475 | K76: =+$C76*K21 -> 42.28125 | L76: =+$C76*L21 -> 100.122 | M76: =+$C76*M21 -> 86.13 | N76: =+$C76*N21 -> 73.8738 | O76: =+$C76*O21 -> 12.582075 | P76: =+$C76*P21 -> 100.32 | Q76: =+$C76*Q21 -> 122.661
A77: Vidrio Templado 10mm Color | C77: =+'Costo M.P.yMat.'!D31 -> 48.4 | D77: =+$C77*D22 -> 0 | E77: =+$C77*E22 -> 0 | G77: =ROUNDUP(SUM(I77:IV77),1) -> 0 | I77: =+$C77*I22 -> 0 | J77: =+$C77*J22 -> 0 | K77: =+$C77*K22 -> 0 | L77: =+$C77*L22 -> 0 | M77: =+$C77*M22 -> 0 | N77: =+$C77*N22 -> 0 | O77: =+$C77*O22 -> 0 | P77: =+$C77*P22 -> 0 | Q77: =+$C77*Q22 -> 0
A78: Vidrio Templado 8mm Incoloro | C78: =+'Costo M.P.yMat.'!D27 -> 30.8 | D78: =+$C78*D23 -> 0 | E78: =+$C78*E23 -> 32.34 | G78: =ROUNDUP(SUM(I78:IV78),1) -> 0 | I78: =+$C78*I23 -> 0 | J78: =+$C78*J23 -> 0 | K78: =+$C78*K23 -> 0 | L78: =+$C78*L23 -> 0 | M78: =+$C78*M23 -> 0 | N78: =+$C78*N23 -> 0 | O78: =+$C78*O23 -> 0 | P78: =+$C78*P23 -> 0 | Q78: =+$C78*Q23 -> 0
A79: Vidrio Templado 8mm Color | C79: =+'Costo M.P.yMat.'!D32 -> 46.2 | D79: =+$C79*D24 -> 0 | E79: =+$C79*E24 -> 0 | G79: =ROUNDUP(SUM(I79:IV79),1) -> 0 | I79: =+$C79*I24 -> 0 | J79: =+$C79*J24 -> 0 | K79: =+$C79*K24 -> 0 | L79: =+$C79*L24 -> 0 | M79: =+$C79*M24 -> 0 | N79: =+$C79*N24 -> 0 | O79: =+$C79*O24 -> 0 | P79: =+$C79*P24 -> 0 | Q79: =+$C79*Q24 -> 0
A80: Mano de obra | C80: =+'Costo M.P.yMat.'!D84 -> 11 | D80: =+$C80*D25 -> 11 | E80: =+$C80*E25 -> 11 | G80: =ROUNDUP(SUM(I80:IV80),1) -> 223.2 | I80: =+$C80*I25 -> 16.349025 | J80: =+$C80*J25 -> 33 | K80: =+$C80*K25 -> 13.53 | L80: =+$C80*L25 -> 32.56 | M80: =+$C80*M25 -> 27.885 | N80: =+$C80*N25 -> 23.83535 | O80: =+$C80*O25 -> 3.916275 | P80: =+$C80*P25 -> 32.34 | Q80: =+$C80*Q25 -> 39.732
A81: Silicona transp., blanca o negra | C81: =+'Costo M.P.yMat.'!D7 -> 2.67 | D81: =+$C81*D26 -> 2.67 | E81: =+$C81*E26 -> 2.67 | G81: =ROUNDUP(SUM(I81:IV81),1) -> 36.4 | I81: =+$C81*I26 -> 4.21415 | J81: =+$C81*J26 -> 4.895 | K81: =+$C81*K26 -> 3.04825 | L81: =+$C81*L26 -> 4.8772 | M81: =+$C81*M26 -> 4.3432 | N81: =+$C81*N26 -> 3.96495 | O81: =+$C81*O26 -> 1.70435 | P81: =+$C81*P26 -> 4.3966 | Q81: =+$C81*Q26 -> 4.9306
A82: Cinta masking 1/2 " (rollo de 20) | C82: =+'Costo M.P.yMat.'!D9 -> 0.72 | D82: =+$C82*D27 -> 0.432 | E82: =+$C82*E27 -> 0.432 | G82: =ROUNDUP(SUM(I82:IV82),1) -> 5.9 | I82: =+$C82*I27 -> 0.68184 | J82: =+$C82*J27 -> 0.792 | K82: =+$C82*K27 -> 0.4932 | L82: =+$C82*L27 -> 0.78912 | M82: =+$C82*M27 -> 0.70272 | N82: =+$C82*N27 -> 0.64152 | O82: =+$C82*O27 -> 0.27576 | P82: =+$C82*P27 -> 0.71136 | Q82: =+$C82*Q27 -> 0.79776
A83: "U" 15x25 - Kg/Mt lineal. | B83: 0.2 | C83: =+'Costo M.P.yMat.'!$C$89 -> 8.82 | D83: =+$C83*D28 -> 3.528 | E83: =+$C83*E28 -> 3.528 | G83: =ROUNDUP(SUM(I83:IV83),1) -> 43.4 | I83: =+$C83*I28 -> 2.62836 | J83: =+$C83*J28 -> 5.292 | K83: =+$C83*K28 -> 3.6162 | L83: =+$C83*L28 -> 5.22144 | M83: =+$C83*M28 -> 5.292 | N83: =+$C83*N28 -> 5.06268 | O83: =+$C83*O28 -> 1.78164 | P83: =+$C83*P28 -> 7.056 | Q83: =+$C83*Q28 -> 7.4088
A84: Felpa | C84: =+'Costo M.P.yMat.'!D17 -> 0.17 | D84: =+$C84*D29 -> 0.68 | E84: =+$C84*E29 -> 0.68 | G84: =ROUNDUP(SUM(I84:IV84),1) -> 9.4 | I84: =+$C84*I29 -> 1.1441 | J84: =+$C84*J29 -> 1.275 | K84: =+$C84*K29 -> 0.78625 | L84: =+$C84*L29 -> 1.2716 | M84: =+$C84*M29 -> 1.1169 | N84: =+$C84*N29 -> 1.01405 | O84: =+$C84*O29 -> 0.4454 | P84: =+$C84*P29 -> 1.0897 | Q84: =+$C84*Q29 -> 1.2342
A85: Tarugos No. 6 | C85: =+'Costo M.P.yMat.'!D19 -> 0.04 | D85: =+$C85*D30 -> 0.4 | E85: =+$C85*E30 -> 0.4 | G85: =ROUNDUP(SUM(I85:IV85),1) -> 5.4 | I85: =+$C85*I30 -> 0.548 | J85: =+$C85*J30 -> 0.7 | K85: =+$C85*K30 -> 0.445 | L85: =+$C85*L30 -> 0.696 | M85: =+$C85*M30 -> 0.638 | N85: =+$C85*N30 -> 0.589 | O85: =+$C85*O30 -> 0.242 | P85: =+$C85*P30 -> 0.694 | Q85: =+$C85*Q30 -> 0.764
A86: Tornillos 8 x 1 1/2 | C86: =+'Costo M.P.yMat.'!D20 -> 0.04 | D86: =+$C86*D31 -> 0.4 | E86: =+$C86*E31 -> 0.4 | G86: =ROUNDUP(SUM(I86:IV86),1) -> 5.4 | I86: =+$C86*I31 -> 0.548 | J86: =+$C86*J31 -> 0.7 | K86: =+$C86*K31 -> 0.445 | L86: =+$C86*L31 -> 0.696 | M86: =+$C86*M31 -> 0.638 | N86: =+$C86*N31 -> 0.589 | O86: =+$C86*O31 -> 0.242 | P86: =+$C86*P31 -> 0.694 | Q86: =+$C86*Q31 -> 0.764
A87: Vedapres 001 - u - Kg/Mt l. | B87: 0.151 | C87: =+'Costo M.P.yMat.'!$C$89 -> 8.82 | D87: =+$C87*D32 -> 1.33182 | E87: =+$C87*E32 -> 2.66364 | G87: =ROUNDUP(SUM(I87:IV87),1) -> 16.4 | I87: =+$C87*I32 -> 0.9922059 | J87: =+$C87*J32 -> 1.99773 | K87: =+$C87*K32 -> 1.3651155 | L87: =+$C87*L32 -> 1.9710936 | M87: =+$C87*M32 -> 1.99773 | N87: =+$C87*N32 -> 1.9111617 | O87: =+$C87*O32 -> 0.6725691 | P87: =+$C87*P32 -> 2.66364 | Q87: =+$C87*Q32 -> 2.796822
A88: Vedapres 001 - h - Kg/Mt l. | B88: 0.257 | C88: =+'Costo M.P.yMat.'!$C$89 -> 8.82 | D88: =+$C88*D33 -> 0 | E88: =+$C88*E33 -> 2.26674 | G88: =ROUNDUP(SUM(I88:IV88),1) -> 0 | I88: =+$C88*I33 -> 0 | J88: =+$C88*J33 -> 0 | K88: =+$C88*K33 -> 0 | L88: =+$C88*L33 -> 0 | M88: =+$C88*M33 -> 0 | N88: =+$C88*N33 -> 0 | O88: =+$C88*O33 -> 0 | P88: =+$C88*P33 -> 0 | Q88: =+$C88*Q33 -> 0
A89: Cabezal 7313 - Kg/Mt l. | B89: 1.013 | C89: =+'Costo M.P.yMat.'!$C$89 -> 8.82 | D89: =+$C89*D34 -> 8.93466 | E89: =+$C89*E34 -> 8.93466 | G89: =ROUNDUP(SUM(I89:IV89),1) -> 127.7 | I89: =+$C89*I34 -> 17.824647 | J89: =+$C89*J34 -> 17.86932 | K89: =+$C89*K34 -> 10.721592 | L89: =+$C89*L34 -> 17.86932 | M89: =+$C89*M34 -> 15.099575 | N89: =+$C89*N34 -> 13.491337 | O89: =+$C89*O34 -> 6.2989353 | P89: =+$C89*P34 -> 13.13395 | Q89: =+$C89*Q34 -> 15.367615
A90: Tapa 7312 - Kg/Mt l. | B90: 0.408 | C90: =+'Costo M.P.yMat.'!$C$89 -> 8.82 | D90: =+$C90*D35 -> 3.59856 | E90: =+$C90*E35 -> 3.59856 | G90: =ROUNDUP(SUM(I90:IV90),1) -> 51.5 | I90: =+$C90*I35 -> 7.1791272 | J90: =+$C90*J35 -> 7.19712 | K90: =+$C90*K35 -> 4.318272 | L90: =+$C90*L35 -> 7.19712 | M90: =+$C90*M35 -> 6.0815664 | N90: =+$C90*N35 -> 5.4338256 | O90: =+$C90*O35 -> 2.5369848 | P90: =+$C90*P35 -> 5.2898832 | Q90: =+$C90*Q35 -> 6.1895232
A91: Trillo 7314 - Kg/Mt l. | B91: 0.478 | C91: =+'Costo M.P.yMat.'!$C$89 -> 8.82 | D91: =+$C91*D36 -> 4.21596 | E91: =+$C91*E36 -> 4.21596 | G91: =ROUNDUP(SUM(I91:IV91),1) -> 60.3 | I91: =+$C91*I36 -> 8.4108402 | J91: =+$C91*J36 -> 8.43192 | K91: =+$C91*K36 -> 5.059152 | L91: =+$C91*L36 -> 8.43192 | M91: =+$C91*M36 -> 7.1249724 | N91: =+$C91*N36 -> 6.3660996 | O91: =+$C91*O36 -> 2.9722518 | P91: =+$C91*P36 -> 6.1974612 | Q91: =+$C91*Q36 -> 7.2514512
A92: TapaTrillo Rev. - Kg/Mt l. | B92: 0.125 | C92: =+'Costo M.P.yMat.'!$C$89 -> 8.82 | D92: =+$C92*D37 -> 1.1025 | E92: =+$C92*E37 -> 1.1025 | G92: =ROUNDUP(SUM(I92:IV92),1) -> 15.8 | I92: =+$C92*I37 -> 2.1994875 | J92: =+$C92*J37 -> 2.205 | K92: =+$C92*K37 -> 1.323 | L92: =+$C92*L37 -> 2.205 | M92: =+$C92*M37 -> 1.863225 | N92: =+$C92*N37 -> 1.664775 | O92: =+$C92*O37 -> 0.7772625 | P92: =+$C92*P37 -> 1.620675 | Q92: =+$C92*Q37 -> 1.8963
A93: 1510 | C93: =+'Costo M.P.yMat.'!D73 -> 25.3 | D93: =+$C93*D38 -> 25.3 | E93: =+$C93*E38 -> 25.3 | G93: =ROUNDUP(SUM(I93:IV93),1) -> 25.3 | I93: =+$C93*I38 -> 0 | J93: =+$C93*J38 -> 0 | K93: =+$C93*K38 -> 0 | L93: =+$C93*L38 -> 0 | M93: =+$C93*M38 -> 0 | N93: =+$C93*N38 -> 0 | O93: =+$C93*O38 -> 0 | P93: =+$C93*P38 -> 0 | Q93: =+$C93*Q38 -> 25.3
A94: 1511 | C94: =+'Costo M.P.yMat.'!D74 -> 15.07 | D94: =+$C94*D39 -> 0 | E94: =+$C94*E39 -> 15.07 | G94: =ROUNDUP(SUM(I94:IV94),1) -> 0 | I94: =+$C94*I39 -> 0 | J94: =+$C94*J39 -> 0 | K94: =+$C94*K39 -> 0 | L94: =+$C94*L39 -> 0 | M94: =+$C94*M39 -> 0 | N94: =+$C94*N39 -> 0 | O94: =+$C94*O39 -> 0 | P94: =+$C94*P39 -> 0 | Q94: =+$C94*Q39 -> 0
A95: 1511a | C95: =+'Costo M.P.yMat.'!D75 -> 3.27 | D95: =+$C95*D40 -> 3.27 | E95: =+$C95*E40 -> 0 | G95: =ROUNDUP(SUM(I95:IV95),1) -> 3.3 | I95: =+$C95*I40 -> 0 | J95: =+$C95*J40 -> 0 | K95: =+$C95*K40 -> 0 | L95: =+$C95*L40 -> 0 | M95: =+$C95*M40 -> 0 | N95: =+$C95*N40 -> 0 | O95: =+$C95*O40 -> 0 | P95: =+$C95*P40 -> 0 | Q95: =+$C95*Q40 -> 3.27
A96: 1125a | C96: =+'Costo M.P.yMat.'!D59 -> 3.52 | D96: =+$C96*D41 -> 7.04 | E96: =+$C96*E41 -> 14.08 | G96: =ROUNDUP(SUM(I96:IV96),1) -> 63.4 | I96: =+$C96*I41 -> 7.04 | J96: =+$C96*J41 -> 7.04 | K96: =+$C96*K41 -> 7.04 | L96: =+$C96*L41 -> 7.04 | M96: =+$C96*M41 -> 7.04 | N96: =+$C96*N41 -> 7.04 | O96: =+$C96*O41 -> 7.04 | P96: =+$C96*P41 -> 7.04 | Q96: =+$C96*Q41 -> 7.04
A97: 1629j | C97: =+'Costo M.P.yMat.'!D79 -> 2.51 | D97: =+$C97*D42 -> 0 | E97: =+$C97*E42 -> 0 | G97: =ROUNDUP(SUM(I97:IV97),1) -> 20.1 | I97: =+$C97*I42 -> 2.51 | J97: =+$C97*J42 -> 2.51 | K97: =+$C97*K42 -> 2.51 | L97: =+$C97*L42 -> 2.51 | M97: =+$C97*M42 -> 2.51 | N97: =+$C97*N42 -> 2.51 | O97: =+$C97*O42 -> 2.51 | P97: =+$C97*P42 -> 2.51 | Q97: =+$C97*Q42 -> 0
A98: 1335 | C98: =+'Costo M.P.yMat.'!D70 -> 6.22 | D98: =+$C98*D43 -> 0 | E98: =+$C98*E43 -> 0 | G98: =ROUNDUP(SUM(I98:IV98),1) -> 49.8 | I98: =+$C98*I43 -> 6.22 | J98: =+$C98*J43 -> 6.22 | K98: =+$C98*K43 -> 6.22 | L98: =+$C98*L43 -> 6.22 | M98: =+$C98*M43 -> 6.22 | N98: =+$C98*N43 -> 6.22 | O98: =+$C98*O43 -> 6.22 | P98: =+$C98*P43 -> 6.22 | Q98: =+$C98*Q43 -> 0
A99: 1038c | C99: =+'Costo M.P.yMat.'!D51 -> 1.1 | D99: =+$C99*D44 -> 0 | E99: =+$C99*E44 -> 0 | G99: =ROUNDUP(SUM(I99:IV99),1) -> 8.8 | I99: =+$C99*I44 -> 1.1 | J99: =+$C99*J44 -> 1.1 | K99: =+$C99*K44 -> 1.1 | L99: =+$C99*L44 -> 1.1 | M99: =+$C99*M44 -> 1.1 | N99: =+$C99*N44 -> 1.1 | O99: =+$C99*O44 -> 1.1 | P99: =+$C99*P44 -> 1.1 | Q99: =+$C99*Q44 -> 0
A102: FORMULAS - PUERTA - 2 HOJAS | C102: B | D102: H | E102: BxH | G102: CANT. | I102: H | J102: H | K102: H | L102: H | M102: H | N102: H | O102: H | P102: H | Q102: H
A103: Vidrio Templado 10mm Incoloro | B103: =+C49 -> 36.46 | E103: 1
A104: Vidrio Templado 10mm Color | B104: =+C50 -> 52.41 | E104: 1
A105: Vidrio Templado 8mm Incoloro | B105: =+C51 -> 34.18 | E105: 1
A106: Vidrio Templado 8mm Color | B106: =+C52 -> 50.13 | E106: 1
A107: Mano de obra | B107: =+C53 -> 12.08 | E107: 1
A108: Silicona transp., blanca o negra | B108: =+C54 -> 2.76 | C108: 0.66666667 | D108: 0.33333333 | I108: 0.33333333 | J108: 0.33333333 | K108: 0.33333333 | L108: 0.33333333 | M108: 0.33333333 | N108: 0.33333333 | O108: 0.33333333 | P108: 0.33333333 | Q108: 0.33333333
...

Sheet P.Batiente
A2: PUERTAS DE VIDRIO TEMPLADO | D2: PB1H | E2: PB2H | F2: PB4H | H2: Total | J2: PB1H
A3: 8 o 10 mm. c/PERFIL U 15x15 DE ALUMINIO | D3: 10mm. | E3: 10mm. | F3: 10mm. | J3: 10mm.
A4: DATOS BASE PARA EL ANALISIS | D4: =IF(D8=1,"INCOLORO","COLOR") -> INCOLORO | E4: =IF(E8=1,"INCOLORO","COLOR") -> INCOLORO | F4: =IF(F8=1,"INCOLORO","COLOR") -> INCOLORO | J4: =IF(J8=1,"INCOLORO","COLOR") -> COLOR
A5: BASE ( Metros ) | D5: 1 | E5: 1 | F5: 1.2 | J5: 1.01
A6: ALTURA ( Metros ) | D6: 1 | E6: 1 | F6: 2 | J6: 2.1
A7: CANTIDAD DE PIEZAS | D7: 1 | E7: 1 | F7: 1 | H7: =SUM(J7:IV7) -> 1 | I7: Puertas | J7: 1
A8: INCOLORO = 1 ; COLOR =2 | D8: 1 | E8: 1 | F8: 1 | J8: 2
A9: C/FRENO = 1 ; S/FRENO =2 | D9: 1 | E9: 1 | F9: 2 | J9: 1
A10: Total Precio c/factura | D10: =+D44 -> 194.61 | E10: =+E44 -> 341.41674 | F10: =+F44 -> 257.60788 | H10: =SUM(J10:IV10) -> 282.85329 | I10: $us. | J10: =+J44 -> 282.85329
A11: Superficie Mt² | D11: =+D5*D6*D$7 -> 1 | E11: =+E5*E6*E$7 -> 1 | F11: =+F5*F6*F$7 -> 2.4 | H11: =SUM(J11:IV11) -> 2.121 | I11: Mt² | J11: =+J5*J6*J$7 -> 2.121
A12: Precio con factura en $us / Mt² | D12: =+D10/D11 -> 194.61 | E12: =+E10/E11 -> 341.41674 | F12: =+F10/F11 -> 107.33662 | H12: =+H10/H11 -> 133.35846 | I12: $us./Mt² | J12: =+J10/J11 -> 133.35846
A13: Total Precio s/factura | D13: =+D69 -> 181.77 | E13: =+E69 -> 320.24226 | F13: =+F69 -> 235.19492 | H13: =SUM(J13:IV13) -> 263.7574 | I13: $us. | J13: =+J69 -> 263.7574
A14: Precio sin factura en $us / Mt² | D14: =+D13/D11 -> 181.77 | E14: =+E13/E11 -> 320.24226 | F14: =+F13/F11 -> 97.997883 | H14: =+H13/H11 -> 124.35521 | I14: $us./Mt² | J14: =+J13/J11 -> 124.35521
A15: Total Kgr.
A16: % descuento del con al sin | D16: =+(D10-D13)/D10 -> 0.06597811 | E16: =+(E10-E13)/E10 -> 0.062019455 | F16: =+(F10-F13)/F10 -> 0.087004171 | H16: =+(H10-H13)/H10 -> 0.067511642 | J16: =+(J10-J13)/J10 -> 0.067511642
A18: DETALLE DE MATERIALES A UTILIZAR
A19: MATERIAL | C19: Unidad | D19: PB1H | E19: PB2H | F19: PB4H | H19: Cantidad | I19: Unidad | J19: PB1H
A20: Vidrio Templado 10mm Incoloro | C20: Mt² | D20: =IF(D8=1,D$5*D$6*D$7,0) -> 1 | E20: =IF(E8=1,E$5*E$6*E$7,0) -> 1 | F20: =IF(F8=1,F$5*F$6*F$7,0) -> 2.4 | H20: =ROUNDUP(SUM(J20:IV20),1) -> 0 | I20: Mt² | J20: =IF(J8=1,J$5*J$6*J$7,0) -> 0
A21: Vidrio Templado 10mm Color | C21: Mt² | D21: =IF(D8=2,D$5*D$6*D$7,0) -> 0 | E21: =IF(E8=2,E$5*E$6*E$7,0) -> 0 | F21: =IF(F8=2,F$5*F$6*F$7,0) -> 0 | H21: =ROUNDUP(SUM(J21:IV21),1) -> 2.2 | I21: Mt² | J21: =IF(J8=2,J$5*J$6*J$7,0) -> 2.121
A22: Mano de obra | C22: Mt² | D22: =+D11 -> 1 | E22: =+E11 -> 1 | F22: =+F11 -> 2.4 | H22: =ROUNDUP(SUM(J22:IV22),1) -> 2.2 | I22: Mt² | J22: =+J11 -> 2.121
A23: Silicona transp., blanca o negra | C23: Tubo | F23: =((2*F$6+F$5)/6)*F$7 -> 0.86666667 | H23: =ROUNDUP(SUM(J23:IV23),1) -> 0 | I23: Tubo
A24: Cinta masking 1/2 " (rollo de 20) | C24: Rollo | F24: =2*(2*F$6+F$5)*F$7/20 -> 0.52 | H24: =ROUNDUP(SUM(J24:IV24),1) -> 0 | I24: Rollo
A25: "U" 15x25 - Kg/Mt lineal. | B25: 0.2 | C25: Kgr | F25: =(2*F$6+F$5)*$B25*F$7 -> 1.04 | H25: =ROUNDUP(SUM(J25:IV25)/(B25*6),1) -> 0 | I25: Barras
A26: Felpa | C26: Mt lineal | E26: =+E$6*E$7 -> 1 | F26: =+F$6*F$7 -> 2 | H26: =ROUNDUP(SUM(J26:IV26),1) -> 0 | I26: Mt lineal
A27: Tarugos No. 6 | C27: Pza. | F27: =F$7*((2*F$6+F$5)/0.4) -> 13 | H27: =ROUNDUP(SUM(J27:IV27),1) -> 0 | I27: Pza.
A28: Tornillos 8 x 1 1/2 | C28: Pza. | F28: =F$7*((2*F$6+F$5)/0.4) -> 13 | H28: =ROUNDUP(SUM(J28:IV28),1) -> 0 | I28: Pza.
A29: Vedapres 001 - h - Kg/Mt l. | B29: 0.257 | C29: Kgr | E29: =(E$6)*$B29*E$7 -> 0.257 | F29: =(F$6)*$B29*F$7 -> 0.514 | H29: =ROUNDUP(SUM(J29:IV29),1) -> 0 | I29: Barra
A30: Freno Hidráulico HyH | C30: Pza. | D30: =IF(D$9=1,D$7,0) -> 1 | E30: =IF(E$9=1,2*E$7,0) -> 2 | F30: =IF(F$9=1,2*F$7,0) -> 0 | H30: =ROUNDUP(SUM(J30:IV30),1) -> 1 | I30: Pza. | J30: =IF(J$9=1,J$7,0) -> 1
A31: Manijones de vidrio | C31: Pza. | D31: =2*D$7 -> 2 | E31: =4*E$7 -> 4 | F31: =4*F$7 -> 4 | H31: =ROUNDUP(SUM(J31:IV31),1) -> 2 | I31: Pza. | J31: =2*J$7 -> 2
A32: 1335 | C32: Pza. | E32: =E$7*2 -> 2 | F32: =F$7*2 -> 2 | H32: =ROUNDUP(SUM(J32:IV32),1) -> 0 | I32: Pza.
A33: 1103 | C33: Pza. | D33: =D$7 -> 1 | E33: =E$7*2 -> 2 | F33: =F$7*2 -> 2 | H33: =ROUNDUP(SUM(J33:IV33),1) -> 1 | I33: Pza. | J33: =J$7 -> 1
A34: 1101 | C34: Pza. | D34: =D$7 -> 1 | E34: =E$7*2 -> 2 | F34: =F$7*2 -> 2 | H34: =ROUNDUP(SUM(J34:IV34),1) -> 1 | I34: Pza. | J34: =J$7 -> 1
A35: 1636 | C35: Pza. | D35: =D$7*2 -> 2 | E35: =E$7*4 -> 4 | F35: =F$7*4 -> 4 | H35: =ROUNDUP(SUM(J35:IV35),1) -> 2 | I35: Pza. | J35: =J$7*2 -> 2
A36: 1520 | C36: Pza. | D36: =D$7 -> 1 | E36: =E$7 -> 1 | F36: =F$7 -> 1 | H36: =ROUNDUP(SUM(J36:IV36),1) -> 1 | I36: Pza. | J36: =J$7 -> 1
A37: 1531 | C37: Pza. | E37: =E$7 -> 1 | F37: =F$7 -> 1 | H37: =ROUNDUP(SUM(J37:IV37),1) -> 0 | I37: Pza.
A38: 1038 | C38: Pza. | E38: =E$7*4 -> 4 | F38: =F$7*4 -> 4 | H38: =ROUNDUP(SUM(J38:IV38),1) -> 0 | I38: Pza.
A39: 1013 | C39: Pza. | D39: =D$7 -> 1 | E39: =E$7*2 -> 2 | F39: =F$7*2 -> 2 | H39: =ROUNDUP(SUM(J39:IV39),1) -> 1 | I39: Pza. | J39: =J$7 -> 1
A40: 1201 | C40: Pza. | D40: =+D$7 -> 1 | E40: =E$7*4 -> 4 | F40: =F$7*4 -> 4 | H40: =ROUNDUP(SUM(J40:IV40),1) -> 1 | I40: Pza. | J40: =+J$7 -> 1
A41: 1504a | C41: Pza. | D41: =D$7 -> 1 | H41: =ROUNDUP(SUM(J41:IV41),1) -> 1 | I41: Pza. | J41: =J$7 -> 1
A44: COSTO CON FACTURA | D44: =SUM(D45:D66) -> 194.61 | E44: =SUM(E45:E66) -> 341.41674 | F44: =SUM(F45:F66) -> 257.60788 | J44: =SUM(J45:J66) -> 282.85329
A45: Vidrio Templado 10mm Incoloro | C45: =+'Costo M.P.yMat.'!C26 -> 36.46 | D45: =+D20*$C45 -> 36.46 | E45: =+E20*$C45 -> 36.46 | F45: =+F20*$C45 -> 87.504 | J45: =+J20*$C45 -> 0
A46: Vidrio Templado 10mm Color | C46: =+'Costo M.P.yMat.'!C31 -> 52.41 | D46: =+D21*$C46 -> 0 | E46: =+E21*$C46 -> 0 | F46: =+F21*$C46 -> 0 | J46: =+J21*$C46 -> 111.16161
A47: Mano de obra | C47: =+'Costo M.P.yMat.'!C84 -> 12.08 | D47: =+D22*$C47 -> 12.08 | E47: =+E22*$C47 -> 12.08 | F47: =+F22*$C47 -> 28.992 | J47: =+J22*$C47 -> 25.62168
A48: Silicona transp., blanca o negra | C48: =+'Costo M.P.yMat.'!C7 -> 2.76 | D48: =+D23*$C48 -> 0 | E48: =+E23*$C48 -> 0 | F48: =+F23*$C48 -> 2.392 | J48: =+J23*$C48 -> 0
A49: Cinta masking 1/2 " (rollo de 20) | C49: =+'Costo M.P.yMat.'!C9 -> 0.75 | D49: =+D24*$C49 -> 0 | E49: =+E24*$C49 -> 0 | F49: =+F24*$C49 -> 0.39 | J49: =+J24*$C49 -> 0
A50: "U" 15x25 - Kg/Mt lineal. | C50: =+'Costo M.P.yMat.'!C10 -> 1.41 | D50: =+D25*$C50 -> 0 | E50: =+E25*$C50 -> 0 | F50: =+F25*$C50 -> 1.4664 | J50: =+J25*$C50 -> 0
A51: Felpa | C51: =+'Costo M.P.yMat.'!C17 -> 0.18 | D51: =+D26*$C51 -> 0 | E51: =+E26*$C51 -> 0.18 | F51: =+F26*$C51 -> 0.36 | J51: =+J26*$C51 -> 0
A52: Tarugos No. 6 | C52: =+'Costo M.P.yMat.'!C19 -> 0.04 | D52: =+D27*$C52 -> 0 | E52: =+E27*$C52 -> 0 | F52: =+F27*$C52 -> 0.52 | J52: =+J27*$C52 -> 0
A53: Tornillos 8 x 1 1/2 | C53: =+'Costo M.P.yMat.'!C20 -> 0.04 | D53: =+D28*$C53 -> 0 | E53: =+E28*$C53 -> 0 | F53: =+F28*$C53 -> 0.52 | J53: =+J28*$C53 -> 0
A54: Vedapres 001 - h - Kg/Mt l. | B54: 0.257 | C54: =+'Costo M.P.yMat.'!C89 -> 8.82 | D54: =+D29*$C54 -> 0 | E54: =+E29*$C54 -> 2.26674 | F54: =+F29*$C54 -> 4.53348 | J54: =+J29*$C54 -> 0
A55: Freno Hidráulico HyH | C55: =+'Costo M.P.yMat.'!C46 -> 79.75 | D55: =+D30*$C55 -> 79.75 | E55: =+E30*$C55 -> 159.5 | F55: =+F30*$C55 -> 0 | J55: =+J30*$C55 -> 79.75
A56: Manijones de vidrio | C56: =+'Costo M.P.yMat.'!C47 -> 3.42 | D56: =+D31*$C56 -> 6.84 | E56: =+E31*$C56 -> 13.68 | F56: =+F31*$C56 -> 13.68 | J56: =+J31*$C56 -> 6.84
A57: 1335 | C57: =+'Costo M.P.yMat.'!C70 -> 6.83 | D57: =+D32*$C57 -> 0 | E57: =+E32*$C57 -> 13.66 | F57: =+F32*$C57 -> 13.66 | J57: =+J32*$C57 -> 0
A58: 1103 | C58: =+'Costo M.P.yMat.'!C53 -> 12.08 | D58: =+D33*$C58 -> 12.08 | E58: =+E33*$C58 -> 24.16 | F58: =+F33*$C58 -> 24.16 | J58: =+J33*$C58 -> 12.08
A59: 1101 | C59: =+'Costo M.P.yMat.'!C52 -> 8.89 | D59: =+D34*$C59 -> 8.89 | E59: =+E34*$C59 -> 17.78 | F59: =+F34*$C59 -> 17.78 | J59: =+J34*$C59 -> 8.89
A60: 1636 | C60: =+'Costo M.P.yMat.'!C81 -> 3.59 | D60: =+D35*$C60 -> 7.18 | E60: =+E35*$C60 -> 14.36 | F60: =+F35*$C60 -> 14.36 | J60: =+J35*$C60 -> 7.18
A61: 1520 | C61: =+'Costo M.P.yMat.'!C76 -> 22.95 | D61: =+D36*$C61 -> 22.95 | E61: =+E36*$C61 -> 22.95 | F61: =+F36*$C61 -> 22.95 | J61: =+J36*$C61 -> 22.95
A62: 1531 | C62: =+'Costo M.P.yMat.'!C78 -> 8.48 | D62: =+D37*$C62 -> 0 | E62: =+E37*$C62 -> 8.48 | F62: =+F37*$C62 -> 8.48 | J62: =+J37*$C62 -> 0
A63: 1038 | C63: =+'Costo M.P.yMat.'!C50 -> 0.97 | D63: =+D38*$C63 -> 0 | E63: =+E38*$C63 -> 3.88 | F63: =+F38*$C63 -> 3.88 | J63: =+J38*$C63 -> 0
A64: 1013 | C64: =+'Costo M.P.yMat.'!C49 -> 3.59 | D64: =+D39*$C64 -> 3.59 | E64: =+E39*$C64 -> 7.18 | F64: =+F39*$C64 -> 7.18 | J64: =+J39*$C64 -> 3.59
A65: 1201 | C65: =+'Costo M.P.yMat.'!C60 -> 1.2 | D65: =+D40*$C65 -> 1.2 | E65: =+E40*$C65 -> 4.8 | F65: =+F40*$C65 -> 4.8 | J65: =+J40*$C65 -> 1.2
A66: 1504a | C66: =+'Costo M.P.yMat.'!C75 -> 3.59 | D66: =+D41*$C66 -> 3.59 | E66: =+E41*$C66 -> 0 | F66: =+F41*$C66 -> 0 | J66: =+J41*$C66 -> 3.59
A69: COSTO SIN FACTURA | D69: =SUM(D70:D91) -> 181.77 | E69: =SUM(E70:E91) -> 320.24226 | F69: =SUM(F70:F91) -> 235.19492 | J69: =SUM(J70:J91) -> 263.7574
A70: Vidrio Templado 10mm Incoloro | C70: =+'Costo M.P.yMat.'!D26 -> 33 | D70: =+$C70*D20 -> 33 | E70: =+$C70*E20 -> 33 | F70: =+$C70*F20 -> 79.2 | J70: =+$C70*J20 -> 0
A71: Vidrio Templado 10mm Color | C71: =+'Costo M.P.yMat.'!D31 -> 48.4 | D71: =+$C71*D21 -> 0 | E71: =+$C71*E21 -> 0 | F71: =+$C71*F21 -> 0 | J71: =+$C71*J21 -> 102.6564
A72: Mano de obra | C72: =+'Costo M.P.yMat.'!D84 -> 11 | D72: =+$C72*D22 -> 11 | E72: =+$C72*E22 -> 11 | F72: =+$C72*F22 -> 26.4 | J72: =+$C72*J22 -> 23.331
A73: Silicona transp., blanca o negra | C73: =+'Costo M.P.yMat.'!D7 -> 2.67 | D73: =+$C73*D23 -> 0 | E73: =+$C73*E23 -> 0 | F73: =+$C73*F23 -> 2.314 | J73: =+$C73*J23 -> 0
A74: Cinta masking 1/2 " (rollo de 20) | C74: =+'Costo M.P.yMat.'!D9 -> 0.72 | D74: =+$C74*D24 -> 0 | E74: =+$C74*E24 -> 0 | F74: =+$C74*F24 -> 0.3744 | J74: =+$C74*J24 -> 0
A75: "U" 15x25 - Kg/Mt lineal. | C75: =+'Costo M.P.yMat.'!D10 -> 1.3 | D75: =+$C75*D25 -> 0 | E75: =+$C75*E25 -> 0 | F75: =+$C75*F25 -> 1.352 | J75: =+$C75*J25 -> 0
A76: Felpa | C76: =+'Costo M.P.yMat.'!D17 -> 0.17 | D76: =+$C76*D26 -> 0 | E76: =+$C76*E26 -> 0.17 | F76: =+$C76*F26 -> 0.34 | J76: =+$C76*J26 -> 0
A77: Tarugos No. 6 | C77: =+'Costo M.P.yMat.'!D19 -> 0.04 | D77: =+$C77*D27 -> 0 | E77: =+$C77*E27 -> 0 | F77: =+$C77*F27 -> 0.52 | J77: =+$C77*J27 -> 0
A78: Tornillos 8 x 1 1/2 | C78: =+'Costo M.P.yMat.'!D20 -> 0.04 | D78: =+$C78*D28 -> 0 | E78: =+$C78*E28 -> 0 | F78: =+$C78*F28 -> 0.52 | J78: =+$C78*J28 -> 0
A79: Vedapres 001 - h - Kg/Mt l. | B79: 0.257 | C79: =+'Costo M.P.yMat.'!D89 -> 8.18 | D79: =+$C79*D29 -> 0 | E79: =+$C79*E29 -> 2.10226 | F79: =+$C79*F29 -> 4.20452 | J79: =+$C79*J29 -> 0
A80: Freno Hidráulico HyH | C80: =+'Costo M.P.yMat.'!D46 -> 77 | D80: =+$C80*D30 -> 77 | E80: =+$C80*E30 -> 154 | F80: =+$C80*F30 -> 0 | J80: =+$C80*J30 -> 77
A81: Manijones de vidrio | C81: =+'Costo M.P.yMat.'!D47 -> 3.3 | D81: =+$C81*D31 -> 6.6 | E81: =+$C81*E31 -> 13.2 | F81: =+$C81*F31 -> 13.2 | J81: =+$C81*J31 -> 6.6
A82: 1335 | C82: =+'Costo M.P.yMat.'!D70 -> 6.22 | D82: =+$C82*D32 -> 0 | E82: =+$C82*E32 -> 12.44 | F82: =+$C82*F32 -> 12.44 | J82: =+$C82*J32 -> 0
A83: 1103 | C83: =+'Costo M.P.yMat.'!D53 -> 11 | D83: =+$C83*D33 -> 11 | E83: =+$C83*E33 -> 22 | F83: =+$C83*F33 -> 22 | J83: =+$C83*J33 -> 11
A84: 1101 | C84: =+'Costo M.P.yMat.'!D52 -> 8.1 | D84: =+$C84*D34 -> 8.1 | E84: =+$C84*E34 -> 16.2 | F84: =+$C84*F34 -> 16.2 | J84: =+$C84*J34 -> 8.1
A85: 1636 | C85: =+'Costo M.P.yMat.'!D81 -> 3.27 | D85: =+$C85*D35 -> 6.54 | E85: =+$C85*E35 -> 13.08 | F85: =+$C85*F35 -> 13.08 | J85: =+$C85*J35 -> 6.54
A86: 1520 | C86: =+'Costo M.P.yMat.'!D76 -> 20.9 | D86: =+$C86*D36 -> 20.9 | E86: =+$C86*E36 -> 20.9 | F86: =+$C86*F36 -> 20.9 | J86: =+$C86*J36 -> 20.9
A87: 1531 | C87: =+'Costo M.P.yMat.'!D78 -> 7.73 | D87: =+$C87*D37 -> 0 | E87: =+$C87*E37 -> 7.73 | F87: =+$C87*F37 -> 7.73 | J87: =+$C87*J37 -> 0
A88: 1038 | C88: =+'Costo M.P.yMat.'!D50 -> 0.88 | D88: =+$C88*D38 -> 0 | E88: =+$C88*E38 -> 3.52 | F88: =+$C88*F38 -> 3.52 | J88: =+$C88*J38 -> 0
A89: 1013 | C89: =+'Costo M.P.yMat.'!D49 -> 3.27 | D89: =+$C89*D39 -> 3.27 | E89: =+$C89*E39 -> 6.54 | F89: =+$C89*F39 -> 6.54 | J89: =+$C89*J39 -> 3.27
A90: 1201 | C90: =+'Costo M.P.yMat.'!D60 -> 1.09 | D90: =+$C90*D40 -> 1.09 | E90: =+$C90*E40 -> 4.36 | F90: =+$C90*F40 -> 4.36 | J90: =+$C90*J40 -> 1.09
A91: 1504a | C91: =+'Costo M.P.yMat.'!D75 -> 3.27 | D91: =+$C91*D41 -> 3.27 | E91: =+$C91*E41 -> 0 | F91: =+$C91*F41 -> 0 | J91: =+$C91*J41 -> 3.27
A94: FORMULA PUERTA 2 HOJA+fijo | D94: BASE | E94: ALTURA | F94: BxH | H94: CANTIDAD
A95: Vidrio Templado 10mm Incoloro | C95: =+C45 -> 36.46
A96: Vidrio Templado 10mm Color | C96: =+C46 -> 52.41
A97: Mano de obra | C97: =+C47 -> 12.08 | F97: 1
A98: Silicona transp., blanca o negra | C98: =+C48 -> 2.76 | D98: 0.34 | E98: 0.17
A99: Cinta masking 1/2 " (rollo de 20) | C99: =+C49 -> 0.75 | D99: =0.34/10 -> 0.034 | E99: =0.17/10 -> 0.017
A100: "U" 15x15 - Kg/Mt lineal. | C100: =+C50 -> 1.41 | D100: 2 | E100: 1
A101: Felpa | C101: =+C51 -> 0.18 | E101: 1
A102: Tarugos No. 6 | C102: =+C52 -> 0.04 | D102: 3 | E102: 5
A103: Tornillos 8 x 1 1/2 | C103: =+C53 -> 0.04 | D103: 3 | E103: 5
A104: Vedapres 001 - h - Kg/Mt l. | B104: 0.257 | C104: =+C54 -> 8.82 | E104: 1
A105: Freno Hidráulico HyH | C105: =+C55 -> 79.75 | H105: 2
A106: Manijones de vidrio | C106: =+C56 -> 3.42 | H106: 4
A107: 1335 | C107: =+C57 -> 6.83 | H107: 2
A108: 1103 | C108: =+C58 -> 12.08 | H108: 2
...

Sheet Pano Fijo
D1: =ROUND(D5/0.9,0) -> 1 | H1: =ROUND(H5/0.9,0) -> 1 | I1: =ROUND(I5/0.9,0) -> 2
A2: PANO FIJO | D2: PF | F2: Total | H2: PF | I2: PF
A3: 8 o 10 mm. c/PERFIL U 15x15 DE ALUMINIO | D3: =IF(D10=8,"8 mm.","10 mm.") -> 10 mm. | H3: =IF(H10=8,"8 mm.","10 mm.") -> 10 mm. | I3: =IF(I10=8,"8 mm.","10 mm.") -> 10 mm.
A4: DATOS BASE PARA EL ANALISIS | D4: =IF(D9=1,"INCOLORO","COLOR") -> INCOLORO | H4: =IF(H9=1,"INCOLORO","COLOR") -> INCOLORO | I4: =IF(I9=1,"INCOLORO","COLOR") -> INCOLORO
A5: BASE ( Metros ) | D5: 1 | H5: 1.01 | I5: 1.72
A6: ALTURA ( Metros ) | D6: 1 | H6: 0.555 | I6: 0.545
A7: CANTIDAD DE PIEZAS | D7: 1 | F7: =SUM(H7:IV7) -> 2 | G7: Pzas. | H7: 1 | I7: 1
A8: CANTIDAD DE VANOS | D8: 1 | H8: 1 | I8: 1
A9: INCOLORO = 1 ; COLOR =2 | D9: 1 | H9: 1 | I9: 1
A10: ESPESOR DEL VIDRIO = 8 ó 10 mm. | D10: 10 | H10: 10 | I10: 10
A11: ESMERILADO = E
A12: Total Precio c/factura | C12: pn | D12: =+D49 -> 62.499 | F12: =SUM(H12:IV12) -> 97.956233 | G12: $us. | H12: =+H49 -> 37.717282 | I12: =+I49 -> 60.238951
A13: Superficie Mt² | D13: =+D5*D6*D$7 -> 1 | F13: =SUM(H13:IV13) -> 1.49795 | G13: Mt² | H13: =+H5*H6*H$7 -> 0.56055 | I13: =+I5*I6*I$7 -> 0.9374
A14: Precio con factura en $us / Mt² | D14: =+D12/D13 -> 62.499 | F14: =+F12/F13 -> 65.393526 | G14: $us./Mt² | H14: =+H12/H13 -> 67.286205 | I14: =+I12/I13 -> 64.261736
A15: Total Precio s/factura | D15: =+D76 -> 57.642 | F15: =SUM(H15:IV15) -> 90.68948 | G15: $us. | H15: =+H76 -> 34.96369 | I15: =+I76 -> 55.72579
A16: Precio sin factura en $us / Mt² | D16: =+D15/D13 -> 57.642 | F16: =+F15/F13 -> 60.542395 | G16: $us./Mt² | H16: =+H15/H13 -> 62.373901 | I16: =+I15/I13 -> 59.447184
A17: Total Kgr.
A18: % descuento del con al sin | D18: =+(D12-D15)/D12 -> 0.077713243 | F18: =+(F12-F15)/F12 -> 0.074183671 | H18: =+(H12-H15)/H12 -> 0.073006109 | I18: =+(I12-I15)/I12 -> 0.074920976
A20: DETALLE DE MATERIALES A UTILIZAR
A21: MATERIAL | C21: Unidad | D21: =+D2 -> PF | F21: Cantidad | G21: Unidad | H21: =+H2 -> PF | I21: =+I2 -> PF
A22: Vidrio Templado 10mm Incoloro | C22: Mt² | D22: =IF(D$9=1,IF(D$10=10,((D$6*0.05)+(D$5*D$6))*D$7,0),0) -> 1.05 | F22: =ROUNDUP(SUM(H22:IV22),1) -> 1.6 | G22: Mt² | H22: =IF(H$9=1,IF(H$10=10,((H$6*0.05)+(H$5*H$6))*H$7,0),0) -> 0.5883 | I22: =IF(I$9=1,IF(I$10=10,((I$6*0.05)+(I$5*I$6))*I$7,0),0) -> 0.96465
A23: Vidrio Templado 10mm Color | C23: Mt² | D23: =IF(D$9=2,IF(D$10=10,((D$6*0.05)+(D$5*D$6))*D$7,0),0) -> 0 | F23: =ROUNDUP(SUM(H23:IV23),1) -> 0 | G23: Mt² | H23: =IF(H$9=2,IF(H$10=10,((H$6*0.05)+(H$5*H$6))*H$7,0),0) -> 0 | I23: =IF(I$9=2,IF(I$10=10,((I$6*0.05)+(I$5*I$6))*I$7,0),0) -> 0
A24: Vidrio Templado 8mm Incoloro | C24: Mt² | D24: =IF(D$9=1,IF(D$10=8,((D$6*0.05)+(D$5*D$6))*D$7,0),0) -> 0 | F24: =ROUNDUP(SUM(H24:IV24),1) -> 0 | G24: Mt² | H24: =IF(H$9=1,IF(H$10=8,((H$6*0.05)+(H$5*H$6))*H$7,0),0) -> 0 | I24: =IF(I$9=1,IF(I$10=8,((I$6*0.05)+(I$5*I$6))*I$7,0),0) -> 0
A25: Vidrio Templado 8mm Color | C25: Mt² | D25: =IF(D$9=2,IF(D$10=8,((D$5*D$6))*D$7,0),0) -> 0 | F25: =ROUNDUP(SUM(H25:IV25),1) -> 0 | G25: Mt² | H25: =IF(H$9=2,IF(H$10=8,((H$5*H$6))*H$7,0),0) -> 0 | I25: =IF(I$9=2,IF(I$10=8,((I$5*I$6))*I$7,0),0) -> 0
A26: Mano de obra | C26: Mt² | D26: =+D13 -> 1 | F26: =ROUNDUP(SUM(H26:IV26),1) -> 1.5 | G26: Mt² | H26: =+H13 -> 0.56055 | I26: =+I13 -> 0.9374
A27: Silicona transp., blanca o negra | C27: Tubo | D27: =D7*(4*D5+4*D6+(D8-1)*D6)/6 -> 1.3333333 | F27: =ROUNDUP(SUM(H27:IV27),1) -> 2.6 | G27: Tubo | H27: =H7*(4*H5+4*H6+(H8-1)*H6)/6 -> 1.0433333 | I27: =I7*(4*I5+4*I6+(I8-1)*I6)/6 -> 1.51
A28: Cinta masking 1/2 " (rollo de 20) | C28: Rollo | D28: =+D27*12/20 -> 0.8 | F28: =ROUNDUP(SUM(H28:IV28),1) -> 1.6 | G28: Rollo | H28: =+H27*12/20 -> 0.626 | I28: =+I27*12/20 -> 0.906
A29: "U" 15x25 - Kg/Mt lineal. | B29: 0.2 | C29: Kgr | D29: =(2*D$6+2*D5)*$B29*D$7 -> 0.8 | F29: =ROUNDUP(SUM(H29:IV29)/(6*B29),1) -> 1.3 | G29: Barras | H29: =(2*H$6+2*H5)*$B29*H$7 -> 0.626 | I29: =(2*I$6+2*I5)*$B29*I$7 -> 0.906
A30: Esmerilado | C30: Mt² | D30: =IF((D11="e"),D13,IF( (D11="E"),D13,0)) -> 0 | F30: =ROUNDUP(SUM(H30:IV30),1) -> 0 | G30: Mt lineal | H30: =IF((H11="e"),H13,IF( (H11="E"),H13,0)) -> 0 | I30: =IF((I11="e"),I13,IF( (I11="E"),I13,0)) -> 0
A31: Tarugos No. 6 | C31: Pza. | D31: =D$7*(2*D$5+2*D$6)/0.4 -> 10 | F31: =ROUNDUP(SUM(H31:IV31),1) -> 19.2 | G31: Pza. | H31: =H$7*(2*H$5+2*H$6)/0.4 -> 7.825 | I31: =I$7*(2*I$5+2*I$6)/0.4 -> 11.325
A32: Tornillos 8 x 1 1/2 | C32: Pza. | D32: =D$7*(2*D$5+2*D$6)/0.4 -> 10 | F32: =ROUNDUP(SUM(H32:IV32),1) -> 19.2 | G32: Pza. | H32: =H$7*(2*H$5+2*H$6)/0.4 -> 7.825 | I32: =I$7*(2*I$5+2*I$6)/0.4 -> 11.325
A33: Vedapres 001 - u (2,10mt/barra) | C33: Barra | F33: =ROUNDUP(SUM(H33:IV33),1) -> 0 | G33: Barra
A34: Vedapres 001 - h (2,10mt/barra) | C34: Barra | F34: =ROUNDUP(SUM(H34:IV34),1) -> 0 | G34: Barra
A35: Cabezal 7313 - Kg/Mt l. | B35: 1.013 | C35: Kgr | F35: =ROUNDUP(SUM(H35:IV35)/(6*B35),1) -> 0 | G35: Barras
A36: Tapa 7312 - Kg/Mt l. | B36: 0.408 | C36: Kgr | F36: =ROUNDUP(SUM(H36:IV36)/(6*B36),1) -> 0 | G36: Barras
A37: Trillo 7314 - Kg/Mt l. | B37: 0.478 | C37: Kgr | F37: =ROUNDUP(SUM(H37:IV37)/(6*B37),1) -> 0 | G37: Barras
A38: TapaTrillo Rev. - Kg/Mt l. | B38: 0.125 | C38: Kgr | F38: =ROUNDUP(SUM(H38:IV38)/(6*B38),1) -> 0 | G38: Barras
A39: 1510 | C39: Pza. | F39: =ROUNDUP(SUM(H39:IV39),1) -> 0 | G39: Pza.
A40: 1511 | C40: Pza. | F40: =ROUNDUP(SUM(H40:IV40),1) -> 0 | G40: Pza.
A41: 1511a | C41: Pza. | F41: =ROUNDUP(SUM(H41:IV41),1) -> 0 | G41: Pza.
A42: 1125a | C42: Pza. | F42: =ROUNDUP(SUM(H42:IV42),1) -> 0 | G42: Pza.
A43: 1629j | C43: Pza. | F43: =ROUNDUP(SUM(H43:IV43),1) -> 0 | G43: Pza.
A44: 1335 | C44: Pza. | F44: =ROUNDUP(SUM(H44:IV44),1) -> 0 | G44: Pza.
A45: 1038c | C45: Pza. | F45: =ROUNDUP(SUM(H45:IV45),1) -> 0 | G45: Pza.
A49: COSTO CON FACTURA | D49: =SUM(D50:D73) -> 62.499 | F49: =ROUNDUP(SUM(H49:IV49),1) -> 98 | H49: =SUM(H50:H73) -> 37.717282 | I49: =SUM(I50:I73) -> 60.238951
A50: Vidrio Templado 10mm Incoloro | C50: =+'Costo M.P.yMat.'!C26 -> 36.46 | D50: =+$C50*D22 -> 38.283 | F50: =ROUNDUP(SUM(H50:IV50),1) -> 56.7 | H50: =+$C50*H22 -> 21.449418 | I50: =+$C50*I22 -> 35.171139
A51: Vidrio Templado 10mm Color | C51: =+'Costo M.P.yMat.'!C31 -> 52.41 | D51: =+$C51*D23 -> 0 | F51: =ROUNDUP(SUM(H51:IV51),1) -> 0 | H51: =+$C51*H23 -> 0 | I51: =+$C51*I23 -> 0
A52: Vidrio Templado 8mm Incoloro | C52: =+'Costo M.P.yMat.'!C27 -> 34.18 | D52: =+$C52*D24 -> 0 | F52: =ROUNDUP(SUM(H52:IV52),1) -> 0 | H52: =+$C52*H24 -> 0 | I52: =+$C52*I24 -> 0
A53: Vidrio Templado 8mm Color | C53: =+'Costo M.P.yMat.'!C32 -> 50.13 | D53: =+$C53*D25 -> 0 | F53: =ROUNDUP(SUM(H53:IV53),1) -> 0 | H53: =+$C53*H25 -> 0 | I53: =+$C53*I25 -> 0
A54: Mano de obra | C54: =+'Costo M.P.yMat.'!C84 -> 12.08 | D54: =+$C54*D26 -> 12.08 | F54: =ROUNDUP(SUM(H54:IV54),1) -> 18.1 | H54: =+$C54*H26 -> 6.771444 | I54: =+$C54*I26 -> 11.323792
A55: Silicona transp., blanca o negra | C55: =+'Costo M.P.yMat.'!C7 -> 2.76 | D55: =+$C55*D27 -> 3.68 | F55: =ROUNDUP(SUM(H55:IV55),1) -> 7.1 | H55: =+$C55*H27 -> 2.8796 | I55: =+$C55*I27 -> 4.1676
A56: Cinta masking 1/2 " (rollo de 20) | C56: =+'Costo M.P.yMat.'!C9 -> 0.75 | D56: =+$C56*D28 -> 0.6 | F56: =ROUNDUP(SUM(H56:IV56),1) -> 1.2 | H56: =+$C56*H28 -> 0.4695 | I56: =+$C56*I28 -> 0.6795
A57: "U" 15x25 - Kg/Mt lineal. | B57: 0.2 | C57: =+'Costo M.P.yMat.'!$C$89 -> 8.82 | D57: =+$C57*D29 -> 7.056 | F57: =ROUNDUP(SUM(H57:IV57),1) -> 13.6 | H57: =+$C57*H29 -> 5.52132 | I57: =+$C57*I29 -> 7.99092
A58: Esmerilado | C58: =+'Costo M.P.yMat.'!C160 -> 1.14 | D58: =+$C58*D30 -> 0 | F58: =ROUNDUP(SUM(H58:IV58),1) -> 0 | H58: =+$C58*H30 -> 0 | I58: =+$C58*I30 -> 0
A59: Tarugos No. 6 | C59: =+'Costo M.P.yMat.'!C19 -> 0.04 | D59: =+$C59*D31 -> 0.4 | F59: =ROUNDUP(SUM(H59:IV59),1) -> 0.8 | H59: =+$C59*H31 -> 0.313 | I59: =+$C59*I31 -> 0.453
A60: Tornillos 8 x 1 1/2 | C60: =+'Costo M.P.yMat.'!C20 -> 0.04 | D60: =+$C60*D32 -> 0.4 | F60: =ROUNDUP(SUM(H60:IV60),1) -> 0.8 | H60: =+$C60*H32 -> 0.313 | I60: =+$C60*I32 -> 0.453
A61: Vedapres 001 - u (2,10mt/barra) | C61: =+'Costo M.P.yMat.'!C40 -> 5.99 | D61: =+$C61*D33 -> 0 | F61: =ROUNDUP(SUM(H61:IV61),1) -> 0 | H61: =+$C61*H33 -> 0 | I61: =+$C61*I33 -> 0
A62: Vedapres 001 - h (2,10mt/barra) | C62: =+'Costo M.P.yMat.'!C39 -> 5.99 | D62: =+$C62*D34 -> 0 | F62: =ROUNDUP(SUM(H62:IV62),1) -> 0 | H62: =+$C62*H34 -> 0 | I62: =+$C62*I34 -> 0
A63: Cabezal 7313 - Kg/Mt l. | B63: 1.013 | C63: =+'Costo M.P.yMat.'!$C$89 -> 8.82 | D63: =+$C63*D35 -> 0 | F63: =ROUNDUP(SUM(H63:IV63),1) -> 0 | H63: =+$C63*H35 -> 0 | I63: =+$C63*I35 -> 0
A64: Tapa 7312 - Kg/Mt l. | B64: 0.408 | C64: =+'Costo M.P.yMat.'!$C$89 -> 8.82 | D64: =+$C64*D36 -> 0 | F64: =ROUNDUP(SUM(H64:IV64),1) -> 0 | H64: =+$C64*H36 -> 0 | I64: =+$C64*I36 -> 0
A65: Trillo 7314 - Kg/Mt l. | B65: 0.478 | C65: =+'Costo M.P.yMat.'!$C$89 -> 8.82 | D65: =+$C65*D37 -> 0 | F65: =ROUNDUP(SUM(H65:IV65),1) -> 0 | H65: =+$C65*H37 -> 0 | I65: =+$C65*I37 -> 0
A66: TapaTrillo Rev. - Kg/Mt l. | B66: 0.125 | C66: =+'Costo M.P.yMat.'!$C$89 -> 8.82 | D66: =+$C66*D38 -> 0 | F66: =ROUNDUP(SUM(H66:IV66),1) -> 0 | H66: =+$C66*H38 -> 0 | I66: =+$C66*I38 -> 0
A67: 1510 | C67: =+'Costo M.P.yMat.'!C73 -> 27.78 | D67: =+$C67*D39 -> 0 | F67: =ROUNDUP(SUM(H67:IV67),1) -> 0 | H67: =+$C67*H39 -> 0 | I67: =+$C67*I39 -> 0
A68: 1511 | C68: =+'Costo M.P.yMat.'!C74 -> 16.55 | D68: =+$C68*D40 -> 0 | F68: =ROUNDUP(SUM(H68:IV68),1) -> 0 | H68: =+$C68*H40 -> 0 | I68: =+$C68*I40 -> 0
A69: 1511a | C69: =+'Costo M.P.yMat.'!C75 -> 3.59 | D69: =+$C69*D41 -> 0 | F69: =ROUNDUP(SUM(H69:IV69),1) -> 0 | H69: =+$C69*H41 -> 0 | I69: =+$C69*I41 -> 0
A70: 1125a | C70: =+'Costo M.P.yMat.'!C59 -> 3.87 | D70: =+$C70*D42 -> 0 | F70: =ROUNDUP(SUM(H70:IV70),1) -> 0 | H70: =+$C70*H42 -> 0 | I70: =+$C70*I42 -> 0
A71: 1629j | C71: =+'Costo M.P.yMat.'!C79 -> 2.76 | D71: =+$C71*D43 -> 0 | F71: =ROUNDUP(SUM(H71:IV71),1) -> 0 | H71: =+$C71*H43 -> 0 | I71: =+$C71*I43 -> 0
A72: 1335 | C72: =+'Costo M.P.yMat.'!C70 -> 6.83 | D72: =+$C72*D44 -> 0 | F72: =ROUNDUP(SUM(H72:IV72),1) -> 0 | H72: =+$C72*H44 -> 0 | I72: =+$C72*I44 -> 0
A73: 1038c | C73: =+'Costo M.P.yMat.'!C51 -> 1.21 | D73: =+$C73*D45 -> 0 | F73: =ROUNDUP(SUM(H73:IV73),1) -> 0 | H73: =+$C73*H45 -> 0 | I73: =+$C73*I45 -> 0
A76: COSTO SIN FACTURA | D76: =SUM(D77:D100) -> 57.642 | F76: =ROUNDUP(SUM(H76:IV76),1) -> 90.7 | H76: =SUM(H77:H100) -> 34.96369 | I76: =SUM(I77:I100) -> 55.72579
A77: Vidrio Templado 10mm Incoloro | C77: =+'Costo M.P.yMat.'!D26 -> 33 | D77: =+$C77*D22 -> 34.65 | F77: =ROUNDUP(SUM(H77:IV77),1) -> 51.3 | H77: =+$C77*H22 -> 19.4139 | I77: =+$C77*I22 -> 31.83345
A78: Vidrio Templado 10mm Color | C78: =+'Costo M.P.yMat.'!D31 -> 48.4 | D78: =+$C78*D23 -> 0 | F78: =ROUNDUP(SUM(H78:IV78),1) -> 0 | H78: =+$C78*H23 -> 0 | I78: =+$C78*I23 -> 0
A79: Vidrio Templado 8mm Incoloro | C79: =+'Costo M.P.yMat.'!D27 -> 30.8 | D79: =+$C79*D24 -> 0 | F79: =ROUNDUP(SUM(H79:IV79),1) -> 0 | H79: =+$C79*H24 -> 0 | I79: =+$C79*I24 -> 0
A80: Vidrio Templado 8mm Color | C80: =+'Costo M.P.yMat.'!D32 -> 46.2 | D80: =+$C80*D25 -> 0 | F80: =ROUNDUP(SUM(H80:IV80),1) -> 0 | H80: =+$C80*H25 -> 0 | I80: =+$C80*I25 -> 0
A81: Mano de obra | C81: =+'Costo M.P.yMat.'!D84 -> 11 | D81: =+$C81*D26 -> 11 | F81: =ROUNDUP(SUM(H81:IV81),1) -> 16.5 | H81: =+$C81*H26 -> 6.16605 | I81: =+$C81*I26 -> 10.3114
A82: Silicona transp., blanca o negra | C82: =+'Costo M.P.yMat.'!D7 -> 2.67 | D82: =+$C82*D27 -> 3.56 | F82: =ROUNDUP(SUM(H82:IV82),1) -> 6.9 | H82: =+$C82*H27 -> 2.7857 | I82: =+$C82*I27 -> 4.0317
A83: Cinta masking 1/2 " (rollo de 20) | C83: =+'Costo M.P.yMat.'!D9 -> 0.72 | D83: =+$C83*D28 -> 0.576 | F83: =ROUNDUP(SUM(H83:IV83),1) -> 1.2 | H83: =+$C83*H28 -> 0.45072 | I83: =+$C83*I28 -> 0.65232
A84: "U" 15x25 - Kg/Mt lineal. | B84: 0.2 | C84: =+'Costo M.P.yMat.'!$C$89 -> 8.82 | D84: =+$C84*D29 -> 7.056 | F84: =ROUNDUP(SUM(H84:IV84),1) -> 13.6 | H84: =+$C84*H29 -> 5.52132 | I84: =+$C84*I29 -> 7.99092
A85: Esmerilado | C85: =+'Costo M.P.yMat.'!D160 -> 1.1 | D85: =+$C85*D30 -> 0 | F85: =ROUNDUP(SUM(H85:IV85),1) -> 0 | H85: =+$C85*H30 -> 0 | I85: =+$C85*I30 -> 0
A86: Tarugos No. 6 | C86: =+'Costo M.P.yMat.'!D19 -> 0.04 | D86: =+$C86*D31 -> 0.4 | F86: =ROUNDUP(SUM(H86:IV86),1) -> 0.8 | H86: =+$C86*H31 -> 0.313 | I86: =+$C86*I31 -> 0.453
A87: Tornillos 8 x 1 1/2 | C87: =+'Costo M.P.yMat.'!D20 -> 0.04 | D87: =+$C87*D32 -> 0.4 | F87: =ROUNDUP(SUM(H87:IV87),1) -> 0.8 | H87: =+$C87*H32 -> 0.313 | I87: =+$C87*I32 -> 0.453
A88: Vedapres 001 - u (2,10mt/barra) | C88: =+'Costo M.P.yMat.'!D40 -> 5.5 | D88: =+$C88*D33 -> 0 | F88: =ROUNDUP(SUM(H88:IV88),1) -> 0 | H88: =+$C88*H33 -> 0 | I88: =+$C88*I33 -> 0
A89: Vedapres 001 - h (2,10mt/barra) | C89: =+'Costo M.P.yMat.'!D39 -> 5.5 | D89: =+$C89*D34 -> 0 | F89: =ROUNDUP(SUM(H89:IV89),1) -> 0 | H89: =+$C89*H34 -> 0 | I89: =+$C89*I34 -> 0
A90: Cabezal 7313 - Kg/Mt l. | B90: 1.013 | C90: =+'Costo M.P.yMat.'!$C$89 -> 8.82 | D90: =+$C90*D35 -> 0 | F90: =ROUNDUP(SUM(H90:IV90),1) -> 0 | H90: =+$C90*H35 -> 0 | I90: =+$C90*I35 -> 0
A91: Tapa 7312 - Kg/Mt l. | B91: 0.408 | C91: =+'Costo M.P.yMat.'!$C$89 -> 8.82 | D91: =+$C91*D36 -> 0 | F91: =ROUNDUP(SUM(H91:IV91),1) -> 0 | H91: =+$C91*H36 -> 0 | I91: =+$C91*I36 -> 0
A92: Trillo 7314 - Kg/Mt l. | B92: 0.478 | C92: =+'Costo M.P.yMat.'!$C$89 -> 8.82 | D92: =+$C92*D37 -> 0 | F92: =ROUNDUP(SUM(H92:IV92),1) -> 0 | H92: =+$C92*H37 -> 0 | I92: =+$C92*I37 -> 0
A93: TapaTrillo Rev. - Kg/Mt l. | B93: 0.125 | C93: =+'Costo M.P.yMat.'!$C$89 -> 8.82 | D93: =+$C93*D38 -> 0 | F93: =ROUNDUP(SUM(H93:IV93),1) -> 0 | H93: =+$C93*H38 -> 0 | I93: =+$C93*I38 -> 0
A94: 1510 | C94: =+'Costo M.P.yMat.'!D73 -> 25.3 | D94: =+$C94*D39 -> 0 | F94: =ROUNDUP(SUM(H94:IV94),1) -> 0 | H94: =+$C94*H39 -> 0 | I94: =+$C94*I39 -> 0
A95: 1511 | C95: =+'Costo M.P.yMat.'!D74 -> 15.07 | D95: =+$C95*D40 -> 0 | F95: =ROUNDUP(SUM(H95:IV95),1) -> 0 | H95: =+$C95*H40 -> 0 | I95: =+$C95*I40 -> 0
A96: 1511a | C96: =+'Costo M.P.yMat.'!D75 -> 3.27 | D96: =+$C96*D41 -> 0 | F96: =ROUNDUP(SUM(H96:IV96),1) -> 0 | H96: =+$C96*H41 -> 0 | I96: =+$C96*I41 -> 0
A97: 1125a | C97: =+'Costo M.P.yMat.'!D59 -> 3.52 | D97: =+$C97*D42 -> 0 | F97: =ROUNDUP(SUM(H97:IV97),1) -> 0 | H97: =+$C97*H42 -> 0 | I97: =+$C97*I42 -> 0
A98: 1629j | C98: =+'Costo M.P.yMat.'!D79 -> 2.51 | D98: =+$C98*D43 -> 0 | F98: =ROUNDUP(SUM(H98:IV98),1) -> 0 | H98: =+$C98*H43 -> 0 | I98: =+$C98*I43 -> 0
A99: 1335 | C99: =+'Costo M.P.yMat.'!D70 -> 6.22 | D99: =+$C99*D44 -> 0 | F99: =ROUNDUP(SUM(H99:IV99),1) -> 0 | H99: =+$C99*H44 -> 0 | I99: =+$C99*I44 -> 0
A100: 1038c | C100: =+'Costo M.P.yMat.'!D51 -> 1.1 | D100: =+$C100*D45 -> 0 | F100: =ROUNDUP(SUM(H100:IV100),1) -> 0 | H100: =+$C100*H45 -> 0 | I100: =+$C100*I45 -> 0
A103: FORMULA | C103: BASE | D103: ALTURA | F103: BXH | G103: (N-1)*h
A104: Vidrio Templado 10mm Incoloro | B104: =+C50 -> 36.46
A105: Vidrio Templado 10mm Color | B105: =+C51 -> 52.41
A106: Vidrio Templado 8mm Incoloro | B106: =+C52 -> 34.18
A107: Vidrio Templado 8mm Color | B107: =+C53 -> 50.13
A108: Mano de obra | B108: =+C54 -> 12.08 | F108: 1
...

Sheet Hoja3
