Workbook

Sheet 1erT
A2: UNIDAD EDUCATIVA: COLEGIO DESPERTAD | M2: INICIO DE BIMESTRE : | T2: 45323 | AD2: No. TOTAL DE APROBADOS | AL2: =COUNTIF(BF15:BF56,">51") -> 11 | BC2: DIAS RESTANTES PARA FIN DE TRIMESTRE
A3: EDUCACION SECUNDARIA COMUNITARIA PRODUCTIVA | M3: FIN DE BIMESTRE : | T3: 45418 | AD3: No. TOTAL DE REPROBADOS | AL3: =COUNTIF(BF15:BF56,"<=51") -> 2 | BC3: =+T3-S8 -> 33
A4: CURSO: 2ndo A Secundaria | R4: =T3-T2 -> 95 | Z4: Días
A5: DIRECTORA : EUGENIA CONDORI MOYA
A6: MAESTRO : MARCELO A. RODRIGUEZ GRACIA
A7: CAMPO : COMUNIDAD Y SOCIEDAD
A8: MATERIA : HISTORIA | M8: FECHA ACTUAL : | S8: =TODAY() -> 45385
E9: EVALUACION DEL MAESTRO DIMENSIONES | BC9: AUTO EVALUACION DIMENSIONES (5) | BF9: TOTAL BIMESTRAL | BG9: SITUACION BIMESTRAL
A10: Nº | B10: Nombre completo | C10: ACUMULADA | D10: BIMESTRE | E10: SER (5) | M10: SABER (45) | AD10: HACER (40) | AU10: DECIDIR (5) | BC10: SER (2.5) | BD10: DECIDIR (2.5) | BE10: TOTAL
E11: EXPRESA ACTITUDES DE RESPETO EN PALABRAS Y ACCIONES HACIA EL Y CON LOS DEMAS | F11: ES RESPONSIBLE Y PUNTUAL AL LLEGAR A CLASE Y AL ENTREGAR TRABAJOS | G11: DEMUESTRA SOLIDARIDAD EN SUS ACTIVIDADES Y RELACIONES INTERPERSONALES | H11: FORTALEZCO MI IDENTIDAD PERSONAL SIN RECURRIR A COPIAS DE IDENTIDADES | I11: PRACTICO EL EQUILIBRIO EMOCIONAL QUE ES EL REFLEJO DE LO QUE VEO EN MI HOGAR | J11: OTROS VALORES | K11: 50%S - 50%H | L11: TOTAL | M11: Test Troy Movie | N11: Test Ancient Greece | AB11: EVALUACION PROMEDIO MAESTRO - 5 | AC11: TOTAL | AD11: 1 Early people of the Aegean | AE11: 2 The Rise of Greek City States | AF11: 3 Victory and Defeat in the Greek World | AG11: 4 The Glory That Was Greece | AH11: 5 Alexander and the Hellenistic Age | AS11: EVALUACION PROMEDIO MAESTRO - 5 | AT11: TOTAL | AU11: DEMUESTRO INICIATIVA DURANTE LAS ACTIVIDADES DEL AULA | AV11: RESPETO LAS NORMAS DE CONVIVENCIA ENTRE LOS COMPA;EROS | AW11: ME HAGO CARGO DE LAS PERTENENCIAS QUE TRAIGO AL COLEGIO | AX11: HAGO USO APROPIADO DEL LENGUAJE SIN USAR INSULTOS O APODOS OFENSIVOS | AY11: SOY PERSEVERANTE Y RESPONSABLEAL ASUMIR UN TRABAJO GRUPAL | AZ11: OTROS VALORES | BA11: 50%S - 50%H | BB11: TOTAL | BC11: HAGO USO APROPIADO DEL LENGUAJE SIN USAR INSULTOS O APODOS OFENSIVOS | BD11: SOY PERSEVERANTE Y RESPONSABLEAL ASUMIR UN TRABAJO GRUPAL
B12: FECHA ENCARGADA | L12: =IFERROR(AVERAGE(L15:L56),"") -> 3.5836939 | M12: 45331 | N12: 45365 | AC12: =IFERROR(AVERAGE(AC15:AC56),"") -> 31.776923 | AD12: 45331 | AE12: 45345 | AF12: 45352 | AG12: 45363 | AH12: 45366 | AT12: =IFERROR(AVERAGE(AT15:AT56),"") -> 28.915385 | BB12: =IFERROR(AVERAGE(BB15:BB56),"") -> 3.5836939 | BE12: =IFERROR(AVERAGE(BE15:BE56),"") | BF12: =IF(SUM(BB12,AT12,AC12,L12)=0,"",SUM(BB12,AT12,AC12,L12)) -> 67.859696 | BG12: /
B13: FECHA DE ENTREGA | M13: 45342 | N13: 45372 | AD13: 45338 | AE13: 45349 | AF13: 45356 | AG13: 45365 | AH13: 45370
B14: TIEMPO ( DIAS ) | E14: =+E13-E12 -> 0 | F14: =+F13-F12 -> 0 | G14: =+G13-G12 -> 0 | H14: =+H13-H12 -> 0 | I14: =+I13-I12 -> 0 | J14: =+J13-J12 -> 0 | K14: =+K13-K12 -> 0 | M14: =+M13-M12 -> 11 | N14: =+N13-N12 -> 7 | O14: =+O13-O12 -> 0 | P14: =+P13-P12 -> 0 | Q14: =+Q13-Q12 -> 0 | R14: =+R13-R12 -> 0 | S14: =+S13-S12 -> 0 | T14: =+T13-T12 -> 0 | ... AA14: =+AA13-AA12 -> 0 | AD14: =+AD13-AD12 -> 7 | AE14: =+AE13-AE12 -> 4 | AF14: =+AF13-AF12 -> 4 | AG14: =+AG13-AG12 -> 2 | AH14: =+AH13-AH12 -> 4 | AI14: =+AI13-AI12 -> 0 | AJ14: =+AJ13-AJ12 -> 0 | AK14: =+AK13-AK12 -> 0 | ... AR14: =+AR13-AR12 -> 0 | AU14: =+AU13-AU12 -> 0 | AV14: =+AV13-AV12 -> 0 | AW14: =+AW13-AW12 -> 0 | AX14: =+AX13-AX12 -> 0 | AY14: =+AY13-AY12 -> 0 | AZ14: =+AZ13-AZ12 -> 0 | BA14: =+BA13-BA12 -> 0 | BC14: =+BC13-BC12 -> 0 | BD14: =+BD13-BD12 -> 0
A15: 1 | B15: AGUILA SEJAS MATIAS HERNAN | C15: =IF(B15<>"",IFERROR(EVAL.ANUAL!X9,""),"") -> 26 | D15: =IF(B15<>"",IFERROR(EVAL.ANUAL!I9,""),"") -> 77 | K15: =IFERROR((AVERAGE(M15:AB15,AD15:AS15)),"") -> 85.666667 | L15: =IFERROR((AVERAGE(E15:K15)*0.05),"") -> 4.2833333 | M15: 100 | N15: 30 | AB15: =IFERROR(AVERAGE(M15:AA15),"") -> 65 | AC15: =IFERROR((AVERAGE(M15:AA15)*0.4)+(AB15*0.05),"") -> 29.25 | AD15: 85 | AE15: 100 | AF15: 100 | AG15: 100 | AH15: 95 | AS15: =IFERROR(AVERAGE(AD15:AR15),"") -> 96 | AT15: =IFERROR((AVERAGE(AD15:AR15)*0.35)+(AS15*0.05),"") -> 38.4 | BA15: =IFERROR(AVERAGE(M15:AB15,AD15:AS15),"") -> 85.666667 | BB15: =IFERROR((AVERAGE(AU15:BA15)*0.05),"") -> 4.2833333 | BE15: =IFERROR((AVERAGE(BC15)*0.025)+(BD15*0.025),"") | BF15: =IF(SUM(BB15,AT15,AC15,L15,BE15)=0,"",SUM(BB15,AT15,AC15,L15,BE15)) -> 76.216667 | BG15: =IF(BF15="","",IF(BF15<51,"REPROBADO",IF(BF15>=51,"APROBADO"," "))) -> APROBADO
A16: 2 | B16: ANTEZANA ARANIBAR JAVIER LEANDRO | C16: =IF(B16<>"",IFERROR(EVAL.ANUAL!X10,""),"") -> 30 | D16: =IF(B16<>"",IFERROR(EVAL.ANUAL!I10,""),"") -> 88 | K16: =IFERROR((AVERAGE(M16:AB16,AD16:AS16)),"") -> 94 | L16: =IFERROR((AVERAGE(E16:K16)*0.05),"") -> 4.7 | M16: 100 | N16: 68 | AB16: =IFERROR(AVERAGE(M16:AA16),"") -> 84 | AC16: =IFERROR((AVERAGE(M16:AA16)*0.4)+(AB16*0.05),"") -> 37.8 | AD16: 100 | AE16: 100 | AF16: 100 | AG16: 100 | AS16: =IFERROR(AVERAGE(AD16:AR16),"") -> 100 | AT16: =IFERROR((AVERAGE(AD16:AR16)*0.35)+(AS16*0.05),"") -> 40 | BA16: =IFERROR(AVERAGE(M16:AB16,AD16:AS16),"") -> 94 | BB16: =IFERROR((AVERAGE(AU16:BA16)*0.05),"") -> 4.7 | BE16: =IFERROR((AVERAGE(BC16)*0.025)+(BD16*0.025),"") | BF16: =IF(SUM(BB16,AT16,AC16,L16,BE16)=0,"",SUM(BB16,AT16,AC16,L16,BE16)) -> 87.2 | BG16: =IF(BF16="","",IF(BF16<51,"REPROBADO",IF(BF16>=51,"APROBADO"," "))) -> APROBADO
A17: 3 | B17: ANTEZANA TORREZ MATIAS ANDRE | C17: =IF(B17<>"",IFERROR(EVAL.ANUAL!X11,""),"") -> 29 | D17: =IF(B17<>"",IFERROR(EVAL.ANUAL!I11,""),"") -> 87 | K17: =IFERROR((AVERAGE(M17:AB17,AD17:AS17)),"") -> 92 | L17: =IFERROR((AVERAGE(E17:K17)*0.05),"") -> 4.6 | M17: 100 | N17: 76 | AB17: =IFERROR(AVERAGE(M17:AA17),"") -> 88 | AC17: =IFERROR((AVERAGE(M17:AA17)*0.4)+(AB17*0.05),"") -> 39.6 | AD17: 100 | AE17: 100 | AF17: 70 | AG17: 100 | AH17: 100 | AS17: =IFERROR(AVERAGE(AD17:AR17),"") -> 94 | AT17: =IFERROR((AVERAGE(AD17:AR17)*0.35)+(AS17*0.05),"") -> 37.6 | BA17: =IFERROR(AVERAGE(M17:AB17,AD17:AS17),"") -> 92 | BB17: =IFERROR((AVERAGE(AU17:BA17)*0.05),"") -> 4.6 | BE17: =IFERROR((AVERAGE(BC17)*0.025)+(BD17*0.025),"") | BF17: =IF(SUM(BB17,AT17,AC17,L17,BE17)=0,"",SUM(BB17,AT17,AC17,L17,BE17)) -> 86.4 | BG17: =IF(BF17="","",IF(BF17<51,"REPROBADO",IF(BF17>=51,"APROBADO"," "))) -> APROBADO
A18: 4 | B18: CARDOZO FRANCO JOHNNY LEONARDO | C18: =IF(B18<>"",IFERROR(EVAL.ANUAL!X12,""),"") -> 30 | D18: =IF(B18<>"",IFERROR(EVAL.ANUAL!I12,""),"") -> 89 | K18: =IFERROR((AVERAGE(M18:AB18,AD18:AS18)),"") -> 94.6875 | L18: =IFERROR((AVERAGE(E18:K18)*0.05),"") -> 4.734375 | M18: 100 | N18: 80 | AB18: =IFERROR(AVERAGE(M18:AA18),"") -> 90 | AC18: =IFERROR((AVERAGE(M18:AA18)*0.4)+(AB18*0.05),"") -> 40.5 | AD18: 100 | AE18: 100 | AF18: 90 | AG18: 100 | AS18: =IFERROR(AVERAGE(AD18:AR18),"") -> 97.5 | AT18: =IFERROR((AVERAGE(AD18:AR18)*0.35)+(AS18*0.05),"") -> 39 | BA18: =IFERROR(AVERAGE(M18:AB18,AD18:AS18),"") -> 94.6875 | BB18: =IFERROR((AVERAGE(AU18:BA18)*0.05),"") -> 4.734375 | BE18: =IFERROR((AVERAGE(BC18)*0.025)+(BD18*0.025),"") | BF18: =IF(SUM(BB18,AT18,AC18,L18,BE18)=0,"",SUM(BB18,AT18,AC18,L18,BE18)) -> 88.96875 | BG18: =IF(BF18="","",IF(BF18<51,"REPROBADO",IF(BF18>=51,"APROBADO"," "))) -> APROBADO
A19: 5 | B19: ESPINOZA MUÑOZ RUBEN SEBASTIAN | C19: =IF(B19<>"",IFERROR(EVAL.ANUAL!X13,""),"") -> 10 | D19: =IF(B19<>"",IFERROR(EVAL.ANUAL!I13,""),"") -> 29 | K19: =IFERROR((AVERAGE(M19:AB19,AD19:AS19)),"") -> 28.34375 | L19: =IFERROR((AVERAGE(E19:K19)*0.05),"") -> 1.4171875 | M19: 60 | N19: 12 | AB19: =IFERROR(AVERAGE(M19:AA19),"") -> 36 | AC19: =IFERROR((AVERAGE(M19:AA19)*0.4)+(AB19*0.05),"") -> 16.2 | AD19: 60 | AE19: 0 | AF19: 0 | AG19: 35 | AS19: =IFERROR(AVERAGE(AD19:AR19),"") -> 23.75 | AT19: =IFERROR((AVERAGE(AD19:AR19)*0.35)+(AS19*0.05),"") -> 9.5 | BA19: =IFERROR(AVERAGE(M19:AB19,AD19:AS19),"") -> 28.34375 | BB19: =IFERROR((AVERAGE(AU19:BA19)*0.05),"") -> 1.4171875 | BE19: =IFERROR((AVERAGE(BC19)*0.025)+(BD19*0.025),"") | BF19: =IF(SUM(BB19,AT19,AC19,L19,BE19)=0,"",SUM(BB19,AT19,AC19,L19,BE19)) -> 28.534375 | BG19: =IF(BF19="","",IF(BF19<51,"REPROBADO",IF(BF19>=51,"APROBADO"," "))) -> REPROBADO
A20: 6 | B20: HUANCA AMURRIO VALENTINA RAFAELA | C20: =IF(B20<>"",IFERROR(EVAL.ANUAL!X14,""),"") -> 22 | D20: =IF(B20<>"",IFERROR(EVAL.ANUAL!I14,""),"") -> 64 | K20: =IFERROR((AVERAGE(M20:AB20,AD20:AS20)),"") -> 72.6875 | L20: =IFERROR((AVERAGE(E20:K20)*0.05),"") -> 3.634375 | M20: 40 | N20: 56 | AB20: =IFERROR(AVERAGE(M20:AA20),"") -> 48 | AC20: =IFERROR((AVERAGE(M20:AA20)*0.4)+(AB20*0.05),"") -> 21.6 | AD20: 100 | AE20: 90 | AF20: 100 | AG20: 60 | AS20: =IFERROR(AVERAGE(AD20:AR20),"") -> 87.5 | AT20: =IFERROR((AVERAGE(AD20:AR20)*0.35)+(AS20*0.05),"") -> 35 | BA20: =IFERROR(AVERAGE(M20:AB20,AD20:AS20),"") -> 72.6875 | BB20: =IFERROR((AVERAGE(AU20:BA20)*0.05),"") -> 3.634375 | BE20: =IFERROR((AVERAGE(BC20)*0.025)+(BD20*0.025),"") | BF20: =IF(SUM(BB20,AT20,AC20,L20,BE20)=0,"",SUM(BB20,AT20,AC20,L20,BE20)) -> 63.86875 | BG20: =IF(BF20="","",IF(BF20<51,"REPROBADO",IF(BF20>=51,"APROBADO"," "))) -> APROBADO
A21: 7 | B21: MERCADO ROJAS MARIA BELEN | C21: =IF(B21<>"",IFERROR(EVAL.ANUAL!X15,""),"") -> 52 | D21: =IF(B21<>"",IFERROR(EVAL.ANUAL!I15,""),"") -> 78 | K21: =IFERROR((AVERAGE(M21:AB21,AD21:AS21)),"") -> 79.0625 | L21: =IFERROR((AVERAGE(E21:K21)*0.05),"") -> 3.953125 | M21: 100 | N21: 80 | AB21: =IFERROR(AVERAGE(M21:AA21),"") -> 90 | AC21: =IFERROR((AVERAGE(M21:AA21)*0.4)+(AB21*0.05),"") -> 40.5 | AD21: 100 | AE21: 0 | AF21: 100 | AG21: 90 | AS21: =IFERROR(AVERAGE(AD21:AR21),"") -> 72.5 | AT21: =IFERROR((AVERAGE(AD21:AR21)*0.35)+(AS21*0.05),"") -> 29 | BA21: =IFERROR(AVERAGE(M21:AB21,AD21:AS21),"") -> 79.0625 | BB21: =IFERROR((AVERAGE(AU21:BA21)*0.05),"") -> 3.953125 | BE21: =IFERROR((AVERAGE(BC21)*0.025)+(BD21*0.025),"") | BF21: =IF(SUM(BB21,AT21,AC21,L21,BE21)=0,"",SUM(BB21,AT21,AC21,L21,BE21)) -> 77.40625 | BG21: =IF(BF21="","",IF(BF21<51,"REPROBADO",IF(BF21>=51,"APROBADO"," "))) -> APROBADO
A22: 8 | B22: NUMBELA SAAVEDRA RAFAEL | C22: =IF(B22<>"",IFERROR(EVAL.ANUAL!X16,""),"") -> 27 | D22: =IF(B22<>"",IFERROR(EVAL.ANUAL!I16,""),"") -> 80 | K22: =IFERROR((AVERAGE(M22:AB22,AD22:AS22)),"") -> 85.666667 | L22: =IFERROR((AVERAGE(E22:K22)*0.05),"") -> 4.2833333 | M22: 100 | N22: 54 | AB22: =IFERROR(AVERAGE(M22:AA22),"") -> 77 | AC22: =IFERROR((AVERAGE(M22:AA22)*0.4)+(AB22*0.05),"") -> 34.65 | AD22: 100 | AE22: 100 | AF22: 90 | AG22: 90 | AH22: 70 | AS22: =IFERROR(AVERAGE(AD22:AR22),"") -> 90 | AT22: =IFERROR((AVERAGE(AD22:AR22)*0.35)+(AS22*0.05),"") -> 36 | BA22: =IFERROR(AVERAGE(M22:AB22,AD22:AS22),"") -> 85.666667 | BB22: =IFERROR((AVERAGE(AU22:BA22)*0.05),"") -> 4.2833333 | BE22: =IFERROR((AVERAGE(BC22)*0.025)+(BD22*0.025),"") | BF22: =IF(SUM(BB22,AT22,AC22,L22,BE22)=0,"",SUM(BB22,AT22,AC22,L22,BE22)) -> 79.216667 | BG22: =IF(BF22="","",IF(BF22<51,"REPROBADO",IF(BF22>=51,"APROBADO"," "))) -> APROBADO
A23: 9 | B23: PEÑALOZA PRADO RAFAEL ANDRES | C23: =IF(B23<>"",IFERROR(EVAL.ANUAL!X17,""),"") -> 18 | D23: =IF(B23<>"",IFERROR(EVAL.ANUAL!I17,""),"") -> 53 | K23: =IFERROR((AVERAGE(M23:AB23,AD23:AS23)),"") -> 48.333333 | L23: =IFERROR((AVERAGE(E23:K23)*0.05),"") -> 2.4166667 | M23: 80 | N23: 66 | AB23: =IFERROR(AVERAGE(M23:AA23),"") -> 73 | AC23: =IFERROR((AVERAGE(M23:AA23)*0.4)+(AB23*0.05),"") -> 32.85 | AD23: 0 | AE23: 0 | AF23: 0 | AG23: 80 | AH23: 100 | AS23: =IFERROR(AVERAGE(AD23:AR23),"") -> 36 | AT23: =IFERROR((AVERAGE(AD23:AR23)*0.35)+(AS23*0.05),"") -> 14.4 | BA23: =IFERROR(AVERAGE(M23:AB23,AD23:AS23),"") -> 48.333333 | BB23: =IFERROR((AVERAGE(AU23:BA23)*0.05),"") -> 2.4166667 | BE23: =IFERROR((AVERAGE(BC23)*0.025)+(BD23*0.025),"") | BF23: =IF(SUM(BB23,AT23,AC23,L23,BE23)=0,"",SUM(BB23,AT23,AC23,L23,BE23)) -> 52.083333 | BG23: =IF(BF23="","",IF(BF23<51,"REPROBADO",IF(BF23>=51,"APROBADO"," "))) -> APROBADO
A24: 10 | B24: PARDO LOPEZ ABIGAIL | C24: =IF(B24<>"",IFERROR(EVAL.ANUAL!X18,""),"") -> 11 | D24: =IF(B24<>"",IFERROR(EVAL.ANUAL!I18,""),"") -> 32 | K24: =IFERROR((AVERAGE(M24:AB24,AD24:AS24)),"") -> 32.333333 | L24: =IFERROR((AVERAGE(E24:K24)*0.05),"") -> 1.6166667 | M24: 10 | N24: 64 | AB24: =IFERROR(AVERAGE(M24:AA24),"") -> 37 | AC24: =IFERROR((AVERAGE(M24:AA24)*0.4)+(AB24*0.05),"") -> 16.65 | AD24: 0 | AE24: 0 | AF24: 0 | AG24: 50 | AH24: 100 | AS24: =IFERROR(AVERAGE(AD24:AR24),"") -> 30 | AT24: =IFERROR((AVERAGE(AD24:AR24)*0.35)+(AS24*0.05),"") -> 12 | BA24: =IFERROR(AVERAGE(M24:AB24,AD24:AS24),"") -> 32.333333 | BB24: =IFERROR((AVERAGE(AU24:BA24)*0.05),"") -> 1.6166667 | BE24: =IFERROR((AVERAGE(BC24)*0.025)+(BD24*0.025),"") | BF24: =IF(SUM(BB24,AT24,AC24,L24,BE24)=0,"",SUM(BB24,AT24,AC24,L24,BE24)) -> 31.883333 | BG24: =IF(BF24="","",IF(BF24<51,"REPROBADO",IF(BF24>=51,"APROBADO"," "))) -> REPROBADO
A25: 11 | B25: ROCABADO ANDIA MARIANA | C25: =IF(B25<>"",IFERROR(EVAL.ANUAL!X19,""),"") -> 26 | D25: =IF(B25<>"",IFERROR(EVAL.ANUAL!I19,""),"") -> 77 | K25: =IFERROR((AVERAGE(M25:AB25,AD25:AS25)),"") -> 82 | L25: =IFERROR((AVERAGE(E25:K25)*0.05),"") -> 4.1 | M25: 100 | N25: 56 | AB25: =IFERROR(AVERAGE(M25:AA25),"") -> 78 | AC25: =IFERROR((AVERAGE(M25:AA25)*0.4)+(AB25*0.05),"") -> 35.1 | AD25: 100 | AE25: 40 | AF25: 90 | AG25: 90 | AH25: 100 | AS25: =IFERROR(AVERAGE(AD25:AR25),"") -> 84 | AT25: =IFERROR((AVERAGE(AD25:AR25)*0.35)+(AS25*0.05),"") -> 33.6 | BA25: =IFERROR(AVERAGE(M25:AB25,AD25:AS25),"") -> 82 | BB25: =IFERROR((AVERAGE(AU25:BA25)*0.05),"") -> 4.1 | BE25: =IFERROR((AVERAGE(BC25)*0.025)+(BD25*0.025),"") | BF25: =IF(SUM(BB25,AT25,AC25,L25,BE25)=0,"",SUM(BB25,AT25,AC25,L25,BE25)) -> 76.9 | BG25: =IF(BF25="","",IF(BF25<51,"REPROBADO",IF(BF25>=51,"APROBADO"," "))) -> APROBADO
A26: 12 | B26: SEJAS CAMPOS ZULMA | C26: =IF(B26<>"",IFERROR(EVAL.ANUAL!X20,""),"") -> 26 | D26: =IF(B26<>"",IFERROR(EVAL.ANUAL!I20,""),"") -> 77 | K26: =IFERROR((AVERAGE(M26:AB26,AD26:AS26)),"") -> 78.3125 | L26: =IFERROR((AVERAGE(E26:K26)*0.05),"") -> 3.915625 | M26: 100 | N26: 76 | AB26: =IFERROR(AVERAGE(M26:AA26),"") -> 88 | AC26: =IFERROR((AVERAGE(M26:AA26)*0.4)+(AB26*0.05),"") -> 39.6 | AD26: 0 | AE26: 100 | AF26: 90 | AG26: 100 | AS26: =IFERROR(AVERAGE(AD26:AR26),"") -> 72.5 | AT26: =IFERROR((AVERAGE(AD26:AR26)*0.35)+(AS26*0.05),"") -> 29 | BA26: =IFERROR(AVERAGE(M26:AB26,AD26:AS26),"") -> 78.3125 | BB26: =IFERROR((AVERAGE(AU26:BA26)*0.05),"") -> 3.915625 | BE26: =IFERROR((AVERAGE(BC26)*0.025)+(BD26*0.025),"") | BF26: =IF(SUM(BB26,AT26,AC26,L26,BE26)=0,"",SUM(BB26,AT26,AC26,L26,BE26)) -> 76.43125 | BG26: =IF(BF26="","",IF(BF26<51,"REPROBADO",IF(BF26>=51,"APROBADO"," "))) -> APROBADO
A27: 13 | B27: VARGAS REQUEZ ZOE | C27: =IF(B27<>"",IFERROR(EVAL.ANUAL!X21,""),"") -> 20 | D27: =IF(B27<>"",IFERROR(EVAL.ANUAL!I21,""),"") -> 58 | K27: =IFERROR((AVERAGE(M27:AB27,AD27:AS27)),"") -> 58.666667 | L27: =IFERROR((AVERAGE(E27:K27)*0.05),"") -> 2.9333333 | M27: 70 | N27: 58 | AB27: =IFERROR(AVERAGE(M27:AA27),"") -> 64 | AC27: =IFERROR((AVERAGE(M27:AA27)*0.4)+(AB27*0.05),"") -> 28.8 | AD27: 100 | AE27: 0 | AF27: 0 | AG27: 90 | AH27: 90 | AS27: =IFERROR(AVERAGE(AD27:AR27),"") -> 56 | AT27: =IFERROR((AVERAGE(AD27:AR27)*0.35)+(AS27*0.05),"") -> 22.4 | BA27: =IFERROR(AVERAGE(M27:AB27,AD27:AS27),"") -> 58.666667 | BB27: =IFERROR((AVERAGE(AU27:BA27)*0.05),"") -> 2.9333333 | BE27: =IFERROR((AVERAGE(BC27)*0.025)+(BD27*0.025),"") | BF27: =IF(SUM(BB27,AT27,AC27,L27,BE27)=0,"",SUM(BB27,AT27,AC27,L27,BE27)) -> 57.066667 | BG27: =IF(BF27="","",IF(BF27<51,"REPROBADO",IF(BF27>=51,"APROBADO"," "))) -> APROBADO
A28: 14 | C28: =IF(B28<>"",IFERROR(EVAL.ANUAL!X22,""),"") | D28: =IF(B28<>"",IFERROR(EVAL.ANUAL!I22,""),"") | K28: =IFERROR((AVERAGE(M28:AB28,AD28:AS28)),"") | L28: =IFERROR((AVERAGE(E28:K28)*0.05),"") | AB28: =IFERROR(AVERAGE(M28:AA28),"") | AC28: =IFERROR((AVERAGE(M28:AA28)*0.4)+(AB28*0.05),"") | AS28: =IFERROR(AVERAGE(AD28:AR28),"") | AT28: =IFERROR((AVERAGE(AD28:AR28)*0.35)+(AS28*0.05),"") | BA28: =IFERROR(AVERAGE(M28:AB28,AD28:AS28),"") | BB28: =IFERROR((AVERAGE(AU28:BA28)*0.05),"") | BE28: =IFERROR((AVERAGE(BC28)*0.025)+(BD28*0.025),"") | BF28: =IF(SUM(BB28,AT28,AC28,L28,BE28)=0,"",SUM(BB28,AT28,AC28,L28,BE28)) | BG28: =IF(BF28="","",IF(BF28<51,"REPROBADO",IF(BF28>=51,"APROBADO"," ")))
A29: 15 | C29: =IF(B29<>"",IFERROR(EVAL.ANUAL!X23,""),"") | D29: =IF(B29<>"",IFERROR(EVAL.ANUAL!I23,""),"") | K29: =IFERROR((AVERAGE(M29:AB29,AD29:AS29)),"") | L29: =IFERROR((AVERAGE(E29:K29)*0.05),"") | AB29: =IFERROR(AVERAGE(M29:AA29),"") | AC29: =IFERROR((AVERAGE(M29:AA29)*0.4)+(AB29*0.05),"") | AS29: =IFERROR(AVERAGE(AD29:AR29),"") | AT29: =IFERROR((AVERAGE(AD29:AR29)*0.35)+(AS29*0.05),"") | BA29: =IFERROR(AVERAGE(M29:AB29,AD29:AS29),"") | BB29: =IFERROR((AVERAGE(AU29:BA29)*0.05),"") | BE29: =IFERROR((AVERAGE(BC29)*0.025)+(BD29*0.025),"") | BF29: =IF(SUM(BB29,AT29,AC29,L29,BE29)=0,"",SUM(BB29,AT29,AC29,L29,BE29)) | BG29: =IF(BF29="","",IF(BF29<51,"REPROBADO",IF(BF29>=51,"APROBADO"," ")))
A30: 16 | C30: =IF(B30<>"",IFERROR(EVAL.ANUAL!X24,""),"") | D30: =IF(B30<>"",IFERROR(EVAL.ANUAL!I24,""),"") | K30: =IFERROR((AVERAGE(M30:AB30,AD30:AS30)),"") | L30: =IFERROR((AVERAGE(E30:K30)*0.05),"") | AB30: =IFERROR(AVERAGE(M30:AA30),"") | AC30: =IFERROR((AVERAGE(M30:AA30)*0.4)+(AB30*0.05),"") | AS30: =IFERROR(AVERAGE(AD30:AR30),"") | AT30: =IFERROR((AVERAGE(AD30:AR30)*0.35)+(AS30*0.05),"") | BA30: =IFERROR(AVERAGE(M30:AB30,AD30:AS30),"") | BB30: =IFERROR((AVERAGE(AU30:BA30)*0.05),"") | BE30: =IFERROR((AVERAGE(BC30)*0.025)+(BD30*0.025),"") | BF30: =IF(SUM(BB30,AT30,AC30,L30,BE30)=0,"",SUM(BB30,AT30,AC30,L30,BE30)) | BG30: =IF(BF30="","",IF(BF30<51,"REPROBADO",IF(BF30>=51,"APROBADO"," ")))
A31: 17 | C31: =IF(B31<>"",IFERROR(EVAL.ANUAL!X25,""),"") | D31: =IF(B31<>"",IFERROR(EVAL.ANUAL!I25,""),"") | K31: =IFERROR((AVERAGE(M31:AB31,AD31:AS31)),"") | L31: =IFERROR((AVERAGE(E31:K31)*0.05),"") | AB31: =IFERROR(AVERAGE(M31:AA31),"") | AC31: =IFERROR((AVERAGE(M31:AA31)*0.4)+(AB31*0.05),"") | AS31: =IFERROR(AVERAGE(AD31:AR31),"") | AT31: =IFERROR((AVERAGE(AD31:AR31)*0.35)+(AS31*0.05),"") | BA31: =IFERROR(AVERAGE(M31:AB31,AD31:AS31),"") | BB31: =IFERROR((AVERAGE(AU31:BA31)*0.05),"") | BE31: =IFERROR((AVERAGE(BC31)*0.025)+(BD31*0.025),"") | BF31: =IF(SUM(BB31,AT31,AC31,L31,BE31)=0,"",SUM(BB31,AT31,AC31,L31,BE31)) | BG31: =IF(BF31="","",IF(BF31<51,"REPROBADO",IF(BF31>=51,"APROBADO"," ")))
A32: 18 | C32: =IF(B32<>"",IFERROR(EVAL.ANUAL!X26,""),"") | D32: =IF(B32<>"",IFERROR(EVAL.ANUAL!I26,""),"") | K32: =IFERROR((AVERAGE(M32:AB32,AD32:AS32)),"") | L32: =IFERROR((AVERAGE(E32:K32)*0.05),"") | AB32: =IFERROR(AVERAGE(M32:AA32),"") | AC32: =IFERROR((AVERAGE(M32:AA32)*0.4)+(AB32*0.05),"") | AS32: =IFERROR(AVERAGE(AD32:AR32),"") | AT32: =IFERROR((AVERAGE(AD32:AR32)*0.35)+(AS32*0.05),"") | BA32: =IFERROR(AVERAGE(M32:AB32,AD32:AS32),"") | BB32: =IFERROR((AVERAGE(AU32:BA32)*0.05),"") | BE32: =IFERROR((AVERAGE(BC32)*0.025)+(BD32*0.025),"") | BF32: =IF(SUM(BB32,AT32,AC32,L32,BE32)=0,"",SUM(BB32,AT32,AC32,L32,BE32)) | BG32: =IF(BF32="","",IF(BF32<51,"REPROBADO",IF(BF32>=51,"APROBADO"," ")))
A33: 19 | C33: =IF(B33<>"",IFERROR(EVAL.ANUAL!X27,""),"") | D33: =IF(B33<>"",IFERROR(EVAL.ANUAL!I27,""),"") | K33: =IFERROR((AVERAGE(M33:AB33,AD33:AS33)),"") | L33: =IFERROR((AVERAGE(E33:K33)*0.05),"") | AC33: =IFERROR((AVERAGE(M33:AA33)*0.4)+(AB33*0.05),"") | AS33: =IFERROR(AVERAGE(AD33:AR33),"") | AT33: =IFERROR((AVERAGE(AD33:AR33)*0.35)+(AS33*0.05),"") | BB33: =IFERROR((AVERAGE(AU33:BA33)*0.05),"") | BE33: =IFERROR((AVERAGE(BC33)*0.025)+(BD33*0.025),"") | BF33: =IF(SUM(BB33,AT33,AC33,L33,BE33)=0,"",SUM(BB33,AT33,AC33,L33,BE33)) | BG33: =IF(BF33="","",IF(BF33<51,"REPROBADO",IF(BF33>=51,"APROBADO"," ")))
A34: 20 | C34: =IF(B34<>"",IFERROR(EVAL.ANUAL!X28,""),"") | D34: =IF(B34<>"",IFERROR(EVAL.ANUAL!I28,""),"") | K34: =IFERROR((AVERAGE(M34:AB34,AD34:AS34)),"") | L34: =IFERROR((AVERAGE(E34:K34)*0.05),"") | AB34: =IFERROR(AVERAGE(M34:AA34),"") | AC34: =IFERROR((AVERAGE(M34:AA34)*0.4)+(AB34*0.05),"") | AS34: =IFERROR(AVERAGE(AD34:AR34),"") | AT34: =IFERROR((AVERAGE(AD34:AR34)*0.35)+(AS34*0.05),"") | BA34: =IFERROR(AVERAGE(M34:AB34,AD34:AS34),"") | BB34: =IFERROR((AVERAGE(AU34:BA34)*0.05),"") | BE34: =IFERROR((AVERAGE(BC34)*0.025)+(BD34*0.025),"") | BF34: =IF(SUM(BB34,AT34,AC34,L34,BE34)=0,"",SUM(BB34,AT34,AC34,L34,BE34)) | BG34: =IF(BF34="","",IF(BF34<51,"REPROBADO",IF(BF34>=51,"APROBADO"," ")))
A35: 21 | C35: =IF(B35<>"",IFERROR(EVAL.ANUAL!X29,""),"") | D35: =IF(B35<>"",IFERROR(EVAL.ANUAL!I29,""),"") | K35: =IFERROR((AVERAGE(M35:AB35,AD35:AS35)),"") | L35: =IFERROR((AVERAGE(E35:K35)*0.05),"") | AB35: =IFERROR(AVERAGE(M35:AA35),"") | AC35: =IFERROR((AVERAGE(M35:AA35)*0.4)+(AB35*0.05),"") | AS35: =IFERROR(AVERAGE(AD35:AR35),"") | AT35: =IFERROR((AVERAGE(AD35:AR35)*0.35)+(AS35*0.05),"") | BA35: =IFERROR(AVERAGE(M35:AB35,AD35:AS35),"") | BB35: =IFERROR((AVERAGE(AU35:BA35)*0.05),"") | BE35: =IFERROR((AVERAGE(BC35)*0.025)+(BD35*0.025),"") | BF35: =IF(SUM(BB35,AT35,AC35,L35,BE35)=0,"",SUM(BB35,AT35,AC35,L35,BE35)) | BG35: =IF(BF35="","",IF(BF35<51,"REPROBADO",IF(BF35>=51,"APROBADO"," ")))
A36: 22 | C36: =IF(B36<>"",IFERROR(EVAL.ANUAL!X30,""),"") | D36: =IF(B36<>"",IFERROR(EVAL.ANUAL!I30,""),"") | K36: =IFERROR((AVERAGE(M36:AB36,AD36:AS36)),"") | L36: =IFERROR((AVERAGE(E36:K36)*0.05),"") | AB36: =IFERROR(AVERAGE(M36:AA36),"") | AC36: =IFERROR((AVERAGE(M36:AA36)*0.4)+(AB36*0.05),"") | AS36: =IFERROR(AVERAGE(AD36:AR36),"") | AT36: =IFERROR((AVERAGE(AD36:AR36)*0.35)+(AS36*0.05),"") | BA36: =IFERROR(AVERAGE(M36:AB36,AD36:AS36),"") | BB36: =IFERROR((AVERAGE(AU36:BA36)*0.05),"") | BE36: =IFERROR((AVERAGE(BC36)*0.025)+(BD36*0.025),"") | BF36: =IF(SUM(BB36,AT36,AC36,L36,BE36)=0,"",SUM(BB36,AT36,AC36,L36,BE36)) | BG36: =IF(BF36="","",IF(BF36<51,"REPROBADO",IF(BF36>=51,"APROBADO"," ")))
A37: 23 | C37: =IF(B37<>"",IFERROR(EVAL.ANUAL!X31,""),"") | D37: =IF(B37<>"",IFERROR(EVAL.ANUAL!I31,""),"") | K37: =IFERROR((AVERAGE(M37:AB37,AD37:AS37)),"") | L37: =IFERROR((AVERAGE(E37:K37)*0.05),"") | AB37: =IFERROR(AVERAGE(M37:AA37),"") | AC37: =IFERROR((AVERAGE(M37:AA37)*0.4)+(AB37*0.05),"") | AS37: =IFERROR(AVERAGE(AD37:AR37),"") | AT37: =IFERROR((AVERAGE(AD37:AR37)*0.35)+(AS37*0.05),"") | BA37: =IFERROR(AVERAGE(M37:AB37,AD37:AS37),"") | BB37: =IFERROR((AVERAGE(AU37:BA37)*0.05),"") | BE37: =IFERROR((AVERAGE(BC37)*0.025)+(BD37*0.025),"") | BF37: =IF(SUM(BB37,AT37,AC37,L37,BE37)=0,"",SUM(BB37,AT37,AC37,L37,BE37)) | BG37: =IF(BF37="","",IF(BF37<51,"REPROBADO",IF(BF37>=51,"APROBADO"," ")))
C38: =IF(B38<>"",IFERROR(EVAL.ANUAL!X32,""),"") | D38: =IF(B38<>"",IFERROR(EVAL.ANUAL!I32,""),"") | K38: =IFERROR((AVERAGE(M38:AB38,AD38:AS38)),"") | L38: =IFERROR((AVERAGE(E38:K38)*0.05),"") | AB38: =IFERROR(AVERAGE(M38:AA38),"") | AC38: =IFERROR((AVERAGE(M38:AA38)*0.4)+(AB38*0.05),"") | AS38: =IFERROR(AVERAGE(AD38:AR38),"") | AT38: =IFERROR((AVERAGE(AD38:AR38)*0.35)+(AS38*0.05),"") | BA38: =IFERROR(AVERAGE(M38:AB38,AD38:AS38),"") | BB38: =IFERROR((AVERAGE(AU38:BA38)*0.05),"") | BE38: =IFERROR((AVERAGE(BC38)*0.025)+(BD38*0.025),"") | BF38: =IF(SUM(BB38,AT38,AC38,L38,BE38)=0,"",SUM(BB38,AT38,AC38,L38,BE38)) | BG38: =IF(BF38="","",IF(BF38<51,"REPROBADO",IF(BF38>=51,"APROBADO"," ")))
C39: =IF(B39<>"",IFERROR(EVAL.ANUAL!X33,""),"") | D39: =IF(B39<>"",IFERROR(EVAL.ANUAL!I33,""),"") | K39: =IFERROR((AVERAGE(M39:AB39,AD39:AS39)),"") | L39: =IFERROR((AVERAGE(E39:K39)*0.05),"") | AB39: =IFERROR(AVERAGE(M39:AA39),"") | AC39: =IFERROR((AVERAGE(M39:AA39)*0.4)+(AB39*0.05),"") | AS39: =IFERROR(AVERAGE(AD39:AR39),"") | AT39: =IFERROR((AVERAGE(AD39:AR39)*0.35)+(AS39*0.05),"") | BA39: =IFERROR(AVERAGE(M39:AB39,AD39:AS39),"") | BB39: =IFERROR((AVERAGE(AU39:BA39)*0.05),"") | BE39: =IFERROR((AVERAGE(BC39)*0.025)+(BD39*0.025),"") | BF39: =IF(SUM(BB39,AT39,AC39,L39,BE39)=0,"",SUM(BB39,AT39,AC39,L39,BE39)) | BG39: =IF(BF39="","",IF(BF39<51,"REPROBADO",IF(BF39>=51,"APROBADO"," ")))
C40: =IF(B40<>"",IFERROR(EVAL.ANUAL!X34,""),"") | D40: =IF(B40<>"",IFERROR(EVAL.ANUAL!I34,""),"") | K40: =IFERROR((AVERAGE(M40:AB40,AD40:AS40)),"") | L40: =IFERROR((AVERAGE(E40:K40)*0.05),"") | AB40: =IFERROR(AVERAGE(M40:AA40),"") | AC40: =IFERROR((AVERAGE(M40:AA40)*0.4)+(AB40*0.05),"") | AS40: =IFERROR(AVERAGE(AD40:AR40),"") | AT40: =IFERROR((AVERAGE(AD40:AR40)*0.35)+(AS40*0.05),"") | BA40: =IFERROR(AVERAGE(M40:AB40,AD40:AS40),"") | BB40: =IFERROR((AVERAGE(AU40:BA40)*0.05),"") | BE40: =IFERROR((AVERAGE(BC40)*0.025)+(BD40*0.025),"") | BF40: =IF(SUM(BB40,AT40,AC40,L40,BE40)=0,"",SUM(BB40,AT40,AC40,L40,BE40)) | BG40: =IF(BF40="","",IF(BF40<51,"REPROBADO",IF(BF40>=51,"APROBADO"," ")))
C41: =IF(B41<>"",IFERROR(EVAL.ANUAL!X35,""),"") | D41: =IF(B41<>"",IFERROR(EVAL.ANUAL!I35,""),"") | K41: =IFERROR((AVERAGE(M41:AB41,AD41:AS41)),"") | L41: =IFERROR((AVERAGE(E41:K41)*0.05),"") | AB41: =IFERROR(AVERAGE(M41:AA41),"") | AC41: =IFERROR((AVERAGE(M41:AA41)*0.4)+(AB41*0.05),"") | AS41: =IFERROR(AVERAGE(AD41:AR41),"") | AT41: =IFERROR((AVERAGE(AD41:AR41)*0.35)+(AS41*0.05),"") | BA41: =IFERROR(AVERAGE(M41:AB41,AD41:AS41),"") | BB41: =IFERROR((AVERAGE(AU41:BA41)*0.05),"") | BE41: =IFERROR((AVERAGE(BC41)*0.025)+(BD41*0.025),"") | BF41: =IF(SUM(BB41,AT41,AC41,L41,BE41)=0,"",SUM(BB41,AT41,AC41,L41,BE41)) | BG41: =IF(BF41="","",IF(BF41<51,"REPROBADO",IF(BF41>=51,"APROBADO"," ")))
C42: =IF(B42<>"",IFERROR(EVAL.ANUAL!X36,""),"") | D42: =IF(B42<>"",IFERROR(EVAL.ANUAL!I36,""),"") | K42: =IFERROR((AVERAGE(M42:AB42,AD42:AS42)),"") | L42: =IFERROR((AVERAGE(E42:K42)*0.05),"") | AB42: =IFERROR(AVERAGE(M42:AA42),"") | AC42: =IFERROR((AVERAGE(M42:AA42)*0.4)+(AB42*0.05),"") | AS42: =IFERROR(AVERAGE(AD42:AR42),"") | AT42: =IFERROR((AVERAGE(AD42:AR42)*0.35)+(AS42*0.05),"") | BA42: =IFERROR(AVERAGE(M42:AB42,AD42:AS42),"") | BB42: =IFERROR((AVERAGE(AU42:BA42)*0.05),"") | BE42: =IFERROR((AVERAGE(BC42)*0.025)+(BD42*0.025),"") | BF42: =IF(SUM(BB42,AT42,AC42,L42,BE42)=0,"",SUM(BB42,AT42,AC42,L42,BE42)) | BG42: =IF(BF42="","",IF(BF42<51,"REPROBADO",IF(BF42>=51,"APROBADO"," ")))
C43: =IF(B43<>"",IFERROR(EVAL.ANUAL!X37,""),"") | D43: =IF(B43<>"",IFERROR(EVAL.ANUAL!I37,""),"") | K43: =IFERROR((AVERAGE(M43:AB43,AD43:AS43)),"") | L43: =IFERROR((AVERAGE(E43:K43)*0.05),"") | AB43: =IFERROR(AVERAGE(M43:AA43),"") | AC43: =IFERROR((AVERAGE(M43:AA43)*0.4)+(AB43*0.05),"") | AS43: =IFERROR(AVERAGE(AD43:AR43),"") | AT43: =IFERROR((AVERAGE(AD43:AR43)*0.35)+(AS43*0.05),"") | BA43: =IFERROR(AVERAGE(M43:AB43,AD43:AS43),"") | BB43: =IFERROR((AVERAGE(AU43:BA43)*0.05),"") | BE43: =IFERROR((AVERAGE(BC43)*0.025)+(BD43*0.025),"") | BF43: =IF(SUM(BB43,AT43,AC43,L43,BE43)=0,"",SUM(BB43,AT43,AC43,L43,BE43)) | BG43: =IF(BF43="","",IF(BF43<51,"REPROBADO",IF(BF43>=51,"APROBADO"," ")))
C44: =IF(B44<>"",IFERROR(EVAL.ANUAL!X38,""),"") | D44: =IF(B44<>"",IFERROR(EVAL.ANUAL!I38,""),"") | K44: =IFERROR((AVERAGE(M44:AB44,AD44:AS44)),"") | L44: =IFERROR((AVERAGE(E44:K44)*0.05),"") | AB44: =IFERROR(AVERAGE(M44:AA44),"") | AC44: =IFERROR((AVERAGE(M44:AA44)*0.4)+(AB44*0.05),"") | AS44: =IFERROR(AVERAGE(AD44:AR44),"") | AT44: =IFERROR((AVERAGE(AD44:AR44)*0.35)+(AS44*0.05),"") | BA44: =IFERROR(AVERAGE(M44:AB44,AD44:AS44),"") | BB44: =IFERROR((AVERAGE(AU44:BA44)*0.05),"") | BE44: =IFERROR((AVERAGE(BC44)*0.025)+(BD44*0.025),"") | BF44: =IF(SUM(BB44,AT44,AC44,L44,BE44)=0,"",SUM(BB44,AT44,AC44,L44,BE44)) | BG44: =IF(BF44="","",IF(BF44<51,"REPROBADO",IF(BF44>=51,"APROBADO"," ")))
C45: =IF(B45<>"",IFERROR(EVAL.ANUAL!X39,""),"") | D45: =IF(B45<>"",IFERROR(EVAL.ANUAL!I39,""),"") | K45: =IFERROR((AVERAGE(M45:AB45,AD45:AS45)),"") | L45: =IFERROR((AVERAGE(E45:K45)*0.05),"") | AB45: =IFERROR(AVERAGE(M45:AA45),"") | AC45: =IFERROR((AVERAGE(M45:AA45)*0.4)+(AB45*0.05),"") | AS45: =IFERROR(AVERAGE(AD45:AR45),"") | AT45: =IFERROR((AVERAGE(AD45:AR45)*0.35)+(AS45*0.05),"") | BA45: =IFERROR(AVERAGE(M45:AB45,AD45:AS45),"") | BB45: =IFERROR((AVERAGE(AU45:BA45)*0.05),"") | BE45: =IFERROR((AVERAGE(BC45)*0.025)+(BD45*0.025),"") | BF45: =IF(SUM(BB45,AT45,AC45,L45,BE45)=0,"",SUM(BB45,AT45,AC45,L45,BE45)) | BG45: =IF(BF45="","",IF(BF45<51,"REPROBADO",IF(BF45>=51,"APROBADO"," ")))
C46: =IF(B46<>"",IFERROR(EVAL.ANUAL!X40,""),"") | D46: =IF(B46<>"",IFERROR(EVAL.ANUAL!I40,""),"") | K46: =IFERROR((AVERAGE(M46:AB46,AD46:AS46)),"") | L46: =IFERROR((AVERAGE(E46:K46)*0.05),"") | AB46: =IFERROR(AVERAGE(M46:AA46),"") | AC46: =IFERROR((AVERAGE(M46:AA46)*0.4)+(AB46*0.05),"") | AS46: =IFERROR(AVERAGE(AD46:AR46),"") | AT46: =IFERROR((AVERAGE(AD46:AR46)*0.35)+(AS46*0.05),"") | BA46: =IFERROR(AVERAGE(M46:AB46,AD46:AS46),"") | BB46: =IFERROR((AVERAGE(AU46:BA46)*0.05),"") | BE46: =IFERROR((AVERAGE(BC46)*0.025)+(BD46*0.025),"") | BF46: =IF(SUM(BB46,AT46,AC46,L46,BE46)=0,"",SUM(BB46,AT46,AC46,L46,BE46)) | BG46: =IF(BF46="","",IF(BF46<51,"REPROBADO",IF(BF46>=51,"APROBADO"," ")))
C47: =IF(B47<>"",IFERROR(EVAL.ANUAL!X41,""),"") | D47: =IF(B47<>"",IFERROR(EVAL.ANUAL!I41,""),"") | K47: =IFERROR((AVERAGE(M47:AB47,AD47:AS47)),"") | L47: =IFERROR((AVERAGE(E47:K47)*0.05),"") | AB47: =IFERROR(AVERAGE(M47:AA47),"") | AC47: =IFERROR((AVERAGE(M47:AA47)*0.4)+(AB47*0.05),"") | AS47: =IFERROR(AVERAGE(AD47:AR47),"") | AT47: =IFERROR((AVERAGE(AD47:AR47)*0.35)+(AS47*0.05),"") | BA47: =IFERROR(AVERAGE(M47:AB47,AD47:AS47),"") | BB47: =IFERROR((AVERAGE(AU47:BA47)*0.05),"") | BE47: =IFERROR((AVERAGE(BC47)*0.025)+(BD47*0.025),"") | BF47: =IF(SUM(BB47,AT47,AC47,L47,BE47)=0,"",SUM(BB47,AT47,AC47,L47,BE47)) | BG47: =IF(BF47="","",IF(BF47<51,"REPROBADO",IF(BF47>=51,"APROBADO"," ")))
C48: =IF(B48<>"",IFERROR(EVAL.ANUAL!X42,""),"") | D48: =IF(B48<>"",IFERROR(EVAL.ANUAL!I42,""),"") | K48: =IFERROR((AVERAGE(M48:AB48,AD48:AS48)),"") | L48: =IFERROR((AVERAGE(E48:K48)*0.05),"") | AB48: =IFERROR(AVERAGE(M48:AA48),"") | AC48: =IFERROR((AVERAGE(M48:AA48)*0.4)+(AB48*0.05),"") | AS48: =IFERROR(AVERAGE(AD48:AR48),"") | AT48: =IFERROR((AVERAGE(AD48:AR48)*0.35)+(AS48*0.05),"") | BA48: =IFERROR(AVERAGE(M48:AB48,AD48:AS48),"") | BB48: =IFERROR((AVERAGE(AU48:BA48)*0.05),"") | BE48: =IFERROR((AVERAGE(BC48)*0.025)+(BD48*0.025),"") | BF48: =IF(SUM(BB48,AT48,AC48,L48,BE48)=0,"",SUM(BB48,AT48,AC48,L48,BE48)) | BG48: =IF(BF48="","",IF(BF48<51,"REPROBADO",IF(BF48>=51,"APROBADO"," ")))
C49: =IF(B49<>"",IFERROR(EVAL.ANUAL!X43,""),"") | D49: =IF(B49<>"",IFERROR(EVAL.ANUAL!I43,""),"") | K49: =IFERROR((AVERAGE(M49:AB49,AD49:AS49)),"") | L49: =IFERROR((AVERAGE(E49:K49)*0.05),"") | AB49: =IFERROR(AVERAGE(M49:AA49),"") | AC49: =IFERROR((AVERAGE(M49:AA49)*0.4)+(AB49*0.05),"") | AS49: =IFERROR(AVERAGE(AD49:AR49),"") | AT49: =IFERROR((AVERAGE(AD49:AR49)*0.35)+(AS49*0.05),"") | BA49: =IFERROR(AVERAGE(M49:AB49,AD49:AS49),"") | BB49: =IFERROR((AVERAGE(AU49:BA49)*0.05),"") | BE49: =IFERROR((AVERAGE(BC49)*0.025)+(BD49*0.025),"") | BF49: =IF(SUM(BB49,AT49,AC49,L49,BE49)=0,"",SUM(BB49,AT49,AC49,L49,BE49)) | BG49: =IF(BF49="","",IF(BF49<51,"REPROBADO",IF(BF49>=51,"APROBADO"," ")))
... C56: =IF(B56<>"",IFERROR(EVAL.ANUAL!X50,""),"") | D56: =IF(B56<>"",IFERROR(EVAL.ANUAL!I50,""),"") | K56: =IFERROR((AVERAGE(M56:AB56,AD56:AS56)),"") | L56: =IFERROR((AVERAGE(E56:K56)*0.05),"") | AB56: =IFERROR(AVERAGE(M56:AA56),"") | AC56: =IFERROR((AVERAGE(M56:AA56)*0.4)+(AB56*0.05),"") | AS56: =IFERROR(AVERAGE(AD56:AR56),"") | AT56: =IFERROR((AVERAGE(AD56:AR56)*0.35)+(AS56*0.05),"") | BA56: =IFERROR(AVERAGE(M56:AB56,AD56:AS56),"") | BB56: =IFERROR((AVERAGE(AU56:BA56)*0.05),"") | BE56: =IFERROR((AVERAGE(BC56)*0.025)+(BD56*0.025),"") | BF56: =IF(SUM(BB56,AT56,AC56,L56,BE56)=0,"",SUM(BB56,AT56,AC56,L56,BE56)) | BG56: =IF(BF56="","",IF(BF56<51,"REPROBADO",IF(BF56>=51,"APROBADO"," ")))

Sheet 2doT
A2: UNIDAD EDUCATIVA: COLEGIO DESPERTAD | M2: INICIO DE BIMESTRE : | T2: 45421 | AD2: No. TOTAL DE APROBADOS | AL2: =COUNTIF(BF15:BF56,">51") -> 0 | BC2: DIAS RESTANTES PARA FIN DE TRIMESTRE
A3: EDUCACION SECUNDARIA COMUNITARIA PRODUCTIVA | M3: FIN DE BIMESTRE : | T3: 45530 | AD3: No. TOTAL DE REPROBADOS | AL3: =COUNTIF(BF15:BF56,"<=51") -> 0 | BC3: =+T3-S8 -> 145
A4: =+'1erT'!A4:AC4 -> CURSO: 2ndo A Secundaria | R4: =T3-T2-10 -> 99 | Z4: Días
A5: =+'1erT'!A5:AC5 -> DIRECTORA : EUGENIA CONDORI MOYA
A6: =+'1erT'!A6:AC6 -> MAESTRO : MARCELO A. RODRIGUEZ GRACIA
A7: =+'1erT'!A7:AC7 -> CAMPO : COMUNIDAD Y SOCIEDAD
A8: =+'1erT'!A8:L8 -> MATERIA : HISTORIA | M8: FECHA ACTUAL : | S8: =TODAY() -> 45385
E9: EVALUACION DEL MAESTRO DIMENSIONES | BC9: AUTO EVALUACION DIMENSIONES (5) | BF9: TOTAL BIMESTRAL | BG9: SITUACION BIMESTRAL
A10: Nº | B10: Nombre completo | C10: ACUMULADA | D10: BIMESTRE | E10: SER (5) | M10: SABER (45) | AD10: HACER (40) | AU10: DECIDIR (5) | BC10: SER (2.5) | BD10: DECIDIR (2.5) | BE10: TOTAL
E11: EXPRESA ACTITUDES DE RESPETO EN PALABRAS Y ACCIONES HACIA EL Y CON LOS DEMAS | F11: ES RESPONSIBLE Y PUNTUAL AL LLEGAR A CLASE Y AL ENTREGAR TRABAJOS | G11: DEMUESTRA SOLIDARIDAD EN SUS ACTIVIDADES Y RELACIONES INTERPERSONALES | H11: FORTALEZCO MI IDENTIDAD PERSONAL SIN RECURRIR A COPIAS DE IDENTIDADES | I11: PRACTICO EL EQUILIBRIO EMOCIONAL QUE ES EL REFLEJO DE LO QUE VEO EN MI HOGAR | J11: OTROS VALORES | K11: OTROS VALORES 2 | L11: TOTAL | AB11: EVALUACION PROMEDIO MAESTRO - 5 | AC11: TOTAL | AS11: EVALUACION PROMEDIO MAESTRO - 5 | AT11: TOTAL | AU11: DEMUESTRO INICIATIVA DURANTE LAS ACTIVIDADES DEL AULA | AV11: RESPETO LAS NORMAS DE CONVIVENCIA ENTRE LOS COMPA;EROS | AW11: ME HAGO CARGO DE LAS PERTENENCIAS QUE TRAIGO AL COLEGIO | AX11: HAGO USO APROPIADO DEL LENGUAJE SIN USAR INSULTOS O APODOS OFENSIVOS | AY11: SOY PERSEVERANTE Y RESPONSABLEAL ASUMIR UN TRABAJO GRUPAL | AZ11: OTROS VALORES | BA11: OTROS VALORES 2 | BB11: TOTAL | BC11: HAGO USO APROPIADO DEL LENGUAJE SIN USAR INSULTOS O APODOS OFENSIVOS | BD11: SOY PERSEVERANTE Y RESPONSABLEAL ASUMIR UN TRABAJO GRUPAL
B12: FECHA ENCARGADA | L12: =IFERROR(AVERAGE(L15:L56),"") | AC12: =IFERROR(AVERAGE(AC15:AC56),"") | AT12: =IFERROR(AVERAGE(AT15:AT56),"") | BB12: =IFERROR(AVERAGE(BB15:BB56),"") | BE12: =IFERROR(AVERAGE(BE15:BE56),"") | BF12: =IF(SUM(BB12,AT12,AC12,L12)=0,"",SUM(BB12,AT12,AC12,L12)) | BG12: =IF(BF12="","",IF(BF12<=33,"Muestra muy poco interés en el proceso de aprendizaje",IF(BF12<=52,"No comprende las operaciones estudiadas",IF(BF12<=80,"Comprende las propiedades estudiadas y resuelve satisfactoriamente los problemas"," Resuelve satisfactoriamente los problemas y Relaciona lo estudiado con la realidad."))))
B13: FECHA DE ENTREGA
B14: TIEMPO ( DIAS ) | E14: =+E13-E12 -> 0 | F14: =+F13-F12 -> 0 | G14: =+G13-G12 -> 0 | H14: =+H13-H12 -> 0 | I14: =+I13-I12 -> 0 | J14: =+J13-J12 -> 0 | K14: =+K13-K12 -> 0 | M14: =+M13-M12 -> 0 | N14: =+N13-N12 -> 0 | O14: =+O13-O12 -> 0 | P14: =+P13-P12 -> 0 | Q14: =+Q13-Q12 -> 0 | R14: =+R13-R12 -> 0 | S14: =+S13-S12 -> 0 | T14: =+T13-T12 -> 0 | ... AA14: =+AA13-AA12 -> 0 | AD14: =+AD13-AD12 -> 0 | AE14: =+AE13-AE12 -> 0 | AF14: =+AF13-AF12 -> 0 | AG14: =+AG13-AG12 -> 0 | AH14: =+AH13-AH12 -> 0 | AI14: =+AI13-AI12 -> 0 | AJ14: =+AJ13-AJ12 -> 0 | AK14: =+AK13-AK12 -> 0 | ... AR14: =+AR13-AR12 -> 0 | AU14: =+AU13-AU12 -> 0 | AV14: =+AV13-AV12 -> 0 | AW14: =+AW13-AW12 -> 0 | AX14: =+AX13-AX12 -> 0 | AY14: =+AY13-AY12 -> 0 | AZ14: =+AZ13-AZ12 -> 0 | BA14: =+BA13-BA12 -> 0 | BC14: =+BC13-BC12 -> 0 | BD14: =+BD13-BD12 -> 0
A15: =IF('1erT'!A15<>"",'1erT'!A15,"") -> 1 | B15: =IF('1erT'!B15<>"",'1erT'!B15,"") -> AGUILA SEJAS MATIAS HERNAN | C15: =IF(B15<>"",IFERROR(EVAL.ANUAL!X9,""),"") -> 26 | D15: =IF(B15<>"",IFERROR(EVAL.ANUAL!P9,""),"") -> 0 | K15: =IFERROR((AVERAGE(M15:AB15,AD15:AS15)),"") | L15: =IFERROR((AVERAGE(E15:K15)*0.05),"") | AB15: =IFERROR(AVERAGE(M15:AA15),"") | AC15: =IFERROR((AVERAGE(M15:AA15)*0.4)+(AB15*0.05),"") | AS15: =IFERROR(AVERAGE(AD15:AR15),"") | AT15: =IFERROR((AVERAGE(AD15:AR15)*0.35)+(AS15*0.05),"") | BA15: =K15 | BB15: =IFERROR((AVERAGE(AU15:BA15)*0.05),"") | BE15: =IFERROR((AVERAGE(BC15)*0.025)+(BD15*0.025),"") | BF15: =IF(SUM(BB15,AT15,AC15,L15,BE15)=0,"",SUM(BB15,AT15,AC15,L15,BE15)) | BG15: =IF(BF15="","",IF(BF15<51,"REPROBADO",IF(BF15>=51,"APROBADO"," ")))
A16: =IF('1erT'!A16<>"",'1erT'!A16,"") -> 2 | B16: =IF('1erT'!B16<>"",'1erT'!B16,"") -> ANTEZANA ARANIBAR JAVIER LEANDRO | C16: =IF(B16<>"",IFERROR(EVAL.ANUAL!X10,""),"") -> 30 | D16: =IF(B16<>"",IFERROR(EVAL.ANUAL!P10,""),"") -> 0 | K16: =IFERROR((AVERAGE(M16:AB16,AD16:AS16)),"") | L16: =IFERROR((AVERAGE(E16:K16)*0.05),"") | AB16: =IFERROR(AVERAGE(M16:AA16),"") | AC16: =IFERROR((AVERAGE(M16:AA16)*0.4)+(AB16*0.05),"") | AS16: =IFERROR(AVERAGE(AD16:AR16),"") | AT16: =IFERROR((AVERAGE(AD16:AR16)*0.35)+(AS16*0.05),"") | BA16: =K16 | BB16: =IFERROR((AVERAGE(AU16:BA16)*0.05),"") | BE16: =IFERROR((AVERAGE(BC16)*0.025)+(BD16*0.025),"") | BF16: =IF(SUM(BB16,AT16,AC16,L16,BE16)=0,"",SUM(BB16,AT16,AC16,L16,BE16)) | BG16: =IF(BF16="","",IF(BF16<51,"REPROBADO",IF(BF16>=51,"APROBADO"," ")))
A17: =IF('1erT'!A17<>"",'1erT'!A17,"") -> 3 | B17: =IF('1erT'!B17<>"",'1erT'!B17,"") -> ANTEZANA TORREZ MATIAS ANDRE | C17: =IF(B17<>"",IFERROR(EVAL.ANUAL!X11,""),"") -> 29 | D17: =IF(B17<>"",IFERROR(EVAL.ANUAL!P11,""),"") -> 0 | K17: =IFERROR((AVERAGE(M17:AB17,AD17:AS17)),"") | L17: =IFERROR((AVERAGE(E17:K17)*0.05),"") | AB17: =IFERROR(AVERAGE(M17:AA17),"") | AC17: =IFERROR((AVERAGE(M17:AA17)*0.4)+(AB17*0.05),"") | AS17: =IFERROR(AVERAGE(AD17:AR17),"") | AT17: =IFERROR((AVERAGE(AD17:AR17)*0.35)+(AS17*0.05),"") | BA17: =K17 | BB17: =IFERROR((AVERAGE(AU17:BA17)*0.05),"") | BE17: =IFERROR((AVERAGE(BC17)*0.025)+(BD17*0.025),"") | BF17: =IF(SUM(BB17,AT17,AC17,L17,BE17)=0,"",SUM(BB17,AT17,AC17,L17,BE17)) | BG17: =IF(BF17="","",IF(BF17<51,"REPROBADO",IF(BF17>=51,"APROBADO"," ")))
A18: =IF('1erT'!A18<>"",'1erT'!A18,"") -> 4 | B18: =IF('1erT'!B18<>"",'1erT'!B18,"") -> CARDOZO FRANCO JOHNNY LEONARDO | C18: =IF(B18<>"",IFERROR(EVAL.ANUAL!X12,""),"") -> 30 | D18: =IF(B18<>"",IFERROR(EVAL.ANUAL!P12,""),"") -> 0 | K18: =IFERROR((AVERAGE(M18:AB18,AD18:AS18)),"") | L18: =IFERROR((AVERAGE(E18:K18)*0.05),"") | AB18: =IFERROR(AVERAGE(M18:AA18),"") | AC18: =IFERROR((AVERAGE(M18:AA18)*0.4)+(AB18*0.05),"") | AS18: =IFERROR(AVERAGE(AD18:AR18),"") | AT18: =IFERROR((AVERAGE(AD18:AR18)*0.35)+(AS18*0.05),"") | BA18: =K18 | BB18: =IFERROR((AVERAGE(AU18:BA18)*0.05),"") | BE18: =IFERROR((AVERAGE(BC18)*0.025)+(BD18*0.025),"") | BF18: =IF(SUM(BB18,AT18,AC18,L18,BE18)=0,"",SUM(BB18,AT18,AC18,L18,BE18)) | BG18: =IF(BF18="","",IF(BF18<51,"REPROBADO",IF(BF18>=51,"APROBADO"," ")))
A19: =IF('1erT'!A19<>"",'1erT'!A19,"") -> 5 | B19: =IF('1erT'!B19<>"",'1erT'!B19,"") -> ESPINOZA MUÑOZ RUBEN SEBASTIAN | C19: =IF(B19<>"",IFERROR(EVAL.ANUAL!X13,""),"") -> 10 | D19: =IF(B19<>"",IFERROR(EVAL.ANUAL!P13,""),"") -> 0 | K19: =IFERROR((AVERAGE(M19:AB19,AD19:AS19)),"") | L19: =IFERROR((AVERAGE(E19:K19)*0.05),"") | AB19: =IFERROR(AVERAGE(M19:AA19),"") | AC19: =IFERROR((AVERAGE(M19:AA19)*0.4)+(AB19*0.05),"") | AS19: =IFERROR(AVERAGE(AD19:AR19),"") | AT19: =IFERROR((AVERAGE(AD19:AR19)*0.35)+(AS19*0.05),"") | BA19: =K19 | BB19: =IFERROR((AVERAGE(AU19:BA19)*0.05),"") | BE19: =IFERROR((AVERAGE(BC19)*0.025)+(BD19*0.025),"") | BF19: =IF(SUM(BB19,AT19,AC19,L19,BE19)=0,"",SUM(BB19,AT19,AC19,L19,BE19)) | BG19: =IF(BF19="","",IF(BF19<51,"REPROBADO",IF(BF19>=51,"APROBADO"," ")))
A20: =IF('1erT'!A20<>"",'1erT'!A20,"") -> 6 | B20: =IF('1erT'!B20<>"",'1erT'!B20,"") -> HUANCA AMURRIO VALENTINA RAFAELA | C20: =IF(B20<>"",IFERROR(EVAL.ANUAL!X14,""),"") -> 22 | D20: =IF(B20<>"",IFERROR(EVAL.ANUAL!P14,""),"") -> 0 | K20: =IFERROR((AVERAGE(M20:AB20,AD20:AS20)),"") | L20: =IFERROR((AVERAGE(E20:K20)*0.05),"") | AB20: =IFERROR(AVERAGE(M20:AA20),"") | AC20: =IFERROR((AVERAGE(M20:AA20)*0.4)+(AB20*0.05),"") | AS20: =IFERROR(AVERAGE(AD20:AR20),"") | AT20: =IFERROR((AVERAGE(AD20:AR20)*0.35)+(AS20*0.05),"") | BA20: =K20 | BB20: =IFERROR((AVERAGE(AU20:BA20)*0.05),"") | BE20: =IFERROR((AVERAGE(BC20)*0.025)+(BD20*0.025),"") | BF20: =IF(SUM(BB20,AT20,AC20,L20,BE20)=0,"",SUM(BB20,AT20,AC20,L20,BE20)) | BG20: =IF(BF20="","",IF(BF20<51,"REPROBADO",IF(BF20>=51,"APROBADO"," ")))
A21: =IF('1erT'!A21<>"",'1erT'!A21,"") -> 7 | B21: =IF('1erT'!B21<>"",'1erT'!B21,"") -> MERCADO ROJAS MARIA BELEN | C21: =IF(B21<>"",IFERROR(EVAL.ANUAL!X15,""),"") -> 52 | D21: =IF(B21<>"",IFERROR(EVAL.ANUAL!P15,""),"") -> 0 | K21: =IFERROR((AVERAGE(M21:AB21,AD21:AS21)),"") | L21: =IFERROR((AVERAGE(E21:K21)*0.05),"") | AB21: =IFERROR(AVERAGE(M21:AA21),"") | AC21: =IFERROR((AVERAGE(M21:AA21)*0.4)+(AB21*0.05),"") | AS21: =IFERROR(AVERAGE(AD21:AR21),"") | AT21: =IFERROR((AVERAGE(AD21:AR21)*0.35)+(AS21*0.05),"") | BA21: =K21 | BB21: =IFERROR((AVERAGE(AU21:BA21)*0.05),"") | BE21: =IFERROR((AVERAGE(BC21)*0.025)+(BD21*0.025),"") | BF21: =IF(SUM(BB21,AT21,AC21,L21,BE21)=0,"",SUM(BB21,AT21,AC21,L21,BE21)) | BG21: =IF(BF21="","",IF(BF21<51,"REPROBADO",IF(BF21>=51,"APROBADO"," ")))
A22: =IF('1erT'!A22<>"",'1erT'!A22,"") -> 8 | B22: =IF('1erT'!B22<>"",'1erT'!B22,"") -> NUMBELA SAAVEDRA RAFAEL | C22: =IF(B22<>"",IFERROR(EVAL.ANUAL!X16,""),"") -> 27 | D22: =IF(B22<>"",IFERROR(EVAL.ANUAL!P16,""),"") -> 0 | K22: =IFERROR((AVERAGE(M22:AB22,AD22:AS22)),"") | L22: =IFERROR((AVERAGE(E22:K22)*0.05),"") | AB22: =IFERROR(AVERAGE(M22:AA22),"") | AC22: =IFERROR((AVERAGE(M22:AA22)*0.4)+(AB22*0.05),"") | AS22: =IFERROR(AVERAGE(AD22:AR22),"") | AT22: =IFERROR((AVERAGE(AD22:AR22)*0.35)+(AS22*0.05),"") | BA22: =K22 | BB22: =IFERROR((AVERAGE(AU22:BA22)*0.05),"") | BE22: =IFERROR((AVERAGE(BC22)*0.025)+(BD22*0.025),"") | BF22: =IF(SUM(BB22,AT22,AC22,L22,BE22)=0,"",SUM(BB22,AT22,AC22,L22,BE22)) | BG22: =IF(BF22="","",IF(BF22<51,"REPROBADO",IF(BF22>=51,"APROBADO"," ")))
A23: =IF('1erT'!A23<>"",'1erT'!A23,"") -> 9 | B23: =IF('1erT'!B23<>"",'1erT'!B23,"") -> PEÑALOZA PRADO RAFAEL ANDRES | C23: =IF(B23<>"",IFERROR(EVAL.ANUAL!X17,""),"") -> 18 | D23: =IF(B23<>"",IFERROR(EVAL.ANUAL!P17,""),"") -> 0 | K23: =IFERROR((AVERAGE(M23:AB23,AD23:AS23)),"") | L23: =IFERROR((AVERAGE(E23:K23)*0.05),"") | AB23: =IFERROR(AVERAGE(M23:AA23),"") | AC23: =IFERROR((AVERAGE(M23:AA23)*0.4)+(AB23*0.05),"") | AS23: =IFERROR(AVERAGE(AD23:AR23),"") | AT23: =IFERROR((AVERAGE(AD23:AR23)*0.35)+(AS23*0.05),"") | BA23: =K23 | BB23: =IFERROR((AVERAGE(AU23:BA23)*0.05),"") | BE23: =IFERROR((AVERAGE(BC23)*0.025)+(BD23*0.025),"") | BF23: =IF(SUM(BB23,AT23,AC23,L23,BE23)=0,"",SUM(BB23,AT23,AC23,L23,BE23)) | BG23: =IF(BF23="","",IF(BF23<51,"REPROBADO",IF(BF23>=51,"APROBADO"," ")))
A24: =IF('1erT'!A24<>"",'1erT'!A24,"") -> 10 | B24: =IF('1erT'!B24<>"",'1erT'!B24,"") -> PARDO LOPEZ ABIGAIL | C24: =IF(B24<>"",IFERROR(EVAL.ANUAL!X18,""),"") -> 11 | D24: =IF(B24<>"",IFERROR(EVAL.ANUAL!P18,""),"") -> 0 | K24: =IFERROR((AVERAGE(M24:AB24,AD24:AS24)),"") | L24: =IFERROR((AVERAGE(E24:K24)*0.05),"") | AB24: =IFERROR(AVERAGE(M24:AA24),"") | AC24: =IFERROR((AVERAGE(M24:AA24)*0.4)+(AB24*0.05),"") | AS24: =IFERROR(AVERAGE(AD24:AR24),"") | AT24: =IFERROR((AVERAGE(AD24:AR24)*0.35)+(AS24*0.05),"") | BA24: =K24 | BB24: =IFERROR((AVERAGE(AU24:BA24)*0.05),"") | BE24: =IFERROR((AVERAGE(BC24)*0.025)+(BD24*0.025),"") | BF24: =IF(SUM(BB24,AT24,AC24,L24,BE24)=0,"",SUM(BB24,AT24,AC24,L24,BE24)) | BG24: =IF(BF24="","",IF(BF24<51,"REPROBADO",IF(BF24>=51,"APROBADO"," ")))
A25: =IF('1erT'!A25<>"",'1erT'!A25,"") -> 11 | B25: =IF('1erT'!B25<>"",'1erT'!B25,"") -> ROCABADO ANDIA MARIANA | C25: =IF(B25<>"",IFERROR(EVAL.ANUAL!X19,""),"") -> 26 | D25: =IF(B25<>"",IFERROR(EVAL.ANUAL!P19,""),"") -> 0 | K25: =IFERROR((AVERAGE(M25:AB25,AD25:AS25)),"") | L25: =IFERROR((AVERAGE(E25:K25)*0.05),"") | AB25: =IFERROR(AVERAGE(M25:AA25),"") | AC25: =IFERROR((AVERAGE(M25:AA25)*0.4)+(AB25*0.05),"") | AS25: =IFERROR(AVERAGE(AD25:AR25),"") | AT25: =IFERROR((AVERAGE(AD25:AR25)*0.35)+(AS25*0.05),"") | BA25: =K25 | BB25: =IFERROR((AVERAGE(AU25:BA25)*0.05),"") | BE25: =IFERROR((AVERAGE(BC25)*0.025)+(BD25*0.025),"") | BF25: =IF(SUM(BB25,AT25,AC25,L25,BE25)=0,"",SUM(BB25,AT25,AC25,L25,BE25)) | BG25: =IF(BF25="","",IF(BF25<51,"REPROBADO",IF(BF25>=51,"APROBADO"," ")))
A26: =IF('1erT'!A26<>"",'1erT'!A26,"") -> 12 | B26: =IF('1erT'!B26<>"",'1erT'!B26,"") -> SEJAS CAMPOS ZULMA | C26: =IF(B26<>"",IFERROR(EVAL.ANUAL!X20,""),"") -> 26 | D26: =IF(B26<>"",IFERROR(EVAL.ANUAL!P20,""),"") -> 0 | K26: =IFERROR((AVERAGE(M26:AB26,AD26:AS26)),"") | L26: =IFERROR((AVERAGE(E26:K26)*0.05),"") | AB26: =IFERROR(AVERAGE(M26:AA26),"") | AC26: =IFERROR((AVERAGE(M26:AA26)*0.4)+(AB26*0.05),"") | AS26: =IFERROR(AVERAGE(AD26:AR26),"") | AT26: =IFERROR((AVERAGE(AD26:AR26)*0.35)+(AS26*0.05),"") | BA26: =K26 | BB26: =IFERROR((AVERAGE(AU26:BA26)*0.05),"") | BE26: =IFERROR((AVERAGE(BC26)*0.025)+(BD26*0.025),"") | BF26: =IF(SUM(BB26,AT26,AC26,L26,BE26)=0,"",SUM(BB26,AT26,AC26,L26,BE26)) | BG26: =IF(BF26="","",IF(BF26<51,"REPROBADO",IF(BF26>=51,"APROBADO"," ")))
... A56: =IF('1erT'!A56<>"",'1erT'!A56,"") | B56: =IF('1erT'!B56<>"",'1erT'!B56,"") | C56: =IF(B56<>"",IFERROR(EVAL.ANUAL!X50,""),"") | D56: =IF(B56<>"",IFERROR(EVAL.ANUAL!P50,""),"") | K56: =IFERROR((AVERAGE(M56:AB56,AD56:AS56)),"") | L56: =IFERROR((AVERAGE(E56:K56)*0.05),"") | AB56: =IFERROR(AVERAGE(M56:AA56),"") | AC56: =IFERROR((AVERAGE(M56:AA56)*0.4)+(AB56*0.05),"") | AS56: =IFERROR(AVERAGE(AD56:AR56),"") | AT56: =IFERROR((AVERAGE(AD56:AR56)*0.35)+(AS56*0.05),"") | BA56: =K56 | BB56: =IFERROR((AVERAGE(AU56:BA56)*0.05),"") | BE56: =IFERROR((AVERAGE(BC56)*0.025)+(BD56*0.025),"") | BF56: =IF(SUM(BB56,AT56,AC56,L56,BE56)=0,"",SUM(BB56,AT56,AC56,L56,BE56)) | BG56: =IF(BF56="","",IF(BF56<51,"REPROBADO",IF(BF56>=51,"APROBADO"," ")))

Sheet 3erT
A1: REGISTRO DE VALORACION 3er TRIMESTRE
A2: UNIDAD EDUCATIVA: COLEGIO DESPERTAD | M2: INICIO DE BIMESTRE : | T2: 45533 | AD2: No. TOTAL DE APROBADOS | AL2: =COUNTIF(BF15:BF56,">51") -> 0 | BC2: DIAS RESTANTES PARA FIN DE TRIMESTRE
A3: EDUCACION SECUNDARIA COMUNITARIA PRODUCTIVA | M3: FIN DE BIMESTRE : | T3: 45626 | AD3: No. TOTAL DE REPROBADOS | AL3: =COUNTIF(BF15:BF56,"<=51") -> 0 | BC3: =+T3-S8 -> 241
A4: =+'1erT'!A4:AC4 -> CURSO: 2ndo A Secundaria | R4: =T3-T2 -> 93 | Z4: Días
A5: =+'1erT'!A5:AC5 -> DIRECTORA : EUGENIA CONDORI MOYA
A6: =+'1erT'!A6:AC6 -> MAESTRO : MARCELO A. RODRIGUEZ GRACIA
A7: =+'1erT'!A7:AC7 -> CAMPO : COMUNIDAD Y SOCIEDAD
A8: =+'1erT'!A8:L8 -> MATERIA : HISTORIA | M8: FECHA ACTUAL : | S8: =TODAY() -> 45385
E9: EVALUACION DEL MAESTRO DIMENSIONES | BC9: AUTO EVALUACION DIMENSIONES (5) | BF9: TOTAL BIMESTRAL | BG9: SITUACION BIMESTRAL
A10: Nº | B10: Nombre completo | C10: ACUMULADA | D10: BIMESTRE | E10: SER (5) | M10: SABER (45) | AD10: HACER (40) | AU10: DECIDIR (5) | BC10: SER (2.5) | BD10: DECIDIR (2.5) | BE10: TOTAL
E11: EXPRESA ACTITUDES DE RESPETO EN PALABRAS Y ACCIONES HACIA EL Y CON LOS DEMAS | F11: ES RESPONSIBLE Y PUNTUAL AL LLEGAR A CLASE Y AL ENTREGAR TRABAJOS | G11: DEMUESTRA SOLIDARIDAD EN SUS ACTIVIDADES Y RELACIONES INTERPERSONALES | H11: FORTALEZCO MI IDENTIDAD PERSONAL SIN RECURRIR A COPIAS DE IDENTIDADES | I11: PRACTICO EL EQUILIBRIO EMOCIONAL QUE ES EL REFLEJO DE LO QUE VEO EN MI HOGAR | J11: OTROS VALORES | K11: OTROS VALORES 2 | L11: TOTAL | AB11: EVALUACION PROMEDIO MAESTRO - 5 | AC11: TOTAL | AS11: EVALUACION PROMEDIO MAESTRO - 5 | AT11: TOTAL | AU11: DEMUESTRO INICIATIVA DURANTE LAS ACTIVIDADES DEL AULA | AV11: RESPETO LAS NORMAS DE CONVIVENCIA ENTRE LOS COMPA;EROS | AW11: ME HAGO CARGO DE LAS PERTENENCIAS QUE TRAIGO AL COLEGIO | AX11: HAGO USO APROPIADO DEL LENGUAJE SIN USAR INSULTOS O APODOS OFENSIVOS | AY11: SOY PERSEVERANTE Y RESPONSABLEAL ASUMIR UN TRABAJO GRUPAL | AZ11: OTROS VALORES | BA11: OTROS VALORES 2 | BB11: TOTAL | BC11: HAGO USO APROPIADO DEL LENGUAJE SIN USAR INSULTOS O APODOS OFENSIVOS | BD11: SOY PERSEVERANTE Y RESPONSABLEAL ASUMIR UN TRABAJO GRUPAL
B12: FECHA ENCARGADA | L12: =IFERROR(AVERAGE(L15:L56),"") | AC12: =IFERROR(AVERAGE(AC15:AC56),"") | AT12: =IFERROR(AVERAGE(AT15:AT56),"") | BB12: =IFERROR(AVERAGE(BB15:BB56),"") | BE12: =IFERROR(AVERAGE(BE15:BE56),"") | BF12: =IF(SUM(BB12,AT12,AC12,L12)=0,"",SUM(BB12,AT12,AC12,L12)) | BG12: =IF(BF12="","",IF(BF12<=33,"Muestra muy poco interés en el proceso de aprendizaje",IF(BF12<=52,"No comprende las operaciones estudiadas",IF(BF12<=80,"Comprende las propiedades estudiadas y resuelve satisfactoriamente los problemas"," Resuelve satisfactoriamente los problemas y Relaciona lo estudiado con la realidad."))))
B13: FECHA DE ENTREGA
B14: TIEMPO ( DIAS ) | E14: =+E13-E12 -> 0 | F14: =+F13-F12 -> 0 | G14: =+G13-G12 -> 0 | H14: =+H13-H12 -> 0 | I14: =+I13-I12 -> 0 | J14: =+J13-J12 -> 0 | K14: =+K13-K12 -> 0 | M14: =+M13-M12 -> 0 | N14: =+N13-N12 -> 0 | O14: =+O13-O12 -> 0 | P14: =+P13-P12 -> 0 | Q14: =+Q13-Q12 -> 0 | R14: =+R13-R12 -> 0 | S14: =+S13-S12 -> 0 | T14: =+T13-T12 -> 0 | ... AA14: =+AA13-AA12 -> 0 | AD14: =+AD13-AD12 -> 0 | AE14: =+AE13-AE12 -> 0 | AF14: =+AF13-AF12 -> 0 | AG14: =+AG13-AG12 -> 0 | AH14: =+AH13-AH12 -> 0 | AI14: =+AI13-AI12 -> 0 | AJ14: =+AJ13-AJ12 -> 0 | AK14: =+AK13-AK12 -> 0 | ... AR14: =+AR13-AR12 -> 0 | AU14: =+AU13-AU12 -> 0 | AV14: =+AV13-AV12 -> 0 | AW14: =+AW13-AW12 -> 0 | AX14: =+AX13-AX12 -> 0 | AY14: =+AY13-AY12 -> 0 | AZ14: =+AZ13-AZ12 -> 0 | BA14: =+BA13-BA12 -> 0 | BC14: =+BC13-BC12 -> 0 | BD14: =+BD13-BD12 -> 0
A15: =IF('1erT'!A15<>"",'1erT'!A15,"") -> 1 | B15: =IF('1erT'!B15<>"",'1erT'!B15,"") -> AGUILA SEJAS MATIAS HERNAN | C15: =IF(B15<>"",IFERROR(EVAL.ANUAL!X9,""),"") -> 26 | D15: =IF(B15<>"",IFERROR(EVAL.ANUAL!W9,""),"") -> 0 | K15: =IFERROR((AVERAGE(M15:AB15,AD15:AS15)),"") | L15: =IFERROR((AVERAGE(E15:K15)*0.05),"") | AB15: =IFERROR(AVERAGE(M15:AA15),"") | AC15: =IFERROR((AVERAGE(M15:AA15)*0.4)+(AB15*0.05),"") | AS15: =IFERROR(AVERAGE(AD15:AR15),"") | AT15: =IFERROR((AVERAGE(AD15:AR15)*0.35)+(AS15*0.05),"") | BA15: =K15 | BB15: =IFERROR((AVERAGE(AU15:BA15)*0.05),"") | BE15: =IFERROR((AVERAGE(BC15)*0.025)+(BD15*0.025),"") | BF15: =IF(SUM(BB15,AT15,AC15,L15,BE15)=0,"",SUM(BB15,AT15,AC15,L15,BE15)) | BG15: =IF(BF15="","",IF(BF15<51,"REPROBADO",IF(BF15>=51,"APROBADO"," ")))
A16: =IF('1erT'!A16<>"",'1erT'!A16,"") -> 2 | B16: =IF('1erT'!B16<>"",'1erT'!B16,"") -> ANTEZANA ARANIBAR JAVIER LEANDRO | C16: =IF(B16<>"",IFERROR(EVAL.ANUAL!X10,""),"") -> 30 | D16: =IF(B16<>"",IFERROR(EVAL.ANUAL!W10,""),"") -> 0 | K16: =IFERROR((AVERAGE(M16:AB16,AD16:AS16)),"") | L16: =IFERROR((AVERAGE(E16:K16)*0.05),"") | AB16: =IFERROR(AVERAGE(M16:AA16),"") | AC16: =IFERROR((AVERAGE(M16:AA16)*0.4)+(AB16*0.05),"") | AS16: =IFERROR(AVERAGE(AD16:AR16),"") | AT16: =IFERROR((AVERAGE(AD16:AR16)*0.35)+(AS16*0.05),"") | BA16: =K16 | BB16: =IFERROR((AVERAGE(AU16:BA16)*0.05),"") | BE16: =IFERROR((AVERAGE(BC16)*0.025)+(BD16*0.025),"") | BF16: =IF(SUM(BB16,AT16,AC16,L16,BE16)=0,"",SUM(BB16,AT16,AC16,L16,BE16)) | BG16: =IF(BF16="","",IF(BF16<51,"REPROBADO",IF(BF16>=51,"APROBADO"," ")))
A17: =IF('1erT'!A17<>"",'1erT'!A17,"") -> 3 | B17: =IF('1erT'!B17<>"",'1erT'!B17,"") -> ANTEZANA TORREZ MATIAS ANDRE | C17: =IF(B17<>"",IFERROR(EVAL.ANUAL!X11,""),"") -> 29 | D17: =IF(B17<>"",IFERROR(EVAL.ANUAL!W11,""),"") -> 0 | K17: =IFERROR((AVERAGE(M17:AB17,AD17:AS17)),"") | L17: =IFERROR((AVERAGE(E17:K17)*0.05),"") | AB17: =IFERROR(AVERAGE(M17:AA17),"") | AC17: =IFERROR((AVERAGE(M17:AA17)*0.4)+(AB17*0.05),"") | AS17: =IFERROR(AVERAGE(AD17:AR17),"") | AT17: =IFERROR((AVERAGE(AD17:AR17)*0.35)+(AS17*0.05),"") | BA17: =K17 | BB17: =IFERROR((AVERAGE(AU17:BA17)*0.05),"") | BE17: =IFERROR((AVERAGE(BC17)*0.025)+(BD17*0.025),"") | BF17: =IF(SUM(BB17,AT17,AC17,L17,BE17)=0,"",SUM(BB17,AT17,AC17,L17,BE17)) | BG17: =IF(BF17="","",IF(BF17<51,"REPROBADO",IF(BF17>=51,"APROBADO"," ")))
A18: =IF('1erT'!A18<>"",'1erT'!A18,"") -> 4 | B18: =IF('1erT'!B18<>"",'1erT'!B18,"") -> CARDOZO FRANCO JOHNNY LEONARDO | C18: =IF(B18<>"",IFERROR(EVAL.ANUAL!X12,""),"") -> 30 | D18: =IF(B18<>"",IFERROR(EVAL.ANUAL!W12,""),"") -> 0 | K18: =IFERROR((AVERAGE(M18:AB18,AD18:AS18)),"") | L18: =IFERROR((AVERAGE(E18:K18)*0.05),"") | AB18: =IFERROR(AVERAGE(M18:AA18),"") | AC18: =IFERROR((AVERAGE(M18:AA18)*0.4)+(AB18*0.05),"") | AS18: =IFERROR(AVERAGE(AD18:AR18),"") | AT18: =IFERROR((AVERAGE(AD18:AR18)*0.35)+(AS18*0.05),"") | BA18: =K18 | BB18: =IFERROR((AVERAGE(AU18:BA18)*0.05),"") | BE18: =IFERROR((AVERAGE(BC18)*0.025)+(BD18*0.025),"") | BF18: =IF(SUM(BB18,AT18,AC18,L18,BE18)=0,"",SUM(BB18,AT18,AC18,L18,BE18)) | BG18: =IF(BF18="","",IF(BF18<51,"REPROBADO",IF(BF18>=51,"APROBADO"," ")))
A19: =IF('1erT'!A19<>"",'1erT'!A19,"") -> 5 | B19: =IF('1erT'!B19<>"",'1erT'!B19,"") -> ESPINOZA MUÑOZ RUBEN SEBASTIAN | C19: =IF(B19<>"",IFERROR(EVAL.ANUAL!X13,""),"") -> 10 | D19: =IF(B19<>"",IFERROR(EVAL.ANUAL!W13,""),"") -> 0 | K19: =IFERROR((AVERAGE(M19:AB19,AD19:AS19)),"") | L19: =IFERROR((AVERAGE(E19:K19)*0.05),"") | AB19: =IFERROR(AVERAGE(M19:AA19),"") | AC19: =IFERROR((AVERAGE(M19:AA19)*0.4)+(AB19*0.05),"") | AS19: =IFERROR(AVERAGE(AD19:AR19),"") | AT19: =IFERROR((AVERAGE(AD19:AR19)*0.35)+(AS19*0.05),"") | BA19: =K19 | BB19: =IFERROR((AVERAGE(AU19:BA19)*0.05),"") | BE19: =IFERROR((AVERAGE(BC19)*0.025)+(BD19*0.025),"") | BF19: =IF(SUM(BB19,AT19,AC19,L19,BE19)=0,"",SUM(BB19,AT19,AC19,L19,BE19)) | BG19: =IF(BF19="","",IF(BF19<51,"REPROBADO",IF(BF19>=51,"APROBADO"," ")))
A20: =IF('1erT'!A20<>"",'1erT'!A20,"") -> 6 | B20: =IF('1erT'!B20<>"",'1erT'!B20,"") -> HUANCA AMURRIO VALENTINA RAFAELA | C20: =IF(B20<>"",IFERROR(EVAL.ANUAL!X14,""),"") -> 22 | D20: =IF(B20<>"",IFERROR(EVAL.ANUAL!W14,""),"") -> 0 | K20: =IFERROR((AVERAGE(M20:AB20,AD20:AS20)),"") | L20: =IFERROR((AVERAGE(E20:K20)*0.05),"") | AB20: =IFERROR(AVERAGE(M20:AA20),"") | AC20: =IFERROR((AVERAGE(M20:AA20)*0.4)+(AB20*0.05),"") | AS20: =IFERROR(AVERAGE(AD20:AR20),"") | AT20: =IFERROR((AVERAGE(AD20:AR20)*0.35)+(AS20*0.05),"") | BA20: =K20 | BB20: =IFERROR((AVERAGE(AU20:BA20)*0.05),"") | BE20: =IFERROR((AVERAGE(BC20)*0.025)+(BD20*0.025),"") | BF20: =IF(SUM(BB20,AT20,AC20,L20,BE20)=0,"",SUM(BB20,AT20,AC20,L20,BE20)) | BG20: =IF(BF20="","",IF(BF20<51,"REPROBADO",IF(BF20>=51,"APROBADO"," ")))
A21: =IF('1erT'!A21<>"",'1erT'!A21,"") -> 7 | B21: =IF('1erT'!B21<>"",'1erT'!B21,"") -> MERCADO ROJAS MARIA BELEN | C21: =IF(B21<>"",IFERROR(EVAL.ANUAL!X15,""),"") -> 52 | D21: =IF(B21<>"",IFERROR(EVAL.ANUAL!W15,""),"") -> 78 | K21: =IFERROR((AVERAGE(M21:AB21,AD21:AS21)),"") | L21: =IFERROR((AVERAGE(E21:K21)*0.05),"") | AB21: =IFERROR(AVERAGE(M21:AA21),"") | AC21: =IFERROR((AVERAGE(M21:AA21)*0.4)+(AB21*0.05),"") | AS21: =IFERROR(AVERAGE(AD21:AR21),"") | AT21: =IFERROR((AVERAGE(AD21:AR21)*0.35)+(AS21*0.05),"") | BA21: =K21 | BB21: =IFERROR((AVERAGE(AU21:BA21)*0.05),"") | BE21: =IFERROR((AVERAGE(BC21)*0.025)+(BD21*0.025),"") | BF21: =IF(SUM(BB21,AT21,AC21,L21,BE21)=0,"",SUM(BB21,AT21,AC21,L21,BE21)) | BG21: =IF(BF21="","",IF(BF21<51,"REPROBADO",IF(BF21>=51,"APROBADO"," ")))
A22: =IF('1erT'!A22<>"",'1erT'!A22,"") -> 8 | B22: =IF('1erT'!B22<>"",'1erT'!B22,"") -> NUMBELA SAAVEDRA RAFAEL | C22: =IF(B22<>"",IFERROR(EVAL.ANUAL!X16,""),"") -> 27 | D22: =IF(B22<>"",IFERROR(EVAL.ANUAL!W16,""),"") -> 0 | K22: =IFERROR((AVERAGE(M22:AB22,AD22:AS22)),"") | L22: =IFERROR((AVERAGE(E22:K22)*0.05),"") | AB22: =IFERROR(AVERAGE(M22:AA22),"") | AC22: =IFERROR((AVERAGE(M22:AA22)*0.4)+(AB22*0.05),"") | AS22: =IFERROR(AVERAGE(AD22:AR22),"") | AT22: =IFERROR((AVERAGE(AD22:AR22)*0.35)+(AS22*0.05),"") | BA22: =K22 | BB22: =IFERROR((AVERAGE(AU22:BA22)*0.05),"") | BE22: =IFERROR((AVERAGE(BC22)*0.025)+(BD22*0.025),"") | BF22: =IF(SUM(BB22,AT22,AC22,L22,BE22)=0,"",SUM(BB22,AT22,AC22,L22,BE22)) | BG22: =IF(BF22="","",IF(BF22<51,"REPROBADO",IF(BF22>=51,"APROBADO"," ")))
A23: =IF('1erT'!A23<>"",'1erT'!A23,"") -> 9 | B23: =IF('1erT'!B23<>"",'1erT'!B23,"") -> PEÑALOZA PRADO RAFAEL ANDRES | C23: =IF(B23<>"",IFERROR(EVAL.ANUAL!X17,""),"") -> 18 | D23: =IF(B23<>"",IFERROR(EVAL.ANUAL!W17,""),"") -> 0 | K23: =IFERROR((AVERAGE(M23:AB23,AD23:AS23)),"") | L23: =IFERROR((AVERAGE(E23:K23)*0.05),"") | AB23: =IFERROR(AVERAGE(M23:AA23),"") | AC23: =IFERROR((AVERAGE(M23:AA23)*0.4)+(AB23*0.05),"") | AS23: =IFERROR(AVERAGE(AD23:AR23),"") | AT23: =IFERROR((AVERAGE(AD23:AR23)*0.35)+(AS23*0.05),"") | BA23: =K23 | BB23: =IFERROR((AVERAGE(AU23:BA23)*0.05),"") | BE23: =IFERROR((AVERAGE(BC23)*0.025)+(BD23*0.025),"") | BF23: =IF(SUM(BB23,AT23,AC23,L23,BE23)=0,"",SUM(BB23,AT23,AC23,L23,BE23)) | BG23: =IF(BF23="","",IF(BF23<51,"REPROBADO",IF(BF23>=51,"APROBADO"," ")))
A24: =IF('1erT'!A24<>"",'1erT'!A24,"") -> 10 | B24: =IF('1erT'!B24<>"",'1erT'!B24,"") -> PARDO LOPEZ ABIGAIL | C24: =IF(B24<>"",IFERROR(EVAL.ANUAL!X18,""),"") -> 11 | D24: =IF(B24<>"",IFERROR(EVAL.ANUAL!W18,""),"") -> 0 | K24: =IFERROR((AVERAGE(M24:AB24,AD24:AS24)),"") | L24: =IFERROR((AVERAGE(E24:K24)*0.05),"") | AB24: =IFERROR(AVERAGE(M24:AA24),"") | AC24: =IFERROR((AVERAGE(M24:AA24)*0.4)+(AB24*0.05),"") | AS24: =IFERROR(AVERAGE(AD24:AR24),"") | AT24: =IFERROR((AVERAGE(AD24:AR24)*0.35)+(AS24*0.05),"") | BA24: =K24 | BB24: =IFERROR((AVERAGE(AU24:BA24)*0.05),"") | BE24: =IFERROR((AVERAGE(BC24)*0.025)+(BD24*0.025),"") | BF24: =IF(SUM(BB24,AT24,AC24,L24,BE24)=0,"",SUM(BB24,AT24,AC24,L24,BE24)) | BG24: =IF(BF24="","",IF(BF24<51,"REPROBADO",IF(BF24>=51,"APROBADO"," ")))
A25: =IF('1erT'!A25<>"",'1erT'!A25,"") -> 11 | B25: =IF('1erT'!B25<>"",'1erT'!B25,"") -> ROCABADO ANDIA MARIANA | C25: =IF(B25<>"",IFERROR(EVAL.ANUAL!X19,""),"") -> 26 | D25: =IF(B25<>"",IFERROR(EVAL.ANUAL!W19,""),"") -> 0 | K25: =IFERROR((AVERAGE(M25:AB25,AD25:AS25)),"") | L25: =IFERROR((AVERAGE(E25:K25)*0.05),"") | AB25: =IFERROR(AVERAGE(M25:AA25),"") | AC25: =IFERROR((AVERAGE(M25:AA25)*0.4)+(AB25*0.05),"") | AS25: =IFERROR(AVERAGE(AD25:AR25),"") | AT25: =IFERROR((AVERAGE(AD25:AR25)*0.35)+(AS25*0.05),"") | BA25: =K25 | BB25: =IFERROR((AVERAGE(AU25:BA25)*0.05),"") | BE25: =IFERROR((AVERAGE(BC25)*0.025)+(BD25*0.025),"") | BF25: =IF(SUM(BB25,AT25,AC25,L25,BE25)=0,"",SUM(BB25,AT25,AC25,L25,BE25)) | BG25: =IF(BF25="","",IF(BF25<51,"REPROBADO",IF(BF25>=51,"APROBADO"," ")))
A26: =IF('1erT'!A26<>"",'1erT'!A26,"") -> 12 | B26: =IF('1erT'!B26<>"",'1erT'!B26,"") -> SEJAS CAMPOS ZULMA | C26: =IF(B26<>"",IFERROR(EVAL.ANUAL!X20,""),"") -> 26 | D26: =IF(B26<>"",IFERROR(EVAL.ANUAL!W20,""),"") -> 0 | K26: =IFERROR((AVERAGE(M26:AB26,AD26:AS26)),"") | L26: =IFERROR((AVERAGE(E26:K26)*0.05),"") | AB26: =IFERROR(AVERAGE(M26:AA26),"") | AC26: =IFERROR((AVERAGE(M26:AA26)*0.4)+(AB26*0.05),"") | AS26: =IFERROR(AVERAGE(AD26:AR26),"") | AT26: =IFERROR((AVERAGE(AD26:AR26)*0.35)+(AS26*0.05),"") | BA26: =K26 | BB26: =IFERROR((AVERAGE(AU26:BA26)*0.05),"") | BE26: =IFERROR((AVERAGE(BC26)*0.025)+(BD26*0.025),"") | BF26: =IF(SUM(BB26,AT26,AC26,L26,BE26)=0,"",SUM(BB26,AT26,AC26,L26,BE26)) | BG26: =IF(BF26="","",IF(BF26<51,"REPROBADO",IF(BF26>=51,"APROBADO"," ")))
... A56: =IF('1erT'!A56<>"",'1erT'!A56,"") | B56: =IF('1erT'!B56<>"",'1erT'!B56,"") | C56: =IF(B56<>"",IFERROR(EVAL.ANUAL!X50,""),"") | D56: =IF(B56<>"",IFERROR(EVAL.ANUAL!W50,""),"") | K56: =IFERROR((AVERAGE(M56:AB56,AD56:AS56)),"") | L56: =IFERROR((AVERAGE(E56:K56)*0.05),"") | AB56: =IFERROR(AVERAGE(M56:AA56),"") | AC56: =IFERROR((AVERAGE(M56:AA56)*0.4)+(AB56*0.05),"") | AS56: =IFERROR(AVERAGE(AD56:AR56),"") | AT56: =IFERROR((AVERAGE(AD56:AR56)*0.35)+(AS56*0.05),"") | BA56: =K56 | BB56: =IFERROR((AVERAGE(AU56:BA56)*0.05),"") | BE56: =IFERROR((AVERAGE(BC56)*0.025)+(BD56*0.025),"") | BF56: =IF(SUM(BB56,AT56,AC56,L56,BE56)=0,"",SUM(BB56,AT56,AC56,L56,BE56)) | BG56: =IF(BF56="","",IF(BF56<51,"REPROBADO",IF(BF56>=51,"APROBADO"," ")))

Sheet EVAL.ANUAL
A2: CENTRALIZADOR DE REGISTROS DE VALORACION PEDAGOGICA TRIMESTRAL
A3: =+'1erT'!A4:BG4 -> CURSO: 2ndo A Secundaria
A4: =+'1erT'!A8:BG8 -> MATERIA : HISTORIA
A5: Nº | B5: Nombre completo | C5: 1er. TRIMESTRE | J5: 2do. TRIMESTRE | Q5: 3er. TRIMESTRE | X5: NOTA FINAL | Y5: EVALUACION CUALITATIVA
C6: MAESTRO | G6: AUTOE.(5) | J6: MAESTRO | N6: AUTOE.(5) | Q6: MAESTRO | U6: AUTOE.(5)
C7: SER (5) | D7: SABER (45) | E7: HACER (40) | F7: DECIDIR (5) | G7: SER ( 2,5 ) | H7: DECIDIR (2,5) | I7: TOTAL | J7: SER (5) | K7: SABER (45) | L7: HACER (40) | M7: DECIDIR (5) | N7: SER ( 2,5 ) | O7: DECIDIR (2,5) | P7: TOTAL | Q7: SER (5) | R7: SABER (45) | S7: HACER (40) | T7: DECIDIR (5) | U7: SER ( 2,5 ) | V7: DECIDIR (2,5) | W7: TOTAL
C8: =IFERROR(AVERAGE(C9:C50),"") -> 3.5836939 | D8: =IFERROR(AVERAGE(D9:D50),"") -> 31.776923 | E8: =IFERROR(AVERAGE(E9:E50),"") -> 28.915385 | F8: =IFERROR(AVERAGE(F9:F50),"") -> 3.5836939 | G8: =IFERROR(AVERAGE(G9:G50),"") -> 0 | H8: =IFERROR(AVERAGE(H9:H50),"") -> 0 | I8: =ROUNDUP(SUM(C8:H8),0) -> 68 | J8: =IFERROR(AVERAGE(J9:J50),"") | K8: =IFERROR(AVERAGE(K9:K50),"") | L8: =IFERROR(AVERAGE(L9:L50),"") | M8: =IFERROR(AVERAGE(M9:M50),"") | N8: =IFERROR(AVERAGE(N9:N50),"") -> 0 | O8: =IFERROR(AVERAGE(O9:O50),"") -> 0 | P8: =ROUNDUP(SUM(J8:O8),0) -> 0 | Q8: =IFERROR(AVERAGE(Q9:Q50),"") | R8: =IFERROR(AVERAGE(R9:R50),"") | S8: =IFERROR(AVERAGE(S9:S50),"") | T8: =IFERROR(AVERAGE(T9:T50),"") | U8: =IFERROR(AVERAGE(U9:U50),"") -> 0 | V8: =IFERROR(AVERAGE(V9:V50),"") -> 0 | W8: =ROUNDUP(SUM(Q8:V8),0) -> 0 | X8: =IF(I8="","",ROUNDUP(AVERAGE(W8,P8,I8),0)) -> 23
A9: =+'1erT'!A15 -> 1 | B9: =+'1erT'!B15 -> AGUILA SEJAS MATIAS HERNAN | C9: =IFERROR('1erT'!L15,"") -> 4.2833333 | D9: =+'1erT'!AC15 -> 29.25 | E9: =+'1erT'!AT15 -> 38.4 | F9: =IFERROR('1erT'!BB15,"") -> 4.2833333 | G9: =+('1erT'!BC15*0.05) -> 0 | H9: =+'1erT'!BD15*0.05 -> 0 | I9: =ROUNDUP(SUM(C9:H9),0) -> 77 | J9: =IFERROR('2doT'!L15,"") | K9: =+'2doT'!AC15 | L9: =+'2doT'!AT15 | M9: =IFERROR('2doT'!BB15,"") | N9: =+(0.05*'2doT'!BC15) -> 0 | O9: =+(0.05*'2doT'!BD15) -> 0 | P9: =ROUNDUP(SUM(J9:O9),0) -> 0 | Q9: =IFERROR('3erT'!L15,"") | R9: =+'3erT'!AC15 | S9: =+'3erT'!AT15 | T9: =IFERROR('3erT'!BB15,"") | U9: =+(0.05*'3erT'!BC15) -> 0 | V9: =+(0.05*'3erT'!BD15) -> 0 | W9: =ROUNDUP(SUM(Q9:V9),0) -> 0 | X9: =IF(I9="","",ROUNDUP(AVERAGE(W9,P9,I9),0)) -> 26 | Y9: =IF(I9="","",IF(X9<51,"REPROBADO",IF(X9>=51,"APROBADO"," "))) -> REPROBADO
A10: =+'1erT'!A16 -> 2 | B10: =+'1erT'!B16 -> ANTEZANA ARANIBAR JAVIER LEANDRO | C10: =IFERROR('1erT'!L16,"") -> 4.7 | D10: =+'1erT'!AC16 -> 37.8 | E10: =+'1erT'!AT16 -> 40 | F10: =IFERROR('1erT'!BB16,"") -> 4.7 | G10: =+('1erT'!BC16*0.05) -> 0 | H10: =+'1erT'!BD16*0.05 -> 0 | I10: =ROUNDUP(SUM(C10:H10),0) -> 88 | J10: =IFERROR('2doT'!L16,"") | K10: =+'2doT'!AC16 | L10: =+'2doT'!AT16 | M10: =IFERROR('2doT'!BB16,"") | N10: =+(0.05*'2doT'!BC16) -> 0 | O10: =+(0.05*'2doT'!BD16) -> 0 | P10: =ROUNDUP(SUM(J10:O10),0) -> 0 | Q10: =IFERROR('3erT'!L16,"") | R10: =+'3erT'!AC16 | S10: =+'3erT'!AT16 | T10: =IFERROR('3erT'!BB16,"") | U10: =+(0.05*'3erT'!BC16) -> 0 | V10: =+(0.05*'3erT'!BD16) -> 0 | W10: =ROUNDUP(SUM(Q10:V10),0) -> 0 | X10: =IF(I10="","",ROUNDUP(AVERAGE(W10,P10,I10),0)) -> 30 | Y10: =IF(I10="","",IF(X10<51,"REPROBADO",IF(X10>=51,"APROBADO"," "))) -> REPROBADO
A11: =+'1erT'!A17 -> 3 | B11: =+'1erT'!B17 -> ANTEZANA TORREZ MATIAS ANDRE | C11: =IFERROR('1erT'!L17,"") -> 4.6 | D11: =+'1erT'!AC17 -> 39.6 | E11: =+'1erT'!AT17 -> 37.6 | F11: =IFERROR('1erT'!BB17,"") -> 4.6 | G11: =+('1erT'!BC17*0.05) -> 0 | H11: =+'1erT'!BD17*0.05 -> 0 | I11: =ROUNDUP(SUM(C11:H11),0) -> 87 | J11: =IFERROR('2doT'!L17,"") | K11: =+'2doT'!AC17 | L11: =+'2doT'!AT17 | M11: =IFERROR('2doT'!BB17,"") | N11: =+(0.05*'2doT'!BC17) -> 0 | O11: =+(0.05*'2doT'!BD17) -> 0 | P11: =ROUNDUP(SUM(J11:O11),0) -> 0 | Q11: =IFERROR('3erT'!L17,"") | R11: =+'3erT'!AC17 | S11: =+'3erT'!AT17 | T11: =IFERROR('3erT'!BB17,"") | U11: =+(0.05*'3erT'!BC17) -> 0 | V11: =+(0.05*'3erT'!BD17) -> 0 | W11: =ROUNDUP(SUM(Q11:V11),0) -> 0 | X11: =IF(I11="","",ROUNDUP(AVERAGE(W11,P11,I11),0)) -> 29 | Y11: =IF(I11="","",IF(X11<51,"REPROBADO",IF(X11>=51,"APROBADO"," "))) -> REPROBADO
A12: =+'1erT'!A18 -> 4 | B12: =+'1erT'!B18 -> CARDOZO FRANCO JOHNNY LEONARDO | C12: =IFERROR('1erT'!L18,"") -> 4.734375 | D12: =+'1erT'!AC18 -> 40.5 | E12: =+'1erT'!AT18 -> 39 | F12: =IFERROR('1erT'!BB18,"") -> 4.734375 | G12: =+('1erT'!BC18*0.05) -> 0 | H12: =+'1erT'!BD18*0.05 -> 0 | I12: =ROUNDUP(SUM(C12:H12),0) -> 89 | J12: =IFERROR('2doT'!L18,"") | K12: =+'2doT'!AC18 | L12: =+'2doT'!AT18 | M12: =IFERROR('2doT'!BB18,"") | N12: =+(0.05*'2doT'!BC18) -> 0 | O12: =+(0.05*'2doT'!BD18) -> 0 | P12: =ROUNDUP(SUM(J12:O12),0) -> 0 | Q12: =IFERROR('3erT'!L18,"") | R12: =+'3erT'!AC18 | S12: =+'3erT'!AT18 | T12: =IFERROR('3erT'!BB18,"") | U12: =+(0.05*'3erT'!BC18) -> 0 | V12: =+(0.05*'3erT'!BD18) -> 0 | W12: =ROUNDUP(SUM(Q12:V12),0) -> 0 | X12: =IF(I12="","",ROUNDUP(AVERAGE(W12,P12,I12),0)) -> 30 | Y12: =IF(I12="","",IF(X12<51,"REPROBADO",IF(X12>=51,"APROBADO"," "))) -> REPROBADO
A13: =+'1erT'!A19 -> 5 | B13: =+'1erT'!B19 -> ESPINOZA MUÑOZ RUBEN SEBASTIAN | C13: =IFERROR('1erT'!L19,"") -> 1.4171875 | D13: =+'1erT'!AC19 -> 16.2 | E13: =+'1erT'!AT19 -> 9.5 | F13: =IFERROR('1erT'!BB19,"") -> 1.4171875 | G13: =+('1erT'!BC19*0.05) -> 0 | H13: =+'1erT'!BD19*0.05 -> 0 | I13: =ROUNDUP(SUM(C13:H13),0) -> 29 | J13: =IFERROR('2doT'!L19,"") | K13: =+'2doT'!AC19 | L13: =+'2doT'!AT19 | M13: =IFERROR('2doT'!BB19,"") | N13: =+(0.05*'2doT'!BC19) -> 0 | O13: =+(0.05*'2doT'!BD19) -> 0 | P13: =ROUNDUP(SUM(J13:O13),0) -> 0 | Q13: =IFERROR('3erT'!L19,"") | R13: =+'3erT'!AC19 | S13: =+'3erT'!AT19 | T13: =IFERROR('3erT'!BB19,"") | U13: =+(0.05*'3erT'!BC19) -> 0 | V13: =+(0.05*'3erT'!BD19) -> 0 | W13: =ROUNDUP(SUM(Q13:V13),0) -> 0 | X13: =IF(I13="","",ROUNDUP(AVERAGE(W13,P13,I13),0)) -> 10 | Y13: =IF(I13="","",IF(X13<51,"REPROBADO",IF(X13>=51,"APROBADO"," "))) -> REPROBADO
A14: =+'1erT'!A20 -> 6 | B14: =+'1erT'!B20 -> HUANCA AMURRIO VALENTINA RAFAELA | C14: =IFERROR('1erT'!L20,"") -> 3.634375 | D14: =+'1erT'!AC20 -> 21.6 | E14: =+'1erT'!AT20 -> 35 | F14: =IFERROR('1erT'!BB20,"") -> 3.634375 | G14: =+('1erT'!BC20*0.05) -> 0 | H14: =+'1erT'!BD20*0.05 -> 0 | I14: =ROUNDUP(SUM(C14:H14),0) -> 64 | J14: =IFERROR('2doT'!L20,"") | K14: =+'2doT'!AC20 | L14: =+'2doT'!AT20 | M14: =IFERROR('2doT'!BB20,"") | N14: =+(0.05*'2doT'!BC20) -> 0 | O14: =+(0.05*'2doT'!BD20) -> 0 | P14: =ROUNDUP(SUM(J14:O14),0) -> 0 | Q14: =IFERROR('3erT'!L20,"") | R14: =+'3erT'!AC20 | S14: =+'3erT'!AT20 | T14: =IFERROR('3erT'!BB20,"") | U14: =+(0.05*'3erT'!BC20) -> 0 | V14: =+(0.05*'3erT'!BD20) -> 0 | W14: =ROUNDUP(SUM(Q14:V14),0) -> 0 | X14: =IF(I14="","",ROUNDUP(AVERAGE(W14,P14,I14),0)) -> 22 | Y14: =IF(I14="","",IF(X14<51,"REPROBADO",IF(X14>=51,"APROBADO"," "))) -> REPROBADO
A15: =+'1erT'!A21 -> 7 | B15: =+'1erT'!B21 -> MERCADO ROJAS MARIA BELEN | C15: =IFERROR('1erT'!L21,"") -> 3.953125 | D15: =+'1erT'!AC21 -> 40.5 | E15: =+'1erT'!AT21 -> 29 | F15: =IFERROR('1erT'!BB21,"") -> 3.953125 | G15: =+('1erT'!BC21*0.05) -> 0 | H15: =+'1erT'!BD21*0.05 -> 0 | I15: =ROUNDUP(SUM(C15:H15),0) -> 78 | J15: =IFERROR('2doT'!L21,"") | K15: =+'2doT'!AC21 | L15: =+'2doT'!AT21 | M15: =IFERROR('2doT'!BB21,"") | N15: =+(0.05*'2doT'!BC21) -> 0 | O15: =+(0.05*'2doT'!BD21) -> 0 | P15: =ROUNDUP(SUM(J15:O15),0) -> 0 | Q15: =IFERROR('3erT'!L21,"") | R15: =+'3erT'!AC21 | S15: =+'3erT'!AT21 | T15: =IFERROR('3erT'!BB21,"") | U15: =+(0.05*'3erT'!BC21) -> 0 | V15: =+(0.05*'3erT'!BD21) -> 0 | W15: 78 | X15: =IF(I15="","",ROUNDUP(AVERAGE(W15,P15,I15),0)) -> 52 | Y15: =IF(I15="","",IF(X15<51,"REPROBADO",IF(X15>=51,"APROBADO"," "))) -> APROBADO
A16: =+'1erT'!A22 -> 8 | B16: =+'1erT'!B22 -> NUMBELA SAAVEDRA RAFAEL | C16: =IFERROR('1erT'!L22,"") -> 4.2833333 | D16: =+'1erT'!AC22 -> 34.65 | E16: =+'1erT'!AT22 -> 36 | F16: =IFERROR('1erT'!BB22,"") -> 4.2833333 | G16: =+('1erT'!BC22*0.05) -> 0 | H16: =+'1erT'!BD22*0.05 -> 0 | I16: =ROUNDUP(SUM(C16:H16),0) -> 80 | J16: =IFERROR('2doT'!L22,"") | K16: =+'2doT'!AC22 | L16: =+'2doT'!AT22 | M16: =IFERROR('2doT'!BB22,"") | N16: =+(0.05*'2doT'!BC22) -> 0 | O16: =+(0.05*'2doT'!BD22) -> 0 | P16: =ROUNDUP(SUM(J16:O16),0) -> 0 | Q16: =IFERROR('3erT'!L22,"") | R16: =+'3erT'!AC22 | S16: =+'3erT'!AT22 | T16: =IFERROR('3erT'!BB22,"") | U16: =+(0.05*'3erT'!BC22) -> 0 | V16: =+(0.05*'3erT'!BD22) -> 0 | W16: =ROUNDUP(SUM(Q16:V16),0) -> 0 | X16: =IF(I16="","",ROUNDUP(AVERAGE(W16,P16,I16),0)) -> 27 | Y16: =IF(I16="","",IF(X16<51,"REPROBADO",IF(X16>=51,"APROBADO"," "))) -> REPROBADO
A17: =+'1erT'!A23 -> 9 | B17: =+'1erT'!B23 -> PEÑALOZA PRADO RAFAEL ANDRES | C17: =IFERROR('1erT'!L23,"") -> 2.4166667 | D17: =+'1erT'!AC23 -> 32.85 | E17: =+'1erT'!AT23 -> 14.4 | F17: =IFERROR('1erT'!BB23,"") -> 2.4166667 | G17: =+('1erT'!BC23*0.05) -> 0 | H17: =+'1erT'!BD23*0.05 -> 0 | I17: =ROUNDUP(SUM(C17:H17),0) -> 53 | J17: =IFERROR('2doT'!L23,"") | K17: =+'2doT'!AC23 | L17: =+'2doT'!AT23 | M17: =IFERROR('2doT'!BB23,"") | N17: =+(0.05*'2doT'!BC23) -> 0 | O17: =+(0.05*'2doT'!BD23) -> 0 | P17: =ROUNDUP(SUM(J17:O17),0) -> 0 | Q17: =IFERROR('3erT'!L23,"") | R17: =+'3erT'!AC23 | S17: =+'3erT'!AT23 | T17: =IFERROR('3erT'!BB23,"") | U17: =+(0.05*'3erT'!BC23) -> 0 | V17: =+(0.05*'3erT'!BD23) -> 0 | W17: =ROUNDUP(SUM(Q17:V17),0) -> 0 | X17: =IF(I17="","",ROUNDUP(AVERAGE(W17,P17,I17),0)) -> 18 | Y17: =IF(I17="","",IF(X17<51,"REPROBADO",IF(X17>=51,"APROBADO"," "))) -> REPROBADO
A18: =+'1erT'!A24 -> 10 | B18: =+'1erT'!B24 -> PARDO LOPEZ ABIGAIL | C18: =IFERROR('1erT'!L24,"") -> 1.6166667 | D18: =+'1erT'!AC24 -> 16.65 | E18: =+'1erT'!AT24 -> 12 | F18: =IFERROR('1erT'!BB24,"") -> 1.6166667 | G18: =+('1erT'!BC24*0.05) -> 0 | H18: =+'1erT'!BD24*0.05 -> 0 | I18: =ROUNDUP(SUM(C18:H18),0) -> 32 | J18: =IFERROR('2doT'!L24,"") | K18: =+'2doT'!AC24 | L18: =+'2doT'!AT24 | M18: =IFERROR('2doT'!BB24,"") | N18: =+(0.05*'2doT'!BC24) -> 0 | O18: =+(0.05*'2doT'!BD24) -> 0 | P18: =ROUNDUP(SUM(J18:O18),0) -> 0 | Q18: =IFERROR('3erT'!L24,"") | R18: =+'3erT'!AC24 | S18: =+'3erT'!AT24 | T18: =IFERROR('3erT'!BB24,"") | U18: =+(0.05*'3erT'!BC24) -> 0 | V18: =+(0.05*'3erT'!BD24) -> 0 | W18: =ROUNDUP(SUM(Q18:V18),0) -> 0 | X18: =IF(I18="","",ROUNDUP(AVERAGE(W18,P18,I18),0)) -> 11 | Y18: =IF(I18="","",IF(X18<51,"REPROBADO",IF(X18>=51,"APROBADO"," "))) -> REPROBADO
A19: =+'1erT'!A25 -> 11 | B19: =+'1erT'!B25 -> ROCABADO ANDIA MARIANA | C19: =IFERROR('1erT'!L25,"") -> 4.1 | D19: =+'1erT'!AC25 -> 35.1 | E19: =+'1erT'!AT25 -> 33.6 | F19: =IFERROR('1erT'!BB25,"") -> 4.1 | G19: =+('1erT'!BC25*0.05) -> 0 | H19: =+'1erT'!BD25*0.05 -> 0 | I19: =ROUNDUP(SUM(C19:H19),0) -> 77 | J19: =IFERROR('2doT'!L25,"") | K19: =+'2doT'!AC25 | L19: =+'2doT'!AT25 | M19: =IFERROR('2doT'!BB25,"") | N19: =+(0.05*'2doT'!BC25) -> 0 | O19: =+(0.05*'2doT'!BD25) -> 0 | P19: =ROUNDUP(SUM(J19:O19),0) -> 0 | Q19: =IFERROR('3erT'!L25,"") | R19: =+'3erT'!AC25 | S19: =+'3erT'!AT25 | T19: =IFERROR('3erT'!BB25,"") | U19: =+(0.05*'3erT'!BC25) -> 0 | V19: =+(0.05*'3erT'!BD25) -> 0 | W19: =ROUNDUP(SUM(Q19:V19),0) -> 0 | X19: =IF(I19="","",ROUNDUP(AVERAGE(W19,P19,I19),0)) -> 26 | Y19: =IF(I19="","",IF(X19<51,"REPROBADO",IF(X19>=51,"APROBADO"," "))) -> REPROBADO
A20: =+'1erT'!A26 -> 12 | B20: =+'1erT'!B26 -> SEJAS CAMPOS ZULMA | C20: =IFERROR('1erT'!L26,"") -> 3.915625 | D20: =+'1erT'!AC26 -> 39.6 | E20: =+'1erT'!AT26 -> 29 | F20: =IFERROR('1erT'!BB26,"") -> 3.915625 | G20: =+('1erT'!BC26*0.05) -> 0 | H20: =+'1erT'!BD26*0.05 -> 0 | I20: =ROUNDUP(SUM(C20:H20),0) -> 77 | J20: =IFERROR('2doT'!L26,"") | K20: =+'2doT'!AC26 | L20: =+'2doT'!AT26 | M20: =IFERROR('2doT'!BB26,"") | N20: =+(0.05*'2doT'!BC26) -> 0 | O20: =+(0.05*'2doT'!BD26) -> 0 | P20: =ROUNDUP(SUM(J20:O20),0) -> 0 | Q20: =IFERROR('3erT'!L26,"") | R20: =+'3erT'!AC26 | S20: =+'3erT'!AT26 | T20: =IFERROR('3erT'!BB26,"") | U20: =+(0.05*'3erT'!BC26) -> 0 | V20: =+(0.05*'3erT'!BD26) -> 0 | W20: =ROUNDUP(SUM(Q20:V20),0) -> 0 | X20: =IF(I20="","",ROUNDUP(AVERAGE(W20,P20,I20),0)) -> 26 | Y20: =IF(I20="","",IF(X20<51,"REPROBADO",IF(X20>=51,"APROBADO"," "))) -> REPROBADO
A21: =+'1erT'!A27 -> 13 | B21: =+'1erT'!B27 -> VARGAS REQUEZ ZOE | C21: =IFERROR('1erT'!L27,"") -> 2.9333333 | D21: =+'1erT'!AC27 -> 28.8 | E21: =+'1erT'!AT27 -> 22.4 | F21: =IFERROR('1erT'!BB27,"") -> 2.9333333 | G21: =+('1erT'!BC27*0.05) -> 0 | H21: =+'1erT'!BD27*0.05 -> 0 | I21: =ROUNDUP(SUM(C21:H21),0) -> 58 | J21: =IFERROR('2doT'!L27,"") | K21: =+'2doT'!AC27 | L21: =+'2doT'!AT27 | M21: =IFERROR('2doT'!BB27,"") | N21: =+(0.05*'2doT'!BC27) -> 0 | O21: =+(0.05*'2doT'!BD27) -> 0 | P21: =ROUNDUP(SUM(J21:O21),0) -> 0 | Q21: =IFERROR('3erT'!L27,"") | R21: =+'3erT'!AC27 | S21: =+'3erT'!AT27 | T21: =IFERROR('3erT'!BB27,"") | U21: =+(0.05*'3erT'!BC27) -> 0 | V21: =+(0.05*'3erT'!BD27) -> 0 | W21: =ROUNDUP(SUM(Q21:V21),0) -> 0 | X21: =IF(I21="","",ROUNDUP(AVERAGE(W21,P21,I21),0)) -> 20 | Y21: =IF(I21="","",IF(X21<51,"REPROBADO",IF(X21>=51,"APROBADO"," "))) -> REPROBADO
A22: =+'1erT'!A28 -> 14 | B22: =+'1erT'!B28 -> 0 | C22: =IFERROR('1erT'!L28,"") | D22: =+'1erT'!AC28 | E22: =+'1erT'!AT28 | F22: =IFERROR('1erT'!BB28,"") | G22: =+('1erT'!BC28*0.05) -> 0 | H22: =+'1erT'!BD28*0.05 -> 0 | I22: =ROUNDUP(SUM(C22:H22),0) -> 0 | J22: =IFERROR('2doT'!L28,"") | K22: =+'2doT'!AC28 | L22: =+'2doT'!AT28 | M22: =IFERROR('2doT'!BB28,"") | N22: =+(0.05*'2doT'!BC28) -> 0 | O22: =+(0.05*'2doT'!BD28) -> 0 | P22: =ROUNDUP(SUM(J22:O22),0) -> 0 | Q22: =IFERROR('3erT'!L28,"") | R22: =+'3erT'!AC28 | S22: =+'3erT'!AT28 | T22: =IFERROR('3erT'!BB28,"") | U22: =+(0.05*'3erT'!BC28) -> 0 | V22: =+(0.05*'3erT'!BD28) -> 0 | W22: =ROUNDUP(SUM(Q22:V22),0) -> 0 | X22: =IF(I22="","",ROUNDUP(AVERAGE(W22,P22,I22),0)) -> 0 | Y22: =IF(I22="","",IF(X22<51,"REPROBADO",IF(X22>=51,"APROBADO"," "))) -> REPROBADO
A23: =+'1erT'!A29 -> 15 | B23: =+'1erT'!B29 -> 0 | C23: =IFERROR('1erT'!L29,"") | D23: =+'1erT'!AC29 | E23: =+'1erT'!AT29 | F23: =IFERROR('1erT'!BB29,"") | G23: =+('1erT'!BC29*0.05) -> 0 | H23: =+'1erT'!BD29*0.05 -> 0 | I23: =ROUNDUP(SUM(C23:H23),0) -> 0 | J23: =IFERROR('2doT'!L29,"") | K23: =+'2doT'!AC29 | L23: =+'2doT'!AT29 | M23: =IFERROR('2doT'!BB29,"") | N23: =+(0.05*'2doT'!BC29) -> 0 | O23: =+(0.05*'2doT'!BD29) -> 0 | P23: =ROUNDUP(SUM(J23:O23),0) -> 0 | Q23: =IFERROR('3erT'!L29,"") | R23: =+'3erT'!AC29 | S23: =+'3erT'!AT29 | T23: =IFERROR('3erT'!BB29,"") | U23: =+(0.05*'3erT'!BC29) -> 0 | V23: =+(0.05*'3erT'!BD29) -> 0 | W23: =ROUNDUP(SUM(Q23:V23),0) -> 0 | X23: =IF(I23="","",ROUNDUP(AVERAGE(W23,P23,I23),0)) -> 0 | Y23: =IF(I23="","",IF(X23<51,"REPROBADO",IF(X23>=51,"APROBADO"," "))) -> REPROBADO
A24: =+'1erT'!A30 -> 16 | B24: =+'1erT'!B30 -> 0 | C24: =IFERROR('1erT'!L30,"") | D24: =+'1erT'!AC30 | E24: =+'1erT'!AT30 | F24: =IFERROR('1erT'!BB30,"") | G24: =+('1erT'!BC30*0.05) -> 0 | H24: =+'1erT'!BD30*0.05 -> 0 | I24: =ROUNDUP(SUM(C24:H24),0) -> 0 | J24: =IFERROR('2doT'!L30,"") | K24: =+'2doT'!AC30 | L24: =+'2doT'!AT30 | M24: =IFERROR('2doT'!BB30,"") | N24: =+(0.05*'2doT'!BC30) -> 0 | O24: =+(0.05*'2doT'!BD30) -> 0 | P24: =ROUNDUP(SUM(J24:O24),0) -> 0 | Q24: =IFERROR('3erT'!L30,"") | R24: =+'3erT'!AC30 | S24: =+'3erT'!AT30 | T24: =IFERROR('3erT'!BB30,"") | U24: =+(0.05*'3erT'!BC30) -> 0 | V24: =+(0.05*'3erT'!BD30) -> 0 | W24: =ROUNDUP(SUM(Q24:V24),0) -> 0 | X24: =IF(I24="","",ROUNDUP(AVERAGE(W24,P24,I24),0)) -> 0 | Y24: =IF(I24="","",IF(X24<51,"REPROBADO",IF(X24>=51,"APROBADO"," "))) -> REPROBADO
A25: =+'1erT'!A31 -> 17 | B25: =+'1erT'!B31 -> 0 | C25: =IFERROR('1erT'!L31,"") | D25: =+'1erT'!AC31 | E25: =+'1erT'!AT31 | F25: =IFERROR('1erT'!BB31,"") | G25: =+('1erT'!BC31*0.05) -> 0 | H25: =+'1erT'!BD31*0.05 -> 0 | I25: =ROUNDUP(SUM(C25:H25),0) -> 0 | J25: =IFERROR('2doT'!L31,"") | K25: =+'2doT'!AC31 | L25: =+'2doT'!AT31 | M25: =IFERROR('2doT'!BB31,"") | N25: =+(0.05*'2doT'!BC31) -> 0 | O25: =+(0.05*'2doT'!BD31) -> 0 | P25: =ROUNDUP(SUM(J25:O25),0) -> 0 | Q25: =IFERROR('3erT'!L31,"") | R25: =+'3erT'!AC31 | S25: =+'3erT'!AT31 | T25: =IFERROR('3erT'!BB31,"") | U25: =+(0.05*'3erT'!BC31) -> 0 | V25: =+(0.05*'3erT'!BD31) -> 0 | W25: =ROUNDUP(SUM(Q25:V25),0) -> 0 | X25: =IF(I25="","",ROUNDUP(AVERAGE(W25,P25,I25),0)) -> 0 | Y25: =IF(I25="","",IF(X25<51,"REPROBADO",IF(X25>=51,"APROBADO"," "))) -> REPROBADO
A26: =+'1erT'!A32 -> 18 | B26: =+'1erT'!B32 -> 0 | C26: =IFERROR('1erT'!L32,"") | D26: =+'1erT'!AC32 | E26: =+'1erT'!AT32 | F26: =IFERROR('1erT'!BB32,"") | G26: =+('1erT'!BC32*0.05) -> 0 | H26: =+'1erT'!BD32*0.05 -> 0 | I26: =ROUNDUP(SUM(C26:H26),0) -> 0 | J26: =IFERROR('2doT'!L32,"") | K26: =+'2doT'!AC32 | L26: =+'2doT'!AT32 | M26: =IFERROR('2doT'!BB32,"") | N26: =+(0.05*'2doT'!BC32) -> 0 | O26: =+(0.05*'2doT'!BD32) -> 0 | P26: =ROUNDUP(SUM(J26:O26),0) -> 0 | Q26: =IFERROR('3erT'!L32,"") | R26: =+'3erT'!AC32 | S26: =+'3erT'!AT32 | T26: =IFERROR('3erT'!BB32,"") | U26: =+(0.05*'3erT'!BC32) -> 0 | V26: =+(0.05*'3erT'!BD32) -> 0 | W26: =ROUNDUP(SUM(Q26:V26),0) -> 0 | X26: =IF(I26="","",ROUNDUP(AVERAGE(W26,P26,I26),0)) -> 0 | Y26: =IF(I26="","",IF(X26<51,"REPROBADO",IF(X26>=51,"APROBADO"," "))) -> REPROBADO
A27: =+'1erT'!A33 -> 19 | B27: =+'1erT'!B33 -> 0 | C27: =IFERROR('1erT'!L33,"") | D27: =+'1erT'!AC33 | E27: =+'1erT'!AT33 | F27: =IFERROR('1erT'!BB33,"") | G27: =+('1erT'!BC33*0.05) -> 0 | H27: =+'1erT'!BD33*0.05 -> 0 | I27: =ROUNDUP(SUM(C27:H27),0) -> 0 | J27: =IFERROR('2doT'!L33,"") | K27: =+'2doT'!AC33 | L27: =+'2doT'!AT33 | M27: =IFERROR('2doT'!BB33,"") | N27: =+(0.05*'2doT'!BC33) -> 0 | O27: =+(0.05*'2doT'!BD33) -> 0 | P27: =ROUNDUP(SUM(J27:O27),0) -> 0 | Q27: =IFERROR('3erT'!L33,"") | R27: =+'3erT'!AC33 | S27: =+'3erT'!AT33 | T27: =IFERROR('3erT'!BB33,"") | U27: =+(0.05*'3erT'!BC33) -> 0 | V27: =+(0.05*'3erT'!BD33) -> 0 | W27: =ROUNDUP(SUM(Q27:V27),0) -> 0 | X27: =IF(I27="","",ROUNDUP(AVERAGE(W27,P27,I27),0)) -> 0 | Y27: =IF(I27="","",IF(X27<51,"REPROBADO",IF(X27>=51,"APROBADO"," "))) -> REPROBADO
... A50: =+'1erT'!A56 -> 0 | B50: =+'1erT'!B56 -> 0 | C50: =IFERROR('1erT'!L56,"") | D50: =+'1erT'!AC56 | E50: =+'1erT'!AT56 | F50: =IFERROR('1erT'!BB56,"") | G50: =+('1erT'!BC56*0.05) -> 0 | H50: =+'1erT'!BD56*0.05 -> 0 | I50: =ROUNDUP(SUM(C50:H50),0) -> 0 | J50: =IFERROR('2doT'!L56,"") | K50: =+'2doT'!AC56 | L50: =+'2doT'!AT56 | M50: =IFERROR('2doT'!BB56,"") | N50: =+(0.05*'2doT'!BC56) -> 0 | O50: =+(0.05*'2doT'!BD56) -> 0 | P50: =ROUNDUP(SUM(J50:O50),0) -> 0 | Q50: =IFERROR('3erT'!L56,"") | R50: =+'3erT'!AC56 | S50: =+'3erT'!AT56 | T50: =IFERROR('3erT'!BB56,"") | U50: =+(0.05*'3erT'!BC56) -> 0 | V50: =+(0.05*'3erT'!BD56) -> 0 | W50: =ROUNDUP(SUM(Q50:V50),0) -> 0 | X50: =IF(I50="","",ROUNDUP(AVERAGE(W50,P50,I50),0)) -> 0 | Y50: =IF(I50="","",IF(X50<51,"REPROBADO",IF(X50>=51,"APROBADO"," "))) -> REPROBADO

Sheet Asis1Tri
C1: CUADRO DE ASISTENCIA PRIMER TRIMESTRE | AH1: =COUNTA(D6:AR6) -> 28 | AI1: dias | AN1: %A-atrasos | AS1: =AS3/(AH2*AH1) -> 0 | AV1: %F-faltas | AY1: =+AU3/(AH1*AH2) -> 0
C2: EDUCACION SECUNDARIA COMUNITARIA PRODUCTIVA | AH2: =COUNTA(B7:B56) -> 50 | AI2: estudiantes | AN2: %L-licencias | AT2: =+AT3/(AH2*AH1) -> 0 | AV2: %P-presente | AY2: =+AV3/(AH1*AH2) -> 0.54
A3: ='1erT'!A6 -> MAESTRO : MARCELO A. RODRIGUEZ GRACIA | H3: ='1erT'!A4 -> CURSO: 2ndo A Secundaria | AC3: ='1erT'!A8 -> MATERIA : HISTORIA | AS3: =SUM(AS7:AS56) -> 0 | AT3: =SUM(AT7:AT56) -> 0 | AU3: =SUM(AU7:AU56) -> 0 | AV3: =SUM(AV7:AV56) -> 756 | AW3: PORC. %
A4: N° | B4: APELLIDOS Y NOMBRES | C4: MM | D4: FEBRERO | L4: MARZO | U4: ABRIL | AD4: MAYO | AS4: A ATRASO | AT4: L LICENCIA | AU4: F FALTA | AV4: P PRESENTE | AW4: A ATRASO | AX4: L LICENCIA | AY4: F FALTA | AZ4: P PRESENTE
C5: DD | D5: L | E5: M | F5: L | G5: M | H5: L | I5: M | J5: L | K5: M | L5: L | M5: M | N5: L | O5: M | P5: L | Q5: M | R5: L | S5: M | T5: L | U5: M | V5: L | W5: M | X5: L | Y5: M | Z5: L | AA5: M | AB5: L | AC5: M | AD5: L | AE5: M
C6: FF | D6: 3 | E6: 5 | F6: 10 | G6: 12 | H6: 17 | I6: 19 | J6: 24 | K6: 26 | L6: 2 | M6: 4 | N6: 9 | O6: 11 | P6: 16 | Q6: 18 | R6: 23 | S6: 25 | T6: 30 | U6: 1 | V6: 6 | W6: 8 | X6: 13 | Y6: 15 | Z6: 20 | AA6: 22 | AB6: 27 | AC6: 29 | AD6: 4 | AE6: 6
A7: =IF('1erT'!A15<>"",'1erT'!A15,"") -> 1 | B7: =IF('1erT'!B15<>"",'1erT'!B15,"") -> AGUILA SEJAS MATIAS HERNAN | D7: P | E7: P | F7: P | G7: P | H7: P | I7: P | J7: P | K7: P | L7: P | M7: P | N7: P | O7: P | P7: P | Q7: P | R7: P | S7: P | T7: P | U7: P | V7: P | W7: P | X7: P | Y7: P | Z7: P | AA7: P | AB7: P | AC7: P | AD7: P | AE7: P | AR7: 0 | AS7: =COUNTIF(D7:AQ7,"A") -> 0 | AT7: =COUNTIF(D7:AQ7,"L") -> 0 | AU7: =COUNTIF(D7:AQ7,"F") -> 0 | AV7: =COUNTIF(D7:AQ7,"P") -> 28 | AW7: =+AS7/$AH$1 -> 0 | AX7: =+AT7/$AH$1 -> 0 | AY7: =+AU7/$AH$1 -> 0 | AZ7: =+AV7/$AH$1 -> 1
A8: =IF('1erT'!A16<>"",'1erT'!A16,"") -> 2 | B8: =IF('1erT'!B16<>"",'1erT'!B16,"") -> ANTEZANA ARANIBAR JAVIER LEANDRO | D8: P | E8: P | F8: P | G8: P | H8: P | I8: P | J8: P | K8: P | L8: P | M8: P | N8: P | O8: P | P8: P | Q8: P | R8: P | S8: P | T8: P | U8: P | V8: P | W8: P | X8: P | Y8: P | Z8: P | AA8: P | AB8: P | AC8: P | AD8: P | AE8: P | AR8: 0 | AS8: =COUNTIF(D8:AQ8,"A") -> 0 | AT8: =COUNTIF(D8:AQ8,"L") -> 0 | AU8: =COUNTIF(D8:AQ8,"F") -> 0 | AV8: =COUNTIF(D8:AQ8,"P") -> 28 | AW8: =+AS8/$AH$1 -> 0 | AX8: =+AT8/$AH$1 -> 0 | AY8: =+AU8/$AH$1 -> 0 | AZ8: =+AV8/$AH$1 -> 1
A9: =IF('1erT'!A17<>"",'1erT'!A17,"") -> 3 | B9: =IF('1erT'!B17<>"",'1erT'!B17,"") -> ANTEZANA TORREZ MATIAS ANDRE | D9: P | E9: P | F9: P | G9: P | H9: P | I9: P | J9: P | K9: P | L9: P | M9: P | N9: P | O9: P | P9: P | Q9: P | R9: P | S9: P | T9: P | U9: P | V9: P | W9: P | X9: P | Y9: P | Z9: P | AA9: P | AB9: P | AC9: P | AD9: P | AE9: P | AR9: 5 | AS9: =COUNTIF(D9:AQ9,"A") -> 0 | AT9: =COUNTIF(D9:AQ9,"L") -> 0 | AU9: =COUNTIF(D9:AQ9,"F") -> 0 | AV9: =COUNTIF(D9:AQ9,"P") -> 28 | AW9: =+AS9/$AH$1 -> 0 | AX9: =+AT9/$AH$1 -> 0 | AY9: =+AU9/$AH$1 -> 0 | AZ9: =+AV9/$AH$1 -> 1
A10: =IF('1erT'!A18<>"",'1erT'!A18,"") -> 4 | B10: =IF('1erT'!B18<>"",'1erT'!B18,"") -> CARDOZO FRANCO JOHNNY LEONARDO | D10: P | E10: P | F10: P | G10: P | H10: P | I10: P | J10: P | K10: P | L10: P | M10: P | N10: P | O10: P | P10: P | Q10: P | R10: P | S10: P | T10: P | U10: P | V10: P | W10: P | X10: P | Y10: P | Z10: P | AA10: P | AB10: P | AC10: P | AD10: P | AE10: P | AR10: 0 | AS10: =COUNTIF(D10:AQ10,"A") -> 0 | AT10: =COUNTIF(D10:AQ10,"L") -> 0 | AU10: =COUNTIF(D10:AQ10,"F") -> 0 | AV10: =COUNTIF(D10:AQ10,"P") -> 28 | AW10: =+AS10/$AH$1 -> 0 | AX10: =+AT10/$AH$1 -> 0 | AY10: =+AU10/$AH$1 -> 0 | AZ10: =+AV10/$AH$1 -> 1
A11: =IF('1erT'!A19<>"",'1erT'!A19,"") -> 5 | B11: =IF('1erT'!B19<>"",'1erT'!B19,"") -> ESPINOZA MUÑOZ RUBEN SEBASTIAN | D11: P | E11: P | F11: P | G11: P | H11: P | I11: P | J11: P | K11: P | L11: P | M11: P | N11: P | O11: P | P11: P | Q11: P | R11: P | S11: P | T11: P | U11: P | V11: P | W11: P | X11: P | Y11: P | Z11: P | AA11: P | AB11: P | AC11: P | AD11: P | AE11: P | AR11: 0 | AS11: =COUNTIF(D11:AQ11,"A") -> 0 | AT11: =COUNTIF(D11:AQ11,"L") -> 0 | AU11: =COUNTIF(D11:AQ11,"F") -> 0 | AV11: =COUNTIF(D11:AQ11,"P") -> 28 | AW11: =+AS11/$AH$1 -> 0 | AX11: =+AT11/$AH$1 -> 0 | AY11: =+AU11/$AH$1 -> 0 | AZ11: =+AV11/$AH$1 -> 1
A12: =IF('1erT'!A20<>"",'1erT'!A20,"") -> 6 | B12: =IF('1erT'!B20<>"",'1erT'!B20,"") -> HUANCA AMURRIO VALENTINA RAFAELA | D12: P | E12: P | F12: P | G12: P | H12: P | I12: P | J12: P | K12: P | L12: P | M12: P | N12: P | O12: P | P12: P | Q12: P | R12: P | S12: P | T12: P | U12: P | V12: P | W12: P | X12: P | Y12: P | Z12: P | AA12: P | AB12: P | AC12: P | AD12: P | AE12: P | AR12: 0 | AS12: =COUNTIF(D12:AQ12,"A") -> 0 | AT12: =COUNTIF(D12:AQ12,"L") -> 0 | AU12: =COUNTIF(D12:AQ12,"F") -> 0 | AV12: =COUNTIF(D12:AQ12,"P") -> 28 | AW12: =+AS12/$AH$1 -> 0 | AX12: =+AT12/$AH$1 -> 0 | AY12: =+AU12/$AH$1 -> 0 | AZ12: =+AV12/$AH$1 -> 1
A13: =IF('1erT'!A21<>"",'1erT'!A21,"") -> 7 | B13: =IF('1erT'!B21<>"",'1erT'!B21,"") -> MERCADO ROJAS MARIA BELEN | D13: P | E13: P | F13: P | G13: P | H13: P | I13: P | J13: P | K13: P | L13: P | M13: P | N13: P | O13: P | P13: P | Q13: P | R13: P | S13: P | T13: P | U13: P | V13: P | W13: P | X13: P | Y13: P | Z13: P | AA13: P | AB13: P | AC13: P | AD13: P | AE13: P | AR13: 0 | AS13: =COUNTIF(D13:AQ13,"A") -> 0 | AT13: =COUNTIF(D13:AQ13,"L") -> 0 | AU13: =COUNTIF(D13:AQ13,"F") -> 0 | AV13: =COUNTIF(D13:AQ13,"P") -> 28 | AW13: =+AS13/$AH$1 -> 0 | AX13: =+AT13/$AH$1 -> 0 | AY13: =+AU13/$AH$1 -> 0 | AZ13: =+AV13/$AH$1 -> 1
A14: =IF('1erT'!A22<>"",'1erT'!A22,"") -> 8 | B14: =IF('1erT'!B22<>"",'1erT'!B22,"") -> NUMBELA SAAVEDRA RAFAEL | D14: P | E14: P | F14: P | G14: P | H14: P | I14: P | J14: P | K14: P | L14: P | M14: P | N14: P | O14: P | P14: P | Q14: P | R14: P | S14: P | T14: P | U14: P | V14: P | W14: P | X14: P | Y14: P | Z14: P | AA14: P | AB14: P | AC14: P | AD14: P | AE14: P | AR14: 0 | AS14: =COUNTIF(D14:AQ14,"A") -> 0 | AT14: =COUNTIF(D14:AQ14,"L") -> 0 | AU14: =COUNTIF(D14:AQ14,"F") -> 0 | AV14: =COUNTIF(D14:AQ14,"P") -> 28 | AW14: =+AS14/$AH$1 -> 0 | AX14: =+AT14/$AH$1 -> 0 | AY14: =+AU14/$AH$1 -> 0 | AZ14: =+AV14/$AH$1 -> 1
A15: =IF('1erT'!A23<>"",'1erT'!A23,"") -> 9 | B15: =IF('1erT'!B23<>"",'1erT'!B23,"") -> PEÑALOZA PRADO RAFAEL ANDRES | D15: P | E15: P | F15: P | G15: P | H15: P | I15: P | J15: P | K15: P | L15: P | M15: P | N15: P | O15: P | P15: P | Q15: P | R15: P | S15: P | T15: P | U15: P | V15: P | W15: P | X15: P | Y15: P | Z15: P | AA15: P | AB15: P | AC15: P | AD15: P | AE15: P | AR15: 0 | AS15: =COUNTIF(D15:AQ15,"A") -> 0 | AT15: =COUNTIF(D15:AQ15,"L") -> 0 | AU15: =COUNTIF(D15:AQ15,"F") -> 0 | AV15: =COUNTIF(D15:AQ15,"P") -> 28 | AW15: =+AS15/$AH$1 -> 0 | AX15: =+AT15/$AH$1 -> 0 | AY15: =+AU15/$AH$1 -> 0 | AZ15: =+AV15/$AH$1 -> 1
A16: =IF('1erT'!A24<>"",'1erT'!A24,"") -> 10 | B16: =IF('1erT'!B24<>"",'1erT'!B24,"") -> PARDO LOPEZ ABIGAIL | D16: P | E16: P | F16: P | G16: P | H16: P | I16: P | J16: P | K16: P | L16: P | M16: P | N16: P | O16: P | P16: P | Q16: P | R16: P | S16: P | T16: P | U16: P | V16: P | W16: P | X16: P | Y16: P | Z16: P | AA16: P | AB16: P | AC16: P | AD16: P | AE16: P | AR16: 0 | AS16: =COUNTIF(D16:AQ16,"A") -> 0 | AT16: =COUNTIF(D16:AQ16,"L") -> 0 | AU16: =COUNTIF(D16:AQ16,"F") -> 0 | AV16: =COUNTIF(D16:AQ16,"P") -> 28 | AW16: =+AS16/$AH$1 -> 0 | AX16: =+AT16/$AH$1 -> 0 | AY16: =+AU16/$AH$1 -> 0 | AZ16: =+AV16/$AH$1 -> 1
A17: =IF('1erT'!A25<>"",'1erT'!A25,"") -> 11 | B17: =IF('1erT'!B25<>"",'1erT'!B25,"") -> ROCABADO ANDIA MARIANA | D17: P | E17: P | F17: P | G17: P | H17: P | I17: P | J17: P | K17: P | L17: P | M17: P | N17: P | O17: P | P17: P | Q17: P | R17: P | S17: P | T17: P | U17: P | V17: P | W17: P | X17: P | Y17: P | Z17: P | AA17: P | AB17: P | AC17: P | AD17: P | AE17: P | AR17: 0 | AS17: =COUNTIF(D17:AQ17,"A") -> 0 | AT17: =COUNTIF(D17:AQ17,"L") -> 0 | AU17: =COUNTIF(D17:AQ17,"F") -> 0 | AV17: =COUNTIF(D17:AQ17,"P") -> 28 | AW17: =+AS17/$AH$1 -> 0 | AX17: =+AT17/$AH$1 -> 0 | AY17: =+AU17/$AH$1 -> 0 | AZ17: =+AV17/$AH$1 -> 1
A18: =IF('1erT'!A26<>"",'1erT'!A26,"") -> 12 | B18: =IF('1erT'!B26<>"",'1erT'!B26,"") -> SEJAS CAMPOS ZULMA | D18: P | E18: P | F18: P | G18: P | H18: P | I18: P | J18: P | K18: P | L18: P | M18: P | N18: P | O18: P | P18: P | Q18: P | R18: P | S18: P | T18: P | U18: P | V18: P | W18: P | X18: P | Y18: P | Z18: P | AA18: P | AB18: P | AC18: P | AD18: P | AE18: P | AR18: 0 | AS18: =COUNTIF(D18:AQ18,"A") -> 0 | AT18: =COUNTIF(D18:AQ18,"L") -> 0 | AU18: =COUNTIF(D18:AQ18,"F") -> 0 | AV18: =COUNTIF(D18:AQ18,"P") -> 28 | AW18: =+AS18/$AH$1 -> 0 | AX18: =+AT18/$AH$1 -> 0 | AY18: =+AU18/$AH$1 -> 0 | AZ18: =+AV18/$AH$1 -> 1
... A33: =IF('1erT'!A41<>"",'1erT'!A41,"") | B33: =IF('1erT'!B41<>"",'1erT'!B41,"") | D33: P | E33: P | F33: P | G33: P | H33: P | I33: P | J33: P | K33: P | L33: P | M33: P | N33: P | O33: P | P33: P | Q33: P | R33: P | S33: P | T33: P | U33: P | V33: P | W33: P | X33: P | Y33: P | Z33: P | AA33: P | AB33: P | AC33: P | AD33: P | AE33: P | AR33: 0 | AS33: =COUNTIF(D33:AQ33,"A") -> 0 | AT33: =COUNTIF(D33:AQ33,"L") -> 0 | AU33: =COUNTIF(D33:AQ33,"F") -> 0 | AV33: =COUNTIF(D33:AQ33,"P") -> 28 | AW33: =+AS33/$AH$1 -> 0 | AX33: =+AT33/$AH$1 -> 0 | AY33: =+AU33/$AH$1 -> 0 | AZ33: =+AV33/$AH$1 -> 1
A34: =IF('1erT'!A42<>"",'1erT'!A42,"") | B34: =IF('1erT'!B42<>"",'1erT'!B42,"") | AR34: 0 | AS34: =COUNTIF(D34:AQ34,"A") -> 0 | AT34: =COUNTIF(D34:AQ34,"L") -> 0 | AU34: =COUNTIF(D34:AQ34,"F") -> 0 | AV34: =COUNTIF(D34:AQ34,"P") -> 0 | AW34: =+AS34/$AH$1 -> 0 | AX34: =+AT34/$AH$1 -> 0 | AY34: =+AU34/$AH$1 -> 0 | AZ34: =+AV34/$AH$1 -> 0
A35: =IF('1erT'!A43<>"",'1erT'!A43,"") | B35: =IF('1erT'!B43<>"",'1erT'!B43,"") | AR35: 0 | AS35: =COUNTIF(D35:AQ35,"A") -> 0 | AT35: =COUNTIF(D35:AQ35,"L") -> 0 | AU35: =COUNTIF(D35:AQ35,"F") -> 0 | AV35: =COUNTIF(D35:AQ35,"P") -> 0 | AW35: =+AS35/$AH$1 -> 0 | AX35: =+AT35/$AH$1 -> 0 | AY35: =+AU35/$AH$1 -> 0 | AZ35: =+AV35/$AH$1 -> 0
A36: =IF('1erT'!A44<>"",'1erT'!A44,"") | B36: =IF('1erT'!B44<>"",'1erT'!B44,"") | AR36: 0 | AS36: =COUNTIF(D36:AQ36,"A") -> 0 | AT36: =COUNTIF(D36:AQ36,"L") -> 0 | AU36: =COUNTIF(D36:AQ36,"F") -> 0 | AV36: =COUNTIF(D36:AQ36,"P") -> 0 | AW36: =+AS36/$AH$1 -> 0 | AX36: =+AT36/$AH$1 -> 0 | AY36: =+AU36/$AH$1 -> 0 | AZ36: =+AV36/$AH$1 -> 0
A37: =IF('1erT'!A45<>"",'1erT'!A45,"") | B37: =IF('1erT'!B45<>"",'1erT'!B45,"") | AR37: 0 | AS37: =COUNTIF(D37:AQ37,"A") -> 0 | AT37: =COUNTIF(D37:AQ37,"L") -> 0 | AU37: =COUNTIF(D37:AQ37,"F") -> 0 | AV37: =COUNTIF(D37:AQ37,"P") -> 0 | AW37: =+AS37/$AH$1 -> 0 | AX37: =+AT37/$AH$1 -> 0 | AY37: =+AU37/$AH$1 -> 0 | AZ37: =+AV37/$AH$1 -> 0
A38: =IF('1erT'!A46<>"",'1erT'!A46,"") | B38: =IF('1erT'!B46<>"",'1erT'!B46,"") | AR38: 0 | AS38: =COUNTIF(D38:AQ38,"A") -> 0 | AT38: =COUNTIF(D38:AQ38,"L") -> 0 | AU38: =COUNTIF(D38:AQ38,"F") -> 0 | AV38: =COUNTIF(D38:AQ38,"P") -> 0 | AW38: =+AS38/$AH$1 -> 0 | AX38: =+AT38/$AH$1 -> 0 | AY38: =+AU38/$AH$1 -> 0 | AZ38: =+AV38/$AH$1 -> 0
A39: =IF('1erT'!A47<>"",'1erT'!A47,"") | B39: =IF('1erT'!B47<>"",'1erT'!B47,"") | AR39: 0 | AS39: =COUNTIF(D39:AQ39,"A") -> 0 | AT39: =COUNTIF(D39:AQ39,"L") -> 0 | AU39: =COUNTIF(D39:AQ39,"F") -> 0 | AV39: =COUNTIF(D39:AQ39,"P") -> 0 | AW39: =+AS39/$AH$1 -> 0 | AX39: =+AT39/$AH$1 -> 0 | AY39: =+AU39/$AH$1 -> 0 | AZ39: =+AV39/$AH$1 -> 0
A40: =IF('1erT'!A48<>"",'1erT'!A48,"") | B40: =IF('1erT'!B48<>"",'1erT'!B48,"") | AR40: 0 | AS40: =COUNTIF(D40:AQ40,"A") -> 0 | AT40: =COUNTIF(D40:AQ40,"L") -> 0 | AU40: =COUNTIF(D40:AQ40,"F") -> 0 | AV40: =COUNTIF(D40:AQ40,"P") -> 0 | AW40: =+AS40/$AH$1 -> 0 | AX40: =+AT40/$AH$1 -> 0 | AY40: =+AU40/$AH$1 -> 0 | AZ40: =+AV40/$AH$1 -> 0
A41: =IF('1erT'!A49<>"",'1erT'!A49,"") | B41: =IF('1erT'!B49<>"",'1erT'!B49,"") | AR41: 0 | AS41: =COUNTIF(D41:AQ41,"A") -> 0 | AT41: =COUNTIF(D41:AQ41,"L") -> 0 | AU41: =COUNTIF(D41:AQ41,"F") -> 0 | AV41: =COUNTIF(D41:AQ41,"P") -> 0 | AW41: =+AS41/$AH$1 -> 0 | AX41: =+AT41/$AH$1 -> 0 | AY41: =+AU41/$AH$1 -> 0 | AZ41: =+AV41/$AH$1 -> 0
A42: =IF('1erT'!A50<>"",'1erT'!A50,"") | B42: =IF('1erT'!B50<>"",'1erT'!B50,"") | AR42: 0 | AS42: =COUNTIF(D42:AQ42,"A") -> 0 | AT42: =COUNTIF(D42:AQ42,"L") -> 0 | AU42: =COUNTIF(D42:AQ42,"F") -> 0 | AV42: =COUNTIF(D42:AQ42,"P") -> 0 | AW42: =+AS42/$AH$1 -> 0 | AX42: =+AT42/$AH$1 -> 0 | AY42: =+AU42/$AH$1 -> 0 | AZ42: =+AV42/$AH$1 -> 0
A43: =IF('1erT'!A51<>"",'1erT'!A51,"") | B43: =IF('1erT'!B51<>"",'1erT'!B51,"") | AR43: 0 | AS43: =COUNTIF(D43:AQ43,"A") -> 0 | AT43: =COUNTIF(D43:AQ43,"L") -> 0 | AU43: =COUNTIF(D43:AQ43,"F") -> 0 | AV43: =COUNTIF(D43:AQ43,"P") -> 0 | AW43: =+AS43/$AH$1 -> 0 | AX43: =+AT43/$AH$1 -> 0 | AY43: =+AU43/$AH$1 -> 0 | AZ43: =+AV43/$AH$1 -> 0
A44: =IF('1erT'!A52<>"",'1erT'!A52,"") | B44: =IF('1erT'!B52<>"",'1erT'!B52,"") | AR44: 0 | AS44: =COUNTIF(D44:AQ44,"A") -> 0 | AT44: =COUNTIF(D44:AQ44,"L") -> 0 | AU44: =COUNTIF(D44:AQ44,"F") -> 0 | AV44: =COUNTIF(D44:AQ44,"P") -> 0 | AW44: =+AS44/$AH$1 -> 0 | AX44: =+AT44/$AH$1 -> 0 | AY44: =+AU44/$AH$1 -> 0 | AZ44: =+AV44/$AH$1 -> 0
A45: =IF('1erT'!A53<>"",'1erT'!A53,"") | B45: =IF('1erT'!B53<>"",'1erT'!B53,"") | AR45: 0 | AS45: =COUNTIF(D45:AQ45,"A") -> 0 | AT45: =COUNTIF(D45:AQ45,"L") -> 0 | AU45: =COUNTIF(D45:AQ45,"F") -> 0 | AV45: =COUNTIF(D45:AQ45,"P") -> 0 | AW45: =+AS45/$AH$1 -> 0 | AX45: =+AT45/$AH$1 -> 0 | AY45: =+AU45/$AH$1 -> 0 | AZ45: =+AV45/$AH$1 -> 0
... A56: =IF('1erT'!A64<>"",'1erT'!A64,"") | B56: =IF('1erT'!B64<>"",'1erT'!B64,"") | AR56: 0 | AS56: =COUNTIF(D56:AQ56,"A") -> 0 | AT56: =COUNTIF(D56:AQ56,"L") -> 0 | AU56: =COUNTIF(D56:AQ56,"F") -> 0 | AV56: =COUNTIF(D56:AQ56,"P") -> 0 | AW56: =+AS56/$AH$1 -> 0 | AX56: =+AT56/$AH$1 -> 0 | AY56: =+AU56/$AH$1 -> 0 | AZ56: =+AV56/$AH$1 -> 0

Sheet Asis2Tri
C1: CUADRO DE ASISTENCIA SEGUNDO TRIMESTRE | AH1: =COUNTA(D6:AR6) -> 32 | AI1: dias | AN1: %A-atrasos | AS1: =AS3/(AH2*AH1) -> 0 | AV1: %F-faltas | AY1: =+AU3/(AH1*AH2) -> 0
C2: =+Asis1Tri!C2 -> EDUCACION SECUNDARIA COMUNITARIA PRODUCTIVA | AH2: =+Asis1Tri!AH2 -> 50 | AI2: estudiantes | AN2: %L-licencias | AT2: =+AT3/(AH2*AH1) -> 0 | AV2: %P-presente | AY2: =+AV3/(AH1*AH2) -> 0.58
A3: ='1erT'!A6 -> MAESTRO : MARCELO A. RODRIGUEZ GRACIA | H3: ='1erT'!A4 -> CURSO: 2ndo A Secundaria | AC3: ='1erT'!A8 -> MATERIA : HISTORIA | AS3: =SUM(AS7:AS56) -> 0 | AT3: =SUM(AT7:AT56) -> 0 | AU3: =SUM(AU7:AU56) -> 0 | AV3: =SUM(AV7:AV56) -> 928 | AW3: PORC. %
A4: N° | B4: APELLIDOS Y NOMBRES | C4: MM | D4: MAYO | J4: JUNIO | S4: JULIO | AB4: AGOSTO | AS4: A ATRASO | AT4: L LICENCIA | AU4: F FALTA | AV4: P PRESENTE | AW4: A ATRASO | AX4: L LICENCIA | AY4: F FALTA | AZ4: P PRESENTE
C5: DD | D5: L | E5: M | F5: L | G5: M | H5: L | I5: M | J5: L | K5: M | L5: L | M5: M | N5: L | O5: M | P5: L | Q5: M | R5: L | S5: M | T5: L | U5: M | V5: L | W5: M | X5: L | Y5: M | Z5: L | AA5: M | AB5: L | AC5: M | AD5: L | AE5: M | AF5: L | AG5: M | AH5: L | AI5: M
C6: FF | D6: 11 | E6: 13 | F6: 18 | G6: 20 | H6: 25 | I6: 27 | J6: 1 | K6: 3 | L6: 8 | M6: 10 | N6: 15 | O6: 17 | P6: 22 | Q6: 24 | R6: 29 | S6: 1 | T6: 6 | U6: 8 | V6: 13 | W6: 15 | X6: 20 | Y6: 22 | Z6: 27 | AA6: 29 | AB6: 3 | AC6: 5 | AD6: 10 | AE6: 12 | AF6: 17 | AG6: 19 | AH6: 24 | AI6: 26
A7: =IF(Asis1Tri!A7=0,"",Asis1Tri!A7) -> 1 | B7: =IF(Asis1Tri!B7=0,"",Asis1Tri!B7) -> AGUILA SEJAS MATIAS HERNAN | D7: P | E7: P | F7: P | G7: P | H7: P | I7: P | J7: P | K7: P | L7: P | M7: P | N7: P | O7: P | P7: P | Q7: P | R7: P | S7: P | T7: P | U7: P | V7: P | W7: P | X7: P | Y7: P | Z7: P | AA7: P | AB7: P | AC7: P | AD7: P | AE7: P | AF7: P | AG7: P | AH7: P | AI7: P | AR7: 0 | AS7: =COUNTIF(D7:AQ7,"A") -> 0 | AT7: =COUNTIF(D7:AQ7,"L") -> 0 | AU7: =COUNTIF(D7:AQ7,"F") -> 0 | AV7: =COUNTIF(D7:AQ7,"P") -> 32 | AW7: =+AS7/$AH$1 -> 0 | AX7: =+AT7/$AH$1 -> 0 | AY7: =+AU7/$AH$1 -> 0 | AZ7: =+AV7/$AH$1 -> 1
A8: =IF(Asis1Tri!A8=0,"",Asis1Tri!A8) -> 2 | B8: =IF(Asis1Tri!B8=0,"",Asis1Tri!B8) -> ANTEZANA ARANIBAR JAVIER LEANDRO | D8: P | E8: P | F8: P | G8: P | H8: P | I8: P | J8: P | K8: P | L8: P | M8: P | N8: P | O8: P | P8: P | Q8: P | R8: P | S8: P | T8: P | U8: P | V8: P | W8: P | X8: P | Y8: P | Z8: P | AA8: P | AB8: P | AC8: P | AD8: P | AE8: P | AF8: P | AG8: P | AH8: P | AI8: P | AR8: 0 | AS8: =COUNTIF(D8:AQ8,"A") -> 0 | AT8: =COUNTIF(D8:AQ8,"L") -> 0 | AU8: =COUNTIF(D8:AQ8,"F") -> 0 | AV8: =COUNTIF(D8:AQ8,"P") -> 32 | AW8: =+AS8/$AH$1 -> 0 | AX8: =+AT8/$AH$1 -> 0 | AY8: =+AU8/$AH$1 -> 0 | AZ8: =+AV8/$AH$1 -> 1
A9: =IF(Asis1Tri!A9=0,"",Asis1Tri!A9) -> 3 | B9: =IF(Asis1Tri!B9=0,"",Asis1Tri!B9) -> ANTEZANA TORREZ MATIAS ANDRE | D9: P | E9: P | F9: P | G9: P | H9: P | I9: P | J9: P | K9: P | L9: P | M9: P | N9: P | O9: P | P9: P | Q9: P | R9: P | S9: P | T9: P | U9: P | V9: P | W9: P | X9: P | Y9: P | Z9: P | AA9: P | AB9: P | AC9: P | AD9: P | AE9: P | AF9: P | AG9: P | AH9: P | AI9: P | AR9: 5 | AS9: =COUNTIF(D9:AQ9,"A") -> 0 | AT9: =COUNTIF(D9:AQ9,"L") -> 0 | AU9: =COUNTIF(D9:AQ9,"F") -> 0 | AV9: =COUNTIF(D9:AQ9,"P") -> 32 | AW9: =+AS9/$AH$1 -> 0 | AX9: =+AT9/$AH$1 -> 0 | AY9: =+AU9/$AH$1 -> 0 | AZ9: =+AV9/$AH$1 -> 1
A10: =IF(Asis1Tri!A10=0,"",Asis1Tri!A10) -> 4 | B10: =IF(Asis1Tri!B10=0,"",Asis1Tri!B10) -> CARDOZO FRANCO JOHNNY LEONARDO | D10: P | E10: P | F10: P | G10: P | H10: P | I10: P | J10: P | K10: P | L10: P | M10: P | N10: P | O10: P | P10: P | Q10: P | R10: P | S10: P | T10: P | U10: P | V10: P | W10: P | X10: P | Y10: P | Z10: P | AA10: P | AB10: P | AC10: P | AD10: P | AE10: P | AF10: P | AG10: P | AH10: P | AI10: P | AR10: 0 | AS10: =COUNTIF(D10:AQ10,"A") -> 0 | AT10: =COUNTIF(D10:AQ10,"L") -> 0 | AU10: =COUNTIF(D10:AQ10,"F") -> 0 | AV10: =COUNTIF(D10:AQ10,"P") -> 32 | AW10: =+AS10/$AH$1 -> 0 | AX10: =+AT10/$AH$1 -> 0 | AY10: =+AU10/$AH$1 -> 0 | AZ10: =+AV10/$AH$1 -> 1
A11: =IF(Asis1Tri!A11=0,"",Asis1Tri!A11) -> 5 | B11: =IF(Asis1Tri!B11=0,"",Asis1Tri!B11) -> ESPINOZA MUÑOZ RUBEN SEBASTIAN | D11: P | E11: P | F11: P | G11: P | H11: P | I11: P | J11: P | K11: P | L11: P | M11: P | N11: P | O11: P | P11: P | Q11: P | R11: P | S11: P | T11: P | U11: P | V11: P | W11: P | X11: P | Y11: P | Z11: P | AA11: P | AB11: P | AC11: P | AD11: P | AE11: P | AF11: P | AG11: P | AH11: P | AI11: P | AR11: 0 | AS11: =COUNTIF(D11:AQ11,"A") -> 0 | AT11: =COUNTIF(D11:AQ11,"L") -> 0 | AU11: =COUNTIF(D11:AQ11,"F") -> 0 | AV11: =COUNTIF(D11:AQ11,"P") -> 32 | AW11: =+AS11/$AH$1 -> 0 | AX11: =+AT11/$AH$1 -> 0 | AY11: =+AU11/$AH$1 -> 0 | AZ11: =+AV11/$AH$1 -> 1
A12: =IF(Asis1Tri!A12=0,"",Asis1Tri!A12) -> 6 | B12: =IF(Asis1Tri!B12=0,"",Asis1Tri!B12) -> HUANCA AMURRIO VALENTINA RAFAELA | D12: P | E12: P | F12: P | G12: P | H12: P | I12: P | J12: P | K12: P | L12: P | M12: P | N12: P | O12: P | P12: P | Q12: P | R12: P | S12: P | T12: P | U12: P | V12: P | W12: P | X12: P | Y12: P | Z12: P | AA12: P | AB12: P | AC12: P | AD12: P | AE12: P | AF12: P | AG12: P | AH12: P | AI12: P | AR12: 0 | AS12: =COUNTIF(D12:AQ12,"A") -> 0 | AT12: =COUNTIF(D12:AQ12,"L") -> 0 | AU12: =COUNTIF(D12:AQ12,"F") -> 0 | AV12: =COUNTIF(D12:AQ12,"P") -> 32 | AW12: =+AS12/$AH$1 -> 0 | AX12: =+AT12/$AH$1 -> 0 | AY12: =+AU12/$AH$1 -> 0 | AZ12: =+AV12/$AH$1 -> 1
A13: =IF(Asis1Tri!A13=0,"",Asis1Tri!A13) -> 7 | B13: =IF(Asis1Tri!B13=0,"",Asis1Tri!B13) -> MERCADO ROJAS MARIA BELEN | D13: P | E13: P | F13: P | G13: P | H13: P | I13: P | J13: P | K13: P | L13: P | M13: P | N13: P | O13: P | P13: P | Q13: P | R13: P | S13: P | T13: P | U13: P | V13: P | W13: P | X13: P | Y13: P | Z13: P | AA13: P | AB13: P | AC13: P | AD13: P | AE13: P | AF13: P | AG13: P | AH13: P | AI13: P | AR13: 0 | AS13: =COUNTIF(D13:AQ13,"A") -> 0 | AT13: =COUNTIF(D13:AQ13,"L") -> 0 | AU13: =COUNTIF(D13:AQ13,"F") -> 0 | AV13: =COUNTIF(D13:AQ13,"P") -> 32 | AW13: =+AS13/$AH$1 -> 0 | AX13: =+AT13/$AH$1 -> 0 | AY13: =+AU13/$AH$1 -> 0 | AZ13: =+AV13/$AH$1 -> 1
A14: =IF(Asis1Tri!A14=0,"",Asis1Tri!A14) -> 8 | B14: =IF(Asis1Tri!B14=0,"",Asis1Tri!B14) -> NUMBELA SAAVEDRA RAFAEL | D14: P | E14: P | F14: P | G14: P | H14: P | I14: P | J14: P | K14: P | L14: P | M14: P | N14: P | O14: P | P14: P | Q14: P | R14: P | S14: P | T14: P | U14: P | V14: P | W14: P | X14: P | Y14: P | Z14: P | AA14: P | AB14: P | AC14: P | AD14: P | AE14: P | AF14: P | AG14: P | AH14: P | AI14: P | AR14: 0 | AS14: =COUNTIF(D14:AQ14,"A") -> 0 | AT14: =COUNTIF(D14:AQ14,"L") -> 0 | AU14: =COUNTIF(D14:AQ14,"F") -> 0 | AV14: =COUNTIF(D14:AQ14,"P") -> 32 | AW14: =+AS14/$AH$1 -> 0 | AX14: =+AT14/$AH$1 -> 0 | AY14: =+AU14/$AH$1 -> 0 | AZ14: =+AV14/$AH$1 -> 1
A15: =IF(Asis1Tri!A15=0,"",Asis1Tri!A15) -> 9 | B15: =IF(Asis1Tri!B15=0,"",Asis1Tri!B15) -> PEÑALOZA PRADO RAFAEL ANDRES | D15: P | E15: P | F15: P | G15: P | H15: P | I15: P | J15: P | K15: P | L15: P | M15: P | N15: P | O15: P | P15: P | Q15: P | R15: P | S15: P | T15: P | U15: P | V15: P | W15: P | X15: P | Y15: P | Z15: P | AA15: P | AB15: P | AC15: P | AD15: P | AE15: P | AF15: P | AG15: P | AH15: P | AI15: P | AR15: 0 | AS15: =COUNTIF(D15:AQ15,"A") -> 0 | AT15: =COUNTIF(D15:AQ15,"L") -> 0 | AU15: =COUNTIF(D15:AQ15,"F") -> 0 | AV15: =COUNTIF(D15:AQ15,"P") -> 32 | AW15: =+AS15/$AH$1 -> 0 | AX15: =+AT15/$AH$1 -> 0 | AY15: =+AU15/$AH$1 -> 0 | AZ15: =+AV15/$AH$1 -> 1
A16: =IF(Asis1Tri!A16=0,"",Asis1Tri!A16) -> 10 | B16: =IF(Asis1Tri!B16=0,"",Asis1Tri!B16) -> PARDO LOPEZ ABIGAIL | D16: P | E16: P | F16: P | G16: P | H16: P | I16: P | J16: P | K16: P | L16: P | M16: P | N16: P | O16: P | P16: P | Q16: P | R16: P | S16: P | T16: P | U16: P | V16: P | W16: P | X16: P | Y16: P | Z16: P | AA16: P | AB16: P | AC16: P | AD16: P | AE16: P | AF16: P | AG16: P | AH16: P | AI16: P | AR16: 0 | AS16: =COUNTIF(D16:AQ16,"A") -> 0 | AT16: =COUNTIF(D16:AQ16,"L") -> 0 | AU16: =COUNTIF(D16:AQ16,"F") -> 0 | AV16: =COUNTIF(D16:AQ16,"P") -> 32 | AW16: =+AS16/$AH$1 -> 0 | AX16: =+AT16/$AH$1 -> 0 | AY16: =+AU16/$AH$1 -> 0 | AZ16: =+AV16/$AH$1 -> 1
A17: =IF(Asis1Tri!A17=0,"",Asis1Tri!A17) -> 11 | B17: =IF(Asis1Tri!B17=0,"",Asis1Tri!B17) -> ROCABADO ANDIA MARIANA | D17: P | E17: P | F17: P | G17: P | H17: P | I17: P | J17: P | K17: P | L17: P | M17: P | N17: P | O17: P | P17: P | Q17: P | R17: P | S17: P | T17: P | U17: P | V17: P | W17: P | X17: P | Y17: P | Z17: P | AA17: P | AB17: P | AC17: P | AD17: P | AE17: P | AF17: P | AG17: P | AH17: P | AI17: P | AR17: 0 | AS17: =COUNTIF(D17:AQ17,"A") -> 0 | AT17: =COUNTIF(D17:AQ17,"L") -> 0 | AU17: =COUNTIF(D17:AQ17,"F") -> 0 | AV17: =COUNTIF(D17:AQ17,"P") -> 32 | AW17: =+AS17/$AH$1 -> 0 | AX17: =+AT17/$AH$1 -> 0 | AY17: =+AU17/$AH$1 -> 0 | AZ17: =+AV17/$AH$1 -> 1
A18: =IF(Asis1Tri!A18=0,"",Asis1Tri!A18) -> 12 | B18: =IF(Asis1Tri!B18=0,"",Asis1Tri!B18) -> SEJAS CAMPOS ZULMA | D18: P | E18: P | F18: P | G18: P | H18: P | I18: P | J18: P | K18: P | L18: P | M18: P | N18: P | O18: P | P18: P | Q18: P | R18: P | S18: P | T18: P | U18: P | V18: P | W18: P | X18: P | Y18: P | Z18: P | AA18: P | AB18: P | AC18: P | AD18: P | AE18: P | AF18: P | AG18: P | AH18: P | AI18: P | AR18: 0 | AS18: =COUNTIF(D18:AQ18,"A") -> 0 | AT18: =COUNTIF(D18:AQ18,"L") -> 0 | AU18: =COUNTIF(D18:AQ18,"F") -> 0 | AV18: =COUNTIF(D18:AQ18,"P") -> 32 | AW18: =+AS18/$AH$1 -> 0 | AX18: =+AT18/$AH$1 -> 0 | AY18: =+AU18/$AH$1 -> 0 | AZ18: =+AV18/$AH$1 -> 1
... A35: =IF(Asis1Tri!A35=0,"",Asis1Tri!A35) | B35: =IF(Asis1Tri!B35=0,"",Asis1Tri!B35) | D35: P | E35: P | F35: P | G35: P | H35: P | I35: P | J35: P | K35: P | L35: P | M35: P | N35: P | O35: P | P35: P | Q35: P | R35: P | S35: P | T35: P | U35: P | V35: P | W35: P | X35: P | Y35: P | Z35: P | AA35: P | AB35: P | AC35: P | AD35: P | AE35: P | AF35: P | AG35: P | AH35: P | AI35: P | AR35: 0 | AS35: =COUNTIF(D35:AQ35,"A") -> 0 | AT35: =COUNTIF(D35:AQ35,"L") -> 0 | AU35: =COUNTIF(D35:AQ35,"F") -> 0 | AV35: =COUNTIF(D35:AQ35,"P") -> 32 | AW35: =+AS35/$AH$1 -> 0 | AX35: =+AT35/$AH$1 -> 0 | AY35: =+AU35/$AH$1 -> 0 | AZ35: =+AV35/$AH$1 -> 1
A36: =IF(Asis1Tri!A36=0,"",Asis1Tri!A36) | B36: =IF(Asis1Tri!B36=0,"",Asis1Tri!B36) | AR36: 0 | AS36: =COUNTIF(D36:AQ36,"A") -> 0 | AT36: =COUNTIF(D36:AQ36,"L") -> 0 | AU36: =COUNTIF(D36:AQ36,"F") -> 0 | AV36: =COUNTIF(D36:AQ36,"P") -> 0 | AW36: =+AS36/$AH$1 -> 0 | AX36: =+AT36/$AH$1 -> 0 | AY36: =+AU36/$AH$1 -> 0 | AZ36: =+AV36/$AH$1 -> 0
A37: =IF(Asis1Tri!A37=0,"",Asis1Tri!A37) | B37: =IF(Asis1Tri!B37=0,"",Asis1Tri!B37) | AR37: 0 | AS37: =COUNTIF(D37:AQ37,"A") -> 0 | AT37: =COUNTIF(D37:AQ37,"L") -> 0 | AU37: =COUNTIF(D37:AQ37,"F") -> 0 | AV37: =COUNTIF(D37:AQ37,"P") -> 0 | AW37: =+AS37/$AH$1 -> 0 | AX37: =+AT37/$AH$1 -> 0 | AY37: =+AU37/$AH$1 -> 0 | AZ37: =+AV37/$AH$1 -> 0
A38: =IF(Asis1Tri!A38=0,"",Asis1Tri!A38) | B38: =IF(Asis1Tri!B38=0,"",Asis1Tri!B38) | AR38: 0 | AS38: =COUNTIF(D38:AQ38,"A") -> 0 | AT38: =COUNTIF(D38:AQ38,"L") -> 0 | AU38: =COUNTIF(D38:AQ38,"F") -> 0 | AV38: =COUNTIF(D38:AQ38,"P") -> 0 | AW38: =+AS38/$AH$1 -> 0 | AX38: =+AT38/$AH$1 -> 0 | AY38: =+AU38/$AH$1 -> 0 | AZ38: =+AV38/$AH$1 -> 0
A39: =IF(Asis1Tri!A39=0,"",Asis1Tri!A39) | B39: =IF(Asis1Tri!B39=0,"",Asis1Tri!B39) | AR39: 0 | AS39: =COUNTIF(D39:AQ39,"A") -> 0 | AT39: =COUNTIF(D39:AQ39,"L") -> 0 | AU39: =COUNTIF(D39:AQ39,"F") -> 0 | AV39: =COUNTIF(D39:AQ39,"P") -> 0 | AW39: =+AS39/$AH$1 -> 0 | AX39: =+AT39/$AH$1 -> 0 | AY39: =+AU39/$AH$1 -> 0 | AZ39: =+AV39/$AH$1 -> 0
A40: =IF(Asis1Tri!A40=0,"",Asis1Tri!A40) | B40: =IF(Asis1Tri!B40=0,"",Asis1Tri!B40) | AR40: 0 | AS40: =COUNTIF(D40:AQ40,"A") -> 0 | AT40: =COUNTIF(D40:AQ40,"L") -> 0 | AU40: =COUNTIF(D40:AQ40,"F") -> 0 | AV40: =COUNTIF(D40:AQ40,"P") -> 0 | AW40: =+AS40/$AH$1 -> 0 | AX40: =+AT40/$AH$1 -> 0 | AY40: =+AU40/$AH$1 -> 0 | AZ40: =+AV40/$AH$1 -> 0
A41: =IF(Asis1Tri!A41=0,"",Asis1Tri!A41) | B41: =IF(Asis1Tri!B41=0,"",Asis1Tri!B41) | AR41: 0 | AS41: =COUNTIF(D41:AQ41,"A") -> 0 | AT41: =COUNTIF(D41:AQ41,"L") -> 0 | AU41: =COUNTIF(D41:AQ41,"F") -> 0 | AV41: =COUNTIF(D41:AQ41,"P") -> 0 | AW41: =+AS41/$AH$1 -> 0 | AX41: =+AT41/$AH$1 -> 0 | AY41: =+AU41/$AH$1 -> 0 | AZ41: =+AV41/$AH$1 -> 0
A42: =IF(Asis1Tri!A42=0,"",Asis1Tri!A42) | B42: =IF(Asis1Tri!B42=0,"",Asis1Tri!B42) | AR42: 0 | AS42: =COUNTIF(D42:AQ42,"A") -> 0 | AT42: =COUNTIF(D42:AQ42,"L") -> 0 | AU42: =COUNTIF(D42:AQ42,"F") -> 0 | AV42: =COUNTIF(D42:AQ42,"P") -> 0 | AW42: =+AS42/$AH$1 -> 0 | AX42: =+AT42/$AH$1 -> 0 | AY42: =+AU42/$AH$1 -> 0 | AZ42: =+AV42/$AH$1 -> 0
A43: =IF(Asis1Tri!A43=0,"",Asis1Tri!A43) | B43: =IF(Asis1Tri!B43=0,"",Asis1Tri!B43) | AR43: 0 | AS43: =COUNTIF(D43:AQ43,"A") -> 0 | AT43: =COUNTIF(D43:AQ43,"L") -> 0 | AU43: =COUNTIF(D43:AQ43,"F") -> 0 | AV43: =COUNTIF(D43:AQ43,"P") -> 0 | AW43: =+AS43/$AH$1 -> 0 | AX43: =+AT43/$AH$1 -> 0 | AY43: =+AU43/$AH$1 -> 0 | AZ43: =+AV43/$AH$1 -> 0
A44: =IF(Asis1Tri!A44=0,"",Asis1Tri!A44) | B44: =IF(Asis1Tri!B44=0,"",Asis1Tri!B44) | AR44: 0 | AS44: =COUNTIF(D44:AQ44,"A") -> 0 | AT44: =COUNTIF(D44:AQ44,"L") -> 0 | AU44: =COUNTIF(D44:AQ44,"F") -> 0 | AV44: =COUNTIF(D44:AQ44,"P") -> 0 | AW44: =+AS44/$AH$1 -> 0 | AX44: =+AT44/$AH$1 -> 0 | AY44: =+AU44/$AH$1 -> 0 | AZ44: =+AV44/$AH$1 -> 0
A45: =IF(Asis1Tri!A45=0,"",Asis1Tri!A45) | B45: =IF(Asis1Tri!B45=0,"",Asis1Tri!B45) | AR45: 0 | AS45: =COUNTIF(D45:AQ45,"A") -> 0 | AT45: =COUNTIF(D45:AQ45,"L") -> 0 | AU45: =COUNTIF(D45:AQ45,"F") -> 0 | AV45: =COUNTIF(D45:AQ45,"P") -> 0 | AW45: =+AS45/$AH$1 -> 0 | AX45: =+AT45/$AH$1 -> 0 | AY45: =+AU45/$AH$1 -> 0 | AZ45: =+AV45/$AH$1 -> 0
A46: =IF(Asis1Tri!A46=0,"",Asis1Tri!A46) | B46: =IF(Asis1Tri!B46=0,"",Asis1Tri!B46) | AR46: 0 | AS46: =COUNTIF(D46:AQ46,"A") -> 0 | AT46: =COUNTIF(D46:AQ46,"L") -> 0 | AU46: =COUNTIF(D46:AQ46,"F") -> 0 | AV46: =COUNTIF(D46:AQ46,"P") -> 0 | AW46: =+AS46/$AH$1 -> 0 | AX46: =+AT46/$AH$1 -> 0 | AY46: =+AU46/$AH$1 -> 0 | AZ46: =+AV46/$AH$1 -> 0
A47: =IF(Asis1Tri!A47=0,"",Asis1Tri!A47) | B47: =IF(Asis1Tri!B47=0,"",Asis1Tri!B47) | AR47: 0 | AS47: =COUNTIF(D47:AQ47,"A") -> 0 | AT47: =COUNTIF(D47:AQ47,"L") -> 0 | AU47: =COUNTIF(D47:AQ47,"F") -> 0 | AV47: =COUNTIF(D47:AQ47,"P") -> 0 | AW47: =+AS47/$AH$1 -> 0 | AX47: =+AT47/$AH$1 -> 0 | AY47: =+AU47/$AH$1 -> 0 | AZ47: =+AV47/$AH$1 -> 0
... A56: =IF(Asis1Tri!A56=0,"",Asis1Tri!A56) | B56: =IF(Asis1Tri!B56=0,"",Asis1Tri!B56) | AR56: 0 | AS56: =COUNTIF(D56:AQ56,"A") -> 0 | AT56: =COUNTIF(D56:AQ56,"L") -> 0 | AU56: =COUNTIF(D56:AQ56,"F") -> 0 | AV56: =COUNTIF(D56:AQ56,"P") -> 0 | AW56: =+AS56/$AH$1 -> 0 | AX56: =+AT56/$AH$1 -> 0 | AY56: =+AU56/$AH$1 -> 0 | AZ56: =+AV56/$AH$1 -> 0

Sheet Asis3Tri
C1: CUADRO DE ASISTENCIA SEGUNDO TRIMESTRE | AH1: =COUNTA(D6:AR6) -> 28 | AI1: dias | AN1: %A-atrasos | AS1: =AS3/(AH2*AH1) -> 0 | AV1: %F-faltas | AY1: =+AU3/(AH1*AH2) -> 0
C2: =+Asis1Tri!C2 -> EDUCACION SECUNDARIA COMUNITARIA PRODUCTIVA | AH2: =+Asis1Tri!AH2 -> 50 | AI2: estudiantes | AN2: %L-licencias | AT2: =+AT3/(AH2*AH1) -> 0 | AV2: %P-presente | AY2: =+AV3/(AH1*AH2) -> 0.54
A3: ='1erT'!A6 -> MAESTRO : MARCELO A. RODRIGUEZ GRACIA | H3: ='1erT'!A4 -> CURSO: 2ndo A Secundaria | AC3: ='1erT'!A8 -> MATERIA : HISTORIA | AS3: =SUM(AS7:AS56) -> 0 | AT3: =SUM(AT7:AT56) -> 0 | AU3: =SUM(AU7:AU56) -> 0 | AV3: =SUM(AV7:AV56) -> 756 | AW3: PORC. %
A4: N° | B4: APELLIDOS Y NOMBRES | C4: MM | D4: SEPTIEMBRE | N4: OCTUBRE | V4: NOVIEMBRE | AE4: DICIEMBRE | AS4: A ATRASO | AT4: L LICENCIA | AU4: F FALTA | AV4: P PRESENTE | AW4: A ATRASO | AX4: L LICENCIA | AY4: F FALTA | AZ4: P PRESENTE
C5: DD | D5: L | E5: M | F5: L | G5: M | H5: L | I5: M | J5: L | K5: M | L5: L | M5: M | N5: L | O5: M | P5: L | Q5: M | R5: L | S5: M | T5: L | U5: M | V5: L | W5: M | X5: L | Y5: M | Z5: L | AA5: M | AB5: L | AC5: M | AD5: L | AE5: M
C6: FF | D6: 31 | E6: 2 | F6: 7 | G6: 9 | H6: 14 | I6: 16 | J6: 21 | K6: 23 | L6: 28 | M6: 30 | N6: 5 | O6: 7 | P6: 12 | Q6: 14 | R6: 19 | S6: 21 | T6: 26 | U6: 28 | V6: 2 | W6: 4 | X6: 9 | Y6: 11 | Z6: 16 | AA6: 18 | AB6: 23 | AC6: 25 | AD6: 30 | AE6: 2
A7: =IF(Asis1Tri!A7=0,"",Asis1Tri!A7) -> 1 | B7: =IF(Asis1Tri!B7=0,"",Asis1Tri!B7) -> AGUILA SEJAS MATIAS HERNAN | D7: P | E7: P | F7: P | G7: P | H7: P | I7: P | J7: P | K7: P | L7: P | M7: P | N7: P | O7: P | P7: P | Q7: P | R7: P | S7: P | T7: P | U7: P | V7: P | W7: P | X7: P | Y7: P | Z7: P | AA7: P | AB7: P | AC7: P | AD7: P | AE7: P | AR7: 0 | AS7: =COUNTIF(D7:AQ7,"A") -> 0 | AT7: =COUNTIF(D7:AQ7,"L") -> 0 | AU7: =COUNTIF(D7:AQ7,"F") -> 0 | AV7: =COUNTIF(D7:AQ7,"P") -> 28 | AW7: =+AS7/$AH$1 -> 0 | AX7: =+AT7/$AH$1 -> 0 | AY7: =+AU7/$AH$1 -> 0 | AZ7: =+AV7/$AH$1 -> 1
A8: =IF(Asis1Tri!A8=0,"",Asis1Tri!A8) -> 2 | B8: =IF(Asis1Tri!B8=0,"",Asis1Tri!B8) -> ANTEZANA ARANIBAR JAVIER LEANDRO | D8: P | E8: P | F8: P | G8: P | H8: P | I8: P | J8: P | K8: P | L8: P | M8: P | N8: P | O8: P | P8: P | Q8: P | R8: P | S8: P | T8: P | U8: P | V8: P | W8: P | X8: P | Y8: P | Z8: P | AA8: P | AB8: P | AC8: P | AD8: P | AE8: P | AR8: 0 | AS8: =COUNTIF(D8:AQ8,"A") -> 0 | AT8: =COUNTIF(D8:AQ8,"L") -> 0 | AU8: =COUNTIF(D8:AQ8,"F") -> 0 | AV8: =COUNTIF(D8:AQ8,"P") -> 28 | AW8: =+AS8/$AH$1 -> 0 | AX8: =+AT8/$AH$1 -> 0 | AY8: =+AU8/$AH$1 -> 0 | AZ8: =+AV8/$AH$1 -> 1
A9: =IF(Asis1Tri!A9=0,"",Asis1Tri!A9) -> 3 | B9: =IF(Asis1Tri!B9=0,"",Asis1Tri!B9) -> ANTEZANA TORREZ MATIAS ANDRE | D9: P | E9: P | F9: P | G9: P | H9: P | I9: P | J9: P | K9: P | L9: P | M9: P | N9: P | O9: P | P9: P | Q9: P | R9: P | S9: P | T9: P | U9: P | V9: P | W9: P | X9: P | Y9: P | Z9: P | AA9: P | AB9: P | AC9: P | AD9: P | AE9: P | AR9: 5 | AS9: =COUNTIF(D9:AQ9,"A") -> 0 | AT9: =COUNTIF(D9:AQ9,"L") -> 0 | AU9: =COUNTIF(D9:AQ9,"F") -> 0 | AV9: =COUNTIF(D9:AQ9,"P") -> 28 | AW9: =+AS9/$AH$1 -> 0 | AX9: =+AT9/$AH$1 -> 0 | AY9: =+AU9/$AH$1 -> 0 | AZ9: =+AV9/$AH$1 -> 1
A10: =IF(Asis1Tri!A10=0,"",Asis1Tri!A10) -> 4 | B10: =IF(Asis1Tri!B10=0,"",Asis1Tri!B10) -> CARDOZO FRANCO JOHNNY LEONARDO | D10: P | E10: P | F10: P | G10: P | H10: P | I10: P | J10: P | K10: P | L10: P | M10: P | N10: P | O10: P | P10: P | Q10: P | R10: P | S10: P | T10: P | U10: P | V10: P | W10: P | X10: P | Y10: P | Z10: P | AA10: P | AB10: P | AC10: P | AD10: P | AE10: P | AR10: 0 | AS10: =COUNTIF(D10:AQ10,"A") -> 0 | AT10: =COUNTIF(D10:AQ10,"L") -> 0 | AU10: =COUNTIF(D10:AQ10,"F") -> 0 | AV10: =COUNTIF(D10:AQ10,"P") -> 28 | AW10: =+AS10/$AH$1 -> 0 | AX10: =+AT10/$AH$1 -> 0 | AY10: =+AU10/$AH$1 -> 0 | AZ10: =+AV10/$AH$1 -> 1
A11: =IF(Asis1Tri!A11=0,"",Asis1Tri!A11) -> 5 | B11: =IF(Asis1Tri!B11=0,"",Asis1Tri!B11) -> ESPINOZA MUÑOZ RUBEN SEBASTIAN | D11: P | E11: P | F11: P | G11: P | H11: P | I11: P | J11: P | K11: P | L11: P | M11: P | N11: P | O11: P | P11: P | Q11: P | R11: P | S11: P | T11: P | U11: P | V11: P | W11: P | X11: P | Y11: P | Z11: P | AA11: P | AB11: P | AC11: P | AD11: P | AE11: P | AR11: 0 | AS11: =COUNTIF(D11:AQ11,"A") -> 0 | AT11: =COUNTIF(D11:AQ11,"L") -> 0 | AU11: =COUNTIF(D11:AQ11,"F") -> 0 | AV11: =COUNTIF(D11:AQ11,"P") -> 28 | AW11: =+AS11/$AH$1 -> 0 | AX11: =+AT11/$AH$1 -> 0 | AY11: =+AU11/$AH$1 -> 0 | AZ11: =+AV11/$AH$1 -> 1
A12: =IF(Asis1Tri!A12=0,"",Asis1Tri!A12) -> 6 | B12: =IF(Asis1Tri!B12=0,"",Asis1Tri!B12) -> HUANCA AMURRIO VALENTINA RAFAELA | D12: P | E12: P | F12: P | G12: P | H12: P | I12: P | J12: P | K12: P | L12: P | M12: P | N12: P | O12: P | P12: P | Q12: P | R12: P | S12: P | T12: P | U12: P | V12: P | W12: P | X12: P | Y12: P | Z12: P | AA12: P | AB12: P | AC12: P | AD12: P | AE12: P | AR12: 0 | AS12: =COUNTIF(D12:AQ12,"A") -> 0 | AT12: =COUNTIF(D12:AQ12,"L") -> 0 | AU12: =COUNTIF(D12:AQ12,"F") -> 0 | AV12: =COUNTIF(D12:AQ12,"P") -> 28 | AW12: =+AS12/$AH$1 -> 0 | AX12: =+AT12/$AH$1 -> 0 | AY12: =+AU12/$AH$1 -> 0 | AZ12: =+AV12/$AH$1 -> 1
A13: =IF(Asis1Tri!A13=0,"",Asis1Tri!A13) -> 7 | B13: =IF(Asis1Tri!B13=0,"",Asis1Tri!B13) -> MERCADO ROJAS MARIA BELEN | D13: P | E13: P | F13: P | G13: P | H13: P | I13: P | J13: P | K13: P | L13: P | M13: P | N13: P | O13: P | P13: P | Q13: P | R13: P | S13: P | T13: P | U13: P | V13: P | W13: P | X13: P | Y13: P | Z13: P | AA13: P | AB13: P | AC13: P | AD13: P | AE13: P | AR13: 0 | AS13: =COUNTIF(D13:AQ13,"A") -> 0 | AT13: =COUNTIF(D13:AQ13,"L") -> 0 | AU13: =COUNTIF(D13:AQ13,"F") -> 0 | AV13: =COUNTIF(D13:AQ13,"P") -> 28 | AW13: =+AS13/$AH$1 -> 0 | AX13: =+AT13/$AH$1 -> 0 | AY13: =+AU13/$AH$1 -> 0 | AZ13: =+AV13/$AH$1 -> 1
A14: =IF(Asis1Tri!A14=0,"",Asis1Tri!A14) -> 8 | B14: =IF(Asis1Tri!B14=0,"",Asis1Tri!B14) -> NUMBELA SAAVEDRA RAFAEL | D14: P | E14: P | F14: P | G14: P | H14: P | I14: P | J14: P | K14: P | L14: P | M14: P | N14: P | O14: P | P14: P | Q14: P | R14: P | S14: P | T14: P | U14: P | V14: P | W14: P | X14: P | Y14: P | Z14: P | AA14: P | AB14: P | AC14: P | AD14: P | AE14: P | AR14: 0 | AS14: =COUNTIF(D14:AQ14,"A") -> 0 | AT14: =COUNTIF(D14:AQ14,"L") -> 0 | AU14: =COUNTIF(D14:AQ14,"F") -> 0 | AV14: =COUNTIF(D14:AQ14,"P") -> 28 | AW14: =+AS14/$AH$1 -> 0 | AX14: =+AT14/$AH$1 -> 0 | AY14: =+AU14/$AH$1 -> 0 | AZ14: =+AV14/$AH$1 -> 1
A15: =IF(Asis1Tri!A15=0,"",Asis1Tri!A15) -> 9 | B15: =IF(Asis1Tri!B15=0,"",Asis1Tri!B15) -> PEÑALOZA PRADO RAFAEL ANDRES | D15: P | E15: P | F15: P | G15: P | H15: P | I15: P | J15: P | K15: P | L15: P | M15: P | N15: P | O15: P | P15: P | Q15: P | R15: P | S15: P | T15: P | U15: P | V15: P | W15: P | X15: P | Y15: P | Z15: P | AA15: P | AB15: P | AC15: P | AD15: P | AE15: P | AR15: 0 | AS15: =COUNTIF(D15:AQ15,"A") -> 0 | AT15: =COUNTIF(D15:AQ15,"L") -> 0 | AU15: =COUNTIF(D15:AQ15,"F") -> 0 | AV15: =COUNTIF(D15:AQ15,"P") -> 28 | AW15: =+AS15/$AH$1 -> 0 | AX15: =+AT15/$AH$1 -> 0 | AY15: =+AU15/$AH$1 -> 0 | AZ15: =+AV15/$AH$1 -> 1
A16: =IF(Asis1Tri!A16=0,"",Asis1Tri!A16) -> 10 | B16: =IF(Asis1Tri!B16=0,"",Asis1Tri!B16) -> PARDO LOPEZ ABIGAIL | D16: P | E16: P | F16: P | G16: P | H16: P | I16: P | J16: P | K16: P | L16: P | M16: P | N16: P | O16: P | P16: P | Q16: P | R16: P | S16: P | T16: P | U16: P | V16: P | W16: P | X16: P | Y16: P | Z16: P | AA16: P | AB16: P | AC16: P | AD16: P | AE16: P | AR16: 0 | AS16: =COUNTIF(D16:AQ16,"A") -> 0 | AT16: =COUNTIF(D16:AQ16,"L") -> 0 | AU16: =COUNTIF(D16:AQ16,"F") -> 0 | AV16: =COUNTIF(D16:AQ16,"P") -> 28 | AW16: =+AS16/$AH$1 -> 0 | AX16: =+AT16/$AH$1 -> 0 | AY16: =+AU16/$AH$1 -> 0 | AZ16: =+AV16/$AH$1 -> 1
A17: =IF(Asis1Tri!A17=0,"",Asis1Tri!A17) -> 11 | B17: =IF(Asis1Tri!B17=0,"",Asis1Tri!B17) -> ROCABADO ANDIA MARIANA | D17: P | E17: P | F17: P | G17: P | H17: P | I17: P | J17: P | K17: P | L17: P | M17: P | N17: P | O17: P | P17: P | Q17: P | R17: P | S17: P | T17: P | U17: P | V17: P | W17: P | X17: P | Y17: P | Z17: P | AA17: P | AB17: P | AC17: P | AD17: P | AE17: P | AR17: 0 | AS17: =COUNTIF(D17:AQ17,"A") -> 0 | AT17: =COUNTIF(D17:AQ17,"L") -> 0 | AU17: =COUNTIF(D17:AQ17,"F") -> 0 | AV17: =COUNTIF(D17:AQ17,"P") -> 28 | AW17: =+AS17/$AH$1 -> 0 | AX17: =+AT17/$AH$1 -> 0 | AY17: =+AU17/$AH$1 -> 0 | AZ17: =+AV17/$AH$1 -> 1
A18: =IF(Asis1Tri!A18=0,"",Asis1Tri!A18) -> 12 | B18: =IF(Asis1Tri!B18=0,"",Asis1Tri!B18) -> SEJAS CAMPOS ZULMA | D18: P | E18: P | F18: P | G18: P | H18: P | I18: P | J18: P | K18: P | L18: P | M18: P | N18: P | O18: P | P18: P | Q18: P | R18: P | S18: P | T18: P | U18: P | V18: P | W18: P | X18: P | Y18: P | Z18: P | AA18: P | AB18: P | AC18: P | AD18: P | AE18: P | AR18: 0 | AS18: =COUNTIF(D18:AQ18,"A") -> 0 | AT18: =COUNTIF(D18:AQ18,"L") -> 0 | AU18: =COUNTIF(D18:AQ18,"F") -> 0 | AV18: =COUNTIF(D18:AQ18,"P") -> 28 | AW18: =+AS18/$AH$1 -> 0 | AX18: =+AT18/$AH$1 -> 0 | AY18: =+AU18/$AH$1 -> 0 | AZ18: =+AV18/$AH$1 -> 1
... A33: =IF(Asis1Tri!A33=0,"",Asis1Tri!A33) | B33: =IF(Asis1Tri!B33=0,"",Asis1Tri!B33) | D33: P | E33: P | F33: P | G33: P | H33: P | I33: P | J33: P | K33: P | L33: P | M33: P | N33: P | O33: P | P33: P | Q33: P | R33: P | S33: P | T33: P | U33: P | V33: P | W33: P | X33: P | Y33: P | Z33: P | AA33: P | AB33: P | AC33: P | AD33: P | AE33: P | AR33: 0 | AS33: =COUNTIF(D33:AQ33,"A") -> 0 | AT33: =COUNTIF(D33:AQ33,"L") -> 0 | AU33: =COUNTIF(D33:AQ33,"F") -> 0 | AV33: =COUNTIF(D33:AQ33,"P") -> 28 | AW33: =+AS33/$AH$1 -> 0 | AX33: =+AT33/$AH$1 -> 0 | AY33: =+AU33/$AH$1 -> 0 | AZ33: =+AV33/$AH$1 -> 1
A34: =IF(Asis1Tri!A34=0,"",Asis1Tri!A34) | B34: =IF(Asis1Tri!B34=0,"",Asis1Tri!B34) | AR34: 0 | AS34: =COUNTIF(D34:AQ34,"A") -> 0 | AT34: =COUNTIF(D34:AQ34,"L") -> 0 | AU34: =COUNTIF(D34:AQ34,"F") -> 0 | AV34: =COUNTIF(D34:AQ34,"P") -> 0 | AW34: =+AS34/$AH$1 -> 0 | AX34: =+AT34/$AH$1 -> 0 | AY34: =+AU34/$AH$1 -> 0 | AZ34: =+AV34/$AH$1 -> 0
A35: =IF(Asis1Tri!A35=0,"",Asis1Tri!A35) | B35: =IF(Asis1Tri!B35=0,"",Asis1Tri!B35) | AR35: 0 | AS35: =COUNTIF(D35:AQ35,"A") -> 0 | AT35: =COUNTIF(D35:AQ35,"L") -> 0 | AU35: =COUNTIF(D35:AQ35,"F") -> 0 | AV35: =COUNTIF(D35:AQ35,"P") -> 0 | AW35: =+AS35/$AH$1 -> 0 | AX35: =+AT35/$AH$1 -> 0 | AY35: =+AU35/$AH$1 -> 0 | AZ35: =+AV35/$AH$1 -> 0
A36: =IF(Asis1Tri!A36=0,"",Asis1Tri!A36) | B36: =IF(Asis1Tri!B36=0,"",Asis1Tri!B36) | AR36: 0 | AS36: =COUNTIF(D36:AQ36,"A") -> 0 | AT36: =COUNTIF(D36:AQ36,"L") -> 0 | AU36: =COUNTIF(D36:AQ36,"F") -> 0 | AV36: =COUNTIF(D36:AQ36,"P") -> 0 | AW36: =+AS36/$AH$1 -> 0 | AX36: =+AT36/$AH$1 -> 0 | AY36: =+AU36/$AH$1 -> 0 | AZ36: =+AV36/$AH$1 -> 0
A37: =IF(Asis1Tri!A37=0,"",Asis1Tri!A37) | B37: =IF(Asis1Tri!B37=0,"",Asis1Tri!B37) | AR37: 0 | AS37: =COUNTIF(D37:AQ37,"A") -> 0 | AT37: =COUNTIF(D37:AQ37,"L") -> 0 | AU37: =COUNTIF(D37:AQ37,"F") -> 0 | AV37: =COUNTIF(D37:AQ37,"P") -> 0 | AW37: =+AS37/$AH$1 -> 0 | AX37: =+AT37/$AH$1 -> 0 | AY37: =+AU37/$AH$1 -> 0 | AZ37: =+AV37/$AH$1 -> 0
A38: =IF(Asis1Tri!A38=0,"",Asis1Tri!A38) | B38: =IF(Asis1Tri!B38=0,"",Asis1Tri!B38) | AR38: 0 | AS38: =COUNTIF(D38:AQ38,"A") -> 0 | AT38: =COUNTIF(D38:AQ38,"L") -> 0 | AU38: =COUNTIF(D38:AQ38,"F") -> 0 | AV38: =COUNTIF(D38:AQ38,"P") -> 0 | AW38: =+AS38/$AH$1 -> 0 | AX38: =+AT38/$AH$1 -> 0 | AY38: =+AU38/$AH$1 -> 0 | AZ38: =+AV38/$AH$1 -> 0
A39: =IF(Asis1Tri!A39=0,"",Asis1Tri!A39) | B39: =IF(Asis1Tri!B39=0,"",Asis1Tri!B39) | AR39: 0 | AS39: =COUNTIF(D39:AQ39,"A") -> 0 | AT39: =COUNTIF(D39:AQ39,"L") -> 0 | AU39: =COUNTIF(D39:AQ39,"F") -> 0 | AV39: =COUNTIF(D39:AQ39,"P") -> 0 | AW39: =+AS39/$AH$1 -> 0 | AX39: =+AT39/$AH$1 -> 0 | AY39: =+AU39/$AH$1 -> 0 | AZ39: =+AV39/$AH$1 -> 0
A40: =IF(Asis1Tri!A40=0,"",Asis1Tri!A40) | B40: =IF(Asis1Tri!B40=0,"",Asis1Tri!B40) | AR40: 0 | AS40: =COUNTIF(D40:AQ40,"A") -> 0 | AT40: =COUNTIF(D40:AQ40,"L") -> 0 | AU40: =COUNTIF(D40:AQ40,"F") -> 0 | AV40: =COUNTIF(D40:AQ40,"P") -> 0 | AW40: =+AS40/$AH$1 -> 0 | AX40: =+AT40/$AH$1 -> 0 | AY40: =+AU40/$AH$1 -> 0 | AZ40: =+AV40/$AH$1 -> 0
A41: =IF(Asis1Tri!A41=0,"",Asis1Tri!A41) | B41: =IF(Asis1Tri!B41=0,"",Asis1Tri!B41) | AR41: 0 | AS41: =COUNTIF(D41:AQ41,"A") -> 0 | AT41: =COUNTIF(D41:AQ41,"L") -> 0 | AU41: =COUNTIF(D41:AQ41,"F") -> 0 | AV41: =COUNTIF(D41:AQ41,"P") -> 0 | AW41: =+AS41/$AH$1 -> 0 | AX41: =+AT41/$AH$1 -> 0 | AY41: =+AU41/$AH$1 -> 0 | AZ41: =+AV41/$AH$1 -> 0
A42: =IF(Asis1Tri!A42=0,"",Asis1Tri!A42) | B42: =IF(Asis1Tri!B42=0,"",Asis1Tri!B42) | AR42: 0 | AS42: =COUNTIF(D42:AQ42,"A") -> 0 | AT42: =COUNTIF(D42:AQ42,"L") -> 0 | AU42: =COUNTIF(D42:AQ42,"F") -> 0 | AV42: =COUNTIF(D42:AQ42,"P") -> 0 | AW42: =+AS42/$AH$1 -> 0 | AX42: =+AT42/$AH$1 -> 0 | AY42: =+AU42/$AH$1 -> 0 | AZ42: =+AV42/$AH$1 -> 0
A43: =IF(Asis1Tri!A43=0,"",Asis1Tri!A43) | B43: =IF(Asis1Tri!B43=0,"",Asis1Tri!B43) | AR43: 0 | AS43: =COUNTIF(D43:AQ43,"A") -> 0 | AT43: =COUNTIF(D43:AQ43,"L") -> 0 | AU43: =COUNTIF(D43:AQ43,"F") -> 0 | AV43: =COUNTIF(D43:AQ43,"P") -> 0 | AW43: =+AS43/$AH$1 -> 0 | AX43: =+AT43/$AH$1 -> 0 | AY43: =+AU43/$AH$1 -> 0 | AZ43: =+AV43/$AH$1 -> 0
A44: =IF(Asis1Tri!A44=0,"",Asis1Tri!A44) | B44: =IF(Asis1Tri!B44=0,"",Asis1Tri!B44) | AR44: 0 | AS44: =COUNTIF(D44:AQ44,"A") -> 0 | AT44: =COUNTIF(D44:AQ44,"L") -> 0 | AU44: =COUNTIF(D44:AQ44,"F") -> 0 | AV44: =COUNTIF(D44:AQ44,"P") -> 0 | AW44: =+AS44/$AH$1 -> 0 | AX44: =+AT44/$AH$1 -> 0 | AY44: =+AU44/$AH$1 -> 0 | AZ44: =+AV44/$AH$1 -> 0
A45: =IF(Asis1Tri!A45=0,"",Asis1Tri!A45) | B45: =IF(Asis1Tri!B45=0,"",Asis1Tri!B45) | AR45: 0 | AS45: =COUNTIF(D45:AQ45,"A") -> 0 | AT45: =COUNTIF(D45:AQ45,"L") -> 0 | AU45: =COUNTIF(D45:AQ45,"F") -> 0 | AV45: =COUNTIF(D45:AQ45,"P") -> 0 | AW45: =+AS45/$AH$1 -> 0 | AX45: =+AT45/$AH$1 -> 0 | AY45: =+AU45/$AH$1 -> 0 | AZ45: =+AV45/$AH$1 -> 0
... A56: =IF(Asis1Tri!A56=0,"",Asis1Tri!A56) | B56: =IF(Asis1Tri!B56=0,"",Asis1Tri!B56) | AR56: 0 | AS56: =COUNTIF(D56:AQ56,"A") -> 0 | AT56: =COUNTIF(D56:AQ56,"L") -> 0 | AU56: =COUNTIF(D56:AQ56,"F") -> 0 | AV56: =COUNTIF(D56:AQ56,"P") -> 0 | AW56: =+AS56/$AH$1 -> 0 | AX56: =+AT56/$AH$1 -> 0 | AY56: =+AU56/$AH$1 -> 0 | AZ56: =+AV56/$AH$1 -> 0

Sheet CalendEscol
G1: CALENDARIO PLURINACIONAL DE FECHAS CÍVICAS
G2: FECHA | H2: CONMEMORACIÓN
G3: 1ro. de Enero | H3:  Año nuevo, celebrado en todo el mundo.  El 1 de Enero de 1574 se realiza la segunda fundación de Cochabamba por orden del Capitán Sebastián Barba de Padilla, en el valle de Khochapampa (hoy Cochabamba a orillas del río Kunturillo, que posteriormente fue trasladada a la región que hoy ocupa, por mandato del Virrey Toledo a Don Manuel Ascencio Padilla, con el nombre de Villa Oropeza”
G4: 22 de Enero | H4:  Fundación del Estado Plurinacional de Bolivia.
G5: 24 de Enero | H5:  La “Fiesta de Ekeko” (Dios de la Abundancia) tiene lugar el 24 de Enero, y miles de bolivianos acuden a la tradicional “Feria de la Alasita” en las ciudades de La Paz y Al Alto a comprar figuritas artesanas para que sus deseos se hagan realidad. Esta tradición forma parte del patrimonio cultural de Bolivia.
G6: 2 de Febrero | H6:  Se celebra la festividad de la Virgen de Copacabana, nombrada como Patrona y General de la policía Nacional celebrada en La Paz.
G7: 3 de Febrero | H7:  Nacimiento del Mariscal Antonio José de Sucre, libertador de Ecuador quien convocó a la primera Asamblea Constituyente a las provincias del AltoPerú. Nació el 3 de febrero de 1795 en Cumaná – Venezuela
G8: 9 de Febrero | H8:  Fundación de la ciudad de Cobija, hoy capital del departamento de Pando, en 1906.
G9: 10 de Febrero | H9:  Revolución de Oruro, conmemorado al primer grito libertario de Sebastián Pagador de 1781. (Cabe aclarar que dicha ciudad se fundo el 1ro de Noviembre de 1606).
G10: 13 de Febrero | H10:  Festividad de la Virgen de Socavon, patrona de los mineros.
G11: 26 de Febrero | H11:  Fundación de la ciudad Santa Cruz de la Sierra, por Don Ñuflo de Chávez quien dio el nombre de “Santa Cruz” en homenaje a su ciudad natal en España y Sierra por encontrarse a las cercana a las serranías de Chiquitos (1561)
G12: 8 de Marzo | H12:  El Día Internacional de la Mujer Trabajadora o Día Internacional de la Mujer, conmemora la lucha de la mujer por su participación, en pie de igualdad con el hombre, en la sociedad y en su desarrollo íntegro como persona. Se celebra el día 8 de marzo.
G13: 19 de Marzo | H13:  El 19 de marzo es un día especial en el país con múltiples festejos: Se celebra el Día del Padre. En Bolivia Se instituyo bajo la presidencia del General Hugo Suárez. Es también el día del radialista, una actividad peculiar del profesional que acompaña a los hogares en los momentos de tedio. Finalmente, es el día del carpintero, uno de los oficios más antiguos de la humanidad y una tarea reservada a pocos que gustan del arte manual. Cada vez son menos estos artesanos que llevan la imagen de San José como patrono.
... G84: 25 de Diciembre | H84:  Navidad

Sheet CUAD.SEG.
A1: CUADERNO DE SEGUIMIENTO | P1: =+'1erT'!A4 -> CURSO: 2ndo A Secundaria
A2: FECHA | B2: MATERIA | C2: APELLIDOS Y NOMBRE | D2: OBSERVACION ( MARCA CON EL No. 1 ) | Q2: PROFESOR
D3: FALTA | E3: LLEGA TARDE | F3: NO ATIENDE | G3: HABLA MUCHO | H3: NO TRAJO MATERIAL | I3: NO HIZO LA TAREA | J3: TAREA INCOMPLETA | K3: NO TRABAJA EN CLASE | L3: FALTO A EXAMEN | M3: HACE OTRAS MATERIAS | N3: USO DE CELULAR NO AUT. | O3: OTRAS | P3: ACLARACION
B4: =IF(A4="","",'1erT'!$A$8) | Q4: =IF(A4="","",'1erT'!$A$6)
B5: =IF(A5="","",'1erT'!$A$8) | Q5: =IF(A5="","",'1erT'!$A$6)
B6: =IF(A6="","",'1erT'!$A$8) | Q6: =IF(A6="","",'1erT'!$A$6)
B7: =IF(A7="","",'1erT'!$A$8) | Q7: =IF(A7="","",'1erT'!$A$6)
B8: =IF(A8="","",'1erT'!$A$8) | Q8: =IF(A8="","",'1erT'!$A$6)
B9: =IF(A9="","",'1erT'!$A$8) | Q9: =IF(A9="","",'1erT'!$A$6)
B10: =IF(A10="","",'1erT'!$A$8) | Q10: =IF(A10="","",'1erT'!$A$6)
B11: =IF(A11="","",'1erT'!$A$8) | Q11: =IF(A11="","",'1erT'!$A$6)
B12: =IF(A12="","",'1erT'!$A$8) | Q12: =IF(A12="","",'1erT'!$A$6)
B13: =IF(A13="","",'1erT'!$A$8) | Q13: =IF(A13="","",'1erT'!$A$6)
B14: =IF(A14="","",'1erT'!$A$8) | Q14: =IF(A14="","",'1erT'!$A$6)
B15: =IF(A15="","",'1erT'!$A$8) | Q15: =IF(A15="","",'1erT'!$A$6)
... B100: =IF(A100="","",'1erT'!$A$8) | Q100: =IF(A100="","",'1erT'!$A$6)
