Workbook

Sheet proforma
A5: FACTURA PROFORMA | M5: No. : | N5: RAC-105/2014
A6: OBRA : | C6: Edificio LUSSO | L6: Fecha : | M6: 41957
A7: CLIENTE : | C7: Sr. Henry Maldonado | L7: Teléfono:
A8: Item | B8: Cant. | C8: Medidas | F8: Superficie | H8: Tipo de | I8: Material | M8: P R E C I O $us
C9: Ancho | D9: x | E9: Alto | F9: Cant. | G9: Unid. | H9: Cerramiento | M9: x Mt² | N9: T O T A L
A10: 1 | B10: 1 | F10: 269.98 | G10: Mt² | H10: Puerta / Ventanas Corredizas | I10: PUERTA/VENTANAS CORREDIZAS DE 4 HOJAS: Montadas sobre carpintería de aluminio natural con vidrio Templado de Seguridad Incoloro de 10mm de espesor en puerta/ventanas corredizas de 4 hojas, accesorios y mano de obra altamente calificada. | M10: =+N10/F10 -> 70.597674 | N10: 19059.96
A11: 2 | B11: 1 | F11: 55.92 | G11: Mt² | H11: Ventanas Corredizas | I11: VENTANAS CORREDIZAS DE 2 HOJAS: Montadas sobre carpintería de aluminio natural con vidrio Templado de Seguridad Incoloro de 8mm de espesor en ventanas corredizas de 2 hojas, accesorios y mano de obra altamente calificada. | M11: =+N11/F11 -> 89.521638 | N11: 5006.05
A12: 3 | B12: 1 | F12: 18.52 | G12: Mt² | H12: Ventanas Corredizas | I12: PANOS FIJOS 10 MM: Montados sobre carpintería de aluminio natural con vidrio Templado de Seguridad Incoloro de 10mm de espesor en panos fijos, accesorios y mano de obra altamente calificada. | M12: =+N12/F12 -> 51.467063 | N12: 953.17
A13: 4 | B13: 1 | F13: 67.98 | G13: Mt² | H13: Fachada tipo piel de vidrio | I13: PANOS FIJOS 8 MM: Montados sobre carpintería de aluminio natural con vidrio Templado de Seguridad Incoloro de 8mm de espesor en panos fijos, accesorios y mano de obra altamente calificada. | M13: =+N13/F13 -> 53.781259 | N13: 3656.05
A14: 5 | B14: 1 | F14: 16.97 | G14: Mt² | H14: Fachada tipo celosia | I14: PUERTAS BATIENTES DOBLES : Montadas sobre carpintería de aluminio natural con vidrio Templado de Seguridad Incoloro de 10mm de espesor en puertabatientes dobles, accesorios y mano de obra altamente calificada. | M14: =+N14/F14 -> 85.923984 | N14: 1458.13
A17: TOTAL | F17: =SUM(F10:F16) -> 429.37 | G17: Mt² | H17: PRECIO CON IMPUESTOS DE LEY | L17: $us | M17: =+N17/F17 -> 70.180404 | N17: =SUM(N10:N16) -> 30133.36
A18: Forma de pago: | E18: 80% a la firma del contrato, | J18: Son : Treinta Mil Ciento Treinta y Tres 36/100 DOLARES AMERICANOS
E19: 20% a la entrega de la obra
A21: Plazo de Entrega: | E21: 30 días calendario
E22: Plazo computable a partir de la
E23: entrega de vanos terminados. | J23: Ing. Rafael Antequera Caballero
A24: Validez de la oferta: | E24: 30 días | J24: GERENTE

Sheet Costo M.P.yMat.
C1: ANALISIS DE COSTOS Y DETERMINACION DE PRECIOS DE VENTA (/i1,1/,84)
A3: CODIGO | B3: CODIGO | C3: PRODUCTO | D3: cod | E3: Unidad | F3: Precio de | G3: Precio de | H3: Costo oper. | J3: Proveedor
B4: ORIGEN | F4: venta CF | G4: venta SF | H4: CF | I4: SF
F5: $us/unid. | G5: $us/unid. | H5: $us/unid. | I5: $us/unid.
C6: MATERIALES COMUNES PARA EL VIDRIO TEMPLADO Y LA CARPINTERIA DE ALUMINIO
A7: M1 | C7: Silicona transparente, blanca o negra | D7: 1 | E7: Tubo | F7: =ROUNDUP(H7*0.87*1.1/0.84,2) -> 3.31 | G7: =ROUNDUP(I7*1.1,2) -> 3.19 | H7: 2.9 | I7: 2.9 | J7: MAROL 20 Bs. | K7: =(-G7+F7)/F7 -> 0.036253776
A8: M2 | C8: Silicona estructural | D8: 2 | E8: Tubo | F8: =ROUNDUP(H8*0.87*1.1/0.84,2) -> 7.11 | G8: =ROUNDUP(I8*1.1,2) -> 6.59 | H8: 6.24 | I8: =+H8*0.96 -> 5.9904 | J8: MAROL 20 Bs. | K8: =(-G8+F8)/F8 -> 0.073136428
A9: M3 | C9: Cinta masking 1/2 " (rollo de 20) | D9: 3 | E9: Rollo | F9: =ROUNDUP(H9*0.87*1.1/0.84,2) -> 0.75 | G9: =ROUNDUP(I9*1.1,2) -> 0.72 | H9: 0.65 | I9: 0.65 | J9: Ribepar | K9: =(-G9+F9)/F9 -> 0.04
A10: M4 | C10: "U" 15 x 15 ( 16x16 ) - 0,159 Kg/Mt. | D10: 4 | E10: Mt lineal | F10: =ROUNDUP(H10*0.87*1.1/0.84,2) -> 0.9 | G10: =ROUNDUP(I10*1.1,2) -> 0.87 | H10: =+N10/6 -> 0.78583333 | I10: =+H10 -> 0.78583333 | J10: Alvicruz 4,1 + 15% | K10: =(-G10+F10)/F10 -> 0.033333333 | L10: =6*0.159 -> 0.954 | M10: Kgr./barra | N10: =4.1*1.15 -> 4.715 | O10: $us./barra | P10: 4 puesto S.C.
A11: M5 | C11: "U" 15 x 25 - 0,20 Kg/Mt. | D11: 5 | E11: Mt lineal | F11: =ROUNDUP(H11*0.87*1.1/0.84,2) -> 1.29 | G11: =ROUNDUP(I11*1.1,2) -> 1.25 | H11: =+N11/6 -> 1.1308333 | I11: =+H11 -> 1.1308333 | J11: Alvicruz 5,9 + 15% | K11: =(-G11+F11)/F11 -> 0.031007752 | L11: =6*0.2 -> 1.2 | M11: Kgr./barra | N11: =5.9*1.15 -> 6.785 | O11: $us./barra | P11: 5,8 puesto S.C.
A12: M6 | C12: Tubo 50 x 50 - 1,037 Kg/Mt. | D12: 6 | E12: Mt lineal | F12: =ROUNDUP(H12*0.87*1.1/0.84,2) -> 9.15 | G12: =ROUNDUP(I12*1.1,2) -> 8.48 | H12: =+N12/6 -> 8.0258615 | I12: =0.96*H12 -> 7.704827 | J12: Alcoa 6,73 + 15% | K12: =(-G12+F12)/F12 -> 0.073224044 | L12: =6*1.037 -> 6.222 | M12: Kgr./barra | N12: =6.73*1.15*L12 -> 48.155169 | O12: $us./barra
A13: M7 | C13: Tubo 40 x 40 - 0,624 Kg/Mt. | D13: 7 | E13: Mt lineal | F13: =ROUNDUP(H13*0.87*1.1/0.84,2) -> 5.51 | G13: =ROUNDUP(I13*1.1,2) -> 5.1 | H13: =+N13/6 -> 4.829448 | I13: =0.96*H13 -> 4.6362701 | J13: Alcoa 6,73 + 15% | K13: =(-G13+F13)/F13 -> 0.074410163 | L13: =6*0.624 -> 3.744 | M13: Kgr./barra | N13: =6.73*1.15*L13 -> 28.976688 | O13: $us./barra
A14: M8 | C14: Tubo 80 x 40 - 0,948 Kg/Mt. | D14: 8 | E14: Mt lineal | F14: =ROUNDUP(H14*0.87*1.1/0.84,2) -> 5.97 | G14: =ROUNDUP(I14*1.1,2) -> 5.76 | H14: =+N14/6 -> 5.2325 | I14: =+H14 -> 5.2325 | J14: Alvicruz 27,30 + 15% | K14: =(-G14+F14)/F14 -> 0.035175879 | L14: =6*0.948 -> 5.688 | M14: Kgr./barra | N14: =27.3*1.15 -> 31.395 | O14: $us./barra | P14: 26,80 puesto S.C.
A15: M9 | C15: Tubo 60 x 30 - 0,705 Kg/Mt. | D15: 9 | E15: Mt lineal | F15: =ROUNDUP(H15*0.87*1.1/0.84,2) -> 4.02 | G15: =ROUNDUP(I15*1.1,2) -> 3.88 | H15: =+N15/6 -> 3.5266667 | I15: =+H15 -> 3.5266667 | J15: Alvicruz 18,4 + 15% | K15: =(-G15+F15)/F15 -> 0.034825871 | L15: =6*0.705 -> 4.23 | M15: Kgr./barra | N15: =18.4*1.15 -> 21.16 | O15: $us./barra | P15: 18 puesto S.C.
A16: M10 | C16: Tubo 100 x 50 - 1,560 Kg/Mt. | D16: 10 | E16: Mt lineal | F16: =ROUNDUP(H16*0.87*1.1/0.84,2) -> 8.3 | G16: =ROUNDUP(I16*1.1,2) -> 8.02 | H16: =+N16/6 -> 7.2833333 | I16: =+H16 -> 7.2833333 | J16: Alvicruz 38 + 15% | K16: =(-G16+F16)/F16 -> 0.03373494 | L16: =6*0.786 -> 4.716 | M16: Kgr./barra | N16: =38*1.15 -> 43.7 | O16: $us./barra | P16: 37,50 puesto S.C.
A17: M11 | C17: Felpa | D17: 11 | E17: Mt lineal | F17: =ROUNDUP(H17*0.87*1.1/0.84,2) -> 0.18 | G17: =ROUNDUP(I17*1.1,2) -> 0.17 | H17: 0.15 | I17: 0.15 | J17: Indalum | K17: =(-G17+F17)/F17 -> 0.055555556
A18: M12 | C18: Remache 4 x 10 | D18: 12 | E18: Pza. | F18: =ROUNDUP(H18*0.87*1.1/0.84,2) -> 0.04 | G18: =ROUNDUP(I18*1.1,2) -> 0.04 | H18: 0.03 | I18: 0.03 | J18: Perbol | K18: =(-G18+F18)/F18 -> 0
A19: M13 | C19: Tarugos No. 6 | D19: 13 | E19: Pza. | F19: =ROUNDUP(H19*0.87*1.1/0.84,2) -> 0.04 | G19: =ROUNDUP(I19*1.1,2) -> 0.04 | H19: 0.03 | I19: 0.03 | J19: Perbol | K19: =(-G19+F19)/F19 -> 0
A20: M14 | C20: Tornillos 8 x 1 1/2 | D20: 14 | E20: Pza. | F20: =ROUNDUP(H20*0.87*1.1/0.84,2) -> 0.04 | G20: =ROUNDUP(I20*1.1,2) -> 0.04 | H20: 0.03 | I20: 0.03 | J20: Perbol | K20: =(-G20+F20)/F20 -> 0
A21: M15 | C21: Tornillos 8 x 1/2 | D21: 15 | E21: Pza. | F21: =ROUNDUP(H21*0.87*1.1/0.84,2) -> 0.03 | G21: =ROUNDUP(I21*1.1,2) -> 0.03 | H21: 0.02 | I21: 0.02 | J21: Perbol | K21: =(-G21+F21)/F21 -> 0
A22: M16 | C22: Tubo Galvanizado de 4" | D22: 16 | E22: Mt lineal | F22: =ROUNDUP(H22*0.87*1.1/0.84,2) -> 29.91 | G22: =ROUNDUP(I22*1.1,2) -> 27.72 | H22: =150*1.05/6 -> 26.25 | I22: =+H22*0.96 -> 25.2 | J22: Las Lomas ( 150+5%uniones) | K22: =(-G22+F22)/F22 -> 0.073219659
C23: PARA EL VIDRIO TEMPLADO | N23: COCHABAMBA | P23: SANTA PUEJ
A24: V1 | C24: Vidrio Templado 10mm Incoloro | D24: 17 | E24: Mt² | F24: =ROUNDUP(H24*0.87*1.1/0.84,2) -> 35.89 | G24: =ROUNDUP(I24*1.1,2) -> 34.65 | H24: =30*1.05 -> 31.5 | I24: =30*1.05 -> 31.5 | J24: MURANO 26 + 5%desp. | K24: =(-G24+F24)/F24 -> 0.034550014 | M24: =ROUNDUP(N24/6.97,2) -> 25.83 | N24: 180 | O24: 175+4caloi | P24: =+Q24*6.97 -> 209.1 | Q24: 30
A25: V2 | C25: Vidrio Templado 8mm Incoloro | D25: 18 | E25: Mt² | F25: =ROUNDUP(H25*0.87*1.1/0.84,2) -> 34.7 | G25: =ROUNDUP(I25*1.1,2) -> 33.5 | H25: =29*1.05 -> 30.45 | I25: =29*1.05 -> 30.45 | J25: MURANO 25 + 5% desp | K25: =(-G25+F25)/F25 -> 0.034582133 | M25: =ROUNDUP(N25/6.97,2) -> 25.11 | N25: 175 | O25: 170+4caloi | P25: =+Q25*6.97 -> 202.13 | Q25: 29
A26: V3 | C26: Vidrio Templado 6mm Incoloro | D26: 19 | E26: Mt² | F26: =ROUNDUP(H26*0.87*1.1/0.84,2) -> 29.63 | G26: =ROUNDUP(I26*1.1,2) -> 27.5 | H26: 26 | I26: 25 | J26: Revibol | K26: =(-G26+F26)/F26 -> 0.071886601
A27: V4 | C27: Vidrio Templado 5mm Incoloro | D27: 20 | E27: Mt² | F27: =ROUNDUP(H27*0.87*1.1/0.84,2) -> 27.35 | G27: =ROUNDUP(I27*1.1,2) -> 26.4 | H27: 24 | I27: 24 | J27: Revibol | K27: =(-G27+F27)/F27 -> 0.034734918
A28: V5 | C28: Vidrio Templado 4mm Incoloro | D28: 21 | E28: Mt² | F28: =ROUNDUP(H28*0.87*1.1/0.84,2) -> 23.93 | G28: =ROUNDUP(I28*1.1,2) -> 23.1 | H28: 21 | I28: 21 | J28: Revibol | K28: =(-G28+F28)/F28 -> 0.034684496
A29: V6 | C29: Vidrio Templado 10mm Color | D29: 22 | E29: Mt² | F29: =ROUNDUP(H29*0.87*1.1/0.84,2) -> 46.66 | G29: =ROUNDUP(I29*1.1,2) -> 45.05 | H29: =39*1.05 -> 40.95 | I29: =39*1.05 -> 40.95 | J29: MURANO 39 + 5% desp. | K29: =(-G29+F29)/F29 -> 0.034504929 | M29: =+N29/6.96 -> 38.793103 | N29: 270
A30: V7 | C30: Vidrio Templado 8mm Color | D30: 23 | E30: Mt² | F30: =ROUNDUP(H30*0.87*1.1/0.84,2) -> 45.46 | G30: =ROUNDUP(I30*1.1,2) -> 43.89 | H30: =38*1.05 -> 39.9 | I30: =38*1.05 -> 39.9 | J30: MURANO 38 + 5% desp. | K30: =(-G30+F30)/F30 -> 0.034535856 | M30: =+N30/6.96 -> 37.356322 | N30: 260
A31: V8 | C31: Vidrio Templado 6mm Color | D31: 24 | E31: Mt² | F31: =ROUNDUP(H31*0.87*1.1/0.84,2) -> 47.85 | G31: =ROUNDUP(I31*1.1,2) -> 44 | H31: 42 | I31: 40 | J31: Revibol | K31: =(-G31+F31)/F31 -> 0.08045977
A32: V9 | C32: Vidrio Templado 5mm Color | D32: 25 | E32: Mt² | F32: =ROUNDUP(H32*0.87*1.1/0.84,2) -> 45.58 | G32: =ROUNDUP(I32*1.1,2) -> 41.8 | H32: 40 | I32: 38 | J32: Revibol | K32: =(-G32+F32)/F32 -> 0.08293111
A33: V10 | C33: Vidrio Templado 4mm Color | D33: 26 | E33: Mt² | F33: =ROUNDUP(H33*0.87*1.1/0.84,2) -> 43.3 | G33: =ROUNDUP(I33*1.1,2) -> 39.6 | H33: 38 | I33: 36 | J33: Revibol | K33: =(-G33+F33)/F33 -> 0.085450346
A34: V11 | C34: Vidrio Templado Catedral 10mm Incoloro | D34: 27 | E34: Mt² | F34: =ROUNDUP(H34*0.87*1.1/0.84,2) -> 50.13 | G34: =ROUNDUP(I34*1.1,2) -> 48.4 | H34: 44 | I34: 44 | J34: Revibol | K34: =(-G34+F34)/F34 -> 0.034510273
A35: V12 | C35: Vidrio Templado Catedral 10mm Color | D35: 28 | E35: Mt² | F35: =ROUNDUP(H35*0.87*1.1/0.84,2) -> 52.41 | G35: =ROUNDUP(I35*1.1,2) -> 50.6 | H35: 46 | I35: 46 | J35: Revibol | K35: =(-G35+F35)/F35 -> 0.034535394 | P35: nuevos
A36: V13 | C36: Cabezal, Tapa, Guia, Tapa-guia 1.998 Kg/Mt | D36: 29 | E36: Juego | F36: =ROUNDUP(H36*0.87*1.1/0.84,2) -> 10.8 | G36: =ROUNDUP(I36*1.1,2) -> 10.43 | H36: =+N36/6 -> 9.4779167 | I36: =+H36 -> 9.4779167 | J36: Alvicruz 49,45+ 15%desp. | K36: =(-G36+F36)/F36 -> 0.034259259 | L36: =6*1.998 -> 11.988 | M36: Kgr./juego | N36: =49.45*1.15 -> 56.8675 | O36: $us./barra | P36: 47,45 puesto S.C.
A37: V14 | C37: Vedapres 001 - h de aluminio | D37: 30 | E37: Barra | F37: =ROUNDUP(H37*0.87*1.1/0.84,2) -> 9.83 | G37: =ROUNDUP(I37*1.1,2) -> 9.49 | H37: =+N37 -> 8.625 | I37: =+H37 -> 8.625 | J37: Alvicruz 7,25+ 15%desp. | K37: =(-G37+F37)/F37 -> 0.034587996 | L37: =6*0.257 -> 1.542 | M37: Kgr./barra | N37: =7.5*1.15 -> 8.625 | O37: $us./barra | P37: 7,15 puesto S.C.
A38: V15 | C38: Vedapres 002 - u de aluminio | D38: 31 | E38: Barra | F38: =ROUNDUP(H38*0.87*1.1/0.84,2) -> 5.9 | G38: =ROUNDUP(I38*1.1,2) -> 5.7 | H38: =+N38 -> 5.175 | I38: =+H38 -> 5.175 | J38: Alvicruz 4,30+ 15%desp. | K38: =(-G38+F38)/F38 -> 0.033898305 | L38: =6*0.151 -> 0.906 | M38: Kgr./barra | N38: =4.5*1.15 -> 5.175 | O38: $us./barra | P38: 4,20 puesto S.C.
A39: V16 | C39: Vedapres 003 - H (2,10mt/barra) Inc. | D39: 32 | E39: Barra | F39: =ROUNDUP(H39*0.87*1.1/0.84,2) -> 5.99 | G39: =ROUNDUP(I39*1.1,2) -> 5.5 | H39: =+I39*1.05 -> 5.25 | I39: 5 | J39: Florencio Rivero | K39: =(-G39+F39)/F39 -> 0.081803005
A40: V17 | C40: Vedapres 001 - h (2,10mt/barra) Bce. | D40: 33 | E40: Barra | F40: =ROUNDUP(H40*0.87*1.1/0.84,2) -> 5.99 | G40: =ROUNDUP(I40*1.1,2) -> 5.5 | H40: =+I40*1.05 -> 5.25 | I40: 5 | J40: Florencio Rivero | K40: =(-G40+F40)/F40 -> 0.081803005
A41: V18 | C41: Vedapres 002 - Uc (2,10mt/barra) Bce. | D41: 34 | E41: Barra | F41: =ROUNDUP(H41*0.87*1.1/0.84,2) -> 5.99 | G41: =ROUNDUP(I41*1.1,2) -> 5.5 | H41: =+I41*1.05 -> 5.25 | I41: 5 | J41: Florencio Rivero | K41: =(-G41+F41)/F41 -> 0.081803005
A42: V19 | C42: Vedapres 003 - H (2,10mt/barra) Bce. | D42: 35 | E42: Barra | F42: =ROUNDUP(H42*0.87*1.1/0.84,2) -> 5.99 | G42: =ROUNDUP(I42*1.1,2) -> 5.5 | H42: =+I42*1.05 -> 5.25 | I42: 5 | J42: Florencio Rivero | K42: =(-G42+F42)/F42 -> 0.081803005
A43: V20 | C43: Freno Hidráulico DORMA | D43: 36 | E43: Pza. | F43: =ROUNDUP(H43*0.87*1.1/0.84,2) -> 101.69 | G43: =ROUNDUP(I43*1.1,2) -> 93.5 | H43: =+I43*1.05 -> 89.25 | I43: 85 | J43: Florencio Rivero | K43: =(-G43+F43)/F43 -> 0.080538893
A44: V21 | C44: Freno Hidráulico HyH | D44: 37 | E44: Pza. | F44: =ROUNDUP(H44*0.87*1.1/0.84,2) -> 79.75 | G44: =ROUNDUP(I44*1.1,2) -> 77 | H44: 70 | I44: 70 | J44: Cristembo La Paz | K44: =(-G44+F44)/F44 -> 0.034482759
A45: V22 | C45: Manijones de vidrio | D45: 38 | E45: Pza. | F45: =ROUNDUP(H45*0.87*1.1/0.84,2) -> 3.42 | G45: =ROUNDUP(I45*1.1,2) -> 3.3 | H45: 3 | I45: 3 | J45: Revibol | K45: =(-G45+F45)/F45 -> 0.035087719
A46: V23 | C46: 1003 ( cromado ó bronce viejo ) | D46: 39 | E46: Pza. | F46: =ROUNDUP(H46*0.87*1.1/0.84,2) -> 2.91 | G46: =ROUNDUP(I46*1.1,2) -> 2.81 | H46: =+M46+0.15 -> 2.55 | I46: =+H46 -> 2.55 | J46: Alvicruz + 0,15 transp | K46: =(-G46+F46)/F46 -> 0.034364261 | M46: 2.4 | N46: puestos S.C.
A47: V24 | C47: 1013 ( cromado ó bronce viejo ) | D47: 40 | E47: Pza. | F47: =ROUNDUP(H47*0.87*1.1/0.84,2) -> 3.59 | G47: =ROUNDUP(I47*1.1,2) -> 3.47 | H47: =+M47+0.15 -> 3.15 | I47: =+H47 -> 3.15 | J47: Alvicruz + 0,15 transp | K47: =(-G47+F47)/F47 -> 0.033426184 | M47: 3 | N47: puestos S.C.
A48: V25 | C48: 1038 ( cromado ó bronce viejo ) | D48: 41 | E48: Pza. | F48: =ROUNDUP(H48*0.87*1.1/0.84,2) -> 1.32 | G48: =ROUNDUP(I48*1.1,2) -> 1.27 | H48: =+M48+0.15 -> 1.15 | I48: =+H48 -> 1.15 | J48: Alvicruz + 0,15 transp | K48: =(-G48+F48)/F48 -> 0.037878788 | M48: 1 | N48: puestos S.C.
A49: V26 | C49: 1038-C ( cromado ó bronce viejo ) | D49: 42 | E49: Pza. | F49: =ROUNDUP(H49*0.87*1.1/0.84,2) -> 1.32 | G49: =ROUNDUP(I49*1.1,2) -> 1.27 | H49: =+M49+0.15 -> 1.15 | I49: =+H49 -> 1.15 | J49: Alvicruz + 0,15 transp | K49: =(-G49+F49)/F49 -> 0.037878788 | M49: 1 | N49: puestos S.C.
A50: V27 | C50: 1101 ( cromado ó bronce viejo ) | D50: 43 | E50: Pza. | F50: =ROUNDUP(H50*0.87*1.1/0.84,2) -> 8.72 | G50: =ROUNDUP(I50*1.1,2) -> 8.42 | H50: =+M50+0.15 -> 7.65 | I50: =+H50 -> 7.65 | J50: Alvicruz + 0,15 transp | K50: =(-G50+F50)/F50 -> 0.03440367 | M50: 7.5 | N50: puestos S.C.
A51: V28 | C51: 1103 ( cromado ó bronce viejo ) | D51: 44 | E51: Pza. | F51: =ROUNDUP(H51*0.87*1.1/0.84,2) -> 9.86 | G51: =ROUNDUP(I51*1.1,2) -> 9.52 | H51: =+M51+0.15 -> 8.65 | I51: =+H51 -> 8.65 | J51: Alvicruz + 0,15 transp | K51: =(-G51+F51)/F51 -> 0.034482759 | M51: 8.5 | N51: puestos S.C.
A52: V29 | C52: 1114 ( cromado ó bronce viejo ) | D52: 45 | E52: Pza. | F52: =ROUNDUP(H52*0.87*1.1/0.84,2) -> 7.92 | G52: =ROUNDUP(I52*1.1,2) -> 7.65 | H52: =+M52+0.15 -> 6.95 | I52: =+H52 -> 6.95 | J52: Alvicruz + 0,15 transp | K52: =(-G52+F52)/F52 -> 0.034090909 | M52: 6.8 | N52: puestos S.C.
A53: V30 | C53: 1115 ( cromado ó bronce viejo ) | D53: 46 | E53: Pza. | F53: =ROUNDUP(H53*0.87*1.1/0.84,2) -> 7.92 | G53: =ROUNDUP(I53*1.1,2) -> 7.65 | H53: =+M53+0.15 -> 6.95 | I53: =+H53 -> 6.95 | J53: Alvicruz + 0,15 transp | K53: =(-G53+F53)/F53 -> 0.034090909 | M53: 6.8 | N53: puestos S.C.
A54: V31 | C54: 1117 ( cromado ó bronce viejo ) | D54: 47 | E54: Pza. | F54: =ROUNDUP(H54*0.87*1.1/0.84,2) -> 24.1 | G54: =ROUNDUP(I54*1.1,2) -> 23.27 | H54: =+M54+0.15 -> 21.15 | I54: =+H54 -> 21.15 | J54: Alvicruz + 0,15 transp | K54: =(-G54+F54)/F54 -> 0.034439834 | M54: 21 | N54: puestos S.C.
A55: V32 | C55: 1123 ( cromado ó bronce viejo ) | D55: 48 | E55: Pza. | F55: =ROUNDUP(H55*0.87*1.1/0.84,2) -> 4.16 | G55: =ROUNDUP(I55*1.1,2) -> 4.02 | H55: =+M55+0.15 -> 3.65 | I55: =+H55 -> 3.65 | J55: Alvicruz + 0,15 transp | K55: =(-G55+F55)/F55 -> 0.033653846 | M55: 3.5 | N55: puestos S.C.
A56: V33 | C56: 1125 ( cromado ó bronce viejo ) | D56: 49 | E56: Pza. | F56: =ROUNDUP(H56*0.87*1.1/0.84,2) -> 0.8 | G56: =ROUNDUP(I56*1.1,2) -> 0.77 | H56: =+M56+0.15 -> 0.7 | I56: =+H56 -> 0.7 | J56: Alvicruz + 0,15 transp | K56: =(-G56+F56)/F56 -> 0.0375 | M56: 0.55 | N56: puestos S.C.
A57: V34 | C57: 1125-A ( cromado ó bronce viejo ) | D57: 50 | E57: Pza. | F57: =ROUNDUP(H57*0.87*1.1/0.84,2) -> 2.68 | G57: =ROUNDUP(I57*1.1,2) -> 2.59 | H57: =+M57+0.15 -> 2.35 | I57: =+H57 -> 2.35 | J57: Alvicruz + 0,15 transp | K57: =(-G57+F57)/F57 -> 0.03358209 | M57: 2.2 | N57: puestos S.C.
... A81: V58 | C81: 1800-C ( cromado ó bronce viejo ) | D81: 74 | E81: Pza. | F81: =ROUNDUP(H81*0.87*1.1/0.84,2) -> 8.15 | G81: =ROUNDUP(I81*1.1,2) -> 7.87 | H81: =+M81+0.15 -> 7.15 | I81: =+H81 -> 7.15 | J81: Alvicruz + 0,15 transp | K81: =(-G81+F81)/F81 -> 0.034355828 | M81: 7 | N81: puestos S.C.
A82: V59 | C82: Mano de obra instalaciòn templado | D82: 75 | E82: Mt² | F82: =ROUNDUP(H82*0.87*1.1/0.84,2) -> 11.4 | G82: =ROUNDUP(I82*1.1,2) -> 11 | H82: 10 | I82: 10 | J82: Hilarion - 8 col.+dis. + 2 tec | K82: =(-G82+F82)/F82 -> 0.035087719 | M82: 8 | N82: Sus/mt2
A83: V60 | C83: Herraje Arana | D83: 76 | E83: Pza. | F83: =ROUNDUP(H83*0.87*1.1/0.84,2) -> 68.36 | G83: =ROUNDUP(I83*1.1,2) -> 66 | H83: 60 | I83: 60 | J83: ALVICRUZ | K83: =(-G83+F83)/F83 -> 0.034523113
A84: V61 | C84: Soporte herraje - tubo | D84: 77 | E84: Pza. | F84: =ROUNDUP(H84*0.87*1.1/0.84,2) -> 22.79 | G84: =ROUNDUP(I84*1.1,2) -> 21.12 | H84: 20 | I84: =+H84*0.96 -> 19.2 | J84: 8D La Paz | K84: =(-G84+F84)/F84 -> 0.073277753
A85: V62 | C85: 1318 ( cromado ó bronce viejo ) | D85: 78 | E85: Pza. | F85: =ROUNDUP(H85*0.87*1.1/0.84,2) -> 16.64 | G85: =ROUNDUP(I85*1.1,2) -> 16.06 | H85: =H65+H63 -> 14.6 | I85: =I65+I63 -> 14.6 | J85: Alvicruz + 0,15 transp | K85: =(-G85+F85)/F85 -> 0.034855769 | M85: =I85-0.15 -> 14.45 | N85: puestos S.C.
A86: V63 | D86: 79
A87: V64 | D87: 80
A88: V65 | D88: 81
A89: V66 | D89: 82
A90: V67 | D90: 83
A91: V68 | D91: 84
A92: V69 | D92: 85
A93: V70 | D93: 86
A94: V71 | D94: 87
C95: MATERIALES Y MATERIA PRIMA PARA LA CARPINTERIA DE ALUMINIO
A96: A1 | C96: Aluminio Anodizado Bronce o Champagne | D96: 88 | E96: Kgr. | F96: =ROUNDUP(H96*0.87*1.1/0.84,2) -> 8.82 | G96: =ROUNDUP(I96*1.1,2) -> 8.18 | H96: =6.73*1.15 -> 7.7395 | I96: =0.96*H96 -> 7.42992 | J96: Alcoa 6,73 + 15% | K96: =(-G96+F96)/F96 -> 0.072562358
A97: A2 | C97: Aluminio Anodizado natural | D97: 89 | E97: Kgr. | F97: =ROUNDUP(H97*0.87*1.1/0.84,2) -> 8.82 | G97: =ROUNDUP(I97*1.1,2) -> 8.18 | H97: =6.73*1.15 -> 7.7395 | I97: =0.96*H97 -> 7.42992 | J97: Alcoa 6,73 + 15% | K97: =(-G97+F97)/F97 -> 0.072562358
A98: A3 | C98: Vidrio Incolororo 3mm | D98: 90 | E98: Mt² | F98: =ROUNDUP(H98*0.87*1.1/0.84,2) -> 10.07 | G98: =ROUNDUP(I98*1.1,2) -> 9.72 | H98: =7.68*1.15 -> 8.832 | I98: =7.68*1.15 -> 8.832 | J98: Oriental 7.68 + 15% | K98: =(-G98+F98)/F98 -> 0.034756703
A99: A4 | C99: Vidrio Incolororo 4mm | D99: 91 | E99: Mt² | F99: =ROUNDUP(H99*0.87*1.1/0.84,2) -> 12.43 | G99: =ROUNDUP(I99*1.1,2) -> 12 | H99: =9.48*1.15 -> 10.902 | I99: =9.48*1.15 -> 10.902 | J99: Oriental 9.48 + 15% | K99: =(-G99+F99)/F99 -> 0.034593725 | L99: =74/(3.66*2.134) -> 9.4744982
A100: A5 | C100: Vidrio Incolororo 5mm | D100: 92 | E100: Mt² | F100: =ROUNDUP(H100*0.87*1.1/0.84,2) -> 14.1 | G100: =ROUNDUP(I100*1.1,2) -> 13.62 | H100: =10.76*1.15 -> 12.374 | I100: =10.76*1.15 -> 12.374 | J100: Oriental 10.76 + 15% | K100: =(-G100+F100)/F100 -> 0.034042553 | L100: =84/(3.66*2.134) -> 10.754836
A101: A6 | C101: Vidrio Incolororo 6mm | D101: 93 | E101: Mt² | F101: =ROUNDUP(H101*0.87*1.1/0.84,2) -> 18.74 | G101: =ROUNDUP(I101*1.1,2) -> 18.09 | H101: =14.3*1.15 -> 16.445 | I101: =14.3*1.15 -> 16.445 | J101: Oriental 14.30 + 15% | K101: =(-G101+F101)/F101 -> 0.034685165 | L101: =110/(3.66*2.134) -> 14.083714
A102: A7 | C102: Vidrio Color 3mm | D102: 94 | E102: Mt² | F102: =ROUNDUP(H102*0.87*1.1/0.84,2) -> 13.22 | G102: =ROUNDUP(I102*1.1,2) -> 12.77 | H102: =10.09*1.15 -> 11.6035 | I102: =10.09*1.15 -> 11.6035 | J102: Garcia 10.09 + 15% | K102: =(-G102+F102)/F102 -> 0.034039334
A103: A8 | C103: Vidrio Color 4mm | D103: 95 | E103: Mt² | F103: =ROUNDUP(H103*0.87*1.1/0.84,2) -> 14.52 | G103: =ROUNDUP(I103*1.1,2) -> 14.02 | H103: =11.08*1.15 -> 12.742 | I103: =11.08*1.15 -> 12.742 | J103: Oriental 11.08 + 15% | K103: =(-G103+F103)/F103 -> 0.034435262
A104: A9 | C104: Vidrio Color 5mm | D104: 96 | E104: Mt² | F104: =ROUNDUP(H104*0.87*1.1/0.84,2) -> 18.78 | G104: =ROUNDUP(I104*1.1,2) -> 18.13 | H104: =14.33*1.15 -> 16.4795 | I104: =14.33*1.15 -> 16.4795 | J104: Garcia 14.33 + 15% | K104: =(-G104+F104)/F104 -> 0.034611289
A105: A10 | C105: Vidrio Color 6mm | D105: 97 | E105: Mt² | F105: =ROUNDUP(H105*0.87*1.1/0.84,2) -> 21.82 | G105: =ROUNDUP(I105*1.1,2) -> 21.07 | H105: =16.65*1.15 -> 19.1475 | I105: =16.65*1.15 -> 19.1475 | J105: Oriental 16.65 + 15% | K105: =(-G105+F105)/F105 -> 0.034372136
A106: A11 | C106: Vidrio catedral claro | D106: 98 | E106: Mt² | F106: =ROUNDUP(H106*0.87*1.1/0.84,2) -> 7.21 | G106: =ROUNDUP(I106*1.1,2) -> 6.68 | H106: =5.5*1.15 -> 6.325 | I106: =+H106*0.96 -> 6.072 | J106: Revibol - 5,55 + 15% | K106: =(-G106+F106)/F106 -> 0.073509015
A107: A12 | C107: Vidrio catedral color | D107: 99 | E107: Mt² | F107: =ROUNDUP(H107*0.87*1.1/0.84,2) -> 9.39 | G107: =ROUNDUP(I107*1.1,2) -> 8.7 | H107: =7.16*1.15 -> 8.234 | I107: =+H107*0.96 -> 7.90464 | J107: Revibol - 7,16 + 15% | K107: =(-G107+F107)/F107 -> 0.073482428
A108: A13 | C108: Vidrio Reflectivo Bronce o Gris 4mm | D108: 100 | E108: Mt² | F108: =ROUNDUP(H108*0.87*1.1/0.84,2) -> 31.45 | G108: =ROUNDUP(I108*1.1,2) -> 29.15 | H108: =24*1.15 -> 27.6 | I108: =+H108*0.96 -> 26.496 | J108: Garcia 24 + 15% | K108: =(-G108+F108)/F108 -> 0.073131955
A109: A14 | C109: Vidrio Reflectivo Bronce o Gris 5mm | D109: 101 | E109: Mt² | F109: =ROUNDUP(H109*0.87*1.1/0.84,2) -> 31.45 | G109: =ROUNDUP(I109*1.1,2) -> 29.15 | H109: =24*1.15 -> 27.6 | I109: =+H109*0.96 -> 26.496 | J109: Garcia 24 + 15% | K109: =(-G109+F109)/F109 -> 0.073131955
A110: A15 | C110: Vidrio Reflectivo Bronce o Gris 6mm | D110: 102 | E110: Mt² | F110: =ROUNDUP(H110*0.87*1.1/0.84,2) -> 0 | G110: =ROUNDUP(I110*1.1,2) -> 0
A111: A16 | C111: Vidrio Reflectivo Azurlite 4mm | D111: 103 | E111: Mt² | F111: =ROUNDUP(H111*0.87*1.1/0.84,2) -> 0 | G111: =ROUNDUP(I111*1.1,2) -> 0
A112: A17 | C112: Vidrio Reflectivo Azurlite 5mm | D112: 104 | E112: Mt² | F112: =ROUNDUP(H112*0.87*1.1/0.84,2) -> 0 | G112: =ROUNDUP(I112*1.1,2) -> 0
A113: A18 | C113: Vidrio Reflectivo Azurlite 6mm | D113: 105 | E113: Mt² | F113: =ROUNDUP(H113*0.87*1.1/0.84,2) -> 48.48 | G113: =ROUNDUP(I113*1.1,2) -> 44.94 | H113: =37*1.15 -> 42.55 | I113: =+H113*0.96 -> 40.848 | J113: Garcia 37 + 15% | K113: =(-G113+F113)/F113 -> 0.073019802
A114: A19 | C114: Cinta dob.cont. 4972 - 3M 1/2"=12mm (rollo de 20) | D114: 106 | E114: Rollo | F114: =ROUNDUP(H114*0.87*1.1/0.84,2) -> 29.85 | G114: =ROUNDUP(I114*1.1,2) -> 27.38 | H114: 26.2 | I114: =+H114*0.95 -> 24.89 | J114: America home center | K114: =(-G114+F114)/F114 -> 0.082747069
A115: A20 | C115: Cinta dob.cont. 4972 - 3M 3/4"=19mm (rollo de 20) | D115: 107 | E115: Rollo | F115: =ROUNDUP(H115*0.87*1.1/0.84,2) -> 47.85 | G115: =ROUNDUP(I115*1.1,2) -> 43.89 | H115: 42 | I115: =+H115*0.95 -> 39.9 | J115: America home center | K115: =(-G115+F115)/F115 -> 0.082758621
A116: A21 | C116: Cinta dob.cont. 4972 - 3M 1"=25mm (rollo de 20) | D116: 108 | E116: Rollo | F116: =ROUNDUP(H116*0.87*1.1/0.84,2) -> 74.06 | G116: =ROUNDUP(I116*1.1,2) -> 67.93 | H116: 65 | I116: =+H116*0.95 -> 61.75 | J116: America home center | K116: =(-G116+F116)/F116 -> 0.082770726
A117: A22 | C117: Felpa | D117: 109 | E117: Mt lineal | F117: =ROUNDUP(H117*0.87*1.1/0.84,2) -> 0.14 | G117: =ROUNDUP(I117*1.1,2) -> 0.14 | H117: 0.12 | I117: =+H117 -> 0.12 | J117: Indalum | K117: =(-G117+F117)/F117 -> 0
A118: A23 | C118: Burlete | D118: 110 | E118: Mt lineal | F118: =ROUNDUP(H118*0.87*1.1/0.84,2) -> 0.35 | G118: =ROUNDUP(I118*1.1,2) -> 0.33 | H118: 0.3 | I118: =+H118 -> 0.3 | J118: Indalum | K118: =(-G118+F118)/F118 -> 0.057142857
A119: A24 | C119: Patin serie 25 | D119: 111 | E119: Pza. | F119: =ROUNDUP(H119*0.87*1.1/0.84,2) -> 1.37 | G119: =ROUNDUP(I119*1.1,2) -> 1.32 | H119: 1.2 | I119: =+H119 -> 1.2 | J119: Indalum | K119: =(-G119+F119)/F119 -> 0.03649635
A120: A25 | C120: Patin serie 20 | D120: 112 | E120: Pza. | F120: =ROUNDUP(H120*0.87*1.1/0.84,2) -> 0.57 | G120: =ROUNDUP(I120*1.1,2) -> 0.55 | H120: 0.5 | I120: =+H120 -> 0.5 | J120: Indalum | K120: =(-G120+F120)/F120 -> 0.035087719
A121: A26 | C121: Patin serie 50 | D121: 113 | E121: Pza. | F121: =ROUNDUP(H121*0.87*1.1/0.84,2) -> 0.46 | G121: =ROUNDUP(I121*1.1,2) -> 0.44 | H121: 0.4 | I121: =+H121 -> 0.4 | J121: Indalum | K121: =(-G121+F121)/F121 -> 0.043478261
A122: A27 | C122: Patin serie 4000 | D122: 114 | E122: Pza. | F122: =ROUNDUP(H122*0.87*1.1/0.84,2) -> 0.46 | G122: =ROUNDUP(I122*1.1,2) -> 0.44 | H122: 0.4 | I122: =+H122 -> 0.4 | J122: Indalum | K122: =(-G122+F122)/F122 -> 0.043478261
A123: A28 | C123: Patin shower door | D123: 115 | E123: Pza. | F123: =ROUNDUP(H123*0.87*1.1/0.84,2) -> 0.57 | G123: =ROUNDUP(I123*1.1,2) -> 0.55 | H123: 0.5 | I123: =+H123 -> 0.5 | J123: Indalum | K123: =(-G123+F123)/F123 -> 0.035087719
A124: A29 | C124: Cierre serie 20 | D124: 116 | E124: Pza. | F124: =ROUNDUP(H124*0.87*1.1/0.84,2) -> 1.83 | G124: =ROUNDUP(I124*1.1,2) -> 1.76 | H124: 1.6 | I124: =+H124 -> 1.6 | J124: Indalum | K124: =(-G124+F124)/F124 -> 0.038251366
...

Sheet Fachada tub.herr.
A2: FACHADA EN VIDRIO TEMPLADO | D2: PF | F2: Total | H2: PF | I2: PF
A3: HERRAJES Y VIENTOS VIDRIO o TUBULAR 4" CON ARANA | D3: =IF(D11=8,"8 mm.","10 mm.") -> 8 mm. | H3: =IF(H11=8,"8 mm.","10 mm.") -> 10 mm. | I3: =IF(I11=8,"8 mm.","10 mm.") -> 10 mm.
A4: DATOS BASE PARA EL ANALISIS | D4: =IF(D10=1,"INCOLORO","COLOR") -> INCOLORO | H4: =IF(H10=1,"INCOLORO","COLOR") -> INCOLORO | I4: =IF(I10=1,"INCOLORO","COLOR") -> INCOLORO
A5: BASE ( Metros ) | D5: 5 | H5: 6 | I5: 6
A6: ALTURA ( Metros ) | D6: 6 | H6: 6 | I6: 6
A7: CANTIDAD DE PIEZAS | D7: 3 | F7: =SUM(H7:IU7) -> 2 | G7: Pzas. | H7: 1 | I7: 1
A8: n = div. Verticales | D8: 5 | H8: 5 | I8: 5
A9: m = div. Horizontales | D9: 6 | H9: 3 | I9: 3
A10: INCOLORO = 1 ; COLOR =2 | D10: 1 | H10: 1 | I10: 1
A11: ESPESOR DEL VIDRIO = 8 ó 10 mm. | D11: 8 | H11: 10 | I11: 10
A12: ESMERILADO = E
A13: VIENTOS VIDRIO ( 1 ) o TUBULAR + ARANA ( 2 ) | D13: 2 | H13: 1 | I13: 2
A14: MODULOS
A15: ANCHO ( metros ) | D15: =+D5/D8 -> 1 | H15: =+H5/H8 -> 1.2 | I15: =+I5/I8 -> 1.2
A16: ALTO ( metros ) | D16: =+D6/D9 -> 1 | H16: =+H6/H9 -> 2 | I16: =+I6/I9 -> 2
A17: Total Precio c/factura | C17: pn | D17: =+D51 -> 13860.894 | F17: =SUM(H17:IU17) -> 6745.438 | G17: $us. | H17: =+H51 -> 2832.455 | I17: =+I51 -> 3912.983
A18: Superficie Mt² | D18: =+D5*D6*D$7+IF(D13=1,D7*D6*(D8-1)*0.2,0) -> 90 | F18: =SUM(H18:IU18) -> 76.8 | G18: Mt² | H18: =+H5*H6*H$7+IF(H13=1,H7*H6*(H8-1)*0.2,0) -> 40.8 | I18: =+I5*I6*I$7+IF(I13=1,I7*I6*(I8-1)*0.2,0) -> 36
A19: Precio con factura en $us / Mt² | D19: =+D17/D18 -> 154.00993 | F19: =+F17/F18 -> 87.831224 | G19: $us./Mt² | H19: =+H17/H18 -> 69.422917 | I19: =+I17/I18 -> 108.69397
A20: Total Precio s/factura | D20: =+D72 -> 13360.197 | F20: =SUM(H20:IU20) -> 6500.558 | G20: $us. | H20: =+H72 -> 2739.399 | I20: =+I72 -> 3761.159
A21: Precio sin factura en $us / Mt² | D21: =+D20/D18 -> 148.44663 | F21: =+F20/F18 -> 84.642682 | G21: $us./Mt² | H21: =+H20/H18 -> 67.142132 | I21: =+I20/I18 -> 104.47664
A22: Materia Prima ( Vidrio ) | D22: =0.9*SUM(D52:D55) -> 2838.807 | F22: =SUM(H22:IU22) -> 2500.0974 | G22: $us. | H22: =0.9*SUM(H52:H55) -> 1327.5711 | I22: =0.9*SUM(I52:I55) -> 1172.5263
A23: Materia Prima ( materiales ) | D23: =0.9*SUM(D57:D69) -> 7789.1976 | F23: =SUM(H23:IU23) -> 1994.8608 | G23: $us. | H23: =0.9*SUM(H57:H69) -> 384.4224 | I23: =0.9*SUM(I57:I69) -> 1610.4384
A24: Mano de obra | D24: =0.9*D56 -> 1846.8 | F24: =SUM(H24:IU24) -> 1575.936 | G24: $us. | H24: =0.9*H56 -> 837.216 | I24: =0.9*I56 -> 738.72
A25: Otros Gastos + Util | D25: =+D17-D24-D23-D22 -> 1386.0894 | F25: =SUM(H25:IU25) -> 674.5438 | G25: $us. | H25: =+H17-H24-H23-H22 -> 283.2455 | I25: =+I17-I24-I23-I22 -> 391.2983
A26: TOTAL | D26: =SUM(D22:D25) -> 13860.894 | F26: =SUM(H26:IU26) -> 6745.438 | G26: $us. | H26: =SUM(H22:H25) -> 2832.455 | I26: =SUM(I22:I25) -> 3912.983
A27: % descuento del con al sin | D27: =+(D17-D20)/D17 -> 0.036122995 | F27: =+(F17-F20)/F17 -> 0.036303054 | H27: =+(H17-H20)/H17 -> 0.032853479 | I27: =+(I17-I20)/I17 -> 0.038800066
A29: DETALLE DE MATERIALES A UTILIZAR
A30: MATERIAL | C30: Unidad | D30: =+D2 -> PF | F30: Cantidad | G30: Unidad | H30: =+H2 -> PF | I30: =+I2 -> PF
A31: Vidrio Templado 10mm Incoloro | C31: Mt² | D31: =IF(D$10=1,IF(D$11=10,((D$6*0.05)+(D$5*D$6))*D$7+IF(D13=1,D$7*D6*(D8-1)*0.2,0),0),0) -> 0 | E31: 17 | F31: =ROUNDUP(SUM(H31:IU31),1) -> 77.4 | G31: Mt² | H31: =IF(H$10=1,IF(H$11=10,((H$6*0.05)+(H$5*H$6))*H$7+IF(H13=1,H$7*H6*(H8-1)*0.2,0),0),0) -> 41.1 | I31: =IF(I$10=1,IF(I$11=10,((I$6*0.05)+(I$5*I$6))*I$7+IF(I13=1,I$7*I6*(I8-1)*0.2,0),0),0) -> 36.3
A32: Vidrio Templado 10mm Color | C32: Mt² | D32: =IF(D$10=2,IF(D$11=10,((D$6*0.05)+(D$5*D$6))*D$7+IF(D13=1,D7*D6*(D8-1)*0.2,0),0),0) -> 0 | E32: 22 | F32: =ROUNDUP(SUM(H32:IU32),1) -> 0 | G32: Mt² | H32: =IF(H$10=2,IF(H$11=10,((H$6*0.05)+(H$5*H$6))*H$7+IF(H13=1,H7*H6*(H8-1)*0.2,0),0),0) -> 0 | I32: =IF(I$10=2,IF(I$11=10,((I$6*0.05)+(I$5*I$6))*I$7+IF(I13=1,I7*I6*(I8-1)*0.2,0),0),0) -> 0
A33: Vidrio Templado 8mm Incoloro | C33: Mt² | D33: =IF(D$10=1,IF(D$11=8,((D$6*0.05)+(D$5*D$6))*D$7+IF(D13=1,D7*D6*(D8-1)*0.2,0),0),0) -> 90.9 | E33: 18 | F33: =ROUNDUP(SUM(H33:IU33),1) -> 0 | G33: Mt² | H33: =IF(H$10=1,IF(H$11=8,((H$6*0.05)+(H$5*H$6))*H$7+IF(H13=1,H7*H6*(H8-1)*0.2,0),0),0) -> 0 | I33: =IF(I$10=1,IF(I$11=8,((I$6*0.05)+(I$5*I$6))*I$7+IF(I13=1,I7*I6*(I8-1)*0.2,0),0),0) -> 0
A34: Vidrio Templado 8mm Color | C34: Mt² | D34: =IF(D$10=2,IF(D$11=8,((D$5*D$6))*D$7+IF(D13=1,D7*D6*(D8-1)*0.2,0),0),0) -> 0 | E34: 23 | F34: =ROUNDUP(SUM(H34:IU34),1) -> 0 | G34: Mt² | H34: =IF(H$10=2,IF(H$11=8,((H$5*H$6))*H$7+IF(H13=1,H7*H6*(H8-1)*0.2,0),0),0) -> 0 | I34: =IF(I$10=2,IF(I$11=8,((I$5*I$6))*I$7+IF(I13=1,I7*I6*(I8-1)*0.2,0),0),0) -> 0
A35: Mano de obra | C35: Mt² | D35: =+D18 -> 90 | E35: 75 | F35: =ROUNDUP(SUM(H35:IU35),1) -> 76.8 | G35: Mt² | H35: =+H18 -> 40.8 | I35: =+I18 -> 36
A36: Silicona transparente, blanca o negra | C36: Tubo | D36: =D7*(4*D5+4*D6+(D8-1)*D6+(D9-1)*D5)/6 -> 46.5 | E36: 1 | F36: =ROUNDUP(SUM(H36:IU36),1) -> 28 | G36: Tubo | H36: =H7*(4*H5+4*H6+(H8-1)*H6+(H9-1)*H5)/6 -> 14 | I36: =I7*(4*I5+4*I6+(I8-1)*I6+(I9-1)*I5)/6 -> 14
A37: Cinta masking 1/2 " (rollo de 20) | C37: Rollo | D37: =+D36*12/20 -> 27.9 | E37: 3 | F37: =ROUNDUP(SUM(H37:IU37),1) -> 16.8 | G37: Rollo | H37: =+H7*H36*12/20 -> 8.4 | I37: =+I7*I36*12/20 -> 8.4
A38: "U" 15x25 - Kg/Mt lineal. | B38: 0.2 | C38: Kgr | D38: =(2*D$6+2*D5)*$B38*D$7 -> 13.2 | E38: 5 | F38: =ROUNDUP(SUM(H38:IU38)/(6*B38),1) -> 8 | G38: BARRAS | H38: =(2*H$6+2*H5)*$B38*H$7 -> 4.8 | I38: =(2*I$6+2*I5)*$B38*I$7 -> 4.8
A39: Esmerilado | C39: Mt² | D39: =IF((D12="e"),D18*D7,IF( (D12="E"),D18*D7,0)) -> 0 | E39: 186 | F39: =ROUNDUP(SUM(H39:IU39),1) -> 0 | G39: Mt² | H39: =IF((H12="e"),H18*H7,IF( (H12="E"),H18*H7,0)) -> 0 | I39: =IF((I12="e"),I18*I7,IF( (I12="E"),I18*I7,0)) -> 0
A40: Tarugos No. 6 | C40: Pza. | D40: =D$7*(2*D$5+2*D$6)/0.4 -> 165 | E40: 13 | F40: =ROUNDUP(SUM(H40:IU40),1) -> 120 | G40: Pza. | H40: =H$7*(2*H$5+2*H$6)/0.4 -> 60 | I40: =I$7*(2*I$5+2*I$6)/0.4 -> 60
A41: Tornillos 8 x 1 1/2 | C41: Pza. | D41: =D$7*(2*D$5+2*D$6)/0.4 -> 165 | E41: 14 | F41: =ROUNDUP(SUM(H41:IU41),1) -> 120 | G41: Pza. | H41: =H$7*(2*H$5+2*H$6)/0.4 -> 60 | I41: =I$7*(2*I$5+2*I$6)/0.4 -> 60
A42: Tubo galvanizado de 4" | C42: Mt.lin. | D42: =IF(D13=2,D7*(D8-1)*D6,0) -> 72 | E42: 16 | F42: =ROUNDUP(SUM(H42:IU42),1) -> 24 | G42: Mt.lin. | H42: =IF(H13=2,H7*(H8-1)*H6,0) -> 0 | I42: =IF(I13=2,I7*(I8-1)*I6,0) -> 24
A43: Herraje arana | C43: Pza. | D43: =IF(D13=2,D7*(D8-1)*(D9-1),0) -> 60 | E43: 76 | F43: =ROUNDUP(SUM(H43:IU43),1) -> 8 | G43: Pza. | H43: =IF(H13=2,H7*(H8-1)*(H9-1),0) -> 0 | I43: =IF(I13=2,I7*(I8-1)*(I9-1),0) -> 8
A44: Soporte Herraje - tubo | C44: Pza. | D44: =+D43 -> 60 | E44: 77 | F44: =ROUNDUP(SUM(H44:IU44),1) -> 8 | G44: Pza. | H44: =+H43*H7 -> 0 | I44: =+I43*I7 -> 8
A45: Anclaje tubo | C45: Pza. | D45: =+(D8-1)*2*D7 -> 24 | E45: 147 | F45: =ROUNDUP(SUM(H45:IU45),1) -> 16 | G45: Pza. | H45: =+(H8-1)*2*H7 -> 8 | I45: =+(I8-1)*2*I7 -> 8
A46: 1318 | C46: Pza. | D46: =IF(D13=1,D7*(D8-1)*(D9-1),0) -> 0 | E46: 78 | F46: =ROUNDUP(SUM(H46:IU46),1) -> 8 | G46: Pza. | H46: =IF(H13=1,H7*(H8-1)*(H9-1),0) -> 8 | I46: =IF(I13=1,I7*(I8-1)*(I9-1),0) -> 0
A47: 1302 | C47: Pza. | D47: =IF(D13=1,D7*2*(D8-1),0) -> 0 | E47: 55 | F47: =ROUNDUP(SUM(H47:IU47),1) -> 8 | G47: Pza. | H47: =IF(H13=1,H7*2*(H8-1),0) -> 8 | I47: =IF(I13=1,I7*2*(I8-1),0) -> 0
A48: 1306 | C48: Pza. | D48: =IF(D13=1,D7*(D8-1)*(D9-1),0) -> 0 | E48: 56 | F48: =ROUNDUP(SUM(H48:IU48),1) -> 8 | G48: Pza. | H48: =IF(H13=1,H7*(H8-1)*(H9-1),0) -> 8 | I48: =IF(I13=1,I7*(I8-1)*(I9-1),0) -> 0
A51: COSTO CON FACTURA | D51: =SUM(D52:D69) -> 13860.894 | F51: =SUM(F52:F68) -> 6694.3 | H51: =SUM(H52:H69) -> 2832.455 | I51: =SUM(I52:I69) -> 3912.983
A52: Vidrio Templado 10mm Incoloro | C52: =+'Costo M.P.yMat.'!F24 -> 35.89 | D52: =+$C52*D31 -> 0 | E52: 17 | F52: =ROUNDUP(SUM(H52:IU52),1) -> 2777.9 | H52: =+$C52*H31 -> 1475.079 | I52: =+$C52*I31 -> 1302.807
A53: Vidrio Templado 10mm Color | C53: =+'Costo M.P.yMat.'!F29 -> 46.66 | D53: =+$C53*D32 -> 0 | E53: 22 | F53: =ROUNDUP(SUM(H53:IU53),1) -> 0 | H53: =+$C53*H32 -> 0 | I53: =+$C53*I32 -> 0
A54: Vidrio Templado 8mm Incoloro | C54: =+'Costo M.P.yMat.'!F25 -> 34.7 | D54: =+$C54*D33 -> 3154.23 | E54: 18 | F54: =ROUNDUP(SUM(H54:IU54),1) -> 0 | H54: =+$C54*H33 -> 0 | I54: =+$C54*I33 -> 0
A55: Vidrio Templado 8mm Color | C55: =+'Costo M.P.yMat.'!F30 -> 45.46 | D55: =+$C55*D34 -> 0 | E55: 23 | F55: =ROUNDUP(SUM(H55:IU55),1) -> 0 | H55: =+$C55*H34 -> 0 | I55: =+$C55*I34 -> 0
A56: Mano de obra | C56: =+'Costo M.P.yMat.'!F82*2 -> 22.8 | D56: =+$C56*D35 -> 2052 | E56: 75 | F56: =ROUNDUP(SUM(H56:IU56),1) -> 1751.1 | H56: =+$C56*H35 -> 930.24 | I56: =+$C56*I35 -> 820.8
A57: Silicona transp., blanca o negra | C57: =+'Costo M.P.yMat.'!F7 -> 3.31 | D57: =+$C57*D36 -> 153.915 | E57: 1 | F57: =ROUNDUP(SUM(H57:IU57),1) -> 92.7 | H57: =+$C57*H36 -> 46.34 | I57: =+$C57*I36 -> 46.34
A58: Cinta masking 1/2 " (rollo de 20) | C58: =+'Costo M.P.yMat.'!F9 -> 0.75 | D58: =+$C58*D37 -> 20.925 | E58: 3 | F58: =ROUNDUP(SUM(H58:IU58),1) -> 12.6 | H58: =+$C58*H37 -> 6.3 | I58: =+$C58*I37 -> 6.3
A59: "U" 15x25 - Kg/Mt lineal. | B59: 0.2 | C59: =+'Costo M.P.yMat.'!$F$96 -> 8.82 | D59: =+$C59*D38 -> 116.424 | E59: 5 | F59: =ROUNDUP(SUM(H59:IU59),1) -> 84.7 | H59: =+$C59*H38 -> 42.336 | I59: =+$C59*I38 -> 42.336
A60: Esmerilado | C60: =+'Costo M.P.yMat.'!F194 -> 5.7 | D60: =+$C60*D39 -> 0 | E60: 186 | F60: =ROUNDUP(SUM(H60:IU60),1) -> 0 | H60: =+$C60*H39 -> 0 | I60: =+$C60*I39 -> 0
A61: Tarugos No. 6 | C61: =+'Costo M.P.yMat.'!F19 -> 0.04 | D61: =+$C61*D40 -> 6.6 | E61: 13 | F61: =ROUNDUP(SUM(H61:IU61),1) -> 4.8 | H61: =+$C61*H40 -> 2.4 | I61: =+$C61*I40 -> 2.4
A62: Tornillos 8 x 1 1/2 | C62: =+'Costo M.P.yMat.'!F20 -> 0.04 | D62: =+$C62*D41 -> 6.6 | E62: 14 | F62: =ROUNDUP(SUM(H62:IU62),1) -> 4.8 | H62: =+$C62*H41 -> 2.4 | I62: =+$C62*I41 -> 2.4
A63: Tubo galvanizado de 4" | C63: =+'Costo M.P.yMat.'!F22 -> 29.91 | D63: =+$C63*D42 -> 2153.52 | E63: 16 | F63: =ROUNDUP(SUM(H63:IU63),1) -> 717.9 | H63: =+$C63*H42 -> 0 | I63: =+$C63*I42 -> 717.84
A64: Herraje arana | C64: =+'Costo M.P.yMat.'!F83 -> 68.36 | D64: =+$C64*D43 -> 4101.6 | E64: 76 | F64: =ROUNDUP(SUM(H64:IU64),1) -> 546.9 | H64: =+$C64*H43 -> 0 | I64: =+$C64*I43 -> 546.88
A65: Soporte Herraje - tubo | C65: =+'Costo M.P.yMat.'!F84 -> 22.79 | D65: =+$C65*D44 -> 1367.4 | E65: 77 | F65: =ROUNDUP(SUM(H65:IU65),1) -> 182.4 | H65: =+$C65*H44 -> 0 | I65: =+$C65*I44 -> 182.32
A66: Anclaje tubo | C66: =+'Costo M.P.yMat.'!F165 -> 13.68 | D66: =+$C66*D45 -> 328.32 | E66: 147 | F66: =ROUNDUP(SUM(H66:IU66),1) -> 218.9 | H66: =+$C66*H45 -> 109.44 | I66: =+$C66*I45 -> 109.44
A67: 1318 | C67: =+'Costo M.P.yMat.'!F85 -> 16.64 | D67: =+$C67*D45 -> 399.36 | E67: 78 | F67: =ROUNDUP(SUM(H67:IU67),1) -> 266.3 | H67: =+$C67*H45 -> 133.12 | I67: =+$C67*I45 -> 133.12
A68: 1302 | C68: =+'Costo M.P.yMat.'!F62 -> 4.16 | D68: =+$C68*D46 -> 0 | E68: 55 | F68: =ROUNDUP(SUM(H68:IU68),1) -> 33.3 | H68: =+$C68*H46 -> 33.28 | I68: =+$C68*I46 -> 0
A69: 1306 | C69: =+'Costo M.P.yMat.'!F63 -> 6.44 | D69: =+$C69*D48 -> 0 | E69: 56 | F69: =ROUNDUP(SUM(H69:IU69),1) -> 51.6 | H69: =+$C69*H48 -> 51.52 | I69: =+$C69*I48 -> 0
A72: COSTO SIN FACTURA | D72: =SUM(D73:D90) -> 13360.197 | F72: =SUM(F73:F89) -> 6451.2 | H72: =SUM(H73:H90) -> 2739.399 | I72: =SUM(I73:I90) -> 3761.159
A73: Vidrio Templado 10mm Incoloro | C73: =+'Costo M.P.yMat.'!G24 -> 34.65 | D73: =+$C73*D31 -> 0 | E73: 17 | F73: =ROUNDUP(SUM(H73:IU73),1) -> 2682 | H73: =+$C73*H31 -> 1424.115 | I73: =+$C73*I31 -> 1257.795
A74: Vidrio Templado 10mm Color | C74: =+'Costo M.P.yMat.'!G29 -> 45.05 | D74: =+$C74*D32 -> 0 | E74: 22 | F74: =ROUNDUP(SUM(H74:IU74),1) -> 0 | H74: =+$C74*H32 -> 0 | I74: =+$C74*I32 -> 0
A75: Vidrio Templado 8mm Incoloro | C75: =+'Costo M.P.yMat.'!G25 -> 33.5 | D75: =+$C75*D33 -> 3045.15 | E75: 18 | F75: =ROUNDUP(SUM(H75:IU75),1) -> 0 | H75: =+$C75*H33 -> 0 | I75: =+$C75*I33 -> 0
A76: Vidrio Templado 8mm Color | C76: =+'Costo M.P.yMat.'!G30 -> 43.89 | D76: =+$C76*D34 -> 0 | E76: 23 | F76: =ROUNDUP(SUM(H76:IU76),1) -> 0 | H76: =+$C76*H34 -> 0 | I76: =+$C76*I34 -> 0
A77: Mano de obra | C77: =+'Costo M.P.yMat.'!G82*2 -> 22 | D77: =+$C77*D35 -> 1980 | E77: 75 | F77: =ROUNDUP(SUM(H77:IU77),1) -> 1689.6 | H77: =+$C77*H35 -> 897.6 | I77: =+$C77*I35 -> 792
A78: Silicona transp., blanca o negra | C78: =+'Costo M.P.yMat.'!G7 -> 3.19 | D78: =+$C78*D36 -> 148.335 | E78: 1 | F78: =ROUNDUP(SUM(H78:IU78),1) -> 89.4 | H78: =+$C78*H36 -> 44.66 | I78: =+$C78*I36 -> 44.66
A79: Cinta masking 1/2 " (rollo de 20) | C79: =+'Costo M.P.yMat.'!G9 -> 0.72 | D79: =+$C79*D37 -> 20.088 | E79: 3 | F79: =ROUNDUP(SUM(H79:IU79),1) -> 12.1 | H79: =+$C79*H37 -> 6.048 | I79: =+$C79*I37 -> 6.048
A80: "U" 15x25 - Kg/Mt lineal. | B80: 0.2 | C80: =+'Costo M.P.yMat.'!$F$96 -> 8.82 | D80: =+$C80*D38 -> 116.424 | E80: 5 | F80: =ROUNDUP(SUM(H80:IU80),1) -> 84.7 | H80: =+$C80*H38 -> 42.336 | I80: =+$C80*I38 -> 42.336
A81: Esmerilado | C81: =+'Costo M.P.yMat.'!G194 -> 5.5 | D81: =+$C81*D39 -> 0 | E81: 186 | F81: =ROUNDUP(SUM(H81:IU81),1) -> 0 | H81: =+$C81*H39 -> 0 | I81: =+$C81*I39 -> 0
A82: Tarugos No. 6 | C82: =+'Costo M.P.yMat.'!G19 -> 0.04 | D82: =+$C82*D40 -> 6.6 | E82: 13 | F82: =ROUNDUP(SUM(H82:IU82),1) -> 4.8 | H82: =+$C82*H40 -> 2.4 | I82: =+$C82*I40 -> 2.4
A83: Tornillos 8 x 1 1/2 | C83: =+'Costo M.P.yMat.'!G20 -> 0.04 | D83: =+$C83*D41 -> 6.6 | E83: 14 | F83: =ROUNDUP(SUM(H83:IU83),1) -> 4.8 | H83: =+$C83*H41 -> 2.4 | I83: =+$C83*I41 -> 2.4
A84: Tubo galvanizado de 4" | C84: =+'Costo M.P.yMat.'!G22 -> 27.72 | D84: =+$C84*D42 -> 1995.84 | E84: 16 | F84: =ROUNDUP(SUM(H84:IU84),1) -> 665.3 | H84: =+$C84*H42 -> 0 | I84: =+$C84*I42 -> 665.28
A85: Herraje arana | C85: =+'Costo M.P.yMat.'!G83 -> 66 | D85: =+$C85*D43 -> 3960 | E85: 76 | F85: =ROUNDUP(SUM(H85:IU85),1) -> 528 | H85: =+$C85*H43 -> 0 | I85: =+$C85*I43 -> 528
A86: Soporte Herraje - tubo | C86: =+'Costo M.P.yMat.'!F84 -> 22.79 | D86: =+$C86*D44 -> 1367.4 | E86: 77 | F86: =ROUNDUP(SUM(H86:IU86),1) -> 182.4 | H86: =+$C86*H44 -> 0 | I86: =+$C86*I44 -> 182.32
A87: Anclaje tubo | C87: =+'Costo M.P.yMat.'!F165 -> 13.68 | D87: =+$C87*D45 -> 328.32 | E87: 147 | F87: =ROUNDUP(SUM(H87:IU87),1) -> 218.9 | H87: =+$C87*H45 -> 109.44 | I87: =+$C87*I45 -> 109.44
A88: 1318 | C88: =+'Costo M.P.yMat.'!G85 -> 16.06 | D88: =+$C88*D45 -> 385.44 | E88: 78 | F88: =ROUNDUP(SUM(H88:IU88),1) -> 257 | H88: =+$C88*H45 -> 128.48 | I88: =+$C88*I45 -> 128.48
A89: 1302 | C89: =+'Costo M.P.yMat.'!G62 -> 4.02 | D89: =+$C89*D46 -> 0 | E89: 55 | F89: =ROUNDUP(SUM(H89:IU89),1) -> 32.2 | H89: =+$C89*H46 -> 32.16 | I89: =+$C89*I46 -> 0
A90: 1306 | C90: =+'Costo M.P.yMat.'!G63 -> 6.22 | D90: =+$C90*D48 -> 0 | E90: 56 | F90: =ROUNDUP(SUM(H90:IU90),1) -> 49.8 | H90: =+$C90*H48 -> 49.76 | I90: =+$C90*I48 -> 0
A93: FORMULA CON TUBOS Y ARANAS | C93: BASE | D93: ALTURA | F93: BXH | G93: (N-1)*(M-1) | H93: ALTURA | I93: ALTURA
A94: Vidrio Templado 10mm Incoloro | B94: =+C52 -> 35.89 | E94: 17
A95: Vidrio Templado 10mm Color | B95: =+C53 -> 46.66 | E95: 22
A96: Vidrio Templado 8mm Incoloro | B96: =+C54 -> 34.7 | E96: 18
A97: Vidrio Templado 8mm Color | B97: =+C55 -> 45.46 | E97: 23
A98: Mano de obra | B98: =+C56 -> 22.8 | E98: 75 | F98: 1
A99: Silicona transp., blanca o negra | B99: =+C57 -> 3.31 | C99: 0.34 | D99: 0.34 | E99: 1 | H99: 0.34 | I99: 0.34
A100: Cinta masking 1/2 " (rollo de 20) | B100: =+C58 -> 0.75 | C100: 0.4 | D100: 0.4 | E100: 3 | H100: 0.4 | I100: 0.4
A101: "U" 15x15 - Kg/Mt lineal. | B101: =+C59 -> 8.82 | C101: =2*0.159 -> 0.318 | D101: =2*0.159 -> 0.318 | E101: 5 | H101: =2*0.159 -> 0.318 | I101: =2*0.159 -> 0.318
A102: Esmerilado | B102: =+C60 -> 5.7 | E102: 186 | F102: 1
A103: Tarugos No. 6 | B103: =+C61 -> 0.04 | C103: 5 | D103: 5 | E103: 13 | H103: 5 | I103: 5
A104: Tornillos 8 x 1 1/2 | B104: =+C62 -> 0.04 | C104: 5 | D104: 5 | E104: 14 | H104: 5 | I104: 5
A105: Tubo galvanizado de 4" | B105: =+C63 -> 29.91 | E105: 16
A106: Herraje arana | B106: =+C64 -> 68.36 | E106: 76 | G106: 1
A107: Soporte Herraje - tubo | B107: =+C65 -> 22.79 | E107: 77 | G107: 1
A108: Anclaje tubo | B108: =+C66 -> 13.68 | E108: 147
...

Sheet Pano Fijo
D1: =ROUNDUP(D5/1.5,0) -> 6 | F1: =+F12+#REF! -> #REF!
A2: PANO FIJO | D2: PF | F2: Total | H2: piso1 | I2: piso1 | J2: piso1 | K2: piso1
A3: 8 o 10 mm. c/PERFIL U 15x15 DE ALUMINIO | D3: =IF(D10=8,"8 mm.","10 mm.") -> 10 mm. | H3: =IF(H10=8,"8 mm.","10 mm.") -> 10 mm. | I3: =IF(I10=8,"8 mm.","10 mm.") -> 10 mm. | J3: =IF(J10=8,"8 mm.","10 mm.") -> 10 mm. | K3: =IF(K10=8,"8 mm.","10 mm.") -> 10 mm.
A4: DATOS BASE PARA EL ANALISIS | D4: =IF(D9=1,"INCOLORO","COLOR") -> INCOLORO | H4: =IF(H9=1,"INCOLORO","COLOR") -> INCOLORO | I4: =IF(I9=1,"INCOLORO","COLOR") -> INCOLORO | J4: =IF(J9=1,"INCOLORO","COLOR") -> INCOLORO | K4: =IF(K9=1,"INCOLORO","COLOR") -> INCOLORO
A5: BASE ( Metros ) | D5: 8 | H5: 4.4 | I5: 4 | J5: 4.3 | K5: 5
A6: ALTURA ( Metros ) | D6: 0.7 | H6: 2.7 | I6: 2.7 | J6: 2.7 | K6: 2.7
A7: CANTIDAD DE PIEZAS | D7: 1 | F7: =SUM(H7:HZ7) -> 4 | G7: Pzas. | H7: 1 | I7: 1 | J7: 1 | K7: 1
A8: CANTIDAD DE VANOS | D8: 6 | H8: 4 | I8: 4 | J8: 4 | K8: 4
A9: INCOLORO = 1 ; COLOR =2 | D9: 1 | H9: 1 | I9: 1 | J9: 1 | K9: 1
A10: ESPESOR DEL VIDRIO = 8 ó 10 mm. | D10: 10 | H10: 10 | I10: 10 | J10: 10 | K10: 10
A11: ESMERILADO = E
A12: Total Precio c/factura | C12: pn | D12: =+D53 -> 324.25508 | F12: =SUM(H12:HZ12) -> 2483.0617 | G12: $us. | H12: =+H53 -> 617.41248 | I12: =+I53 -> 563.76542 | J12: =+J53 -> 604.00072 | K12: =+K53 -> 697.88308
A13: Superficie Mt² | D13: =+D5*D6*D$7 -> 5.6 | F13: =SUM(H13:HZ13) -> 47.79 | G13: Mt² | H13: =+H5*H6*H$7 -> 11.88 | I13: =+I5*I6*I$7 -> 10.8 | J13: =+J5*J6*J$7 -> 11.61 | K13: =+K5*K6*K$7 -> 13.5
A14: Precio con factura en $us / Mt² | D14: =+D12/D13 -> 57.902693 | F14: =+F12/F13 -> 51.957767 | G14: $us./Mt² | H14: =+H12/H13 -> 51.970748 | I14: =+I12/I13 -> 52.200502 | J14: =+J12/J13 -> 52.024179 | K14: =+K12/K13 -> 51.695043
A15: Total Precio s/factura | D15: =+D80 -> 314.14678 | F15: =SUM(H15:HZ15) -> 2400.6493 | G15: $us. | H15: =+H80 -> 596.92238 | I15: =+I80 -> 545.08332 | J15: =+J80 -> 583.96262 | K15: =+K80 -> 674.68098
A16: Precio sin factura en $us / Mt² | D16: =+D15/D13 -> 56.09764 | F16: =+F15/F13 -> 50.233298 | G16: $us./Mt² | H16: =+H15/H13 -> 50.245992 | I16: =+I15/I13 -> 50.470677 | J16: =+J15/J13 -> 50.298244 | K16: =+K15/K13 -> 49.976369
A17: Materia Prima ( Vidrio ) | D17: =0.9*SUM(D54:D57) -> 182.01613 | F17: =SUM(H17:HZ17) -> 1561.1073 | G17: $us. | H17: =0.9*SUM(H54:H57) -> 388.09652 | I17: =0.9*SUM(I54:I57) -> 353.21143 | J17: =0.9*SUM(J54:J57) -> 379.37524 | K17: =0.9*SUM(K54:K57) -> 440.42413
A18: Materia Prima ( materiales ) | D18: =0.9*SUM(D59:D77) -> 52.35744 | F18: =SUM(H18:HZ18) -> 183.3228 | G18: $us. | H18: =0.9*SUM(H59:H77) -> 45.68592 | I18: =0.9*SUM(I59:I77) -> 43.36944 | J18: =0.9*SUM(J59:J77) -> 45.1068 | K18: =0.9*SUM(K59:K77) -> 49.16064
A19: Mano de obra | D19: =+D58*0.9 -> 57.456 | F19: =SUM(H19:HZ19) -> 490.3254 | G19: $us. | H19: =+H58*0.9 -> 121.8888 | I19: =+I58*0.9 -> 110.808 | J19: =+J58*0.9 -> 119.1186 | K19: =+K58*0.9 -> 138.51
A20: Otros Gastos + Util | D20: =+D12-D19-D18-D17 -> 32.425508 | F20: =SUM(H20:HZ20) -> 248.30617 | G20: $us. | H20: =+H12-H19-H18-H17 -> 61.741248 | I20: =+I12-I19-I18-I17 -> 56.376542 | J20: =+J12-J19-J18-J17 -> 60.400072 | K20: =+K12-K19-K18-K17 -> 69.788308
A21: TOTAL | D21: =SUM(D17:D20) -> 324.25508 | F21: =SUM(H21:HZ21) -> 2483.0617 | G21: $us. | H21: =SUM(H17:H20) -> 617.41248 | I21: =SUM(I17:I20) -> 563.76542 | J21: =SUM(J17:J20) -> 604.00072 | K21: =SUM(K17:K20) -> 697.88308
A22: % descuento del con al sin | D22: =+(D12-D15)/D12 -> 0.031173914 | F22: =+(F12-F15)/F12 -> 0.033189832 | H22: =+(H12-H15)/H12 -> 0.033187052 | I22: =+(I12-I15)/I12 -> 0.033138074 | J22: =+(J12-J15)/J12 -> 0.033175623 | K22: =+(K12-K15)/K12 -> 0.0332464
A24: DETALLE DE MATERIALES A UTILIZAR
A25: MATERIAL | C25: Unidad | D25: =+D2 -> PF | F25: Cantidad | G25: Unidad | H25: =+H2 -> piso1 | I25: =+I2 -> piso1 | J25: =+J2 -> piso1 | K25: =+K2 -> piso1
A26: Vidrio Templado 10mm Incoloro | C26: Mt² | D26: =IF(D$9=1,IF(D$10=10,((D$6*0.05)+(D$5*D$6))*D$7,0),0) -> 5.635 | E26: =VLOOKUP(A26,'Costo M.P.yMat.'!C7:D203,2,FALSE) -> 17 | F26: =ROUNDUP(SUM(H26:HZ26),1) -> 48.4 | G26: Mt² | H26: =IF(H$9=1,IF(H$10=10,((H$6*0.05)+(H$5*H$6))*H$7,0),0) -> 12.015 | I26: =IF(I$9=1,IF(I$10=10,((I$6*0.05)+(I$5*I$6))*I$7,0),0) -> 10.935 | J26: =IF(J$9=1,IF(J$10=10,((J$6*0.05)+(J$5*J$6))*J$7,0),0) -> 11.745 | K26: =IF(K$9=1,IF(K$10=10,((K$6*0.05)+(K$5*K$6))*K$7,0),0) -> 13.635
A27: Vidrio Templado 10mm Color | C27: Mt² | D27: =IF(D$9=2,IF(D$10=10,((D$6*0.05)+(D$5*D$6))*D$7,0),0) -> 0 | E27: =VLOOKUP(A27,'Costo M.P.yMat.'!C8:D204,2,FALSE) -> 22 | F27: =ROUNDUP(SUM(H27:HZ27),1) -> 0 | G27: Mt² | H27: =IF(H$9=2,IF(H$10=10,((H$6*0.05)+(H$5*H$6))*H$7,0),0) -> 0 | I27: =IF(I$9=2,IF(I$10=10,((I$6*0.05)+(I$5*I$6))*I$7,0),0) -> 0 | J27: =IF(J$9=2,IF(J$10=10,((J$6*0.05)+(J$5*J$6))*J$7,0),0) -> 0 | K27: =IF(K$9=2,IF(K$10=10,((K$6*0.05)+(K$5*K$6))*K$7,0),0) -> 0
A28: Vidrio Templado 8mm Incoloro | C28: Mt² | D28: =IF(D$9=1,IF(D$10=8,((D$6*0.05)+(D$5*D$6))*D$7,0),0) -> 0 | E28: =VLOOKUP(A28,'Costo M.P.yMat.'!C9:D205,2,FALSE) -> 18 | F28: =ROUNDUP(SUM(H28:HZ28),1) -> 0 | G28: Mt² | H28: =IF(H$9=1,IF(H$10=8,((H$6*0.05)+(H$5*H$6))*H$7,0),0) -> 0 | I28: =IF(I$9=1,IF(I$10=8,((I$6*0.05)+(I$5*I$6))*I$7,0),0) -> 0 | J28: =IF(J$9=1,IF(J$10=8,((J$6*0.05)+(J$5*J$6))*J$7,0),0) -> 0 | K28: =IF(K$9=1,IF(K$10=8,((K$6*0.05)+(K$5*K$6))*K$7,0),0) -> 0
A29: Vidrio Templado 8mm Color | C29: Mt² | D29: =IF(D$9=2,IF(D$10=8,((D$5*D$6))*D$7,0),0) -> 0 | E29: =VLOOKUP(A29,'Costo M.P.yMat.'!C10:D206,2,FALSE) -> 23 | F29: =ROUNDUP(SUM(H29:HZ29),1) -> 0 | G29: Mt² | H29: =IF(H$9=2,IF(H$10=8,((H$5*H$6))*H$7,0),0) -> 0 | I29: =IF(I$9=2,IF(I$10=8,((I$5*I$6))*I$7,0),0) -> 0 | J29: =IF(J$9=2,IF(J$10=8,((J$5*J$6))*J$7,0),0) -> 0 | K29: =IF(K$9=2,IF(K$10=8,((K$5*K$6))*K$7,0),0) -> 0
A30: Mano de obra | C30: Mt² | D30: =+D13 -> 5.6 | E30: 75 | F30: =ROUNDUP(SUM(H30:HZ30),1) -> 47.8 | G30: Mt² | H30: =+H13 -> 11.88 | I30: =+I13 -> 10.8 | J30: =+J13 -> 11.61 | K30: =+K13 -> 13.5
A31: Silicona transparente, blanca o negra | C31: Tubo | D31: =D7*(4*D5+4*D6+(D8-1)*D6)/6 -> 6.3833333 | E31: 1 | F31: =ROUNDUP(SUM(H31:HZ31),1) -> 24.4 | G31: Tubo | H31: =H7*(4*H5+4*H6+(H8-1)*H6)/6 -> 6.0833333 | I31: =I7*(4*I5+4*I6+(I8-1)*I6)/6 -> 5.8166667 | J31: =J7*(4*J5+4*J6+(J8-1)*J6)/6 -> 6.0166667 | K31: =K7*(4*K5+4*K6+(K8-1)*K6)/6 -> 6.4833333
A32: Cinta masking 1/2 " (rollo de 20) | C32: Rollo | D32: =+D31*12/20 -> 3.83 | E32: 3 | F32: =ROUNDUP(SUM(H32:HZ32),1) -> 14.7 | G32: Rollo | H32: =+H31*12/20 -> 3.65 | I32: =+I31*12/20 -> 3.49 | J32: =+J31*12/20 -> 3.61 | K32: =+K31*12/20 -> 3.89
A33: "U" 15x25 - Kg/Mt lineal. | B33: 0.2 | C33: Kgr | D33: =(2*D$6+2*D5)*$B33*D$7 -> 3.48 | E33: 5 | F33: =ROUNDUP(SUM(H33:HZ33)/(6*B33),1) -> 9.5 | G33: Barras | H33: =(2*H$6+2*H5)*$B33*H$7 -> 2.84 | I33: =(2*I$6+2*I5)*$B33*I$7 -> 2.68 | J33: =(2*J$6+2*J5)*$B33*J$7 -> 2.8 | K33: =(2*K$6+2*K5)*$B33*K$7 -> 3.08
A34: Esmerilado | C34: Mt² | D34: =IF((D11="e"),D13,IF( (D11="E"),D13,0)) -> 0 | E34: 186 | F34: =ROUNDUP(SUM(H34:HZ34),1) -> 0 | G34: Mt lineal | H34: =IF((H11="e"),H13,IF( (H11="E"),H13,0)) -> 0 | I34: =IF((I11="e"),I13,IF( (I11="E"),I13,0)) -> 0 | J34: =IF((J11="e"),J13,IF( (J11="E"),J13,0)) -> 0 | K34: =IF((K11="e"),K13,IF( (K11="E"),K13,0)) -> 0
A35: Tarugos No. 6 | C35: Pza. | D35: =D$7*(2*D$5+2*D$6)/0.4 -> 43.5 | E35: =VLOOKUP(A35,'Costo M.P.yMat.'!C16:D212,2,FALSE) -> 13 | F35: =ROUNDUP(SUM(H35:HZ35),1) -> 142.5 | G35: Pza. | H35: =H$7*(2*H$5+2*H$6)/0.4 -> 35.5 | I35: =I$7*(2*I$5+2*I$6)/0.4 -> 33.5 | J35: =J$7*(2*J$5+2*J$6)/0.4 -> 35 | K35: =K$7*(2*K$5+2*K$6)/0.4 -> 38.5
A36: Tornillos 8 x 1 1/2 | C36: Pza. | D36: =D$7*(2*D$5+2*D$6)/0.4 -> 43.5 | E36: =VLOOKUP(A36,'Costo M.P.yMat.'!C17:D213,2,FALSE) -> 14 | F36: =ROUNDUP(SUM(H36:HZ36),1) -> 142.5 | G36: Pza. | H36: =H$7*(2*H$5+2*H$6)/0.4 -> 35.5 | I36: =I$7*(2*I$5+2*I$6)/0.4 -> 33.5 | J36: =J$7*(2*J$5+2*J$6)/0.4 -> 35 | K36: =K$7*(2*K$5+2*K$6)/0.4 -> 38.5
A37: Vedapres 001 - u (2,10mt/barra) | C37: Barra | F37: =ROUNDUP(SUM(H37:HZ37),1) -> 0 | G37: Barra
A38: Vedapres 001 - h (2,10mt/barra) | C38: Barra | F38: =ROUNDUP(SUM(H38:HZ38),1) -> 0 | G38: Barra
A39: Cabezal 7313 - Kg/Mt l. | B39: 1.013 | C39: Kgr | F39: =ROUNDUP(SUM(H39:HZ39)/(6*B39),1) -> 0 | G39: Barras
A40: Tapa 7312 - Kg/Mt l. | B40: 0.408 | C40: Kgr | F40: =ROUNDUP(SUM(H40:HZ40)/(6*B40),1) -> 0 | G40: Barras
A41: Trillo 7314 - Kg/Mt l. | B41: 0.478 | C41: Kgr | F41: =ROUNDUP(SUM(H41:HZ41)/(6*B41),1) -> 0 | G41: Barras
A42: TapaTrillo Rev. - Kg/Mt l. | B42: 0.125 | C42: Kgr | F42: =ROUNDUP(SUM(H42:HZ42)/(6*B42),1) -> 0 | G42: Barras
A43: 1510 | C43: Pza. | F43: =ROUNDUP(SUM(H43:HZ43),1) -> 0 | G43: Pza.
A44: 1511 | C44: Pza. | F44: =ROUNDUP(SUM(H44:HZ44),1) -> 0 | G44: Pza.
A45: 1511a | C45: Pza. | F45: =ROUNDUP(SUM(H45:HZ45),1) -> 0 | G45: Pza.
A46: 1125a | C46: Pza. | F46: =ROUNDUP(SUM(H46:HZ46),1) -> 0 | G46: Pza.
A47: 1629j | C47: Pza. | F47: =ROUNDUP(SUM(H47:HZ47),1) -> 0 | G47: Pza.
A48: 1335 | C48: Pza. | F48: =ROUNDUP(SUM(H48:HZ48),1) -> 0 | G48: Pza.
A49: 1038c | C49: Pza. | F49: =ROUNDUP(SUM(H49:HZ49),1) -> 0 | G49: Pza.
A53: COSTO CON FACTURA | D53: =SUM(D54:D77) -> 324.25508 | F53: =ROUNDUP(SUM(H53:HZ53),1) -> 2483.1 | H53: =SUM(H54:H77) -> 617.41248 | I53: =SUM(I54:I77) -> 563.76542 | J53: =SUM(J54:J77) -> 604.00072 | K53: =SUM(K54:K77) -> 697.88308
A54: Vidrio Templado 10mm Incoloro | C54: =+'Costo M.P.yMat.'!F24 -> 35.89 | D54: =+$C54*D26 -> 202.24015 | E54: 17 | F54: =ROUNDUP(SUM(H54:HZ54),1) -> 1734.6 | H54: =+$C54*H26 -> 431.21835 | I54: =+$C54*I26 -> 392.45715 | J54: =+$C54*J26 -> 421.52805 | K54: =+$C54*K26 -> 489.36015
A55: Vidrio Templado 10mm Color | C55: =+'Costo M.P.yMat.'!F29 -> 46.66 | D55: =+$C55*D27 -> 0 | E55: 22 | F55: =ROUNDUP(SUM(H55:HZ55),1) -> 0 | H55: =+$C55*H27 -> 0 | I55: =+$C55*I27 -> 0 | J55: =+$C55*J27 -> 0 | K55: =+$C55*K27 -> 0
A56: Vidrio Templado 8mm Incoloro | C56: =+'Costo M.P.yMat.'!F25 -> 34.7 | D56: =+$C56*D28 -> 0 | E56: 18 | F56: =ROUNDUP(SUM(H56:HZ56),1) -> 0 | H56: =+$C56*H28 -> 0 | I56: =+$C56*I28 -> 0 | J56: =+$C56*J28 -> 0 | K56: =+$C56*K28 -> 0
A57: Vidrio Templado 8mm Color | C57: =+'Costo M.P.yMat.'!F30 -> 45.46 | D57: =+$C57*D29 -> 0 | E57: 23 | F57: =ROUNDUP(SUM(H57:HZ57),1) -> 0 | H57: =+$C57*H29 -> 0 | I57: =+$C57*I29 -> 0 | J57: =+$C57*J29 -> 0 | K57: =+$C57*K29 -> 0
A58: Mano de obra | C58: =+'Costo M.P.yMat.'!F82 -> 11.4 | D58: =+$C58*D30 -> 63.84 | E58: 75 | F58: =ROUNDUP(SUM(H58:HZ58),1) -> 544.9 | H58: =+$C58*H30 -> 135.432 | I58: =+$C58*I30 -> 123.12 | J58: =+$C58*J30 -> 132.354 | K58: =+$C58*K30 -> 153.9
A59: Silicona transp., blanca o negra | C59: =+'Costo M.P.yMat.'!F7 -> 3.31 | D59: =+$C59*D31 -> 21.128833 | E59: 1 | F59: =ROUNDUP(SUM(H59:HZ59),1) -> 80.8 | H59: =+$C59*H31 -> 20.135833 | I59: =+$C59*I31 -> 19.253167 | J59: =+$C59*J31 -> 19.915167 | K59: =+$C59*K31 -> 21.459833
A60: Cinta masking 1/2 " (rollo de 20) | C60: =+'Costo M.P.yMat.'!F9 -> 0.75 | D60: =+$C60*D32 -> 2.8725 | E60: 3 | F60: =ROUNDUP(SUM(H60:HZ60),1) -> 11 | H60: =+$C60*H32 -> 2.7375 | I60: =+$C60*I32 -> 2.6175 | J60: =+$C60*J32 -> 2.7075 | K60: =+$C60*K32 -> 2.9175
A61: "U" 15x25 - Kg/Mt lineal. | B61: 0.2 | C61: =+'Costo M.P.yMat.'!$F$96 -> 8.82 | D61: =+$C61*D33 -> 30.6936 | E61: 5 | F61: =ROUNDUP(SUM(H61:HZ61),1) -> 100.6 | H61: =+$C61*H33 -> 25.0488 | I61: =+$C61*I33 -> 23.6376 | J61: =+$C61*J33 -> 24.696 | K61: =+$C61*K33 -> 27.1656
A62: Esmerilado | C62: =+'Costo M.P.yMat.'!F167 -> 1.14 | D62: =+$C62*D34 -> 0 | E62: 186 | F62: =ROUNDUP(SUM(H62:HZ62),1) -> 0 | H62: =+$C62*H34 -> 0 | I62: =+$C62*I34 -> 0 | J62: =+$C62*J34 -> 0 | K62: =+$C62*K34 -> 0
A63: Tarugos No. 6 | C63: =+'Costo M.P.yMat.'!F19 -> 0.04 | D63: =+$C63*D35 -> 1.74 | E63: 13 | F63: =ROUNDUP(SUM(H63:HZ63),1) -> 5.7 | H63: =+$C63*H35 -> 1.42 | I63: =+$C63*I35 -> 1.34 | J63: =+$C63*J35 -> 1.4 | K63: =+$C63*K35 -> 1.54
A64: Tornillos 8 x 1 1/2 | C64: =+'Costo M.P.yMat.'!F20 -> 0.04 | D64: =+$C64*D36 -> 1.74 | E64: 14 | F64: =ROUNDUP(SUM(H64:HZ64),1) -> 5.7 | H64: =+$C64*H36 -> 1.42 | I64: =+$C64*I36 -> 1.34 | J64: =+$C64*J36 -> 1.4 | K64: =+$C64*K36 -> 1.54
A65: Vedapres 001 - u (2,10mt/barra) | C65: =+'Costo M.P.yMat.'!F38 -> 5.9 | D65: =+$C65*D37 -> 0 | F65: =ROUNDUP(SUM(H65:HZ65),1) -> 0 | H65: =+$C65*H37 -> 0 | I65: =+$C65*I37 -> 0 | J65: =+$C65*J37 -> 0 | K65: =+$C65*K37 -> 0
A66: Vedapres 001 - h (2,10mt/barra) | C66: =+'Costo M.P.yMat.'!F37 -> 9.83 | D66: =+$C66*D38 -> 0 | F66: =ROUNDUP(SUM(H66:HZ66),1) -> 0 | H66: =+$C66*H38 -> 0 | I66: =+$C66*I38 -> 0 | J66: =+$C66*J38 -> 0 | K66: =+$C66*K38 -> 0
A67: Cabezal 7313 - Kg/Mt l. | B67: 1.013 | C67: =+'Costo M.P.yMat.'!$F$96 -> 8.82 | D67: =+$C67*D39 -> 0 | F67: =ROUNDUP(SUM(H67:HZ67),1) -> 0 | H67: =+$C67*H39 -> 0 | I67: =+$C67*I39 -> 0 | J67: =+$C67*J39 -> 0 | K67: =+$C67*K39 -> 0
A68: Tapa 7312 - Kg/Mt l. | B68: 0.408 | C68: =+'Costo M.P.yMat.'!$F$96 -> 8.82 | D68: =+$C68*D40 -> 0 | F68: =ROUNDUP(SUM(H68:HZ68),1) -> 0 | H68: =+$C68*H40 -> 0 | I68: =+$C68*I40 -> 0 | J68: =+$C68*J40 -> 0 | K68: =+$C68*K40 -> 0
A69: Trillo 7314 - Kg/Mt l. | B69: 0.478 | C69: =+'Costo M.P.yMat.'!$F$96 -> 8.82 | D69: =+$C69*D41 -> 0 | F69: =ROUNDUP(SUM(H69:HZ69),1) -> 0 | H69: =+$C69*H41 -> 0 | I69: =+$C69*I41 -> 0 | J69: =+$C69*J41 -> 0 | K69: =+$C69*K41 -> 0
A70: TapaTrillo Rev. - Kg/Mt l. | B70: 0.125 | C70: =+'Costo M.P.yMat.'!$F$96 -> 8.82 | D70: =+$C70*D42 -> 0 | F70: =ROUNDUP(SUM(H70:HZ70),1) -> 0 | H70: =+$C70*H42 -> 0 | I70: =+$C70*I42 -> 0 | J70: =+$C70*J42 -> 0 | K70: =+$C70*K42 -> 0
A71: 1510 | C71: =+'Costo M.P.yMat.'!F71 -> 20.68 | D71: =+$C71*D43 -> 0 | F71: =ROUNDUP(SUM(H71:HZ71),1) -> 0 | H71: =+$C71*H43 -> 0 | I71: =+$C71*I43 -> 0 | J71: =+$C71*J43 -> 0 | K71: =+$C71*K43 -> 0
A72: 1511 | C72: =+'Costo M.P.yMat.'!F72 -> 11 | D72: =+$C72*D44 -> 0 | F72: =ROUNDUP(SUM(H72:HZ72),1) -> 0 | H72: =+$C72*H44 -> 0 | I72: =+$C72*I44 -> 0 | J72: =+$C72*J44 -> 0 | K72: =+$C72*K44 -> 0
A73: 1511a | C73: =+'Costo M.P.yMat.'!F73 -> 2.45 | D73: =+$C73*D45 -> 0 | F73: =ROUNDUP(SUM(H73:HZ73),1) -> 0 | H73: =+$C73*H45 -> 0 | I73: =+$C73*I45 -> 0 | J73: =+$C73*J45 -> 0 | K73: =+$C73*K45 -> 0
A74: 1125a | C74: =+'Costo M.P.yMat.'!F57 -> 2.68 | D74: =+$C74*D46 -> 0 | F74: =ROUNDUP(SUM(H74:HZ74),1) -> 0 | H74: =+$C74*H46 -> 0 | I74: =+$C74*I46 -> 0 | J74: =+$C74*J46 -> 0 | K74: =+$C74*K46 -> 0
A75: 1629j | C75: =+'Costo M.P.yMat.'!F77 -> 2.45 | D75: =+$C75*D47 -> 0 | F75: =ROUNDUP(SUM(H75:HZ75),1) -> 0 | H75: =+$C75*H47 -> 0 | I75: =+$C75*I47 -> 0 | J75: =+$C75*J47 -> 0 | K75: =+$C75*K47 -> 0
A76: 1335 | C76: =+'Costo M.P.yMat.'!F68 -> 5.87 | D76: =+$C76*D48 -> 0 | F76: =ROUNDUP(SUM(H76:HZ76),1) -> 0 | H76: =+$C76*H48 -> 0 | I76: =+$C76*I48 -> 0 | J76: =+$C76*J48 -> 0 | K76: =+$C76*K48 -> 0
A77: 1038c | C77: =+'Costo M.P.yMat.'!F49 -> 1.32 | D77: =+$C77*D49 -> 0 | F77: =ROUNDUP(SUM(H77:HZ77),1) -> 0 | H77: =+$C77*H49 -> 0 | I77: =+$C77*I49 -> 0 | J77: =+$C77*J49 -> 0 | K77: =+$C77*K49 -> 0
A80: COSTO SIN FACTURA | D80: =SUM(D81:D104) -> 314.14678 | F80: =ROUNDUP(SUM(H80:HZ80),1) -> 2400.7 | H80: =SUM(H81:H104) -> 596.92238 | I80: =SUM(I81:I104) -> 545.08332 | J80: =SUM(J81:J104) -> 583.96262 | K80: =SUM(K81:K104) -> 674.68098
A81: Vidrio Templado 10mm Incoloro | C81: =+'Costo M.P.yMat.'!G24 -> 34.65 | D81: =+$C81*D26 -> 195.25275 | E81: 17 | F81: =ROUNDUP(SUM(H81:HZ81),1) -> 1674.7 | H81: =+$C81*H26 -> 416.31975 | I81: =+$C81*I26 -> 378.89775 | J81: =+$C81*J26 -> 406.96425 | K81: =+$C81*K26 -> 472.45275
A82: Vidrio Templado 10mm Color | C82: =+'Costo M.P.yMat.'!G29 -> 45.05 | D82: =+$C82*D27 -> 0 | E82: 22 | F82: =ROUNDUP(SUM(H82:HZ82),1) -> 0 | H82: =+$C82*H27 -> 0 | I82: =+$C82*I27 -> 0 | J82: =+$C82*J27 -> 0 | K82: =+$C82*K27 -> 0
A83: Vidrio Templado 8mm Incoloro | C83: =+'Costo M.P.yMat.'!G25 -> 33.5 | D83: =+$C83*D28 -> 0 | E83: 18 | F83: =ROUNDUP(SUM(H83:HZ83),1) -> 0 | H83: =+$C83*H28 -> 0 | I83: =+$C83*I28 -> 0 | J83: =+$C83*J28 -> 0 | K83: =+$C83*K28 -> 0
A84: Vidrio Templado 8mm Color | C84: =+'Costo M.P.yMat.'!G30 -> 43.89 | D84: =+$C84*D29 -> 0 | E84: 23 | F84: =ROUNDUP(SUM(H84:HZ84),1) -> 0 | H84: =+$C84*H29 -> 0 | I84: =+$C84*I29 -> 0 | J84: =+$C84*J29 -> 0 | K84: =+$C84*K29 -> 0
A85: Mano de obra | C85: =+'Costo M.P.yMat.'!G82 -> 11 | D85: =+$C85*D30 -> 61.6 | E85: 75 | F85: =ROUNDUP(SUM(H85:HZ85),1) -> 525.7 | H85: =+$C85*H30 -> 130.68 | I85: =+$C85*I30 -> 118.8 | J85: =+$C85*J30 -> 127.71 | K85: =+$C85*K30 -> 148.5
A86: Silicona transp., blanca o negra | C86: =+'Costo M.P.yMat.'!G7 -> 3.19 | D86: =+$C86*D31 -> 20.362833 | E86: 1 | F86: =ROUNDUP(SUM(H86:HZ86),1) -> 77.9 | H86: =+$C86*H31 -> 19.405833 | I86: =+$C86*I31 -> 18.555167 | J86: =+$C86*J31 -> 19.193167 | K86: =+$C86*K31 -> 20.681833
A87: Cinta masking 1/2 " (rollo de 20) | C87: =+'Costo M.P.yMat.'!G9 -> 0.72 | D87: =+$C87*D32 -> 2.7576 | E87: 3 | F87: =ROUNDUP(SUM(H87:HZ87),1) -> 10.6 | H87: =+$C87*H32 -> 2.628 | I87: =+$C87*I32 -> 2.5128 | J87: =+$C87*J32 -> 2.5992 | K87: =+$C87*K32 -> 2.8008
A88: "U" 15x25 - Kg/Mt lineal. | B88: 0.2 | C88: =+'Costo M.P.yMat.'!$F$96 -> 8.82 | D88: =+$C88*D33 -> 30.6936 | E88: 5 | F88: =ROUNDUP(SUM(H88:HZ88),1) -> 100.6 | H88: =+$C88*H33 -> 25.0488 | I88: =+$C88*I33 -> 23.6376 | J88: =+$C88*J33 -> 24.696 | K88: =+$C88*K33 -> 27.1656
A89: Esmerilado | C89: =+'Costo M.P.yMat.'!G167 -> 1.1 | D89: =+$C89*D34 -> 0 | E89: 186 | F89: =ROUNDUP(SUM(H89:HZ89),1) -> 0 | H89: =+$C89*H34 -> 0 | I89: =+$C89*I34 -> 0 | J89: =+$C89*J34 -> 0 | K89: =+$C89*K34 -> 0
A90: Tarugos No. 6 | C90: =+'Costo M.P.yMat.'!G19 -> 0.04 | D90: =+$C90*D35 -> 1.74 | E90: 13 | F90: =ROUNDUP(SUM(H90:HZ90),1) -> 5.7 | H90: =+$C90*H35 -> 1.42 | I90: =+$C90*I35 -> 1.34 | J90: =+$C90*J35 -> 1.4 | K90: =+$C90*K35 -> 1.54
A91: Tornillos 8 x 1 1/2 | C91: =+'Costo M.P.yMat.'!G20 -> 0.04 | D91: =+$C91*D36 -> 1.74 | E91: 14 | F91: =ROUNDUP(SUM(H91:HZ91),1) -> 5.7 | H91: =+$C91*H36 -> 1.42 | I91: =+$C91*I36 -> 1.34 | J91: =+$C91*J36 -> 1.4 | K91: =+$C91*K36 -> 1.54
A92: Vedapres 001 - u (2,10mt/barra) | C92: =+'Costo M.P.yMat.'!G38 -> 5.7 | D92: =+$C92*D37 -> 0 | F92: =ROUNDUP(SUM(H92:HZ92),1) -> 0 | H92: =+$C92*H37 -> 0 | I92: =+$C92*I37 -> 0 | J92: =+$C92*J37 -> 0 | K92: =+$C92*K37 -> 0
A93: Vedapres 001 - h (2,10mt/barra) | C93: =+'Costo M.P.yMat.'!G37 -> 9.49 | D93: =+$C93*D38 -> 0 | F93: =ROUNDUP(SUM(H93:HZ93),1) -> 0 | H93: =+$C93*H38 -> 0 | I93: =+$C93*I38 -> 0 | J93: =+$C93*J38 -> 0 | K93: =+$C93*K38 -> 0
A94: Cabezal 7313 - Kg/Mt l. | B94: 1.013 | C94: =+'Costo M.P.yMat.'!$F$96 -> 8.82 | D94: =+$C94*D39 -> 0 | F94: =ROUNDUP(SUM(H94:HZ94),1) -> 0 | H94: =+$C94*H39 -> 0 | I94: =+$C94*I39 -> 0 | J94: =+$C94*J39 -> 0 | K94: =+$C94*K39 -> 0
A95: Tapa 7312 - Kg/Mt l. | B95: 0.408 | C95: =+'Costo M.P.yMat.'!$F$96 -> 8.82 | D95: =+$C95*D40 -> 0 | F95: =ROUNDUP(SUM(H95:HZ95),1) -> 0 | H95: =+$C95*H40 -> 0 | I95: =+$C95*I40 -> 0 | J95: =+$C95*J40 -> 0 | K95: =+$C95*K40 -> 0
A96: Trillo 7314 - Kg/Mt l. | B96: 0.478 | C96: =+'Costo M.P.yMat.'!$F$96 -> 8.82 | D96: =+$C96*D41 -> 0 | F96: =ROUNDUP(SUM(H96:HZ96),1) -> 0 | H96: =+$C96*H41 -> 0 | I96: =+$C96*I41 -> 0 | J96: =+$C96*J41 -> 0 | K96: =+$C96*K41 -> 0
A97: TapaTrillo Rev. - Kg/Mt l. | B97: 0.125 | C97: =+'Costo M.P.yMat.'!$F$96 -> 8.82 | D97: =+$C97*D42 -> 0 | F97: =ROUNDUP(SUM(H97:HZ97),1) -> 0 | H97: =+$C97*H42 -> 0 | I97: =+$C97*I42 -> 0 | J97: =+$C97*J42 -> 0 | K97: =+$C97*K42 -> 0
A98: 1510 | C98: =+'Costo M.P.yMat.'!G71 -> 19.97 | D98: =+$C98*D43 -> 0 | F98: =ROUNDUP(SUM(H98:HZ98),1) -> 0 | H98: =+$C98*H43 -> 0 | I98: =+$C98*I43 -> 0 | J98: =+$C98*J43 -> 0 | K98: =+$C98*K43 -> 0
A99: 1511 | C99: =+'Costo M.P.yMat.'!G72 -> 10.62 | D99: =+$C99*D44 -> 0 | F99: =ROUNDUP(SUM(H99:HZ99),1) -> 0 | H99: =+$C99*H44 -> 0 | I99: =+$C99*I44 -> 0 | J99: =+$C99*J44 -> 0 | K99: =+$C99*K44 -> 0
A100: 1511a | C100: =+'Costo M.P.yMat.'!G73 -> 2.37 | D100: =+$C100*D45 -> 0 | F100: =ROUNDUP(SUM(H100:HZ100),1) -> 0 | H100: =+$C100*H45 -> 0 | I100: =+$C100*I45 -> 0 | J100: =+$C100*J45 -> 0 | K100: =+$C100*K45 -> 0
A101: 1125a | C101: =+'Costo M.P.yMat.'!G57 -> 2.59 | D101: =+$C101*D46 -> 0 | F101: =ROUNDUP(SUM(H101:HZ101),1) -> 0 | H101: =+$C101*H46 -> 0 | I101: =+$C101*I46 -> 0 | J101: =+$C101*J46 -> 0 | K101: =+$C101*K46 -> 0
A102: 1629j | C102: =+'Costo M.P.yMat.'!G77 -> 2.37 | D102: =+$C102*D47 -> 0 | F102: =ROUNDUP(SUM(H102:HZ102),1) -> 0 | H102: =+$C102*H47 -> 0 | I102: =+$C102*I47 -> 0 | J102: =+$C102*J47 -> 0 | K102: =+$C102*K47 -> 0
A103: 1335 | C103: =+'Costo M.P.yMat.'!G68 -> 5.67 | D103: =+$C103*D48 -> 0 | F103: =ROUNDUP(SUM(H103:HZ103),1) -> 0 | H103: =+$C103*H48 -> 0 | I103: =+$C103*I48 -> 0 | J103: =+$C103*J48 -> 0 | K103: =+$C103*K48 -> 0
A104: 1038c | C104: =+'Costo M.P.yMat.'!G49 -> 1.27 | D104: =+$C104*D49 -> 0 | F104: =ROUNDUP(SUM(H104:HZ104),1) -> 0 | H104: =+$C104*H49 -> 0 | I104: =+$C104*I49 -> 0 | J104: =+$C104*J49 -> 0 | K104: =+$C104*K49 -> 0
A107: FORMULA | C107: BASE | D107: ALTURA | F107: BXH | G107: (N-1)*h | H107: ALTURA | I107: ALTURA | J107: ALTURA | K107: ALTURA
A108: Vidrio Templado 10mm Incoloro | B108: =+C54 -> 35.89 | E108: 17
...

Sheet P-V.Corrediza
A2: PUERTA / VENTANA CORREDIZA | D2: =IF(D8=1,"PC2H","VC2H") -> VC2H | E2: =IF(E8=1,"PC4H","VC4H") -> VC4H | G2: Total | I2: piso1 | J2: piso1 | K2: piso12 | L2: piso12
A3: 8 o 10 mm. c/PERFIL U 15x15 DE ALUMINIO | D3: =IF(D10=8,"8 mm.","10 mm.") -> 10 mm. | E3: =IF(E10=8,"8 mm.","10 mm.") -> 10 mm. | I3: =IF(I10=8,"8 mm.","10 mm.") -> 10 mm. | J3: =IF(J10=8,"8 mm.","10 mm.") -> 10 mm. | K3: =IF(K10=8,"8 mm.","10 mm.") -> 10 mm. | L3: =IF(L10=8,"8 mm.","10 mm.") -> 10 mm.
A4: DATOS BASE PARA EL ANALISIS | D4: =IF(D9=1,"INCOLORO","COLOR") -> INCOLORO | E4: =IF(E9=1,"INCOLORO","COLOR") -> INCOLORO | I4: =IF(I9=1,"INCOLORO","COLOR") -> INCOLORO | J4: =IF(J9=1,"INCOLORO","COLOR") -> INCOLORO | K4: =IF(K9=1,"INCOLORO","COLOR") -> INCOLORO | L4: =IF(L9=1,"INCOLORO","COLOR") -> INCOLORO
A5: BASE ( Metros ) | D5: 2 | E5: 3.5 | I5: 5.8 | J5: 5.3 | K5: 4.1 | L5: 4.1
A6: ALTURA ( Metros ) | D6: 2.1 | E6: 2.3 | I6: 2.2 | J6: 2.2 | K6: 2.2 | L6: 2.2
A7: CANTIDAD DE PIEZAS | D7: 1 | E7: 1 | G7: =SUM(I7:IF7) -> 4 | H7: Pzas. | I7: 1 | J7: 1 | K7: 1 | L7: 1
A8: PUERTA = 1; VENTANA = 2 | D8: 2 | E8: 2 | I8: 1 | J8: 1 | K8: 1 | L8: 1
A9: INCOLORO = 1 ; COLOR =2 | D9: 1 | E9: 1 | I9: 1 | J9: 1 | K9: 1 | L9: 1
A10: ESPESOR DEL VIDRIO = 8 ó 10 mm. | D10: 10 | E10: 10 | I10: 10 | J10: 10 | K10: 10 | L10: 10
A11: Total Precio c/factura | C11: pn | D11: =+D57 -> 271.85393 | E11: =+E57 -> 510.50703 | G11: =SUM(I11:IF11) -> 2473.4415 | H11: $us. | I11: =+I57 -> 735.79514 | J11: =+J57 -> 661.49197 | K11: =+K57 -> 538.0772 | L11: =+L57 -> 538.0772
A12: Superficie Mt² | D12: =+D5*D6*D$7 -> 4.2 | E12: =+E5*E6*E$7 -> 8.05 | G12: =SUM(I12:IF12) -> 42.46 | H12: Mt² | I12: =+I5*I6*I$7 -> 12.76 | J12: =+J5*J6*J$7 -> 11.66 | K12: =+K5*K6*K$7 -> 9.02 | L12: =+L5*L6*L$7 -> 9.02
A13: Precio con factura en $us / Mt² | D13: =+D11/D12 -> 64.727125 | E13: =+E11/E12 -> 63.417023 | G13: =+G11/G12 -> 58.253451 | H13: $us./Mt² | I13: =+I11/I12 -> 57.664196 | J13: =+J11/J12 -> 56.73173 | K13: =+K11/K12 -> 59.653792 | L13: =+L11/L12 -> 59.653792
A14: Total Precio s/factura | D14: =+D84 -> 293.01349 | E14: =+E84 -> 525.71551 | G14: =SUM(I14:IF14) -> 2415.8741 | H14: $us. | I14: =+I84 -> 708.73954 | J14: =+J84 -> 670.23337 | K14: =+K84 -> 518.4506 | L14: =+L84 -> 518.4506
A15: Precio sin factura en $us / Mt² | D15: =+D14/D12 -> 69.765116 | E15: =+E14/E12 -> 65.306275 | G15: =+G14/G12 -> 56.897647 | H15: $us./Mt² | I15: =+I14/I12 -> 55.543851 | J15: =+J14/J12 -> 57.481421 | K15: =+K14/K12 -> 57.477894 | L15: =+L14/L12 -> 57.477894
A16: Materia Prima ( Vidrio ) | D16: =0.9*SUM(D58:D61) -> 139.05581 | E16: =0.9*SUM(E58:E61) -> 263.73766 | G16: =SUM(I16:IF16) -> 1385.7129 | H16: Sus. | I16: =0.9*SUM(I58:I61) -> 415.71387 | J16: =0.9*SUM(J58:J61) -> 380.18277 | K16: =0.9*SUM(K58:K61) -> 294.90813 | L16: =0.9*SUM(L58:L61) -> 294.90813
A17: Materia Prima ( materiales ) | D17: =0.9*SUM(D63:D81) -> 62.520728 | E17: =0.9*SUM(E63:E81) -> 113.12567 | G17: =SUM(I17:IF17) -> 404.74486 | H17: Sus. | I17: =0.9*SUM(I63:I81) -> 115.58415 | J17: =0.9*SUM(J63:J81) -> 95.528404 | K17: =0.9*SUM(K63:K81) -> 96.816152 | L17: =0.9*SUM(L63:L81) -> 96.816152
A18: Mano de obra | D18: =+D62*0.9 -> 43.092 | E18: =+E62*0.9 -> 82.593 | G18: =SUM(I18:IF18) -> 435.6396 | H18: Sus. | I18: =+I62*0.9 -> 130.9176 | J18: =+J62*0.9 -> 119.6316 | K18: =+K62*0.9 -> 92.5452 | L18: =+L62*0.9 -> 92.5452
A19: Otros Gastos + Util | D19: =+D11-SUM(D16:D18) -> 27.185393 | E19: =+E11-SUM(E16:E18) -> 51.050703 | G19: =SUM(I19:IF19) -> 247.34415 | H19: Sus. | I19: =+I11-SUM(I16:I18) -> 73.579514 | J19: =+J11-SUM(J16:J18) -> 66.149197 | K19: =+K11-SUM(K16:K18) -> 53.80772 | L19: =+L11-SUM(L16:L18) -> 53.80772
A20: TOTAL | D20: =SUM(D16:D19) -> 271.85393 | E20: =SUM(E16:E19) -> 510.50703 | G20: =SUM(I20:IF20) -> 2473.4415 | H20: Sus. | I20: =SUM(I16:I19) -> 735.79514 | J20: =SUM(J16:J19) -> 661.49197 | K20: =SUM(K16:K19) -> 538.0772 | L20: =SUM(L16:L19) -> 538.0772
A21: Materia Prima ( Vidrio ) / Mt2 | D21: =+D16/D$12 -> 33.108525 | E21: =+E16/E$12 -> 32.762443 | G21: =SUM(I21:IF21) -> 79.507726 | H21: Sus. | I21: =0.9*SUM(I63:I66) -> 18.7416 | J21: =+J16/J$12 -> 32.605726 | K21: =0.9*SUM(K63:K66) -> 14.0802 | L21: =0.9*SUM(L63:L66) -> 14.0802
A22: Materia Prima ( materiales ) / Mt2 | D22: =+D17/D$12 -> 14.885888 | E22: =+E17/E$12 -> 14.052878 | G22: =SUM(I22:IF22) -> 2808.665 | H22: Sus. | I22: =0.9*SUM(I68:I86) -> 1134.6191 | J22: =+J17/J$12 -> 8.1928305 | K22: =0.9*SUM(K68:K86) -> 832.92654 | L22: =0.9*SUM(L68:L86) -> 832.92654
A23: Mano de obra / Mt2 | D23: =+D18/D$12 -> 10.26 | E23: =+E18/E$12 -> 10.26 | G23: =SUM(I23:IF23) -> 13.968 | H23: Sus. | I23: =+I67*0.9 -> 1.44 | J23: =+J18/J$12 -> 10.26 | K23: =+K67*0.9 -> 1.134 | L23: =+L67*0.9 -> 1.134
A24: Otros Gastos + Util / Mt2 | D24: =+D19/D$12 -> 6.4727125 | E24: =+E19/E$12 -> 6.3417023 | G24: =SUM(I24:IF24) -> -1839.8789 | H24: Sus. | I24: =+I16-SUM(I21:I23) -> -739.08681 | J24: =+J19/J$12 -> 5.673173 | K24: =+K16-SUM(K21:K23) -> -553.23261 | L24: =+L16-SUM(L21:L23) -> -553.23261
A25: TOTAL | D25: =SUM(D21:D24) -> 64.727125 | E25: =SUM(E21:E24) -> 63.417023 | G25: =SUM(I25:IF25) -> 1062.2619 | H25: Sus. | I25: =SUM(I21:I24) -> 415.71387 | J25: =SUM(J21:J24) -> 56.73173 | K25: =SUM(K21:K24) -> 294.90813 | L25: =SUM(L21:L24) -> 294.90813
A26: % descuento del con al sin | D26: =+(D11-D14)/D11 -> -0.0778343 | E26: =+(E11-E14)/E11 -> -0.029790931 | G26: =ROUNDDOWN(+(G11-G14)/G11,2) -> 0.02 | I26: =+(I11-I14)/I11 -> 0.036770561 | J26: =+(J11-J14)/J11 -> -0.013214673 | K26: =+(K11-K14)/K11 -> 0.036475435 | L26: =+(L11-L14)/L11 -> 0.036475435
G27: =+G11+'Pano Fijo'!F12+('Costo M.P.yMat.'!L15*4) -> 4973.4232
A28: DETALLE DE MATERIALES A UTILIZAR
A29: MATERIAL | C29: Unidad | D29: =+D2 -> VC2H | E29: =+E2 -> VC4H | G29: Cantidad | H29: Unidad | I29: =+I2 -> piso1 | J29: =+J2 -> piso1 | K29: =+K2 -> piso12 | L29: =+L2 -> piso12
A30: Vidrio Templado 10mm Incoloro | C30: Mt² | D30: =IF(D$9=1,IF(D$10=10,((D$6*0.05)+(D$5*D$6))*D$7,0),0) -> 4.305 | E30: =IF(E$9=1,IF(E$10=10,((E$6*0.05)+(E$5*E$6))*E$7,0),0) -> 8.165 | F30: 17 | G30: =ROUNDUP(SUM(I30:IF30),1) -> 42.9 | H30: Mt² | I30: =IF(I$9=1,IF(I$10=10,((I$6*0.05)+(I$5*I$6))*I$7,0),0) -> 12.87 | J30: =IF(J$9=1,IF(J$10=10,((J$6*0.05)+(J$5*J$6))*J$7,0),0) -> 11.77 | K30: =IF(K$9=1,IF(K$10=10,((K$6*0.05)+(K$5*K$6))*K$7,0),0) -> 9.13 | L30: =IF(L$9=1,IF(L$10=10,((L$6*0.05)+(L$5*L$6))*L$7,0),0) -> 9.13
A31: Vidrio Templado 10mm Color | C31: Mt² | D31: =IF(D$9=2,IF(D$10=10,((D$6*0.05)+(D$5*D$6))*D$7,0),0) -> 0 | E31: =IF(E$9=2,IF(E$10=10,((E$6*0.05)+(E$5*E$6))*E$7,0),0) -> 0 | F31: 22 | G31: =ROUNDUP(SUM(I31:IF31),1) -> 0 | H31: Mt² | I31: =IF(I$9=2,IF(I$10=10,((I$6*0.05)+(I$5*I$6))*I$7,0),0) -> 0 | J31: =IF(J$9=2,IF(J$10=10,((J$6*0.05)+(J$5*J$6))*J$7,0),0) -> 0 | K31: =IF(K$9=2,IF(K$10=10,((K$6*0.05)+(K$5*K$6))*K$7,0),0) -> 0 | L31: =IF(L$9=2,IF(L$10=10,((L$6*0.05)+(L$5*L$6))*L$7,0),0) -> 0
A32: Vidrio Templado 8mm Incoloro | C32: Mt² | D32: =IF(D$9=1,IF(D$10=8,((D$6*0.05)+(D$5*D$6))*D$7,0),0) -> 0 | E32: =IF(E$9=1,IF(E$10=8,((E$6*0.05)+(E$5*E$6))*E$7,0),0) -> 0 | F32: 18 | G32: =ROUNDUP(SUM(I32:IF32),1) -> 0 | H32: Mt² | I32: =IF(I$9=1,IF(I$10=8,((I$6*0.05)+(I$5*I$6))*I$7,0),0) -> 0 | J32: =IF(J$9=1,IF(J$10=8,((J$6*0.05)+(J$5*J$6))*J$7,0),0) -> 0 | K32: =IF(K$9=1,IF(K$10=8,((K$6*0.05)+(K$5*K$6))*K$7,0),0) -> 0 | L32: =IF(L$9=1,IF(L$10=8,((L$6*0.05)+(L$5*L$6))*L$7,0),0) -> 0
A33: Vidrio Templado 8mm Color | C33: Mt² | D33: =IF(D$9=2,IF(D$10=8,((D$6*0.05)+(D$5*D$6))*D$7,0),0) -> 0 | E33: =IF(E$9=2,IF(E$10=8,((E$6*0.05)+(E$5*E$6))*E$7,0),0) -> 0 | F33: 23 | G33: =ROUNDUP(SUM(I33:IF33),1) -> 0 | H33: Mt² | I33: =IF(I$9=2,IF(I$10=8,((I$6*0.05)+(I$5*I$6))*I$7,0),0) -> 0 | J33: =IF(J$9=2,IF(J$10=8,((J$6*0.05)+(J$5*J$6))*J$7,0),0) -> 0 | K33: =IF(K$9=2,IF(K$10=8,((K$6*0.05)+(K$5*K$6))*K$7,0),0) -> 0 | L33: =IF(L$9=2,IF(L$10=8,((L$6*0.05)+(L$5*L$6))*L$7,0),0) -> 0
A34: Mano de obra | C34: Mt² | D34: =+D12 -> 4.2 | E34: =+E12 -> 8.05 | F34: 75 | G34: =ROUNDUP(SUM(I34:IF34),1) -> 42.5 | H34: Mt² | I34: =+I12 -> 12.76 | J34: =+J12 -> 11.66 | K34: =+K12 -> 9.02 | L34: =+L12 -> 9.02
A35: Silicona transparente, blanca o negra | C35: Tubo | D35: =D7*(4*D5+2*D6)/6 -> 2.0333333 | E35: =E7*(4*E5+2*E6)/6 -> 3.1 | F35: 1 | G35: =ROUNDUP(SUM(I35:IF35),1) -> 15.8 | H35: Tubo | I35: =I7*(4*I5+2*I6)/6 -> 4.6 | J35: =J7*(4*J5+2*J6)/6 -> 4.2666667 | K35: =K7*(4*K5+2*K6)/6 -> 3.4666667 | L35: =L7*(4*L5+2*L6)/6 -> 3.4666667
A36: Cinta masking 1/2 " (rollo de 20) | C36: Rollo | D36: =+D35*12/20 -> 1.22 | E36: =+E35*12/20 -> 1.86 | F36: 3 | G36: =ROUNDUP(SUM(I36:IF36),1) -> 9.5 | H36: Rollo | I36: =+I35*12/20 -> 2.76 | J36: =+J35*12/20 -> 2.56 | K36: =+K35*12/20 -> 2.08 | L36: =+L35*12/20 -> 2.08
A37: "U" 15x25 - Kg/Mt lineal. | C37: Mt lineal | D37: =2*D$6*D$7 -> 4.2 | E37: =2*E$6*E$7 -> 4.6 | F37: 5 | G37: =ROUNDUP(SUM(I37:IF37)/(6*B37),1) -> #DIV/0! | H37: Barras | I37: =2*I$6*$B37*I$7 -> 0 | J37: =2*J$6*J$7 -> 4.4 | K37: =2*K$6*$B37*K$7 -> 0 | L37: =2*L$6*$B37*L$7 -> 0
A38: Felpa | C38: Mt lineal | D38: =(D6+3*D5)*D7 -> 8.1 | E38: =(E6+3*E5)*E7 -> 12.8 | F38: 11 | G38: =ROUNDUP(SUM(I38:IF38),1) -> 66.7 | H38: Mt lineal | I38: =(I6+3*I5)*I7 -> 19.6 | J38: =(J6+3*J5)*J7 -> 18.1 | K38: =(K6+3*K5)*K7 -> 14.5 | L38: =(L6+3*L5)*L7 -> 14.5
A39: Tarugos No. 6 | C39: Pza. | D39: =D$7*(2*D$5+2*D$6)/0.4 -> 20.5 | E39: =E$7*(2*E$5+2*E$6)/0.4 -> 29 | F39: 13 | G39: =ROUNDUP(SUM(I39:IF39),1) -> 140.5 | H39: Pza. | I39: =I$7*(2*I$5+2*I$6)/0.4 -> 40 | J39: =J$7*(2*J$5+2*J$6)/0.4 -> 37.5 | K39: =K$7*(2*K$5+2*K$6)/0.4 -> 31.5 | L39: =L$7*(2*L$5+2*L$6)/0.4 -> 31.5
A40: Tornillos 8 x 1 1/2 | C40: Pza. | D40: =D$7*(2*D$5+2*D$6)/0.4 -> 20.5 | E40: =E$7*(2*E$5+2*E$6)/0.4 -> 29 | F40: 14 | G40: =ROUNDUP(SUM(I40:IF40),1) -> 140.5 | H40: Pza. | I40: =I$7*(2*I$5+2*I$6)/0.4 -> 40 | J40: =J$7*(2*J$5+2*J$6)/0.4 -> 37.5 | K40: =K$7*(2*K$5+2*K$6)/0.4 -> 31.5 | L40: =L$7*(2*L$5+2*L$6)/0.4 -> 31.5
A41: Vedapres 001 - u - Kg/Mt l. | B41: 0.151 | C41: Kgr | D41: =+D$6*$B41*D$7 -> 0.3171 | E41: =2*E$6*$B41*E$7 -> 0.6946 | F41: 30 | G41: =ROUNDUP(SUM(I41:IF41)/(6*B41),1) -> 2.6 | H41: Barras | I41: =2*I$6*$B41*I$7 -> 0.6644 | J41: =+J$6*$B41*J$7 -> 0.3322 | K41: =2*K$6*$B41*K$7 -> 0.6644 | L41: =2*L$6*$B41*L$7 -> 0.6644
A42: Vedapres 001 - h - Kg/Mt l. | B42: 0.257 | C42: Kgr | E42: =+E$6*$B42*E$7 -> 0.5911 | F42: 31 | G42: =ROUNDUP(SUM(I42:IF42)/(6*B42),1) -> 1.1 | H42: Barras | I42: =+I$6*$B42*I$7 -> 0.5654 | K42: =+K$6*$B42*K$7 -> 0.5654 | L42: =+L$6*$B42*L$7 -> 0.5654
A43: CTGyTt 2,013 | B43: 2.013 | C43: Kgr | D43: =D$5*D$7*$B$43 -> 4.026 | E43: =E$5*E$7*$B$43 -> 7.0455 | F43: 88 | G43: =ROUNDUP(SUM(I43:IF43)/6,1) -> 3.3 | H43: Barras | I43: =I$5*I$7 -> 5.8 | J43: =J$5*J$7 -> 5.3 | K43: =K$5*K$7 -> 4.1 | L43: =L$5*L$7 -> 4.1
C44: Kgr | G44: =ROUNDUP(SUM(I44:IF44)/6,1) -> 0 | H44: Barras
C45: Kgr | G45: =ROUNDUP(SUM(I45:IF45)/6,1) -> 0 | H45: Barras
C46: Kgr | G46: =ROUNDUP(SUM(I46:IF46)/6,1) -> 0 | H46: Barras
A47: 1510 | C47: Pza. | D47: =IF(D$8=1,+D$7,0) -> 0 | E47: =IF(E$8=1,+E$7,0) -> 0 | F47: 64 | G47: =ROUNDUP(SUM(I47:IF47),1) -> 4 | H47: Pza. | I47: =IF(I$8=1,+I$7,0) -> 1 | J47: =IF(J$8=1,+J$7,0) -> 1 | K47: =IF(K$8=1,+K$7,0) -> 1 | L47: =IF(L$8=1,+L$7,0) -> 1
A48: 1511 | C48: Pza. | E48: =IF(E$8=1,+E$7,0) -> 0 | F48: 65 | G48: =ROUNDUP(SUM(I48:IF48),1) -> 3 | H48: Pza. | I48: =IF(I$8=1,+I$7,0) -> 1 | K48: =IF(K$8=1,+K$7,0) -> 1 | L48: =IF(L$8=1,+L$7,0) -> 1
A49: 1511a | C49: Pza. | D49: =IF(D$8=1,+D$7,0) -> 0 | F49: 66 | G49: =ROUNDUP(SUM(I49:IF49),1) -> 1 | H49: Pza. | J49: =IF(J$8=1,+J$7,0) -> 1
A50: 1125a | C50: Pza. | D50: =2*D7 -> 2 | E50: =4*E7 -> 4 | F50: 50 | G50: =ROUNDUP(SUM(I50:IF50),1) -> 14 | H50: Pza. | I50: =4*I7 -> 4 | J50: =2*J7 -> 2 | K50: =4*K7 -> 4 | L50: =4*L7 -> 4
A51: 1629j | C51: Pza. | D51: =IF(D$8=2,+D$7,0) -> 1 | E51: =IF(E$8=2,2*E$7,0) -> 2 | F51: 70 | G51: =ROUNDUP(SUM(I51:IF51),1) -> 0 | H51: Pza. | I51: =IF(I$8=2,2*I$7,0) -> 0 | J51: =IF(J$8=2,+J$7,0) -> 0 | K51: =IF(K$8=2,2*K$7,0) -> 0 | L51: =IF(L$8=2,2*L$7,0) -> 0
A52: 1335 | C52: Pza. | D52: =IF(D$8=2,+D$7,0) -> 1 | E52: =IF(E$8=2,2*E$7,0) -> 2 | F52: 61 | G52: =ROUNDUP(SUM(I52:IF52),1) -> 0 | H52: Pza. | I52: =IF(I$8=2,2*I$7,0) -> 0 | J52: =IF(J$8=2,+J$7,0) -> 0 | K52: =IF(K$8=2,2*K$7,0) -> 0 | L52: =IF(L$8=2,2*L$7,0) -> 0
A53: 1038c | C53: Pza. | D53: =IF(D$8=2,+D$7,0) -> 1 | E53: =IF(E$8=2,2*E$7,0) -> 2 | F53: 42 | G53: =ROUNDUP(SUM(I53:IF53),1) -> 0 | H53: Pza. | I53: =IF(I$8=2,2*I$7,0) -> 0 | J53: =IF(J$8=2,+J$7,0) -> 0 | K53: =IF(K$8=2,2*K$7,0) -> 0 | L53: =IF(L$8=2,2*L$7,0) -> 0
A57: COSTO CON FACTURA | D57: =SUM(D58:D81) -> 271.85393 | E57: =SUM(E58:E81) -> 510.50703 | G57: =SUM(G58:G81) -> 450.5 | I57: =SUM(I58:I81) -> 735.79514 | J57: =SUM(J58:J81) -> 661.49197 | K57: =SUM(K58:K81) -> 538.0772 | L57: =SUM(L58:L81) -> 538.0772
A58: Vidrio Templado 10mm Incoloro | C58: =+'Costo M.P.yMat.'!F24 -> 35.89 | D58: =+$C58*D30 -> 154.50645 | E58: =+$C58*E30 -> 293.04185 | F58: 17 | I58: =+$C58*I30 -> 461.9043 | J58: =+$C58*J30 -> 422.4253 | K58: =+$C58*K30 -> 327.6757 | L58: =+$C58*L30 -> 327.6757
A59: Vidrio Templado 10mm Color | C59: =+'Costo M.P.yMat.'!F29 -> 46.66 | D59: =+$C59*D31 -> 0 | E59: =+$C59*E31 -> 0 | F59: 22 | G59: =ROUNDUP(SUM(I59:IF59),1) -> 0 | I59: =+$C59*I31 -> 0 | J59: =+$C59*J31 -> 0 | K59: =+$C59*K31 -> 0 | L59: =+$C59*L31 -> 0
A60: Vidrio Templado 8mm Incoloro | C60: =+'Costo M.P.yMat.'!F25 -> 34.7 | D60: =+$C60*D32 -> 0 | E60: =+$C60*E32 -> 0 | F60: 18 | G60: =ROUNDUP(SUM(I60:IF60),1) -> 0 | I60: =+$C60*I32 -> 0 | J60: =+$C60*J32 -> 0 | K60: =+$C60*K32 -> 0 | L60: =+$C60*L32 -> 0
A61: Vidrio Templado 8mm Color | C61: =+'Costo M.P.yMat.'!F30 -> 45.46 | D61: =+$C61*D33 -> 0 | E61: =+$C61*E33 -> 0 | F61: 23 | G61: =ROUNDUP(SUM(I61:IF61),1) -> 0 | I61: =+$C61*I33 -> 0 | J61: =+$C61*J33 -> 0 | K61: =+$C61*K33 -> 0 | L61: =+$C61*L33 -> 0
A62: Mano de obra | C62: =+'Costo M.P.yMat.'!F82 -> 11.4 | D62: =+$C62*D34 -> 47.88 | E62: =+$C62*E34 -> 91.77 | F62: 75 | I62: =+$C62*I34 -> 145.464 | J62: =+$C62*J34 -> 132.924 | K62: =+$C62*K34 -> 102.828 | L62: =+$C62*L34 -> 102.828
A63: Silicona transp., blanca o negra | C63: =+'Costo M.P.yMat.'!F7 -> 3.31 | D63: =+$C63*D35 -> 6.7303333 | E63: =+$C63*E35 -> 10.261 | F63: 1 | G63: =ROUNDUP(SUM(I63:IF63),1) -> 52.3 | I63: =+$C63*I35 -> 15.226 | J63: =+$C63*J35 -> 14.122667 | K63: =+$C63*K35 -> 11.474667 | L63: =+$C63*L35 -> 11.474667
A64: Cinta masking 1/2 " (rollo de 20) | C64: =+'Costo M.P.yMat.'!F9 -> 0.75 | D64: =+$C64*D36 -> 0.915 | E64: =+$C64*E36 -> 1.395 | F64: 3 | G64: =ROUNDUP(SUM(I64:IF64),1) -> 7.2 | I64: =+$C64*I36 -> 2.07 | J64: =+$C64*J36 -> 1.92 | K64: =+$C64*K36 -> 1.56 | L64: =+$C64*L36 -> 1.56
A65: "U" 15x25 - Kg/Mt lineal. | C65: =+'Costo M.P.yMat.'!F11 -> 1.29 | D65: =+$C65*D37 -> 5.418 | E65: =+$C65*E37 -> 5.934 | F65: 5 | G65: =ROUNDUP(SUM(I65:IF65),1) -> 5.7 | H65: =+#REF!/6 -> #REF! | I65: =+$C65*I37 -> 0 | J65: =+$C65*J37 -> 5.676 | K65: =+$C65*K37 -> 0 | L65: =+$C65*L37 -> 0
A66: Felpa | C66: =+'Costo M.P.yMat.'!F17 -> 0.18 | D66: =+$C66*D38 -> 1.458 | E66: =+$C66*E38 -> 2.304 | F66: 11 | G66: =ROUNDUP(SUM(I66:IF66),1) -> 12.1 | I66: =+$C66*I38 -> 3.528 | J66: =+$C66*J38 -> 3.258 | K66: =+$C66*K38 -> 2.61 | L66: =+$C66*L38 -> 2.61
A67: Tarugos No. 6 | C67: =+'Costo M.P.yMat.'!F19 -> 0.04 | D67: =+$C67*D39 -> 0.82 | E67: =+$C67*E39 -> 1.16 | F67: 13 | G67: =ROUNDUP(SUM(I67:IF67),1) -> 5.7 | I67: =+$C67*I39 -> 1.6 | J67: =+$C67*J39 -> 1.5 | K67: =+$C67*K39 -> 1.26 | L67: =+$C67*L39 -> 1.26
A68: Tornillos 8 x 1 1/2 | C68: =+'Costo M.P.yMat.'!F20 -> 0.04 | D68: =+$C68*D40 -> 0.82 | E68: =+$C68*E40 -> 1.16 | F68: 14 | G68: =ROUNDUP(SUM(I68:IF68),1) -> 5.7 | I68: =+$C68*I40 -> 1.6 | J68: =+$C68*J40 -> 1.5 | K68: =+$C68*K40 -> 1.26 | L68: =+$C68*L40 -> 1.26
A69: Vedapres 001 - u - Kg/Mt l. | B69: 0.151 | C69: =+'Costo M.P.yMat.'!$F$96 -> 8.82 | D69: =+$C69*D41 -> 2.796822 | E69: =+$C69*E41 -> 6.126372 | F69: 30 | G69: =ROUNDUP(SUM(I69:IF69),1) -> 20.6 | I69: =+$C69*I41 -> 5.860008 | J69: =+$C69*J41 -> 2.930004 | K69: =+$C69*K41 -> 5.860008 | L69: =+$C69*L41 -> 5.860008
A70: Vedapres 001 - h - Kg/Mt l. | B70: 0.257 | C70: =+'Costo M.P.yMat.'!$F$96 -> 8.82 | D70: =+$C70*D42 -> 0 | E70: =+$C70*E42 -> 5.213502 | F70: 31 | G70: =ROUNDUP(SUM(I70:IF70),1) -> 15 | I70: =+$C70*I42 -> 4.986828 | J70: =+$C70*J42 -> 0 | K70: =+$C70*K42 -> 4.986828 | L70: =+$C70*L42 -> 4.986828
A71: CTGyTt 2,013 | B71: 2.013 | C71: =+'Costo M.P.yMat.'!F96 -> 8.82 | D71: =+$C71*D43 -> 35.50932 | E71: =+$C71*E43 -> 62.14131 | F71: 88 | G71: =ROUNDUP(SUM(I71:IF71),1) -> 170.3 | I71: =+$C71*I43 -> 51.156 | J71: =+$C71*J43 -> 46.746 | K71: =+$C71*K43 -> 36.162 | L71: =+$C71*L43 -> 36.162
B72: 0.408 | C72: =+'Costo M.P.yMat.'!$M$96 -> 0 | G72: =ROUNDUP(SUM(I72:IF72),1) -> 0 | H72: =+#REF!/6 -> #REF!
B73: 0.478 | C73: =+'Costo M.P.yMat.'!$M$96 -> 0 | G73: =ROUNDUP(SUM(I73:IF73),1) -> 0 | H73: =+#REF!/6 -> #REF!
B74: 0.125 | C74: =+'Costo M.P.yMat.'!$M$96 -> 0 | G74: =ROUNDUP(SUM(I74:IF74),1) -> 0 | H74: =+#REF!/6 -> #REF!
A75: 1510 | C75: =+'Costo M.P.yMat.'!F71 -> 20.68 | D75: =+$C75*D47 -> 0 | E75: =+$C75*E47 -> 0 | F75: 64 | G75: =ROUNDUP(SUM(I75:IF75),1) -> 82.8 | I75: =+$C75*I47 -> 20.68 | J75: =+$C75*J47 -> 20.68 | K75: =+$C75*K47 -> 20.68 | L75: =+$C75*L47 -> 20.68
A76: 1511 | C76: =+'Costo M.P.yMat.'!F72 -> 11 | D76: =+$C76*D48 -> 0 | E76: =+$C76*E48 -> 0 | F76: 65 | G76: =ROUNDUP(SUM(I76:IF76),1) -> 33 | I76: =+$C76*I48 -> 11 | J76: =+$C76*J48 -> 0 | K76: =+$C76*K48 -> 11 | L76: =+$C76*L48 -> 11
A77: 1511a | C77: =+'Costo M.P.yMat.'!F73 -> 2.45 | D77: =+$C77*D49 -> 0 | E77: =+$C77*E49 -> 0 | F77: 66 | G77: =ROUNDUP(SUM(I77:IF77),1) -> 2.5 | I77: =+$C77*I49 -> 0 | J77: =+$C77*J49 -> 2.45 | K77: =+$C77*K49 -> 0 | L77: =+$C77*L49 -> 0
A78: 1125a | C78: =+'Costo M.P.yMat.'!F57 -> 2.68 | D78: =+$C78*D50 -> 5.36 | E78: =+$C78*E50 -> 10.72 | F78: 50 | G78: =ROUNDUP(SUM(I78:IF78),1) -> 37.6 | I78: =+$C78*I50 -> 10.72 | J78: =+$C78*J50 -> 5.36 | K78: =+$C78*K50 -> 10.72 | L78: =+$C78*L50 -> 10.72
A79: 1629j | C79: =+'Costo M.P.yMat.'!F77 -> 2.45 | D79: =+$C79*D51 -> 2.45 | E79: =+$C79*E51 -> 4.9 | F79: 70 | G79: =ROUNDUP(SUM(I79:IF79),1) -> 0 | I79: =+$C79*I51 -> 0 | J79: =+$C79*J51 -> 0 | K79: =+$C79*K51 -> 0 | L79: =+$C79*L51 -> 0
A80: 1335 | C80: =+'Costo M.P.yMat.'!F68 -> 5.87 | D80: =+$C80*D52 -> 5.87 | E80: =+$C80*E52 -> 11.74 | F80: 61 | G80: =ROUNDUP(SUM(I80:IF80),1) -> 0 | I80: =+$C80*I52 -> 0 | J80: =+$C80*J52 -> 0 | K80: =+$C80*K52 -> 0 | L80: =+$C80*L52 -> 0
A81: 1038c | C81: =+'Costo M.P.yMat.'!F49 -> 1.32 | D81: =+$C81*D53 -> 1.32 | E81: =+$C81*E53 -> 2.64 | F81: 42 | G81: =ROUNDUP(SUM(I81:IF81),1) -> 0 | I81: =+$C81*I53 -> 0 | J81: =+$C81*J53 -> 0 | K81: =+$C81*K53 -> 0 | L81: =+$C81*L53 -> 0
A84: COSTO SIN FACTURA | D84: =SUM(D85:D108) -> 293.01349 | E84: =SUM(E85:E108) -> 525.71551 | G84: =ROUNDUP(SUM(I84:IF84),1) -> 2415.9 | I84: =SUM(I85:I108) -> 708.73954 | J84: =SUM(J85:J108) -> 670.23337 | K84: =SUM(K85:K108) -> 518.4506 | L84: =SUM(L85:L108) -> 518.4506
A85: Vidrio Templado 10mm Incoloro | C85: =+'Costo M.P.yMat.'!G24 -> 34.65 | D85: =+$C85*D30 -> 149.16825 | E85: =+$C85*E30 -> 282.91725 | F85: 17 | G85: =ROUNDUP(SUM(I85:IF85),1) -> 1486.5 | I85: =+$C85*I30 -> 445.9455 | J85: =+$C85*J30 -> 407.8305 | K85: =+$C85*K30 -> 316.3545 | L85: =+$C85*L30 -> 316.3545
A86: Vidrio Templado 10mm Color | C86: =+'Costo M.P.yMat.'!G29 -> 45.05 | D86: =+$C86*D31 -> 0 | E86: =+$C86*E31 -> 0 | F86: 22 | G86: =ROUNDUP(SUM(I86:IF86),1) -> 0 | I86: =+$C86*I31 -> 0 | J86: =+$C86*J31 -> 0 | K86: =+$C86*K31 -> 0 | L86: =+$C86*L31 -> 0
A87: Vidrio Templado 8mm Incoloro | C87: =+'Costo M.P.yMat.'!G25 -> 33.5 | D87: =+$C87*D32 -> 0 | E87: =+$C87*E32 -> 0 | F87: 18 | G87: =ROUNDUP(SUM(I87:IF87),1) -> 0 | I87: =+$C87*I32 -> 0 | J87: =+$C87*J32 -> 0 | K87: =+$C87*K32 -> 0 | L87: =+$C87*L32 -> 0
A88: Vidrio Templado 8mm Color | C88: =+'Costo M.P.yMat.'!G30 -> 43.89 | D88: =+$C88*D33 -> 0 | E88: =+$C88*E33 -> 0 | F88: 23 | G88: =ROUNDUP(SUM(I88:IF88),1) -> 0 | I88: =+$C88*I33 -> 0 | J88: =+$C88*J33 -> 0 | K88: =+$C88*K33 -> 0 | L88: =+$C88*L33 -> 0
A89: Mano de obra | C89: =+'Costo M.P.yMat.'!G82 -> 11 | D89: =+$C89*D34 -> 46.2 | E89: =+$C89*E34 -> 88.55 | F89: 75 | G89: =ROUNDUP(SUM(I89:IF89),1) -> 467.1 | I89: =+$C89*I34 -> 140.36 | J89: =+$C89*J34 -> 128.26 | K89: =+$C89*K34 -> 99.22 | L89: =+$C89*L34 -> 99.22
A90: Silicona transp., blanca o negra | C90: =+'Costo M.P.yMat.'!G7 -> 3.19 | D90: =+$C90*D35 -> 6.4863333 | E90: =+$C90*E35 -> 9.889 | F90: 1 | G90: =ROUNDUP(SUM(I90:IF90),1) -> 50.5 | I90: =+$C90*I35 -> 14.674 | J90: =+$C90*J35 -> 13.610667 | K90: =+$C90*K35 -> 11.058667 | L90: =+$C90*L35 -> 11.058667
A91: Cinta masking 1/2 " (rollo de 20) | C91: =+'Costo M.P.yMat.'!G9 -> 0.72 | D91: =+$C91*D36 -> 0.8784 | E91: =+$C91*E36 -> 1.3392 | F91: 3 | G91: =ROUNDUP(SUM(I91:IF91),1) -> 6.9 | I91: =+$C91*I36 -> 1.9872 | J91: =+$C91*J36 -> 1.8432 | K91: =+$C91*K36 -> 1.4976 | L91: =+$C91*L36 -> 1.4976
A92: "U" 15x25 - Kg/Mt lineal. | B92: 0.2 | C92: =+'Costo M.P.yMat.'!$F$96 -> 8.82 | D92: =+$C92*D37 -> 37.044 | E92: =+$C92*E37 -> 40.572 | F92: 5 | G92: =ROUNDUP(SUM(I92:IF92),1) -> 38.9 | I92: =+$C92*I37 -> 0 | J92: =+$C92*J37 -> 38.808 | K92: =+$C92*K37 -> 0 | L92: =+$C92*L37 -> 0
A93: Felpa | C93: =+'Costo M.P.yMat.'!G17 -> 0.17 | D93: =+$C93*D38 -> 1.377 | E93: =+$C93*E38 -> 2.176 | F93: 11 | G93: =ROUNDUP(SUM(I93:IF93),1) -> 11.4 | I93: =+$C93*I38 -> 3.332 | J93: =+$C93*J38 -> 3.077 | K93: =+$C93*K38 -> 2.465 | L93: =+$C93*L38 -> 2.465
A94: Tarugos No. 6 | C94: =+'Costo M.P.yMat.'!G19 -> 0.04 | D94: =+$C94*D39 -> 0.82 | E94: =+$C94*E39 -> 1.16 | F94: 13 | G94: =ROUNDUP(SUM(I94:IF94),1) -> 5.7 | I94: =+$C94*I39 -> 1.6 | J94: =+$C94*J39 -> 1.5 | K94: =+$C94*K39 -> 1.26 | L94: =+$C94*L39 -> 1.26
A95: Tornillos 8 x 1 1/2 | C95: =+'Costo M.P.yMat.'!G20 -> 0.04 | D95: =+$C95*D40 -> 0.82 | E95: =+$C95*E40 -> 1.16 | F95: 14 | G95: =ROUNDUP(SUM(I95:IF95),1) -> 5.7 | I95: =+$C95*I40 -> 1.6 | J95: =+$C95*J40 -> 1.5 | K95: =+$C95*K40 -> 1.26 | L95: =+$C95*L40 -> 1.26
A96: Vedapres 001 - u - Kg/Mt l. | B96: 0.151 | C96: =+'Costo M.P.yMat.'!$F$96 -> 8.82 | D96: =+$C96*D41 -> 2.796822 | E96: =+$C96*E41 -> 6.126372 | F96: 30 | G96: =ROUNDUP(SUM(I96:IF96),1) -> 20.6 | I96: =+$C96*I41 -> 5.860008 | J96: =+$C96*J41 -> 2.930004 | K96: =+$C96*K41 -> 5.860008 | L96: =+$C96*L41 -> 5.860008
A97: Vedapres 001 - h - Kg/Mt l. | B97: 0.257 | C97: =+'Costo M.P.yMat.'!$F$96 -> 8.82 | D97: =+$C97*D42 -> 0 | E97: =+$C97*E42 -> 5.213502 | F97: 31 | G97: =ROUNDUP(SUM(I97:IF97),1) -> 15 | I97: =+$C97*I42 -> 4.986828 | J97: =+$C97*J42 -> 0 | K97: =+$C97*K42 -> 4.986828 | L97: =+$C97*L42 -> 4.986828
A98: CTGyTt 2,013 | B98: 2.013 | C98: =+'Costo M.P.yMat.'!$G$96 -> 8.18 | D98: =+$C98*D43 -> 32.93268 | E98: =+$C98*E43 -> 57.63219 | F98: 88 | G98: =ROUNDUP(SUM(I98:IF98),1) -> 157.9 | I98: =+$C98*I43 -> 47.444 | J98: =+$C98*J43 -> 43.354 | K98: =+$C98*K43 -> 33.538 | L98: =+$C98*L43 -> 33.538
D99: =+$C99*D44 -> 0 | E99: =+$C99*E44 -> 0 | G99: =ROUNDUP(SUM(I99:IF99),1) -> 0 | I99: =+$C99*I44 -> 0 | J99: =+$C99*J44 -> 0 | K99: =+$C99*K44 -> 0 | L99: =+$C99*L44 -> 0
D100: =+$C100*D45 -> 0 | E100: =+$C100*E45 -> 0 | G100: =ROUNDUP(SUM(I100:IF100),1) -> 0 | I100: =+$C100*I45 -> 0 | J100: =+$C100*J45 -> 0 | K100: =+$C100*K45 -> 0 | L100: =+$C100*L45 -> 0
D101: =+$C101*D46 -> 0 | E101: =+$C101*E46 -> 0 | G101: =ROUNDUP(SUM(I101:IF101),1) -> 0 | I101: =+$C101*I46 -> 0 | J101: =+$C101*J46 -> 0 | K101: =+$C101*K46 -> 0 | L101: =+$C101*L46 -> 0
A102: 1510 | C102: =+'Costo M.P.yMat.'!G71 -> 19.97 | D102: =+$C102*D47 -> 0 | E102: =+$C102*E47 -> 0 | F102: 64 | G102: =ROUNDUP(SUM(I102:IF102),1) -> 79.9 | I102: =+$C102*I47 -> 19.97 | J102: =+$C102*J47 -> 19.97 | K102: =+$C102*K47 -> 19.97 | L102: =+$C102*L47 -> 19.97
A103: 1511 | C103: =+'Costo M.P.yMat.'!G72 -> 10.62 | D103: =+$C103*D48 -> 0 | E103: =+$C103*E48 -> 0 | F103: 65 | G103: =ROUNDUP(SUM(I103:IF103),1) -> 31.9 | I103: =+$C103*I48 -> 10.62 | J103: =+$C103*J48 -> 0 | K103: =+$C103*K48 -> 10.62 | L103: =+$C103*L48 -> 10.62
A104: 1511a | C104: =+'Costo M.P.yMat.'!G73 -> 2.37 | D104: =+$C104*D49 -> 0 | E104: =+$C104*E49 -> 0 | F104: 66 | G104: =ROUNDUP(SUM(I104:IF104),1) -> 2.4 | I104: =+$C104*I49 -> 0 | J104: =+$C104*J49 -> 2.37 | K104: =+$C104*K49 -> 0 | L104: =+$C104*L49 -> 0
A105: 1125a | C105: =+'Costo M.P.yMat.'!G57 -> 2.59 | D105: =+$C105*D50 -> 5.18 | E105: =+$C105*E50 -> 10.36 | F105: 50 | G105: =ROUNDUP(SUM(I105:IF105),1) -> 36.3 | I105: =+$C105*I50 -> 10.36 | J105: =+$C105*J50 -> 5.18 | K105: =+$C105*K50 -> 10.36 | L105: =+$C105*L50 -> 10.36
A106: 1629j | C106: =+'Costo M.P.yMat.'!G77 -> 2.37 | D106: =+$C106*D51 -> 2.37 | E106: =+$C106*E51 -> 4.74 | F106: 70 | G106: =ROUNDUP(SUM(I106:IF106),1) -> 0 | I106: =+$C106*I51 -> 0 | J106: =+$C106*J51 -> 0 | K106: =+$C106*K51 -> 0 | L106: =+$C106*L51 -> 0
...

Sheet P.Batiente
A2: PUERTAS DE VIDRIO TEMPLADO | D2: PB1H | E2: PB2H | F2: PB4H | G2: PB4H | H2: PB4HcV | I2: PB4HcV | J2: PB4HcV | L2: Total | N2: piso1 | O2: piso1 | P2: piso1 | Q2: piso1 | R2: piso1 | S2: piso1 | T2: piso1
A3: 8 o 10 mm. c/PERFIL U 15x15 DE ALUMINIO | D3: 10mm. | E3: 10mm. | F3: 10mm. | G3: 10 mm. | H3: 10 mm. | I3: 10mm. | J3: 10mm. | N3: 10 mm. | O3: 10 mm. | P3: 10 mm. | Q3: 10 mm. | R3: 10 mm. | S3: 10 mm. | T3: 10 mm.
A4: DATOS BASE PARA EL ANALISIS | D4: =IF(D8=1,"INCOLORO","COLOR") -> INCOLORO | E4: =IF(E8=1,"INCOLORO","COLOR") -> INCOLORO | F4: =IF(F8=1,"INCOLORO","COLOR") -> INCOLORO | G4: =IF(G8=1,"INCOLORO","COLOR") -> INCOLORO | H4: =IF(H8=1,"INCOLORO","COLOR") -> INCOLORO | I4: =IF(I8=1,"INCOLORO","COLOR") -> INCOLORO | J4: =IF(J8=1,"INCOLORO","COLOR") -> INCOLORO | N4: =IF(N8=1,"INCOLORO","COLOR") -> INCOLORO | O4: =IF(O8=1,"INCOLORO","COLOR") -> INCOLORO | P4: =IF(P8=1,"INCOLORO","COLOR") -> INCOLORO | Q4: =IF(Q8=1,"INCOLORO","COLOR") -> INCOLORO | R4: =IF(R8=1,"INCOLORO","COLOR") -> INCOLORO | S4: =IF(S8=1,"INCOLORO","COLOR") -> INCOLORO | T4: =IF(T8=1,"INCOLORO","COLOR") -> INCOLORO
A5: BASE ( Metros ) | D5: 0.84 | E5: 1.7 | F5: 7.22 | G5: 2 | H5: 4.5 | I5: 5 | J5: 4.5 | N5: 4.8 | O5: 5.94 | P5: 5.95 | Q5: 5.95 | R5: 4.07 | S5: 5.8 | T5: 1.1
A6: ALTURA ( Metros ) | D6: 2.1 | E6: 2.5 | F6: 2.25 | G6: 3 | H6: 2.7 | I6: 3 | J6: 2.7 | N6: 2.7 | O6: 2.7 | P6: 2.7 | Q6: 2.7 | R6: 2.7 | S6: 2.7 | T6: 2.7
A7: CANTIDAD DE PIEZAS | D7: 1 | E7: 1 | F7: 1 | G7: 1 | H7: 1 | I7: 1 | J7: 1 | L7: =SUM(N7:IU7) -> 7 | M7: Puertas | N7: 1 | O7: 1 | P7: 1 | Q7: 1 | R7: 1 | S7: 1 | T7: 1
A8: INCOLORO = 1 ; COLOR =2 | D8: 1 | E8: 1 | F8: 1 | G8: 1 | H8: 1 | I8: 1 | J8: 1 | N8: 1 | O8: 1 | P8: 1 | Q8: 1 | R8: 1 | S8: 1 | T8: 1
A9: C/FRENO = 1 ; S/FRENO =2 | D9: 2 | E9: 1 | F9: 1 | G9: 1 | H9: 1 | I9: 1 | J9: 1 | N9: 2 | O9: 2 | P9: 2 | Q9: 2 | R9: 2 | S9: 2 | T9: 2
A10: Total Precio c/factura | D10: =+D54 -> 154.92956 | E10: =+E54 -> 491.23935 | F10: =+F54 -> 1069.6693 | G10: =+G54 -> 604.12355 | H10: =+H54 -> 918.4012 | I10: =+I54 -> 1066.9152 | J10: =+J54 -> 776.455 | L10: =SUM(N10:IU10) -> 5568.0707 | M10: $us. | N10: =+N54 -> 797.8616 | O10: =+O54 -> 945.91112 | P10: =+P54 -> 947.2098 | Q10: =+Q54 -> 947.2098 | R10: =+R54 -> 703.05796 | S10: =+S54 -> 927.7296 | T10: =+T54 -> 299.09083
A11: Superficie Mt² | D11: =+D5*D6*D$7 -> 1.764 | E11: =+E5*E6*E$7 -> 4.25 | F11: =+F5*F6*F$7 -> 16.245 | G11: =+G5*G6*G$7 -> 6 | H11: =+H5*H6*H$7 -> 12.15 | I11: =+I5*I6*I$7 -> 15 | J11: =+J5*J6*J$7 -> 12.15 | L11: =SUM(N11:IU11) -> 90.747 | M11: Mt² | N11: =+N5*N6*N$7 -> 12.96 | O11: =+O5*O6*O$7 -> 16.038 | P11: =+P5*P6*P$7 -> 16.065 | Q11: =+Q5*Q6*Q$7 -> 16.065 | R11: =+R5*R6*R$7 -> 10.989 | S11: =+S5*S6*S$7 -> 15.66 | T11: =+T5*T6*T$7 -> 2.97
A12: Precio con factura en $us / Mt² | D12: =+D10/D11 -> 87.828549 | E12: =+E10/E11 -> 115.58573 | F12: =+F10/F11 -> 65.846066 | G12: =+G10/G11 -> 100.68726 | H12: =+H10/H11 -> 75.588576 | I12: =+I10/I11 -> 71.127681 | J12: =+J10/J11 -> 63.905761 | L12: =+L10/L11 -> 61.358179 | M12: $us./Mt² | N12: =+N10/N11 -> 61.563395 | O12: =+O10/O11 -> 58.979369 | P12: =+P10/P11 -> 58.961083 | Q12: =+Q10/Q11 -> 58.961083 | R12: =+R10/R11 -> 63.978338 | S12: =+S10/S11 -> 59.241992 | T12: =+T10/T11 -> 100.70398
A13: Total Precio s/factura | D13: =+D85 -> 143.7766 | E13: =+E85 -> 474.03315 | F13: =+F85 -> 1032.4951 | G13: =+G85 -> 583.00811 | H13: =+H85 -> 886.4113 | I13: =+I85 -> 1029.7598 | J13: =+J85 -> 749.6062 | L13: =SUM(N13:IU13) -> 5373.7859 | M13: $us. | N13: =+N85 -> 770.0217 | O13: =+O85 -> 912.94122 | P13: =+P85 -> 914.1949 | Q13: =+Q85 -> 914.1949 | R13: =+R85 -> 678.50306 | S13: =+S85 -> 895.3897 | T13: =+T85 -> 288.54044
A14: Precio sin factura en $us / Mt² | D14: =+D13/D11 -> 81.506009 | E14: =+E13/E11 -> 111.53721 | F14: =+F13/F11 -> 63.557716 | G14: =+G13/G11 -> 97.168019 | H14: =+H13/H11 -> 72.955663 | I14: =+I13/I11 -> 68.650652 | J14: =+J13/J11 -> 61.695984 | L14: =+L13/L11 -> 59.21723 | M14: $us./Mt² | N14: =+N13/N11 -> 59.415255 | O14: =+O13/O11 -> 56.923633 | P14: =+P13/P11 -> 56.906001 | Q14: =+Q13/Q11 -> 56.906001 | R14: =+R13/R11 -> 61.74384 | S14: =+S13/S11 -> 57.176865 | T14: =+T13/T11 -> 97.151662
A15: Materia Prima ( Vidrio ) | D15: =0.9*SUM(D55:D56) -> 56.978964 | E15: =0.9*SUM(E55:E56) -> 137.27925 | F15: =0.9*SUM(F55:F56) -> 524.72974 | G15: =0.9*SUM(G55:G56) -> 193.806 | H15: =0.9*SUM(H55:H56) -> 392.45715 | I15: =0.9*SUM(I55:I56) -> 484.515 | J15: =0.9*SUM(J55:J56) -> 392.45715 | L15: =SUM(N15:IU15) -> 2931.2188 | M15: $us. | N15: =0.9*SUM(N55:N56) -> 418.62096 | O15: =0.9*SUM(O55:O56) -> 518.04344 | P15: =0.9*SUM(P55:P56) -> 518.91557 | Q15: =0.9*SUM(Q55:Q56) -> 518.91557 | R15: =0.9*SUM(R55:R56) -> 354.95569 | S15: =0.9*SUM(S55:S56) -> 505.83366 | T15: =0.9*SUM(T55:T56) -> 95.93397
A16: Materia Prima ( materiales ) | D16: =0.9*SUM(D58:D82) -> 64.359 | E16: =0.9*SUM(E58:E82) -> 261.23116 | F16: =0.9*SUM(F58:F82) -> 271.29897 | G16: =0.9*SUM(G58:G82) -> 288.3452 | H16: =0.9*SUM(H58:H82) -> 309.44493 | I16: =0.9*SUM(I58:I82) -> 321.8087 | J16: =0.9*SUM(J58:J82) -> 181.69335 | L16: =SUM(N16:IU16) -> 1148.9806 | M16: $us. | N16: =0.9*SUM(N58:N82) -> 166.48488 | O16: =0.9*SUM(O58:O82) -> 168.72669 | P16: =0.9*SUM(P58:P82) -> 168.74635 | Q16: =0.9*SUM(Q58:Q82) -> 168.74635 | R16: =0.9*SUM(R58:R82) -> 165.04933 | S16: =0.9*SUM(S58:S82) -> 168.45138 | T16: =0.9*SUM(T58:T82) -> 142.77558
A17: Mano de obra | D17: =0.9*D57 -> 18.09864 | E17: =0.9*E57 -> 43.605 | F17: =0.9*F57 -> 166.6737 | G17: =0.9*G57 -> 61.56 | H17: =0.9*H57 -> 124.659 | I17: =0.9*I57 -> 153.9 | J17: =0.9*J57 -> 124.659 | L17: =SUM(N17:IU17) -> 931.06422 | M17: $us. | N17: =0.9*N57 -> 132.9696 | O17: =0.9*O57 -> 164.54988 | P17: =0.9*P57 -> 164.8269 | Q17: =0.9*Q57 -> 164.8269 | R17: =0.9*R57 -> 112.74714 | S17: =0.9*S57 -> 160.6716 | T17: =0.9*T57 -> 30.4722
A18: Otros Gastos + Util | D18: =+D10-D17-D16-D15 -> 15.492956 | E18: =+E10-E17-E16-E15 -> 49.123935 | F18: =+F10-F17-F16-F15 -> 106.96693 | G18: =+G10-G17-G16-G15 -> 60.412355 | H18: =+H10-H17-H16-H15 -> 91.84012 | I18: =+I10-I17-I16-I15 -> 106.69152 | J18: =+J10-J17-J16-J15 -> 77.6455 | L18: =SUM(N18:IU18) -> 556.80707 | M18: $us. | N18: =+N10-N17-N16-N15 -> 79.78616 | O18: =+O10-O17-O16-O15 -> 94.591112 | P18: =+P10-P17-P16-P15 -> 94.72098 | Q18: =+Q10-Q17-Q16-Q15 -> 94.72098 | R18: =+R10-R17-R16-R15 -> 70.305796 | S18: =+S10-S17-S16-S15 -> 92.77296 | T18: =+T10-T17-T16-T15 -> 29.909083
A19: TOTAL | D19: =SUM(D15:D18) -> 154.92956 | E19: =SUM(E15:E18) -> 491.23935 | F19: =SUM(F15:F18) -> 1069.6693 | G19: =SUM(G15:G18) -> 604.12355 | H19: =SUM(H15:H18) -> 918.4012 | I19: =SUM(I15:I18) -> 1066.9152 | J19: =SUM(J15:J18) -> 776.455 | L19: =SUM(N19:IU19) -> 5568.0707 | M19: $us. | N19: =SUM(N15:N18) -> 797.8616 | O19: =SUM(O15:O18) -> 945.91112 | P19: =SUM(P15:P18) -> 947.2098 | Q19: =SUM(Q15:Q18) -> 947.2098 | R19: =SUM(R15:R18) -> 703.05796 | S19: =SUM(S15:S18) -> 927.7296 | T19: =SUM(T15:T18) -> 299.09083
A20: % descuento del con al sin | D20: =+(D10-D13)/D10 -> 0.071987295 | E20: =+(E10-E13)/E10 -> 0.035026103 | F20: =+(F10-F13)/F10 -> 0.034753038 | G20: =+(G10-G13)/G10 -> 0.034952188 | H20: =+(H10-H13)/H10 -> 0.034832158 | I20: =+(I10-I13)/I10 -> 0.03482511 | J20: =+(J10-J13)/J10 -> 0.034578694 | L20: =+(L10-L13)/L10 -> 0.034892655 | N20: =+(N10-N13)/N10 -> 0.034893139 | O20: =+(O10-O13)/O10 -> 0.034855173 | P20: =+(P10-P13)/P10 -> 0.034854893 | Q20: =+(Q10-Q13)/Q10 -> 0.034854893 | R20: =+(R10-R13)/R10 -> 0.034925849 | S20: =+(S10-S13)/S10 -> 0.034859183 | T20: =+(T10-T13)/T10 -> 0.035274889
A22: DETALLE DE MATERIALES A UTILIZAR
A23: MATERIAL | C23: Unidad | D23: PB1H | E23: PB2H | F23: PB4H | G23: PB4H | H23: PB4H | I23: PB4H | J23: PB4H | L23: Cantidad | M23: Unidad | N23: PB4H | O23: PB4H | P23: PB4H | Q23: PB4H | R23: PB4H | S23: PB4H | T23: PB4H
A24: Vidrio Templado 10mm Incoloro | C24: Mt² | D24: =IF(D8=1,D$5*D$6*D$7,0) -> 1.764 | E24: =IF(E8=1,E$5*E$6*E$7,0) -> 4.25 | F24: =IF(F8=1,F$5*F$6*F$7,0) -> 16.245 | G24: =IF(G8=1,G$5*G$6*G$7,0) -> 6 | H24: =IF(H8=1,H$5*H$6*H$7,0) -> 12.15 | I24: =IF(I8=1,I$5*I$6*I$7,0) -> 15 | J24: =IF(J8=1,J$5*J$6*J$7,0) -> 12.15 | K24: 17 | L24: =ROUNDUP(SUM(N24:IU24),1) -> 90.8 | M24: Mt² | N24: =IF(N8=1,N$5*N$6*N$7,0) -> 12.96 | O24: =IF(O8=1,O$5*O$6*O$7,0) -> 16.038 | P24: =IF(P8=1,P$5*P$6*P$7,0) -> 16.065 | Q24: =IF(Q8=1,Q$5*Q$6*Q$7,0) -> 16.065 | R24: =IF(R8=1,R$5*R$6*R$7,0) -> 10.989 | S24: =IF(S8=1,S$5*S$6*S$7,0) -> 15.66 | T24: =IF(T8=1,T$5*T$6*T$7,0) -> 2.97
A25: Vidrio Templado 10mm Color | C25: Mt² | D25: =IF(D8=2,D$5*D$6*D$7,0) -> 0 | E25: =IF(E8=2,E$5*E$6*E$7,0) -> 0 | F25: =IF(F8=2,F$5*F$6*F$7,0) -> 0 | G25: =IF(G8=2,G$5*G$6*G$7,0) -> 0 | H25: =IF(H8=2,H$5*H$6*H$7,0) -> 0 | I25: =IF(I8=2,I$5*I$6*I$7,0) -> 0 | J25: =IF(J8=2,J$5*J$6*J$7,0) -> 0 | K25: 22 | L25: =ROUNDUP(SUM(N25:IU25),1) -> 0 | M25: Mt² | N25: =IF(N8=2,N$5*N$6*N$7,0) -> 0 | O25: =IF(O8=2,O$5*O$6*O$7,0) -> 0 | P25: =IF(P8=2,P$5*P$6*P$7,0) -> 0 | Q25: =IF(Q8=2,Q$5*Q$6*Q$7,0) -> 0 | R25: =IF(R8=2,R$5*R$6*R$7,0) -> 0 | S25: =IF(S8=2,S$5*S$6*S$7,0) -> 0 | T25: =IF(T8=2,T$5*T$6*T$7,0) -> 0
A26: Mano de obra | C26: Mt² | D26: =+D11 -> 1.764 | E26: =+E11 -> 4.25 | F26: =+F11 -> 16.245 | G26: =+G11 -> 6 | H26: =+H11 -> 12.15 | I26: =+I11 -> 15 | J26: =+J11 -> 12.15 | K26: 75 | L26: =ROUNDUP(SUM(N26:IU26),1) -> 90.8 | M26: Mt² | N26: =+N11 -> 12.96 | O26: =+O11 -> 16.038 | P26: =+P11 -> 16.065 | Q26: =+Q11 -> 16.065 | R26: =+R11 -> 10.989 | S26: =+S11 -> 15.66 | T26: =+T11 -> 2.97
A27: Silicona transparente, blanca o negra | C27: Tubo | F27: =((2*F$6+F$5)/6)*F$7 -> 1.9533333 | G27: =((2*G$6+G$5)/6)*G$7 -> 1.3333333 | H27: =((2*H$6+H$5)/2)*H$7 -> 4.95 | I27: =((2*I$6+I$5)/2)*I$7 -> 5.5 | J27: =((2*J$6+J$5)/2)*J$7 -> 4.95 | K27: 1 | L27: =ROUNDUP(SUM(N27:IU27),1) -> 33.6 | M27: Tubo | N27: =((2*N$6+N$5)/2)*N$7 -> 5.1 | O27: =((2*O$6+O$5)/2)*O$7 -> 5.67 | P27: =((2*P$6+P$5)/2)*P$7 -> 5.675 | Q27: =((2*Q$6+Q$5)/2)*Q$7 -> 5.675 | R27: =((2*R$6+R$5)/2)*R$7 -> 4.735 | S27: =((2*S$6+S$5)/2)*S$7 -> 5.6 | T27: =((2*T$6+T$5)/6)*T$7 -> 1.0833333
A28: Cinta masking 1/2 " (rollo de 20) | C28: Rollo | F28: =2*(2*F$6+F$5)*F$7/20 -> 1.172 | G28: =2*(2*G$6+G$5)*G$7/20 -> 0.8 | H28: =2*(2*H$6+H$5)*H$7/10 -> 1.98 | I28: =2*(2*I$6+I$5)*I$7/10 -> 2.2 | J28: =2*(2*J$6+J$5)*J$7/10 -> 1.98 | K28: 3 | L28: =ROUNDUP(SUM(N28:IU28),1) -> 13.7 | M28: Rollo | N28: =2*(2*N$6+N$5)*N$7/10 -> 2.04 | O28: =2*(2*O$6+O$5)*O$7/10 -> 2.268 | P28: =2*(2*P$6+P$5)*P$7/10 -> 2.27 | Q28: =2*(2*Q$6+Q$5)*Q$7/10 -> 2.27 | R28: =2*(2*R$6+R$5)*R$7/10 -> 1.894 | S28: =2*(2*S$6+S$5)*S$7/10 -> 2.24 | T28: =2*(2*T$6+T$5)*T$7/20 -> 0.65
A29: "U" 15x25 - Kg/Mt lineal. | B29: 0.2 | C29: Kgr | F29: =(2*F$6+F$5)*$B29*F$7 -> 2.344 | G29: =(2*G$6+G$5)*$B29*G$7 -> 1.6 | H29: =(2*H$6+H$5)*$B29*H$7 -> 1.98 | I29: =(2*I$6+I$5)*$B29*I$7 -> 2.2 | J29: =(2*J$6+J$5)*$B29*J$7 -> 1.98 | K29: 5 | L29: =ROUNDUP(SUM(N29:IU29)/(B29*6),1) -> 12 | M29: Barras | N29: =(2*N$6+N$5)*$B29*N$7 -> 2.04 | O29: =(2*O$6+O$5)*$B29*O$7 -> 2.268 | P29: =(2*P$6+P$5)*$B29*P$7 -> 2.27 | Q29: =(2*Q$6+Q$5)*$B29*Q$7 -> 2.27 | R29: =(2*R$6+R$5)*$B29*R$7 -> 1.894 | S29: =(2*S$6+S$5)*$B29*S$7 -> 2.24 | T29: =(2*T$6+T$5)*$B29*T$7 -> 1.3
A30: Felpa | C30: Mt lineal | E30: =+E$6*E$7 -> 2.5 | F30: =+F$6*F$7 -> 2.25 | G30: =+G$6*G$7 -> 3 | H30: =+H$6*H$7 -> 2.7 | I30: =+I$6*I$7 -> 3 | K30: 11 | L30: =ROUNDUP(SUM(N30:IU30),1) -> 18.9 | M30: Mt lineal | N30: =+N$6*N$7 -> 2.7 | O30: =+O$6*O$7 -> 2.7 | P30: =+P$6*P$7 -> 2.7 | Q30: =+Q$6*Q$7 -> 2.7 | R30: =+R$6*R$7 -> 2.7 | S30: =+S$6*S$7 -> 2.7 | T30: =+T$6*T$7 -> 2.7
A31: Tarugos No. 6 | C31: Pza. | F31: =F$7*((2*F$6+F$5)/0.4) -> 29.3 | G31: =G$7*((2*G$6+G$5)/0.4) -> 20 | H31: =H$7*((2*H$6+H$5)/0.4) -> 24.75 | I31: =I$7*((2*I$6+I$5)/0.4) -> 27.5 | J31: =J$7*((2*J$6+J$5)/0.4) -> 24.75 | K31: 13 | L31: =ROUNDUP(SUM(N31:IU31),1) -> 178.6 | M31: Pza. | N31: =N$7*((2*N$6+N$5)/0.4) -> 25.5 | O31: =O$7*((2*O$6+O$5)/0.4) -> 28.35 | P31: =P$7*((2*P$6+P$5)/0.4) -> 28.375 | Q31: =Q$7*((2*Q$6+Q$5)/0.4) -> 28.375 | R31: =R$7*((2*R$6+R$5)/0.4) -> 23.675 | S31: =S$7*((2*S$6+S$5)/0.4) -> 28 | T31: =T$7*((2*T$6+T$5)/0.4) -> 16.25
A32: Tornillos 8 x 1 1/2 | C32: Pza. | F32: =F$7*((2*F$6+F$5)/0.4) -> 29.3 | G32: =G$7*((2*G$6+G$5)/0.4) -> 20 | H32: =H$7*((2*H$6+H$5)/0.4) -> 24.75 | I32: =I$7*((2*I$6+I$5)/0.4) -> 27.5 | J32: =J$7*((2*J$6+J$5)/0.4) -> 24.75 | K32: 14 | L32: =ROUNDUP(SUM(N32:IU32),1) -> 178.6 | M32: Pza. | N32: =N$7*((2*N$6+N$5)/0.4) -> 25.5 | O32: =O$7*((2*O$6+O$5)/0.4) -> 28.35 | P32: =P$7*((2*P$6+P$5)/0.4) -> 28.375 | Q32: =Q$7*((2*Q$6+Q$5)/0.4) -> 28.375 | R32: =R$7*((2*R$6+R$5)/0.4) -> 23.675 | S32: =S$7*((2*S$6+S$5)/0.4) -> 28 | T32: =T$7*((2*T$6+T$5)/0.4) -> 16.25
A33: Vedapres 001 - h - Kg/Mt l. | B33: 0.257 | C33: Kgr | E33: =(E$6)*$B33*E$7 -> 0.6425 | F33: =(F$6)*$B33*F$7 -> 0.57825 | G33: =(G$6)*$B33*G$7 -> 0.771 | H33: =(H$6)*$B33*H$7 -> 0.6939 | I33: =(I$6)*$B33*I$7 -> 0.771 | K33: 31 | L33: =ROUNDUP(SUM(N33:IU33),1) -> 4.9 | M33: Barra | N33: =(N$6)*$B33*N$7 -> 0.6939 | O33: =(O$6)*$B33*O$7 -> 0.6939 | P33: =(P$6)*$B33*P$7 -> 0.6939 | Q33: =(Q$6)*$B33*Q$7 -> 0.6939 | R33: =(R$6)*$B33*R$7 -> 0.6939 | S33: =(S$6)*$B33*S$7 -> 0.6939 | T33: =(T$6)*$B33*T$7 -> 0.6939
A34: Freno Hidráulico HyH | C34: Pza. | D34: =IF(D$9=1,D$7,0) -> 0 | E34: =IF(E$9=1,2*E$7,0) -> 2 | F34: =IF(F$9=1,2*F$7,0) -> 2 | G34: =IF(G$9=1,2*G$7,0) -> 2 | H34: =IF(H$9=1,2*H$7,0) -> 2 | I34: =IF(I$9=1,2*I$7,0) -> 2 | J34: =IF(J$9=1,J$7,0) -> 1 | K34: 37 | L34: =ROUNDUP(SUM(N34:IU34),1) -> 0 | M34: Pza. | N34: =IF(N$9=1,2*N$7,0) -> 0 | O34: =IF(O$9=1,2*O$7,0) -> 0 | P34: =IF(P$9=1,2*P$7,0) -> 0 | Q34: =IF(Q$9=1,2*Q$7,0) -> 0 | R34: =IF(R$9=1,2*R$7,0) -> 0 | S34: =IF(S$9=1,2*S$7,0) -> 0 | T34: =IF(T$9=1,2*T$7,0) -> 0
A35: Manijones de vidrio | C35: Pza. | D35: =2*D$7 -> 2 | E35: =4*E$7 -> 4 | F35: =4*F$7 -> 4 | G35: =4*G$7 -> 4 | H35: =4*H$7 -> 4 | I35: =4*I$7 -> 4 | J35: 2 | K35: 38 | L35: =ROUNDUP(SUM(N35:IU35),1) -> 28 | M35: Pza. | N35: =4*N$7 -> 4 | O35: =4*O$7 -> 4 | P35: =4*P$7 -> 4 | Q35: =4*Q$7 -> 4 | R35: =4*R$7 -> 4 | S35: =4*S$7 -> 4 | T35: =4*T$7 -> 4
A36: 1335 | C36: Pza. | D36: 1 | E36: 3 | F36: 3 | G36: 3 | H36: 3 | I36: 3 | J36: 1 | K36: 61 | L36: =ROUNDUP(SUM(N36:IU36),1) -> 21 | M36: Pza. | N36: 3 | O36: 3 | P36: 3 | Q36: 3 | R36: 3 | S36: 3 | T36: 3
A37: 1103 | C37: Pza. | D37: =D$7 -> 1 | E37: =E$7*2 -> 2 | F37: =F$7*2 -> 2 | G37: =G$7*2 -> 2 | H37: =H$7*2 -> 2 | I37: =I$7*2 -> 2 | J37: =J$7 -> 1 | K37: 44 | L37: =ROUNDUP(SUM(N37:IU37),1) -> 14 | M37: Pza. | N37: =N$7*2 -> 2 | O37: =O$7*2 -> 2 | P37: =P$7*2 -> 2 | Q37: =Q$7*2 -> 2 | R37: =R$7*2 -> 2 | S37: =S$7*2 -> 2 | T37: =T$7*2 -> 2
A38: 1101 | C38: Pza. | D38: =D$7 -> 1 | E38: =E$7*2 -> 2 | F38: =F$7*2 -> 2 | G38: =G$7*2 -> 2 | H38: =H$7*2 -> 2 | I38: =I$7*2 -> 2 | J38: =J$7 -> 1 | K38: 43 | L38: =ROUNDUP(SUM(N38:IU38),1) -> 14 | M38: Pza. | N38: =N$7*2 -> 2 | O38: =O$7*2 -> 2 | P38: =P$7*2 -> 2 | Q38: =Q$7*2 -> 2 | R38: =R$7*2 -> 2 | S38: =S$7*2 -> 2 | T38: =T$7*2 -> 2
A39: 1636 | C39: Pza. | D39: =D$7*2 -> 2 | E39: =E$7*4 -> 4 | F39: =F$7*4 -> 4 | G39: =G$7*4 -> 4 | H39: =H$7*4 -> 4 | I39: =I$7*4 -> 4 | J39: =J$7*2 -> 2 | K39: 72 | L39: =ROUNDUP(SUM(N39:IU39),1) -> 28 | M39: Pza. | N39: =N$7*4 -> 4 | O39: =O$7*4 -> 4 | P39: =P$7*4 -> 4 | Q39: =Q$7*4 -> 4 | R39: =R$7*4 -> 4 | S39: =S$7*4 -> 4 | T39: =T$7*4 -> 4
A40: 1520 | C40: Pza. | D40: =D$7 -> 1 | E40: =E$7 -> 1 | F40: =F$7 -> 1 | G40: =G$7 -> 1 | H40: =H$7 -> 1 | I40: =I$7 -> 1 | J40: =J$7 -> 1 | K40: 67 | L40: =ROUNDUP(SUM(N40:IU40),1) -> 7 | M40: Pza. | N40: =N$7 -> 1 | O40: =O$7 -> 1 | P40: =P$7 -> 1 | Q40: =Q$7 -> 1 | R40: =R$7 -> 1 | S40: =S$7 -> 1 | T40: =T$7 -> 1
A41: 1531 | C41: Pza. | E41: =E$7 -> 1 | F41: =F$7 -> 1 | G41: =G$7 -> 1 | H41: =H$7 -> 1 | I41: =I$7 -> 1 | J41: 1 | K41: 69 | L41: =ROUNDUP(SUM(N41:IU41),1) -> 7 | M41: Pza. | N41: =N$7 -> 1 | O41: =O$7 -> 1 | P41: =P$7 -> 1 | Q41: =Q$7 -> 1 | R41: =R$7 -> 1 | S41: =S$7 -> 1 | T41: =T$7 -> 1
A42: 1038 | C42: Pza. | D42: 2 | E42: =E$7*4 -> 4 | F42: =F$7*4 -> 4 | G42: =G$7*4 -> 4 | H42: =H$7*4 -> 4 | I42: =I$7*4 -> 4 | J42: 2 | K42: 41 | L42: =ROUNDUP(SUM(N42:IU42),1) -> 28 | M42: Pza. | N42: =N$7*4 -> 4 | O42: =O$7*4 -> 4 | P42: =P$7*4 -> 4 | Q42: =Q$7*4 -> 4 | R42: =R$7*4 -> 4 | S42: =S$7*4 -> 4 | T42: =T$7*4 -> 4
A43: 1013 | C43: Pza. | D43: =D$7 -> 1 | E43: =E$7*2 -> 2 | F43: =F$7*2 -> 2 | G43: =G$7*2 -> 2 | H43: =H$7*2 -> 2 | I43: =I$7*2 -> 2 | J43: =J$7 -> 1 | K43: 40 | L43: =ROUNDUP(SUM(N43:IU43),1) -> 14 | M43: Pza. | N43: =N$7*2 -> 2 | O43: =O$7*2 -> 2 | P43: =P$7*2 -> 2 | Q43: =Q$7*2 -> 2 | R43: =R$7*2 -> 2 | S43: =S$7*2 -> 2 | T43: =T$7*2 -> 2
A44: 1201 | C44: Pza. | D44: =+D$7 -> 1 | E44: 3 | F44: 3 | K44: 51 | L44: =ROUNDUP(SUM(N44:IU44),1) -> 0 | M44: Pza.
A45: 1504a | C45: Pza. | D45: =D$7 -> 1 | K45: 63 | L45: =ROUNDUP(SUM(N45:IU45),1) -> 0 | M45: Pza.
A46: 1335c | C46: Pza. | G46: 1 | H46: 1 | I46: 1 | J46: 1 | K46: 62 | L46: =ROUNDUP(SUM(N46:IU46),1) -> 7 | M46: Pza. | N46: 1 | O46: 1 | P46: 1 | Q46: 1 | R46: 1 | S46: 1 | T46: 1
A47: 1203 | C47: Pza. | G47: 2 | H47: 1 | J47: 1 | K47: 52 | L47: =ROUNDUP(SUM(N47:IU47),1) -> 8 | M47: Pza. | N47: 1 | O47: 1 | P47: 1 | Q47: 1 | R47: 1 | S47: 1 | T47: 2
A48: 1209 | C48: Pza. | H48: 1 | I48: 2 | K48: 53 | L48: =ROUNDUP(SUM(N48:IU48),1) -> 6 | M48: Pza. | N48: 1 | O48: 1 | P48: 1 | Q48: 1 | R48: 1 | S48: 1
A49: 1310 | C49: Pza. | J49: 1 | K49: 57 | L49: =ROUNDUP(SUM(N49:IU49),1) -> 0 | M49: Pza.
A50: 1302 | C50: Pza. | H50: 1 | I50: 2 | J50: 1 | K50: 55 | L50: =ROUNDUP(SUM(N50:IU50),1) -> 6 | M50: Pza. | N50: 1 | O50: 1 | P50: 1 | Q50: 1 | R50: 1 | S50: 1
A51: 1329 | C51: Pza. | H51: 1 | I51: 2 | J51: 1 | K51: 60 | L51: =ROUNDUP(SUM(N51:IU51),1) -> 6 | M51: Pza. | N51: 1 | O51: 1 | P51: 1 | Q51: 1 | R51: 1 | S51: 1
A54: COSTO CON FACTURA | D54: =SUM(D55:D82) -> 154.92956 | E54: =SUM(E55:E82) -> 491.23935 | F54: =SUM(F55:F82) -> 1069.6693 | G54: =SUM(G55:G82) -> 604.12355 | H54: =SUM(H55:H82) -> 918.4012 | I54: =SUM(I55:I82) -> 1066.9152 | J54: =SUM(J55:J82) -> 776.455 | L54: =ROUNDUP(SUM(N54:IU54),1) -> 5568.1 | M54: Sus | N54: =SUM(N55:N82) -> 797.8616 | O54: =SUM(O55:O82) -> 945.91112 | P54: =SUM(P55:P82) -> 947.2098 | Q54: =SUM(Q55:Q82) -> 947.2098 | R54: =SUM(R55:R82) -> 703.05796 | S54: =SUM(S55:S82) -> 927.7296 | T54: =SUM(T55:T82) -> 299.09083
A55: Vidrio Templado 10mm Incoloro | C55: =+'Costo M.P.yMat.'!F24 -> 35.89 | D55: =+D24*$C55 -> 63.30996 | E55: =+E24*$C55 -> 152.5325 | F55: =+F24*$C55 -> 583.03305 | G55: =+G24*$C55 -> 215.34 | H55: =+H24*$C55 -> 436.0635 | I55: =+I24*$C55 -> 538.35 | J55: =+J24*$C55 -> 436.0635 | K55: 17 | L55: =ROUNDUP(SUM(N55:IU55),1) -> 3257 | M55: Sus | N55: =+N24*$C55 -> 465.1344 | O55: =+O24*$C55 -> 575.60382 | P55: =+P24*$C55 -> 576.57285 | Q55: =+Q24*$C55 -> 576.57285 | R55: =+R24*$C55 -> 394.39521 | S55: =+S24*$C55 -> 562.0374 | T55: =+T24*$C55 -> 106.5933
A56: Vidrio Templado 10mm Color | C56: =+'Costo M.P.yMat.'!F29 -> 46.66 | D56: =+D25*$C56 -> 0 | E56: =+E25*$C56 -> 0 | F56: =+F25*$C56 -> 0 | G56: =+G25*$C56 -> 0 | H56: =+H25*$C56 -> 0 | I56: =+I25*$C56 -> 0 | J56: =+J25*$C56 -> 0 | K56: 22 | L56: =ROUNDUP(SUM(N56:IU56),1) -> 0 | M56: Sus | N56: =+N25*$C56 -> 0 | O56: =+O25*$C56 -> 0 | P56: =+P25*$C56 -> 0 | Q56: =+Q25*$C56 -> 0 | R56: =+R25*$C56 -> 0 | S56: =+S25*$C56 -> 0 | T56: =+T25*$C56 -> 0
A57: Mano de obra | C57: =+'Costo M.P.yMat.'!F82 -> 11.4 | D57: =+D26*$C57 -> 20.1096 | E57: =+E26*$C57 -> 48.45 | F57: =+F26*$C57 -> 185.193 | G57: =+G26*$C57 -> 68.4 | H57: =+H26*$C57 -> 138.51 | I57: =+I26*$C57 -> 171 | J57: =+J26*$C57 -> 138.51 | K57: 75 | L57: =ROUNDUP(SUM(N57:IU57),1) -> 1034.6 | M57: Sus | N57: =+N26*$C57 -> 147.744 | O57: =+O26*$C57 -> 182.8332 | P57: =+P26*$C57 -> 183.141 | Q57: =+Q26*$C57 -> 183.141 | R57: =+R26*$C57 -> 125.2746 | S57: =+S26*$C57 -> 178.524 | T57: =+T26*$C57 -> 33.858
A58: Silicona transp., blanca o negra | C58: =+'Costo M.P.yMat.'!F7 -> 3.31 | D58: =+D27*$C58 -> 0 | E58: =+E27*$C58 -> 0 | F58: =+F27*$C58 -> 6.4655333 | G58: =+G27*$C58 -> 4.4133333 | H58: =+H27*$C58 -> 16.3845 | I58: =+I27*$C58 -> 18.205 | J58: =+J27*$C58 -> 16.3845 | K58: 1 | L58: =ROUNDUP(SUM(N58:IU58),1) -> 111.1 | M58: Sus | N58: =+N27*$C58 -> 16.881 | O58: =+O27*$C58 -> 18.7677 | P58: =+P27*$C58 -> 18.78425 | Q58: =+Q27*$C58 -> 18.78425 | R58: =+R27*$C58 -> 15.67285 | S58: =+S27*$C58 -> 18.536 | T58: =+T27*$C58 -> 3.5858333
A59: Cinta masking 1/2 " (rollo de 20) | C59: =+'Costo M.P.yMat.'!F9 -> 0.75 | D59: =+D28*$C59 -> 0 | E59: =+E28*$C59 -> 0 | F59: =+F28*$C59 -> 0.879 | G59: =+G28*$C59 -> 0.6 | H59: =+H28*$C59 -> 1.485 | I59: =+I28*$C59 -> 1.65 | J59: =+J28*$C59 -> 1.485 | K59: 3 | L59: =ROUNDUP(SUM(N59:IU59),1) -> 10.3 | M59: Sus | N59: =+N28*$C59 -> 1.53 | O59: =+O28*$C59 -> 1.701 | P59: =+P28*$C59 -> 1.7025 | Q59: =+Q28*$C59 -> 1.7025 | R59: =+R28*$C59 -> 1.4205 | S59: =+S28*$C59 -> 1.68 | T59: =+T28*$C59 -> 0.4875
A60: "U" 15x25 - Kg/Mt lineal. | C60: =+'Costo M.P.yMat.'!F10 -> 0.9 | D60: =+D29*$C60 -> 0 | E60: =+E29*$C60 -> 0 | F60: =+F29*$C60 -> 2.1096 | G60: =+G29*$C60 -> 1.44 | H60: =+H29*$C60 -> 1.782 | I60: =+I29*$C60 -> 1.98 | J60: =+J29*$C60 -> 1.782 | K60: 5 | L60: =ROUNDUP(SUM(N60:IU60),1) -> 12.9 | M60: Sus | N60: =+N29*$C60 -> 1.836 | O60: =+O29*$C60 -> 2.0412 | P60: =+P29*$C60 -> 2.043 | Q60: =+Q29*$C60 -> 2.043 | R60: =+R29*$C60 -> 1.7046 | S60: =+S29*$C60 -> 2.016 | T60: =+T29*$C60 -> 1.17
A61: Felpa | C61: =+'Costo M.P.yMat.'!F17 -> 0.18 | D61: =+D30*$C61 -> 0 | E61: =+E30*$C61 -> 0.45 | F61: =+F30*$C61 -> 0.405 | G61: =+G30*$C61 -> 0.54 | H61: =+H30*$C61 -> 0.486 | I61: =+I30*$C61 -> 0.54 | J61: =+J30*$C61 -> 0 | K61: 11 | L61: =ROUNDUP(SUM(N61:IU61),1) -> 3.5 | M61: Sus | N61: =+N30*$C61 -> 0.486 | O61: =+O30*$C61 -> 0.486 | P61: =+P30*$C61 -> 0.486 | Q61: =+Q30*$C61 -> 0.486 | R61: =+R30*$C61 -> 0.486 | S61: =+S30*$C61 -> 0.486 | T61: =+T30*$C61 -> 0.486
A62: Tarugos No. 6 | C62: =+'Costo M.P.yMat.'!F19 -> 0.04 | D62: =+D31*$C62 -> 0 | E62: =+E31*$C62 -> 0 | F62: =+F31*$C62 -> 1.172 | G62: =+G31*$C62 -> 0.8 | H62: =+H31*$C62 -> 0.99 | I62: =+I31*$C62 -> 1.1 | J62: =+J31*$C62 -> 0.99 | K62: 13 | L62: =ROUNDUP(SUM(N62:IU62),1) -> 7.2 | M62: Sus | N62: =+N31*$C62 -> 1.02 | O62: =+O31*$C62 -> 1.134 | P62: =+P31*$C62 -> 1.135 | Q62: =+Q31*$C62 -> 1.135 | R62: =+R31*$C62 -> 0.947 | S62: =+S31*$C62 -> 1.12 | T62: =+T31*$C62 -> 0.65
A63: Tornillos 8 x 1 1/2 | C63: =+'Costo M.P.yMat.'!F20 -> 0.04 | D63: =+D32*$C63 -> 0 | E63: =+E32*$C63 -> 0 | F63: =+F32*$C63 -> 1.172 | G63: =+G32*$C63 -> 0.8 | H63: =+H32*$C63 -> 0.99 | I63: =+I32*$C63 -> 1.1 | J63: =+J32*$C63 -> 0.99 | K63: 14 | L63: =ROUNDUP(SUM(N63:IU63),1) -> 7.2 | M63: Sus | N63: =+N32*$C63 -> 1.02 | O63: =+O32*$C63 -> 1.134 | P63: =+P32*$C63 -> 1.135 | Q63: =+Q32*$C63 -> 1.135 | R63: =+R32*$C63 -> 0.947 | S63: =+S32*$C63 -> 1.12 | T63: =+T32*$C63 -> 0.65
A64: Vedapres 001 - h - Kg/Mt l. | B64: 0.257 | C64: =+'Costo M.P.yMat.'!F96 -> 8.82 | D64: =+D33*$C64 -> 0 | E64: =+E33*$C64 -> 5.66685 | F64: =+F33*$C64 -> 5.100165 | G64: =+G33*$C64 -> 6.80022 | H64: =+H33*$C64 -> 6.120198 | I64: =+I33*$C64 -> 6.80022 | J64: =+J33*$C64 -> 0 | K64: 31 | L64: =ROUNDUP(SUM(N64:IU64),1) -> 42.9 | M64: Sus | N64: =+N33*$C64 -> 6.120198 | O64: =+O33*$C64 -> 6.120198 | P64: =+P33*$C64 -> 6.120198 | Q64: =+Q33*$C64 -> 6.120198 | R64: =+R33*$C64 -> 6.120198 | S64: =+S33*$C64 -> 6.120198 | T64: =+T33*$C64 -> 6.120198
A65: Freno Hidráulico HyH | C65: =+'Costo M.P.yMat.'!F44 -> 79.75 | D65: =+D34*$C65 -> 0 | E65: =+E34*$C65 -> 159.5 | F65: =+F34*$C65 -> 159.5 | G65: =+G34*$C65 -> 159.5 | H65: =+H34*$C65 -> 159.5 | I65: =+I34*$C65 -> 159.5 | J65: =+J34*$C65 -> 79.75 | K65: 37 | L65: =ROUNDUP(SUM(N65:IU65),1) -> 0 | M65: Sus | N65: =+N34*$C65 -> 0 | O65: =+O34*$C65 -> 0 | P65: =+P34*$C65 -> 0 | Q65: =+Q34*$C65 -> 0 | R65: =+R34*$C65 -> 0 | S65: =+S34*$C65 -> 0 | T65: =+T34*$C65 -> 0
A66: Manijones de vidrio | C66: =+'Costo M.P.yMat.'!F45 -> 3.42 | D66: =+D35*$C66 -> 6.84 | E66: =+E35*$C66 -> 13.68 | F66: =+F35*$C66 -> 13.68 | G66: =+G35*$C66 -> 13.68 | H66: =+H35*$C66 -> 13.68 | I66: =+I35*$C66 -> 13.68 | J66: =+J35*$C66 -> 6.84 | K66: 38 | L66: =ROUNDUP(SUM(N66:IU66),1) -> 95.8 | M66: Sus | N66: =+N35*$C66 -> 13.68 | O66: =+O35*$C66 -> 13.68 | P66: =+P35*$C66 -> 13.68 | Q66: =+Q35*$C66 -> 13.68 | R66: =+R35*$C66 -> 13.68 | S66: =+S35*$C66 -> 13.68 | T66: =+T35*$C66 -> 13.68
A67: 1335 | C67: =+'Costo M.P.yMat.'!F68 -> 5.87 | D67: =+D36*$C67 -> 5.87 | E67: =+E36*$C67 -> 17.61 | F67: =+F36*$C67 -> 17.61 | G67: =+G36*$C67 -> 17.61 | H67: =+H36*$C67 -> 17.61 | I67: =+I36*$C67 -> 17.61 | J67: =+J36*$C67 -> 5.87 | K67: 61 | L67: =ROUNDUP(SUM(N67:IU67),1) -> 123.3 | M67: Sus | N67: =+N36*$C67 -> 17.61 | O67: =+O36*$C67 -> 17.61 | P67: =+P36*$C67 -> 17.61 | Q67: =+Q36*$C67 -> 17.61 | R67: =+R36*$C67 -> 17.61 | S67: =+S36*$C67 -> 17.61 | T67: =+T36*$C67 -> 17.61
A68: 1103 | C68: =+'Costo M.P.yMat.'!F51 -> 9.86 | D68: =+D37*$C68 -> 9.86 | E68: =+E37*$C68 -> 19.72 | F68: =+F37*$C68 -> 19.72 | G68: =+G37*$C68 -> 19.72 | H68: =+H37*$C68 -> 19.72 | I68: =+I37*$C68 -> 19.72 | J68: =+J37*$C68 -> 9.86 | K68: 44 | L68: =ROUNDUP(SUM(N68:IU68),1) -> 138.1 | M68: Sus | N68: =+N37*$C68 -> 19.72 | O68: =+O37*$C68 -> 19.72 | P68: =+P37*$C68 -> 19.72 | Q68: =+Q37*$C68 -> 19.72 | R68: =+R37*$C68 -> 19.72 | S68: =+S37*$C68 -> 19.72 | T68: =+T37*$C68 -> 19.72
A69: 1101 | C69: =+'Costo M.P.yMat.'!F50 -> 8.72 | D69: =+D38*$C69 -> 8.72 | E69: =+E38*$C69 -> 17.44 | F69: =+F38*$C69 -> 17.44 | G69: =+G38*$C69 -> 17.44 | H69: =+H38*$C69 -> 17.44 | I69: =+I38*$C69 -> 17.44 | J69: =+J38*$C69 -> 8.72 | K69: 43 | L69: =ROUNDUP(SUM(N69:IU69),1) -> 122.1 | M69: Sus | N69: =+N38*$C69 -> 17.44 | O69: =+O38*$C69 -> 17.44 | P69: =+P38*$C69 -> 17.44 | Q69: =+Q38*$C69 -> 17.44 | R69: =+R38*$C69 -> 17.44 | S69: =+S38*$C69 -> 17.44 | T69: =+T38*$C69 -> 17.44
A70: 1636 | C70: =+'Costo M.P.yMat.'!F79 -> 3.82 | D70: =+D39*$C70 -> 7.64 | E70: =+E39*$C70 -> 15.28 | F70: =+F39*$C70 -> 15.28 | G70: =+G39*$C70 -> 15.28 | H70: =+H39*$C70 -> 15.28 | I70: =+I39*$C70 -> 15.28 | J70: =+J39*$C70 -> 7.64 | K70: 72 | L70: =ROUNDUP(SUM(N70:IU70),1) -> 107 | M70: Sus | N70: =+N39*$C70 -> 15.28 | O70: =+O39*$C70 -> 15.28 | P70: =+P39*$C70 -> 15.28 | Q70: =+Q39*$C70 -> 15.28 | R70: =+R39*$C70 -> 15.28 | S70: =+S39*$C70 -> 15.28 | T70: =+T39*$C70 -> 15.28
A71: 1520 | C71: =+'Costo M.P.yMat.'!F74 -> 16.13 | D71: =+D40*$C71 -> 16.13 | E71: =+E40*$C71 -> 16.13 | F71: =+F40*$C71 -> 16.13 | G71: =+G40*$C71 -> 16.13 | H71: =+H40*$C71 -> 16.13 | I71: =+I40*$C71 -> 16.13 | J71: =+J40*$C71 -> 16.13 | K71: 67 | L71: =ROUNDUP(SUM(N71:IU71),1) -> 113 | M71: Sus | N71: =+N40*$C71 -> 16.13 | O71: =+O40*$C71 -> 16.13 | P71: =+P40*$C71 -> 16.13 | Q71: =+Q40*$C71 -> 16.13 | R71: =+R40*$C71 -> 16.13 | S71: =+S40*$C71 -> 16.13 | T71: =+T40*$C71 -> 16.13
A72: 1531 | C72: =+'Costo M.P.yMat.'!F76 -> 7.01 | D72: =+D41*$C72 -> 0 | E72: =+E41*$C72 -> 7.01 | F72: =+F41*$C72 -> 7.01 | G72: =+G41*$C72 -> 7.01 | H72: =+H41*$C72 -> 7.01 | I72: =+I41*$C72 -> 7.01 | J72: =+J41*$C72 -> 7.01 | K72: 69 | L72: =ROUNDUP(SUM(N72:IU72),1) -> 49.1 | M72: Sus | N72: =+N41*$C72 -> 7.01 | O72: =+O41*$C72 -> 7.01 | P72: =+P41*$C72 -> 7.01 | Q72: =+Q41*$C72 -> 7.01 | R72: =+R41*$C72 -> 7.01 | S72: =+S41*$C72 -> 7.01 | T72: =+T41*$C72 -> 7.01
A73: 1038 | C73: =+'Costo M.P.yMat.'!F48 -> 1.32 | D73: =+D42*$C73 -> 2.64 | E73: =+E42*$C73 -> 5.28 | F73: =+F42*$C73 -> 5.28 | G73: =+G42*$C73 -> 5.28 | H73: =+H42*$C73 -> 5.28 | I73: =+I42*$C73 -> 5.28 | J73: =+J42*$C73 -> 2.64 | K73: 41 | L73: =ROUNDUP(SUM(N73:IU73),1) -> 37 | M73: Sus | N73: =+N42*$C73 -> 5.28 | O73: =+O42*$C73 -> 5.28 | P73: =+P42*$C73 -> 5.28 | Q73: =+Q42*$C73 -> 5.28 | R73: =+R42*$C73 -> 5.28 | S73: =+S42*$C73 -> 5.28 | T73: =+T42*$C73 -> 5.28
A74: 1013 | C74: =+'Costo M.P.yMat.'!F47 -> 3.59 | D74: =+D43*$C74 -> 3.59 | E74: =+E43*$C74 -> 7.18 | F74: =+F43*$C74 -> 7.18 | G74: =+G43*$C74 -> 7.18 | H74: =+H43*$C74 -> 7.18 | I74: =+I43*$C74 -> 7.18 | J74: =+J43*$C74 -> 3.59 | K74: 40 | L74: =ROUNDUP(SUM(N74:IU74),1) -> 50.3 | M74: Sus | N74: =+N43*$C74 -> 7.18 | O74: =+O43*$C74 -> 7.18 | P74: =+P43*$C74 -> 7.18 | Q74: =+Q43*$C74 -> 7.18 | R74: =+R43*$C74 -> 7.18 | S74: =+S43*$C74 -> 7.18 | T74: =+T43*$C74 -> 7.18
A75: 1201 | C75: =+'Costo M.P.yMat.'!F58 -> 1.77 | D75: =+D44*$C75 -> 1.77 | E75: =+E44*$C75 -> 5.31 | F75: =+F44*$C75 -> 5.31 | G75: =+G44*$C75 -> 0 | H75: =+H44*$C75 -> 0 | I75: =+I44*$C75 -> 0 | J75: =+J44*$C75 -> 0 | K75: 51 | L75: =ROUNDUP(SUM(N75:IU75),1) -> 0 | M75: Sus | N75: =+N44*$C75 -> 0 | O75: =+O44*$C75 -> 0 | P75: =+P44*$C75 -> 0 | Q75: =+Q44*$C75 -> 0 | R75: =+R44*$C75 -> 0 | S75: =+S44*$C75 -> 0 | T75: =+T44*$C75 -> 0
A76: 1504a | C76: =+'Costo M.P.yMat.'!F73 -> 2.45 | D76: =+D45*$C76 -> 2.45 | E76: =+E45*$C76 -> 0 | F76: =+F45*$C76 -> 0 | G76: =+G45*$C76 -> 0 | H76: =+H45*$C76 -> 0 | I76: =+I45*$C76 -> 0 | J76: =+J45*$C76 -> 0 | K76: 63 | L76: =ROUNDUP(SUM(N76:IU76),1) -> 0 | M76: Sus | N76: =+N45*$C76 -> 0 | O76: =+O45*$C76 -> 0 | P76: =+P45*$C76 -> 0 | Q76: =+Q45*$C76 -> 0 | R76: =+R45*$C76 -> 0 | S76: =+S45*$C76 -> 0 | T76: =+T45*$C76 -> 0
A77: 1335c | C77: =+'Costo M.P.yMat.'!F69 -> 5.3 | D77: =D$7 -> 1 | E77: =+E46*$C77 -> 0 | F77: =+F46*$C77 -> 0 | G77: =+G46*$C77 -> 5.3 | H77: =+H46*$C77 -> 5.3 | I77: =+I46*$C77 -> 5.3 | J77: =+J46*$C77 -> 5.3 | K77: 62 | L77: =ROUNDUP(SUM(N77:IU77),1) -> 37.1 | M77: Sus | N77: =+N46*$C77 -> 5.3 | O77: =+O46*$C77 -> 5.3 | P77: =+P46*$C77 -> 5.3 | Q77: =+Q46*$C77 -> 5.3 | R77: =+R46*$C77 -> 5.3 | S77: =+S46*$C77 -> 5.3 | T77: =+T46*$C77 -> 5.3
A78: 1203 | C78: =+'Costo M.P.yMat.'!F59 -> 10.43 | D78: =D$7 -> 1 | E78: =+E47*$C78 -> 0 | F78: =+F47*$C78 -> 0 | G78: =+G47*$C78 -> 20.86 | H78: =+H47*$C78 -> 10.43 | I78: =+I47*$C78 -> 0 | J78: =+J47*$C78 -> 10.43 | K78: 52 | L78: =ROUNDUP(SUM(N78:IU78),1) -> 83.5 | M78: Sus | N78: =+N47*$C78 -> 10.43 | O78: =+O47*$C78 -> 10.43 | P78: =+P47*$C78 -> 10.43 | Q78: =+Q47*$C78 -> 10.43 | R78: =+R47*$C78 -> 10.43 | S78: =+S47*$C78 -> 10.43 | T78: =+T47*$C78 -> 20.86
A79: 1209 | C79: =+'Costo M.P.yMat.'!F60 -> 12.71 | D79: =D$7 -> 1 | E79: =+E48*$C79 -> 0 | F79: =+F48*$C79 -> 0 | G79: =+G48*$C79 -> 0 | H79: =+H48*$C79 -> 12.71 | I79: =+I48*$C79 -> 25.42 | J79: =+J48*$C79 -> 0 | K79: 53 | L79: =ROUNDUP(SUM(N79:IU79),1) -> 76.3 | M79: Sus | N79: =+N48*$C79 -> 12.71 | O79: =+O48*$C79 -> 12.71 | P79: =+P48*$C79 -> 12.71 | Q79: =+Q48*$C79 -> 12.71 | R79: =+R48*$C79 -> 12.71 | S79: =+S48*$C79 -> 12.71 | T79: =+T48*$C79 -> 0
A80: 1310 | C80: =+'Costo M.P.yMat.'!F64 -> 8.15 | D80: =D$7 -> 1 | E80: =+E49*$C80 -> 0 | F80: =+F49*$C80 -> 0 | G80: =+G49*$C80 -> 0 | H80: =+H49*$C80 -> 0 | I80: =+I49*$C80 -> 0 | J80: =+J49*$C80 -> 8.15 | K80: 57 | L80: =ROUNDUP(SUM(N80:IU80),1) -> 0 | M80: Sus | N80: =+N49*$C80 -> 0 | O80: =+O49*$C80 -> 0 | P80: =+P49*$C80 -> 0 | Q80: =+Q49*$C80 -> 0 | R80: =+R49*$C80 -> 0 | S80: =+S49*$C80 -> 0 | T80: =+T49*$C80 -> 0
A81: 1302 | C81: =+'Costo M.P.yMat.'!F62 -> 4.16 | D81: =D$7 -> 1 | E81: =+E50*$C81 -> 0 | F81: =+F50*$C81 -> 0 | G81: =+G50*$C81 -> 0 | H81: =+H50*$C81 -> 4.16 | I81: =+I50*$C81 -> 8.32 | J81: =+J50*$C81 -> 4.16 | K81: 55 | L81: =ROUNDUP(SUM(N81:IU81),1) -> 25 | M81: Sus | N81: =+N50*$C81 -> 4.16 | O81: =+O50*$C81 -> 4.16 | P81: =+P50*$C81 -> 4.16 | Q81: =+Q50*$C81 -> 4.16 | R81: =+R50*$C81 -> 4.16 | S81: =+S50*$C81 -> 4.16 | T81: =+T50*$C81 -> 0
A82: 1329 | C82: =+'Costo M.P.yMat.'!F67 -> 4.16 | D82: =D$7 -> 1 | E82: =+E51*$C82 -> 0 | F82: =+F51*$C82 -> 0 | G82: =+G51*$C82 -> 0 | H82: =+H51*$C82 -> 4.16 | I82: =+I51*$C82 -> 8.32 | J82: =+J51*$C82 -> 4.16 | K82: 60 | L82: =ROUNDUP(SUM(N82:IU82),1) -> 25 | M82: Sus | N82: =+N51*$C82 -> 4.16 | O82: =+O51*$C82 -> 4.16 | P82: =+P51*$C82 -> 4.16 | Q82: =+Q51*$C82 -> 4.16 | R82: =+R51*$C82 -> 4.16 | S82: =+S51*$C82 -> 4.16 | T82: =+T51*$C82 -> 0
A85: COSTO SIN FACTURA | D85: =SUM(D86:D113) -> 143.7766 | E85: =SUM(E86:E113) -> 474.03315 | F85: =SUM(F86:F113) -> 1032.4951 | G85: =SUM(G86:G113) -> 583.00811 | H85: =SUM(H86:H113) -> 886.4113 | I85: =SUM(I86:I113) -> 1029.7598 | J85: =SUM(J86:J113) -> 749.6062 | L85: =ROUNDUP(SUM(N85:IU85),1) -> 5373.8 | M85: Sus | N85: =SUM(N86:N113) -> 770.0217 | O85: =SUM(O86:O113) -> 912.94122 | P85: =SUM(P86:P113) -> 914.1949 | Q85: =SUM(Q86:Q113) -> 914.1949 | R85: =SUM(R86:R113) -> 678.50306 | S85: =SUM(S86:S113) -> 895.3897 | T85: =SUM(T86:T113) -> 288.54044
A86: Vidrio Templado 10mm Incoloro | C86: =+'Costo M.P.yMat.'!G24 -> 34.65 | D86: =+$C86*D24 -> 61.1226 | E86: =+$C86*E24 -> 147.2625 | F86: =+$C86*F24 -> 562.88925 | G86: =+$C86*G24 -> 207.9 | H86: =+$C86*H24 -> 420.9975 | I86: =+$C86*I24 -> 519.75 | J86: =+$C86*J24 -> 420.9975 | K86: 17 | L86: =ROUNDUP(SUM(N86:IU86),1) -> 3144.4 | M86: Sus | N86: =+$C86*N24 -> 449.064 | O86: =+$C86*O24 -> 555.7167 | P86: =+$C86*P24 -> 556.65225 | Q86: =+$C86*Q24 -> 556.65225 | R86: =+$C86*R24 -> 380.76885 | S86: =+$C86*S24 -> 542.619 | T86: =+$C86*T24 -> 102.9105
A87: Vidrio Templado 10mm Color | C87: =+'Costo M.P.yMat.'!G29 -> 45.05 | D87: =+$C87*D25 -> 0 | E87: =+$C87*E25 -> 0 | F87: =+$C87*F25 -> 0 | G87: =+$C87*G25 -> 0 | H87: =+$C87*H25 -> 0 | I87: =+$C87*I25 -> 0 | J87: =+$C87*J25 -> 0 | K87: 22 | L87: =ROUNDUP(SUM(N87:IU87),1) -> 0 | M87: Sus | N87: =+$C87*N25 -> 0 | O87: =+$C87*O25 -> 0 | P87: =+$C87*P25 -> 0 | Q87: =+$C87*Q25 -> 0 | R87: =+$C87*R25 -> 0 | S87: =+$C87*S25 -> 0 | T87: =+$C87*T25 -> 0
A88: Mano de obra | C88: =+'Costo M.P.yMat.'!G82 -> 11 | D88: =+$C88*D26 -> 19.404 | E88: =+$C88*E26 -> 46.75 | F88: =+$C88*F26 -> 178.695 | G88: =+$C88*G26 -> 66 | H88: =+$C88*H26 -> 133.65 | I88: =+$C88*I26 -> 165 | J88: =+$C88*J26 -> 133.65 | K88: 75 | L88: =ROUNDUP(SUM(N88:IU88),1) -> 998.3 | M88: Sus | N88: =+$C88*N26 -> 142.56 | O88: =+$C88*O26 -> 176.418 | P88: =+$C88*P26 -> 176.715 | Q88: =+$C88*Q26 -> 176.715 | R88: =+$C88*R26 -> 120.879 | S88: =+$C88*S26 -> 172.26 | T88: =+$C88*T26 -> 32.67
A89: Silicona transp., blanca o negra | C89: =+'Costo M.P.yMat.'!G7 -> 3.19 | D89: =+$C89*D27 -> 0 | E89: =+$C89*E27 -> 0 | F89: =+$C89*F27 -> 6.2311333 | G89: =+$C89*G27 -> 4.2533333 | H89: =+$C89*H27 -> 15.7905 | I89: =+$C89*I27 -> 17.545 | J89: =+$C89*J27 -> 15.7905 | K89: 1 | L89: =ROUNDUP(SUM(N89:IU89),1) -> 107 | M89: Sus | N89: =+$C89*N27 -> 16.269 | O89: =+$C89*O27 -> 18.0873 | P89: =+$C89*P27 -> 18.10325 | Q89: =+$C89*Q27 -> 18.10325 | R89: =+$C89*R27 -> 15.10465 | S89: =+$C89*S27 -> 17.864 | T89: =+$C89*T27 -> 3.4558333
A90: Cinta masking 1/2 " (rollo de 20) | C90: =+'Costo M.P.yMat.'!G9 -> 0.72 | D90: =+$C90*D28 -> 0 | E90: =+$C90*E28 -> 0 | F90: =+$C90*F28 -> 0.84384 | G90: =+$C90*G28 -> 0.576 | H90: =+$C90*H28 -> 1.4256 | I90: =+$C90*I28 -> 1.584 | J90: =+$C90*J28 -> 1.4256 | K90: 3 | L90: =ROUNDUP(SUM(N90:IU90),1) -> 9.9 | M90: Sus | N90: =+$C90*N28 -> 1.4688 | O90: =+$C90*O28 -> 1.63296 | P90: =+$C90*P28 -> 1.6344 | Q90: =+$C90*Q28 -> 1.6344 | R90: =+$C90*R28 -> 1.36368 | S90: =+$C90*S28 -> 1.6128 | T90: =+$C90*T28 -> 0.468
A91: "U" 15x25 - Kg/Mt lineal. | C91: =+'Costo M.P.yMat.'!G10 -> 0.87 | D91: =+$C91*D29 -> 0 | E91: =+$C91*E29 -> 0 | F91: =+$C91*F29 -> 2.03928 | G91: =+$C91*G29 -> 1.392 | H91: =+$C91*H29 -> 1.7226 | I91: =+$C91*I29 -> 1.914 | J91: =+$C91*J29 -> 1.7226 | K91: 5 | L91: =ROUNDUP(SUM(N91:IU91),1) -> 12.5 | M91: Sus | N91: =+$C91*N29 -> 1.7748 | O91: =+$C91*O29 -> 1.97316 | P91: =+$C91*P29 -> 1.9749 | Q91: =+$C91*Q29 -> 1.9749 | R91: =+$C91*R29 -> 1.64778 | S91: =+$C91*S29 -> 1.9488 | T91: =+$C91*T29 -> 1.131
A92: Felpa | C92: =+'Costo M.P.yMat.'!G17 -> 0.17 | D92: =+$C92*D30 -> 0 | E92: =+$C92*E30 -> 0.425 | F92: =+$C92*F30 -> 0.3825 | G92: =+$C92*G30 -> 0.51 | H92: =+$C92*H30 -> 0.459 | I92: =+$C92*I30 -> 0.51 | J92: =+$C92*J30 -> 0 | K92: 11 | L92: =ROUNDUP(SUM(N92:IU92),1) -> 3.3 | M92: Sus | N92: =+$C92*N30 -> 0.459 | O92: =+$C92*O30 -> 0.459 | P92: =+$C92*P30 -> 0.459 | Q92: =+$C92*Q30 -> 0.459 | R92: =+$C92*R30 -> 0.459 | S92: =+$C92*S30 -> 0.459 | T92: =+$C92*T30 -> 0.459
A93: Tarugos No. 6 | C93: =+'Costo M.P.yMat.'!G19 -> 0.04 | D93: =+$C93*D31 -> 0 | E93: =+$C93*E31 -> 0 | F93: =+$C93*F31 -> 1.172 | G93: =+$C93*G31 -> 0.8 | H93: =+$C93*H31 -> 0.99 | I93: =+$C93*I31 -> 1.1 | J93: =+$C93*J31 -> 0.99 | K93: 13 | L93: =ROUNDUP(SUM(N93:IU93),1) -> 7.2 | M93: Sus | N93: =+$C93*N31 -> 1.02 | O93: =+$C93*O31 -> 1.134 | P93: =+$C93*P31 -> 1.135 | Q93: =+$C93*Q31 -> 1.135 | R93: =+$C93*R31 -> 0.947 | S93: =+$C93*S31 -> 1.12 | T93: =+$C93*T31 -> 0.65
A94: Tornillos 8 x 1 1/2 | C94: =+'Costo M.P.yMat.'!G20 -> 0.04 | D94: =+$C94*D32 -> 0 | E94: =+$C94*E32 -> 0 | F94: =+$C94*F32 -> 1.172 | G94: =+$C94*G32 -> 0.8 | H94: =+$C94*H32 -> 0.99 | I94: =+$C94*I32 -> 1.1 | J94: =+$C94*J32 -> 0.99 | K94: 14 | L94: =ROUNDUP(SUM(N94:IU94),1) -> 7.2 | M94: Sus | N94: =+$C94*N32 -> 1.02 | O94: =+$C94*O32 -> 1.134 | P94: =+$C94*P32 -> 1.135 | Q94: =+$C94*Q32 -> 1.135 | R94: =+$C94*R32 -> 0.947 | S94: =+$C94*S32 -> 1.12 | T94: =+$C94*T32 -> 0.65
A95: Vedapres 001 - h - Kg/Mt l. | B95: 0.257 | C95: =+'Costo M.P.yMat.'!G96 -> 8.18 | D95: =+$C95*D33 -> 0 | E95: =+$C95*E33 -> 5.25565 | F95: =+$C95*F33 -> 4.730085 | G95: =+$C95*G33 -> 6.30678 | H95: =+$C95*H33 -> 5.676102 | I95: =+$C95*I33 -> 6.30678 | J95: =+$C95*J33 -> 0 | K95: 31 | L95: =ROUNDUP(SUM(N95:IU95),1) -> 39.8 | M95: Sus | N95: =+$C95*N33 -> 5.676102 | O95: =+$C95*O33 -> 5.676102 | P95: =+$C95*P33 -> 5.676102 | Q95: =+$C95*Q33 -> 5.676102 | R95: =+$C95*R33 -> 5.676102 | S95: =+$C95*S33 -> 5.676102 | T95: =+$C95*T33 -> 5.676102
A96: Freno Hidráulico HyH | C96: =+'Costo M.P.yMat.'!G44 -> 77 | D96: =+$C96*D34 -> 0 | E96: =+$C96*E34 -> 154 | F96: =+$C96*F34 -> 154 | G96: =+$C96*G34 -> 154 | H96: =+$C96*H34 -> 154 | I96: =+$C96*I34 -> 154 | J96: =+$C96*J34 -> 77 | K96: 37 | L96: =ROUNDUP(SUM(N96:IU96),1) -> 0 | M96: Sus | N96: =+$C96*N34 -> 0 | O96: =+$C96*O34 -> 0 | P96: =+$C96*P34 -> 0 | Q96: =+$C96*Q34 -> 0 | R96: =+$C96*R34 -> 0 | S96: =+$C96*S34 -> 0 | T96: =+$C96*T34 -> 0
A97: Manijones de vidrio | C97: =+'Costo M.P.yMat.'!G45 -> 3.3 | D97: =+$C97*D35 -> 6.6 | E97: =+$C97*E35 -> 13.2 | F97: =+$C97*F35 -> 13.2 | G97: =+$C97*G35 -> 13.2 | H97: =+$C97*H35 -> 13.2 | I97: =+$C97*I35 -> 13.2 | J97: =+$C97*J35 -> 6.6 | K97: 38 | L97: =ROUNDUP(SUM(N97:IU97),1) -> 92.4 | M97: Sus | N97: =+$C97*N35 -> 13.2 | O97: =+$C97*O35 -> 13.2 | P97: =+$C97*P35 -> 13.2 | Q97: =+$C97*Q35 -> 13.2 | R97: =+$C97*R35 -> 13.2 | S97: =+$C97*S35 -> 13.2 | T97: =+$C97*T35 -> 13.2
A98: 1335 | C98: =+'Costo M.P.yMat.'!G68 -> 5.67 | D98: =+$C98*D36 -> 5.67 | E98: =+$C98*E36 -> 17.01 | F98: =+$C98*F36 -> 17.01 | G98: =+$C98*G36 -> 17.01 | H98: =+$C98*H36 -> 17.01 | I98: =+$C98*I36 -> 17.01 | J98: =+$C98*J36 -> 5.67 | K98: 61 | L98: =ROUNDUP(SUM(N98:IU98),1) -> 119.1 | M98: Sus | N98: =+$C98*N36 -> 17.01 | O98: =+$C98*O36 -> 17.01 | P98: =+$C98*P36 -> 17.01 | Q98: =+$C98*Q36 -> 17.01 | R98: =+$C98*R36 -> 17.01 | S98: =+$C98*S36 -> 17.01 | T98: =+$C98*T36 -> 17.01
A99: 1103 | C99: =+'Costo M.P.yMat.'!G51 -> 9.52 | D99: =+$C99*D37 -> 9.52 | E99: =+$C99*E37 -> 19.04 | F99: =+$C99*F37 -> 19.04 | G99: =+$C99*G37 -> 19.04 | H99: =+$C99*H37 -> 19.04 | I99: =+$C99*I37 -> 19.04 | J99: =+$C99*J37 -> 9.52 | K99: 44 | L99: =ROUNDUP(SUM(N99:IU99),1) -> 133.3 | M99: Sus | N99: =+$C99*N37 -> 19.04 | O99: =+$C99*O37 -> 19.04 | P99: =+$C99*P37 -> 19.04 | Q99: =+$C99*Q37 -> 19.04 | R99: =+$C99*R37 -> 19.04 | S99: =+$C99*S37 -> 19.04 | T99: =+$C99*T37 -> 19.04
A100: 1101 | C100: =+'Costo M.P.yMat.'!G50 -> 8.42 | D100: =+$C100*D38 -> 8.42 | E100: =+$C100*E38 -> 16.84 | F100: =+$C100*F38 -> 16.84 | G100: =+$C100*G38 -> 16.84 | H100: =+$C100*H38 -> 16.84 | I100: =+$C100*I38 -> 16.84 | J100: =+$C100*J38 -> 8.42 | K100: 43 | L100: =ROUNDUP(SUM(N100:IU100),1) -> 117.9 | M100: Sus | N100: =+$C100*N38 -> 16.84 | O100: =+$C100*O38 -> 16.84 | P100: =+$C100*P38 -> 16.84 | Q100: =+$C100*Q38 -> 16.84 | R100: =+$C100*R38 -> 16.84 | S100: =+$C100*S38 -> 16.84 | T100: =+$C100*T38 -> 16.84
A101: 1636 | C101: =+'Costo M.P.yMat.'!G79 -> 3.69 | D101: =+$C101*D39 -> 7.38 | E101: =+$C101*E39 -> 14.76 | F101: =+$C101*F39 -> 14.76 | G101: =+$C101*G39 -> 14.76 | H101: =+$C101*H39 -> 14.76 | I101: =+$C101*I39 -> 14.76 | J101: =+$C101*J39 -> 7.38 | K101: 72 | L101: =ROUNDUP(SUM(N101:IU101),1) -> 103.4 | M101: Sus | N101: =+$C101*N39 -> 14.76 | O101: =+$C101*O39 -> 14.76 | P101: =+$C101*P39 -> 14.76 | Q101: =+$C101*Q39 -> 14.76 | R101: =+$C101*R39 -> 14.76 | S101: =+$C101*S39 -> 14.76 | T101: =+$C101*T39 -> 14.76
A102: 1520 | C102: =+'Costo M.P.yMat.'!G74 -> 15.57 | D102: =+$C102*D40 -> 15.57 | E102: =+$C102*E40 -> 15.57 | F102: =+$C102*F40 -> 15.57 | G102: =+$C102*G40 -> 15.57 | H102: =+$C102*H40 -> 15.57 | I102: =+$C102*I40 -> 15.57 | J102: =+$C102*J40 -> 15.57 | K102: 67 | L102: =ROUNDUP(SUM(N102:IU102),1) -> 109 | M102: Sus | N102: =+$C102*N40 -> 15.57 | O102: =+$C102*O40 -> 15.57 | P102: =+$C102*P40 -> 15.57 | Q102: =+$C102*Q40 -> 15.57 | R102: =+$C102*R40 -> 15.57 | S102: =+$C102*S40 -> 15.57 | T102: =+$C102*T40 -> 15.57
A103: 1531 | C103: =+'Costo M.P.yMat.'!G76 -> 6.77 | D103: =+$C103*D41 -> 0 | E103: =+$C103*E41 -> 6.77 | F103: =+$C103*F41 -> 6.77 | G103: =+$C103*G41 -> 6.77 | H103: =+$C103*H41 -> 6.77 | I103: =+$C103*I41 -> 6.77 | J103: =+$C103*J41 -> 6.77 | K103: 69 | L103: =ROUNDUP(SUM(N103:IU103),1) -> 47.4 | M103: Sus | N103: =+$C103*N41 -> 6.77 | O103: =+$C103*O41 -> 6.77 | P103: =+$C103*P41 -> 6.77 | Q103: =+$C103*Q41 -> 6.77 | R103: =+$C103*R41 -> 6.77 | S103: =+$C103*S41 -> 6.77 | T103: =+$C103*T41 -> 6.77
A104: 1038 | C104: =+'Costo M.P.yMat.'!G48 -> 1.27 | D104: =+$C104*D42 -> 2.54 | E104: =+$C104*E42 -> 5.08 | F104: =+$C104*F42 -> 5.08 | G104: =+$C104*G42 -> 5.08 | H104: =+$C104*H42 -> 5.08 | I104: =+$C104*I42 -> 5.08 | J104: =+$C104*J42 -> 2.54 | K104: 41 | L104: =ROUNDUP(SUM(N104:IU104),1) -> 35.6 | M104: Sus | N104: =+$C104*N42 -> 5.08 | O104: =+$C104*O42 -> 5.08 | P104: =+$C104*P42 -> 5.08 | Q104: =+$C104*Q42 -> 5.08 | R104: =+$C104*R42 -> 5.08 | S104: =+$C104*S42 -> 5.08 | T104: =+$C104*T42 -> 5.08
A105: 1013 | C105: =+'Costo M.P.yMat.'!G47 -> 3.47 | D105: =+$C105*D43 -> 3.47 | E105: =+$C105*E43 -> 6.94 | F105: =+$C105*F43 -> 6.94 | G105: =+$C105*G43 -> 6.94 | H105: =+$C105*H43 -> 6.94 | I105: =+$C105*I43 -> 6.94 | J105: =+$C105*J43 -> 3.47 | K105: 40 | L105: =ROUNDUP(SUM(N105:IU105),1) -> 48.6 | M105: Sus | N105: =+$C105*N43 -> 6.94 | O105: =+$C105*O43 -> 6.94 | P105: =+$C105*P43 -> 6.94 | Q105: =+$C105*Q43 -> 6.94 | R105: =+$C105*R43 -> 6.94 | S105: =+$C105*S43 -> 6.94 | T105: =+$C105*T43 -> 6.94
A106: 1201 | C106: =+'Costo M.P.yMat.'!G58 -> 1.71 | D106: =+$C106*D44 -> 1.71 | E106: =+$C106*E44 -> 5.13 | F106: =+$C106*F44 -> 5.13 | G106: =+$C106*G44 -> 0 | H106: =+$C106*H44 -> 0 | I106: =+$C106*I44 -> 0 | J106: =+$C106*J44 -> 0 | K106: 51 | L106: =ROUNDUP(SUM(N106:IU106),1) -> 0 | M106: Sus | N106: =+$C106*N44 -> 0 | O106: =+$C106*O44 -> 0 | P106: =+$C106*P44 -> 0 | Q106: =+$C106*Q44 -> 0 | R106: =+$C106*R44 -> 0 | S106: =+$C106*S44 -> 0 | T106: =+$C106*T44 -> 0
...

Sheet resumen
A1: DETALLE DE MATERIALES A UTILIZAR | C1: puertas | D1: fijos | E1: corred | F1: total
A2: Vidrio Templado 10mm Incoloro | B2: Mt² | C2: 2429.6 | D2: 544.8 | E2: 78.5 | F2: =+E2+D2+C2 -> 3052.9 | G2: Mt²
A3: Mano de obra | B3: Mt² | C3: 2429.6 | D3: 541.1 | E3: 77.6 | F3: =+E3+D3+C3 -> 3048.3 | G3: Mt²
A4: Silicona transparente, blanca o negra | B4: Tubo | C4: 683.9 | D4: 218.3 | E4: 22.5 | F4: 925 | G4: Tubo
A5: Cinta masking 1/2 " (rollo de 20) | B5: Rollo | C5: 274.4 | D5: 131 | E5: 13.5 | F5: 419 | G5: Rollo
A6: "U" 15x25 - Kg/Mt lineal. | B6: Barras | C6: 230.9 | D6: 82.6 | E6: 6.5 | F6: =+E6+D6+C6 -> 320 | G6: Barras
A7: Vedapres 001 - u - Kg/Mt l. | B7: Barras | E7: 6.5 | F7: 7 | G7: Barras
A8: Vedapres 001 - h - Kg/Mt l. | B8: Barras | C8: 79.8 | E8: 3.3 | F8: 84 | G8: Barras
A9: Cabezal 7313 - Kg/Mt l. | B9: Barras | E9: 4 | F9: =+E9+D9+C9 -> 4 | G9: Barras
A10: Tapa 7312 - Kg/Mt l. | B10: Barras | E10: 4 | F10: =+E10+D10+C10 -> 4 | G10: Barras
A11: Trillo 7314 - Kg/Mt l. | B11: Barras | E11: 4 | F11: =+E11+D11+C11 -> 4 | G11: Barras
A12: TapaTrillo Rev. - Kg/Mt l. | B12: Barras | E12: 4 | F12: =+E12+D12+C12 -> 4 | G12: Barras
A13: Felpa | B13: Mt lineal | C13: 306.4 | E13: 91.4 | F13: 398 | G13: Mt lineal
A14: Tarugos No. 6 | B14: Pza. | C14: 3462.3 | D14: 1238.2 | E14: 216.9 | F14: 4918 | G14: Pza.
A15: Tornillos 8 x 1 1/2 | B15: Pza. | C15: 3462.3 | D15: 1238.2 | E15: 216.9 | F15: 4918 | G15: Pza.
A16: JALADORES | B16: Pza. | C16: 386 | F16: =+E16+D16+C16 -> 386 | G16: Pza.
A17: 1335 | B17: Pza. | C17: 288 | F17: =+E17+D17+C17 -> 288 | G17: Pza.
A18: 1103 | B18: Pza. | C18: 193 | F18: =+E18+D18+C18 -> 193 | G18: Pza.
A19: 1101 | B19: Pza. | C19: 193 | F19: =+E19+D19+C19 -> 193 | G19: Pza.
A20: 1125a | B20: Pza. | E20: 24 | F20: =+E20+D20+C20 -> 24 | G20: Pza.
A21: 1636 | B21: Pza. | C21: 386 | F21: =+E21+D21+C21 -> 386 | G21: Pza.
A22: 1510 | B22: Pza. | E22: 6 | F22: =+E22+D22+C22 -> 6 | G22: Pza.
A23: 1511 | B23: Pza. | E23: 6 | F23: =+E23+D23+C23 -> 6 | G23: Pza.
A24: 1520 | B24: Pza. | C24: 98 | F24: =+E24+D24+C24 -> 98 | G24: Pza.
A25: 1531 | B25: Pza. | C25: 98 | F25: 98 | G25: Pza.
A26: 1038 | B26: Pza. | C26: 386 | F26: =+E26+D26+C26 -> 386 | G26: Pza.
A27: 1013 | B27: Pza. | C27: 193 | F27: =+E27+D27+C27 -> 193 | G27: Pza.
A28: 1201 | B28: Pza. | C28: 3 | F28: =+E28+D28+C28 -> 3 | G28: Pza.
A29: 1504a | B29: Pza. | C29: 3 | F29: 0 | G29: Pza.
A30: 1335c | B30: Pza. | C30: 97 | F30: =+E30+D30+C30 -> 97 | G30: Pza.
A31: 1203 | B31: Pza. | C31: 68 | F31: =+E31+D31+C31 -> 68 | G31: Pza.
A32: 1209 | B32: Pza. | C32: 123 | F32: =+E32+D32+C32 -> 123 | G32: Pza.
A33: 1310 | B33: Pza. | C33: 3 | F33: =+E33+D33+C33 -> 3 | G33: Pza.
A34: 1302 | B34: Pza. | C34: 126 | F34: =+E34+D34+C34 -> 126 | G34: Pza.
A35: 1329 | B35: Pza. | C35: 126 | F35: =+E35+D35+C35 -> 126 | G35: Pza.
